Workbook

Sheet Guide
A1: RPG tour par tour : bestiaire de la tour et zones de chasse
A2: Stats des monstres, altérations, dégâts élémentaires, zones de chasse, XP, or et butin, d'après le diagramme du projet.
A4: OBJECTIF
A5: Contenu | B5: 92 monstres répartis en 30 zones et 10 biomes (un élément par biome). Chaque monstre a ses stats (proportionnelles à son niveau), ses altérations, son élément de dégâts, ses faiblesses ses récompenses et son butin (chance de drop et rareté des objets).
A6: Principe de niveau | B6: Un monstre a le niveau de son étage (étage 84 → niveau 84). En zone de chasse, son niveau est tiré entre l'étage de la zone et cet étage + 10 (étage 55 → niveaux 55 à 65).
A7: ONGLETS
A8: Monstres | B8: Les 92 monstres. Les stats sont calculées au niveau d'étage de la zone ; la cellule jaune du haut force un autre niveau pour tous. Colonnes « Butin » : chance de drop et probabilité de chaque rareté.
A9: Calculateur | B9: Un monstre à un niveau choisi, plus ses stats aux niveaux minimum et maximum de sa zone de chasse, et la chance réelle d'appliquer ses altérations.
A10: Zones | B10: Les 30 zones : étages concernés, déblocage de la zone de chasse, niveaux, XP et or par heure de chasse.
A11: Étages | B11: Les 100 étages : type (normal, boss, dragon), durée, dégâts subis estimés et récompenses.
A12: Simulation | B12: Combien de temps faut-il pour atteindre l'étage 100 ? Le joueur farme les zones de chasse quand il est en retard de niveau.
A13: Récompenses | B13: Courbes d'XP et d'or par niveau (1 à 110), XP pour monter de niveau et prix des équipements (Commun → Légendaire), repris dans l'onglet Boutique.
A14: Butin | B14: Chance de drop par rang, rareté des objets par biome (monstres, boss, dragons), Uniques par biome et butin attendu pendant la montée.
A15: Altérations | B15: Les 17 altérations (debuffs) avec effet, durée, cumul maximum et limites.
A16: Éléments | B16: Biomes, faiblesses et résistances de chaque élément (source : fichier Éléments/Fusions).
A17: Rôles | B17: Multiplicateurs de stats par rôle (bête, brute, mage…) et par rang (faible, normal, fort, boss, dragon).
A18: Paramètres | B18: Tous les chiffres d'équilibrage : courbe de niveau, joueur de référence, composition des étages, XP, or, durée de jeu.
A19: RÈGLES DE LA TOUR
A20: Étage normal | B20: 3 vagues de 3 monstres tirés dans la zone de la tranche de 5 étages (étages 1–4 : Forêt de chasse, 6–8 : Village gobelin, etc.).
A21: Étage boss (×5) | B21: 5 vagues : 4 vagues normales, puis le boss accompagné de 2 escortes. Battre l'étage débloque la zone de chasse de même numéro.
A22: Étage dragon (×9) | B22: Une seule vague : le dragon de l'élément du biome, un sac à PV (20 tours pour le tuer, coups modérés).
A23: Zones de chasse | B23: Mêmes monstres que la zone, sans le boss, affrontables à l'infini. Les tannières de dragon n'ont que le boss : pas de zone de chasse.
A24: Butin | B24: Faible 3 %, Normal 5 %, Fort 8 % de chance d'objet ; boss 1,4 objet, dragon 2,5 objets. La rareté dépend du biome : Super rare dès l'étage 11, Épique 21, Mythique 31, Légendaire 51 ; boss et dragons ont de l'avance et font tomber les Uniques de leur biome.
A25: FORMULES
A26: Facteur de niveau | B26: a + (1 − a) × ((N − 1) / 99) ^ p, avec a = 5 % et p = 1,2. Même courbe que les équipements : 1,00 au niveau 100.
A27: PV | B27: Dégâts moyens du joueur par tour (niveau 100 : 788) × facteur de niveau × tours pour tuer (rang) × PV du rôle.
A28: Force / Magie | B28: PV du joueur de référence × facteur de niveau × dégâts par coup (rang) × attaque du rôle ÷ (1 − réduction moyenne du joueur). Les attaques Mixtes donnent 75 % en Force et 75 % en Magie.
A29: Défenses | B29: Résistance, Armure et Agilité étalon × facteur de niveau × rôle (× rang pour les défenses). Précision, critique et pénétration ne dépendent pas du niveau.
A30: Dégâts élémentaires | B30: Chaque monstre inflige l'élément de son biome. La part élémentaire de ses dégâts dépend du rôle (100 % pour un élémentaire, 40 % pour une brute) ; seule cette part subit les avantages ×1,5 / ×0,75 et la Résistance élémentaire du joueur. Biome Neutre : 0 %.
A31: XP et or | B31: XP et or d'un monstre Normal = coefficient × niveau ^ exposant ; × rang (faible 0,7 ; fort 1,4 ; boss 8 ; dragon 12). XP pour monter = XP monstre × (10 + 0,7 × niveau).
A32: HYPOTHÈSES À VALIDER
A33: Joueur de référence | B33: Le diagramme ne donne pas les stats du joueur : niveau 100 = 1 600 Vitalité (PV = Vitalité × 10), 700 en Force/Magie. Les monstres sont calibrés dessus ; modifiez-les dans Paramètres §2.
A34: Composition des vagues | B34: 3 monstres par vague, 2 escortes avec le boss : à confirmer. Les attaques de zone économisent 25 % des tours.
A35: Zones et étages | B35: Les étages intermédiaires utilisent les monstres de la zone de leur tranche de 5 (hypothèse). L'étage ×9 est la tannière du dragon.
A36: Durée de jeu | B36: Résultat de la simulation : environ 7 h pour atteindre l'étage 100 (3 h de combats + 4 h de farm). En 1 h, c'est impossible : même sans farmer, les combats de la tour durent plus de 3 h.
A37: Difficulté | B37: Le seuil « Trop dur » (70 % des PV perdus sur la pire vague) ne tient pas compte des soins entre vagues ni des boucliers, non définis dans le diagramme.
A38: Prix | B38: Boutique de la taverne détaillée dans l'onglet Boutique : renouvellement toutes les heures, ressources, équipements (Commun → Épique) et personnages, avec le temps de chasse équivalent.
A39: Butin | B39: Objet pour la classe du joueur, slot au hasard, amélioration +0, matériau du palier de l'étage. Taux de départ calibrés pour ~1 objet par slot et par biome pendant la montée : à ajuster après tests.
A40: POINTS À VÉRIFIER DANS LE DIAGRAMME
A41: Noms de zones | B41: « Orage » apparaît pour les étages 80 et 90 : la zone 90 (anges) s'appelle ici « Orage (90) » comme dans le diagramme, à renommer (Palais céleste ?). « Maris des morts » est lu « Marais des morts ».
A42: Fautes corrigées | B42: Gobbelin/Bobbelin → Gobelin, humaniode → humanoïde, Annubis → Anubis, Démoniqua → démoniaque, etc. La colonne « Nom dans le diagramme » garde l'orthographe d'origine.
A43: Noms existants | B43: À vérifier avant publication : Jésus et Michel (références religieuses), Malphite (personnage de League of Legends), Anubis, Arrakis (Dune).
A44: LÉGENDE
A45: Cellule jaune, texte bleu | B45: Donnée modifiable. Les autres cellules sont des formules : ne pas les écraser. Lignes orange = boss, violettes = dragons.
A47: MISE À JOUR
A48: Initiative | B48: Monstres (colonne R), Calculateur, Rôles (colonnes N et I) et Paramètres §9 : initiative des monstres et des classes. Le camp à la plus haute initiative moyenne joue en premier à chaque manche.
A49: Boutique | B49: Nouvel onglet : prix des ressources, des équipements et des 2e et 3e personnages, calés sur l'or gagné en chasse.

Sheet Monstres
A1: Bestiaire : stats, altérations, dégâts élémentaires et butin des 92 monstres
A2: Les stats sont calculées au niveau d'étage de la zone (étage 84 → niveau 84). Pour un autre niveau, utilisez la cellule jaune ou le Calculateur. Colonnes AK à AT : chance de butin et rareté de l'objet (réglages dans l'onglet Butin).
A3: Niveau forcé (laisser vide = niveau d'étage de la zone)
A4: Légende : texte bleu sur fond jaune = donnée modifiable ; le reste est calculé. Altérations : chance d'application avant résistance du joueur.
A6: ID | B6: Étage de la zone | C6: Zone | D6: Biome | E6: Élément | F6: Monstre | G6: Boss ? | H6: Rang | I6: Rôle | J6: Type d'attaque | K6: Niveau | L6: PV | M6: Force | N6: Magie | O6: Résistance | P6: Armure | Q6: Agilité | R6: Initiative | S6: Précision | T6: Chance de critique | U6: Dégâts critiques | V6: Pénétration | W6: Rés. aux altérations | X6: Réduction physique (estim.) | Y6: Réduction magique (estim.) | Z6: Part de dégâts élémentaires | AA6: Dégâts par coup (% PV joueur) | AB6: Tours pour le tuer | AC6: Récompenses × | AD6: Faible contre (×1,5) | AE6: Résiste à (×0,75) | AF6: Altération 1 | AG6: Chance 1 | AH6: Altération 2 | AI6: Chance 2 | AJ6: XP | AK6: Or | AL6: Chance de butin | AM6: Objets attendus / victoire | AN6: % Commun | AO6: % Rare | AP6: % Super rare | AQ6: % Épique | AR6: % Mythique | AS6: % Légendaire | AT6: % Unique | AU6: Unique possible (Guerrier · Mage · Tireur) | AV6: Nom dans le diagramme | AW6: (aide) Clé | AX6: (aide) Facteur niveau | AY6: (aide) N° rôle | AZ6: (aide) N° rang
A7: MON-001 | B7: 5 | C7: {=INDEX(Zones!$B$6:$B$35,MATCH(B7,Zones!$A$6:$A$35,0))} -> Forêt de chasse | D7: {=INDEX(Éléments!$B$5:$B$14,MATCH(B7,Éléments!$C$5:$C$14,1))} -> Forêt | E7: {=INDEX(Éléments!$A$5:$A$14,MATCH(B7,Éléments!$C$5:$C$14,1))} -> Neutre | F7: Sanglier | G7: =IF(OR(H7="Boss",H7="Dragon"),"Oui","Non") -> Non | H7: Normal | I7: Bête | J7: Physique | K7: =IF($F$3="",B7,$F$3) -> 5 | L7: {=ROUND(Paramètres!$B$16*(Paramètres!$B$5+(1-Paramètres!$B$5)*((K7-Paramètres!$B$7)/(Paramètres!$B$8-Paramètres!$B$7))^Paramètres!$B$6)*INDEX(Rôles!$B$18:$B$22,AZ7)*INDEX(Rôles!$B$5:$B$13,AY7),0)} -> 105 | M7: {=ROUND(IF(J7="Physique",1,IF(J7="Mixte",Paramètres!$B$32,0))*Paramètres!$B$12*(Paramètres!$B$5+(1-Paramètres!$B$5)*((K7-Paramètres!$B$7)/(Paramètres!$B$8-Paramètres!$B$7))^Paramètres!$B$6)*INDEX(Rôles!$C$18:$C$22,AZ7)*INDEX(Rôles!$C$5:$C$13,AY7)/(Paramètres!$B$35*(1-Paramètres!$B$36)),0)} -> 25 | N7: {=ROUND(IF(J7="Magique",1,IF(J7="Mixte",Paramètres!$B$32,0))*Paramètres!$B$12*(Paramètres!$B$5+(1-Paramètres!$B$5)*((K7-Paramètres!$B$7)/(Paramètres!$B$8-Paramètres!$B$7))^Paramètres!$B$6)*INDEX(Rôles!$C$18:$C$22,AZ7)*INDEX(Rôles!$C$5:$C$13,AY7)/(Paramètres!$B$35*(1-Paramètres!$B$36)),0)} -> 0 | O7: {=ROUND(Paramètres!$B$18*(Paramètres!$B$5+(1-Paramètres!$B$5)*((K7-Paramètres!$B$7)/(Paramètres!$B$8-Paramètres!$B$7))^Paramètres!$B$6)*INDEX(Rôles!$D$5:$D$13,AY7)*INDEX(Rôles!$D$18:$D$22,AZ7),0)} -> 19 | P7: {=ROUND(Paramètres!$B$19*(Paramètres!$B$5+(1-Paramètres!$B$5)*((K7-Paramètres!$B$7)/(Paramètres!$B$8-Paramètres!$B$7))^Paramètres!$B$6)*INDEX(Rôles!$E$5:$E$13,AY7)*INDEX(Rôles!$D$18:$D$22,AZ7),0)} -> 20 | Q7: {=ROUND(Paramètres!$B$20*(Paramètres!$B$5+(1-Paramètres!$B$5)*((K7-Paramètres!$B$7)/(Paramètres!$B$8-Paramètres!$B$7))^Paramètres!$B$6)*INDEX(Rôles!$F$5:$F$13,AY7),0)} -> 10 | R7: =ROUND(Paramètres!$B$64*$AX7*INDEX(Rôles!$N$5:$N$13,$AY7)*INDEX(Rôles!$I$18:$I$22,$AZ7),0) -> 8 | S7: {=MIN(1,ROUND(Paramètres!$B$21*INDEX(Rôles!$G$5:$G$13,AY7),3))} -> 0.9 | T7: {=MIN(Paramètres!$B$28,ROUND(Paramètres!$B$22*INDEX(Rôles!$H$5:$H$13,AY7),3))} -> 0.05 | U7: {=ROUND(Paramètres!$B$23*INDEX(Rôles!$I$5:$I$13,AY7),3)} -> 0.5 | V7: {=MIN(Paramètres!$B$29,ROUND(Paramètres!$B$24*INDEX(Rôles!$J$5:$J$13,AY7),3))} -> 0.025 | W7: {=MIN(Paramètres!$B$27,ROUND((Paramètres!$B$25+(Paramètres!$B$26-Paramètres!$B$25)*(K7-Paramètres!$B$7)/(Paramètres!$B$8-Paramètres!$B$7))*INDEX(Rôles!$K$5:$K$13,AY7)+INDEX(Rôles!$G$18:$G$22,AZ7),3))} -> 0.048 | X7: =ROUND(1-(1-P7/(P7+(Paramètres!$B$19*(Paramètres!$B$5+(1-Paramètres!$B$5)*((K7-Paramètres!$B$7)/(Paramètres!$B$8-Paramètres!$B$7))^Paramètres!$B$6)*(1-Paramètres!$B$30)/Paramètres!$B$30)))*(1-O7/(O7+(Paramètres!$B$18*(Paramètres!$B$5+(1-Paramètres!$B$5)*((K7-Paramètres!$B$7)/(Paramètres!$B$8-Paramètres!$B$7))^Paramètres!$B$6)*(1-Paramètres!$B$31)/Paramètres!$B$31))),3) -> 0.233 | Y7: =ROUND(O7/(O7+(Paramètres!$B$18*(Paramètres!$B$5+(1-Paramètres!$B$5)*((K7-Paramètres!$B$7)/(Paramètres!$B$8-Paramètres!$B$7))^Paramètres!$B$6)*(1-Paramètres!$B$31)/Paramètres!$B$31)),3) -> 0.096 | Z7: {=IF(E7="Neutre",0,MIN(1,INDEX(Rôles!$L$5:$L$13,AY7)+INDEX(Rôles!$F$18:$F$22,AZ7)))} -> 0 | AA7: {=ROUND(INDEX(Rôles!$C$18:$C$22,AZ7)*INDEX(Rôles!$C$5:$C$13,AY7),4)} -> 0.0158 | AB7: {=ROUND(INDEX(Rôles!$B$18:$B$22,AZ7)*INDEX(Rôles!$B$5:$B$13,AY7),2)} -> 1.9 | AC7: {=INDEX(Rôles!$E$18:$E$22,AZ7)} -> 1 | AD7: {=INDEX(Éléments!$F$5:$F$14,MATCH(E7,Éléments!$A$5:$A$14,0))} -> — | AE7: {=INDEX(Éléments!$G$5:$G$14,MATCH(E7,Éléments!$A$5:$A$14,0))} -> — | AF7: Saignement | AG7: 0.2 | AH7: Assommé | AI7: 0.08 | AJ7: {=ROUND(ROUND(Paramètres!$B$49*K7^Paramètres!$B$50,0)*INDEX(Rôles!$E$18:$E$22,AZ7),0)} -> 45 | AK7: {=ROUND(ROUND(Paramètres!$B$53*K7^Paramètres!$B$54,0)*INDEX(Rôles!$E$18:$E$22,AZ7),0)} -> 26 | AL7: =INDEX(Butin!$B$7:$B$11,AZ7) -> 0.05 | AM7: =INDEX(Butin!$E$7:$E$11,AZ7) -> 0.05 | AN7: =IF($H7="Boss",INDEX(Butin!$E$28:$K$37,MATCH($B7,Éléments!$C$5:$C$14,1),1),IF($H7="Dragon",INDEX(Butin!$E$41:$K$50,MATCH($B7,Éléments!$C$5:$C$14,1),1),INDEX(Butin!$E$15:$K$24,MATCH($B7,Éléments!$C$5:$C$14,1),1))) -> 0.8 | AO7: =IF($H7="Boss",INDEX(Butin!$E$28:$K$37,MATCH($B7,Éléments!$C$5:$C$14,1),2),IF($H7="Dragon",INDEX(Butin!$E$41:$K$50,MATCH($B7,Éléments!$C$5:$C$14,1),2),INDEX(Butin!$E$15:$K$24,MATCH($B7,Éléments!$C$5:$C$14,1),2))) -> 0.2 | AP7: =IF($H7="Boss",INDEX(Butin!$E$28:$K$37,MATCH($B7,Éléments!$C$5:$C$14,1),3),IF($H7="Dragon",INDEX(Butin!$E$41:$K$50,MATCH($B7,Éléments!$C$5:$C$14,1),3),INDEX(Butin!$E$15:$K$24,MATCH($B7,Éléments!$C$5:$C$14,1),3))) -> 0 | AQ7: =IF($H7="Boss",INDEX(Butin!$E$28:$K$37,MATCH($B7,Éléments!$C$5:$C$14,1),4),IF($H7="Dragon",INDEX(Butin!$E$41:$K$50,MATCH($B7,Éléments!$C$5:$C$14,1),4),INDEX(Butin!$E$15:$K$24,MATCH($B7,Éléments!$C$5:$C$14,1),4))) -> 0 | AR7: =IF($H7="Boss",INDEX(Butin!$E$28:$K$37,MATCH($B7,Éléments!$C$5:$C$14,1),5),IF($H7="Dragon",INDEX(Butin!$E$41:$K$50,MATCH($B7,Éléments!$C$5:$C$14,1),5),INDEX(Butin!$E$15:$K$24,MATCH($B7,Éléments!$C$5:$C$14,1),5))) -> 0 | AS7: =IF($H7="Boss",INDEX(Butin!$E$28:$K$37,MATCH($B7,Éléments!$C$5:$C$14,1),6),IF($H7="Dragon",INDEX(Butin!$E$41:$K$50,MATCH($B7,Éléments!$C$5:$C$14,1),6),INDEX(Butin!$E$15:$K$24,MATCH($B7,Éléments!$C$5:$C$14,1),6))) -> 0 | AT7: =IF($H7="Boss",INDEX(Butin!$E$28:$K$37,MATCH($B7,Éléments!$C$5:$C$14,1),7),IF($H7="Dragon",INDEX(Butin!$E$41:$K$50,MATCH($B7,Éléments!$C$5:$C$14,1),7),INDEX(Butin!$E$15:$K$24,MATCH($B7,Éléments!$C$5:$C$14,1),7))) -> 0 | AU7: =IF(AT7=0,"—",INDEX(Butin!$D$54:$D$63,MATCH($B7,Éléments!$C$5:$C$14,1))&" · "&INDEX(Butin!$F$54:$F$63,MATCH($B7,Éléments!$C$5:$C$14,1))&" · "&INDEX(Butin!$H$54:$H$63,MATCH($B7,Éléments!$C$5:$C$14,1))) -> — | AV7: Sanglier | AW7: =B7&IF(G7="Oui","|B","|N") -> 5|N | AX7: =(Paramètres!$B$5+(1-Paramètres!$B$5)*((K7-Paramètres!$B$7)/(Paramètres!$B$8-Paramètres!$B$7))^Paramètres!$B$6) -> 0.070203814 | AY7: =MATCH(I7,Rôles!$A$5:$A$13,0) -> 1 | AZ7: =MATCH(H7,Rôles!$A$18:$A$22,0) -> 2
A8: MON-002 | B8: 5 | C8: {=INDEX(Zones!$B$6:$B$35,MATCH(B8,Zones!$A$6:$A$35,0))} -> Forêt de chasse | D8: {=INDEX(Éléments!$B$5:$B$14,MATCH(B8,Éléments!$C$5:$C$14,1))} -> Forêt | E8: {=INDEX(Éléments!$A$5:$A$14,MATCH(B8,Éléments!$C$5:$C$14,1))} -> Neutre | F8: Loup | G8: =IF(OR(H8="Boss",H8="Dragon"),"Oui","Non") -> Non | H8: Normal | I8: Assassin | J8: Physique | K8: =IF($F$3="",B8,$F$3) -> 5 | L8: {=ROUND(Paramètres!$B$16*(Paramètres!$B$5+(1-Paramètres!$B$5)*((K8-Paramètres!$B$7)/(Paramètres!$B$8-Paramètres!$B$7))^Paramètres!$B$6)*INDEX(Rôles!$B$18:$B$22,AZ8)*INDEX(Rôles!$B$5:$B$13,AY8),0)} -> 83 | M8: {=ROUND(IF(J8="Physique",1,IF(J8="Mixte",Paramètres!$B$32,0))*Paramètres!$B$12*(Paramètres!$B$5+(1-Paramètres!$B$5)*((K8-Paramètres!$B$7)/(Paramètres!$B$8-Paramètres!$B$7))^Paramètres!$B$6)*INDEX(Rôles!$C$18:$C$22,AZ8)*INDEX(Rôles!$C$5:$C$13,AY8)/(Paramètres!$B$35*(1-Paramètres!$B$36)),0)} -> 29 | N8: {=ROUND(IF(J8="Magique",1,IF(J8="Mixte",Paramètres!$B$32,0))*Paramètres!$B$12*(Paramètres!$B$5+(1-Paramètres!$B$5)*((K8-Paramètres!$B$7)/(Paramètres!$B$8-Paramètres!$B$7))^Paramètres!$B$6)*INDEX(Rôles!$C$18:$C$22,AZ8)*INDEX(Rôles!$C$5:$C$13,AY8)/(Paramètres!$B$35*(1-Paramètres!$B$36)),0)} -> 0 | O8: {=ROUND(Paramètres!$B$18*(Paramètres!$B$5+(1-Paramètres!$B$5)*((K8-Paramètres!$B$7)/(Paramètres!$B$8-Paramètres!$B$7))^Paramètres!$B$6)*INDEX(Rôles!$D$5:$D$13,AY8)*INDEX(Rôles!$D$18:$D$22,AZ8),0)} -> 19 | P8: {=ROUND(Paramètres!$B$19*(Paramètres!$B$5+(1-Paramètres!$B$5)*((K8-Paramètres!$B$7)/(Paramètres!$B$8-Paramètres!$B$7))^Paramètres!$B$6)*INDEX(Rôles!$E$5:$E$13,AY8)*INDEX(Rôles!$D$18:$D$22,AZ8),0)} -> 14 | Q8: {=ROUND(Paramètres!$B$20*(Paramètres!$B$5+(1-Paramètres!$B$5)*((K8-Paramètres!$B$7)/(Paramètres!$B$8-Paramètres!$B$7))^Paramètres!$B$6)*INDEX(Rôles!$F$5:$F$13,AY8),0)} -> 13 | R8: =ROUND(Paramètres!$B$64*$AX8*INDEX(Rôles!$N$5:$N$13,$AY8)*INDEX(Rôles!$I$18:$I$22,$AZ8),0) -> 11 | S8: {=MIN(1,ROUND(Paramètres!$B$21*INDEX(Rôles!$G$5:$G$13,AY8),3))} -> 1 | T8: {=MIN(Paramètres!$B$28,ROUND(Paramètres!$B$22*INDEX(Rôles!$H$5:$H$13,AY8),3))} -> 0.08 | U8: {=ROUND(Paramètres!$B$23*INDEX(Rôles!$I$5:$I$13,AY8),3)} -> 0.7 | V8: {=MIN(Paramètres!$B$29,ROUND(Paramètres!$B$24*INDEX(Rôles!$J$5:$J$13,AY8),3))} -> 0.06 | W8: {=MIN(Paramètres!$B$27,ROUND((Paramètres!$B$25+(Paramètres!$B$26-Paramètres!$B$25)*(K8-Paramètres!$B$7)/(Paramètres!$B$8-Paramètres!$B$7))*INDEX(Rôles!$K$5:$K$13,AY8)+INDEX(Rôles!$G$18:$G$22,AZ8),3))} -> 0.048 | X8: =ROUND(1-(1-P8/(P8+(Paramètres!$B$19*(Paramètres!$B$5+(1-Paramètres!$B$5)*((K8-Paramètres!$B$7)/(Paramètres!$B$8-Paramètres!$B$7))^Paramètres!$B$6)*(1-Paramètres!$B$30)/Paramètres!$B$30)))*(1-O8/(O8+(Paramètres!$B$18*(Paramètres!$B$5+(1-Paramètres!$B$5)*((K8-Paramètres!$B$7)/(Paramètres!$B$8-Paramètres!$B$7))^Paramètres!$B$6)*(1-Paramètres!$B$31)/Paramètres!$B$31))),3) -> 0.196 | Y8: =ROUND(O8/(O8+(Paramètres!$B$18*(Paramètres!$B$5+(1-Paramètres!$B$5)*((K8-Paramètres!$B$7)/(Paramètres!$B$8-Paramètres!$B$7))^Paramètres!$B$6)*(1-Paramètres!$B$31)/Paramètres!$B$31)),3) -> 0.096 | Z8: {=IF(E8="Neutre",0,MIN(1,INDEX(Rôles!$L$5:$L$13,AY8)+INDEX(Rôles!$F$18:$F$22,AZ8)))} -> 0 | AA8: {=ROUND(INDEX(Rôles!$C$18:$C$22,AZ8)*INDEX(Rôles!$C$5:$C$13,AY8),4)} -> 0.018 | AB8: {=ROUND(INDEX(Rôles!$B$18:$B$22,AZ8)*INDEX(Rôles!$B$5:$B$13,AY8),2)} -> 1.5 | AC8: {=INDEX(Rôles!$E$18:$E$22,AZ8)} -> 1 | AD8: {=INDEX(Éléments!$F$5:$F$14,MATCH(E8,Éléments!$A$5:$A$14,0))} -> — | AE8: {=INDEX(Éléments!$G$5:$G$14,MATCH(E8,Éléments!$A$5:$A$14,0))} -> — | AF8: Saignement | AG8: 0.3 | AJ8: {=ROUND(ROUND(Paramètres!$B$49*K8^Paramètres!$B$50,0)*INDEX(Rôles!$E$18:$E$22,AZ8),0)} -> 45 | AK8: {=ROUND(ROUND(Paramètres!$B$53*K8^Paramètres!$B$54,0)*INDEX(Rôles!$E$18:$E$22,AZ8),0)} -> 26 | AL8: =INDEX(Butin!$B$7:$B$11,AZ8) -> 0.05 | AM8: =INDEX(Butin!$E$7:$E$11,AZ8) -> 0.05 | AN8: =IF($H8="Boss",INDEX(Butin!$E$28:$K$37,MATCH($B8,Éléments!$C$5:$C$14,1),1),IF($H8="Dragon",INDEX(Butin!$E$41:$K$50,MATCH($B8,Éléments!$C$5:$C$14,1),1),INDEX(Butin!$E$15:$K$24,MATCH($B8,Éléments!$C$5:$C$14,1),1))) -> 0.8 | AO8: =IF($H8="Boss",INDEX(Butin!$E$28:$K$37,MATCH($B8,Éléments!$C$5:$C$14,1),2),IF($H8="Dragon",INDEX(Butin!$E$41:$K$50,MATCH($B8,Éléments!$C$5:$C$14,1),2),INDEX(Butin!$E$15:$K$24,MATCH($B8,Éléments!$C$5:$C$14,1),2))) -> 0.2 | AP8: =IF($H8="Boss",INDEX(Butin!$E$28:$K$37,MATCH($B8,Éléments!$C$5:$C$14,1),3),IF($H8="Dragon",INDEX(Butin!$E$41:$K$50,MATCH($B8,Éléments!$C$5:$C$14,1),3),INDEX(Butin!$E$15:$K$24,MATCH($B8,Éléments!$C$5:$C$14,1),3))) -> 0 | AQ8: =IF($H8="Boss",INDEX(Butin!$E$28:$K$37,MATCH($B8,Éléments!$C$5:$C$14,1),4),IF($H8="Dragon",INDEX(Butin!$E$41:$K$50,MATCH($B8,Éléments!$C$5:$C$14,1),4),INDEX(Butin!$E$15:$K$24,MATCH($B8,Éléments!$C$5:$C$14,1),4))) -> 0 | AR8: =IF($H8="Boss",INDEX(Butin!$E$28:$K$37,MATCH($B8,Éléments!$C$5:$C$14,1),5),IF($H8="Dragon",INDEX(Butin!$E$41:$K$50,MATCH($B8,Éléments!$C$5:$C$14,1),5),INDEX(Butin!$E$15:$K$24,MATCH($B8,Éléments!$C$5:$C$14,1),5))) -> 0 | AS8: =IF($H8="Boss",INDEX(Butin!$E$28:$K$37,MATCH($B8,Éléments!$C$5:$C$14,1),6),IF($H8="Dragon",INDEX(Butin!$E$41:$K$50,MATCH($B8,Éléments!$C$5:$C$14,1),6),INDEX(Butin!$E$15:$K$24,MATCH($B8,Éléments!$C$5:$C$14,1),6))) -> 0 | AT8: =IF($H8="Boss",INDEX(Butin!$E$28:$K$37,MATCH($B8,Éléments!$C$5:$C$14,1),7),IF($H8="Dragon",INDEX(Butin!$E$41:$K$50,MATCH($B8,Éléments!$C$5:$C$14,1),7),INDEX(Butin!$E$15:$K$24,MATCH($B8,Éléments!$C$5:$C$14,1),7))) -> 0 | AU8: =IF(AT8=0,"—",INDEX(Butin!$D$54:$D$63,MATCH($B8,Éléments!$C$5:$C$14,1))&" · "&INDEX(Butin!$F$54:$F$63,MATCH($B8,Éléments!$C$5:$C$14,1))&" · "&INDEX(Butin!$H$54:$H$63,MATCH($B8,Éléments!$C$5:$C$14,1))) -> — | AV8: Loup | AW8: =B8&IF(G8="Oui","|B","|N") -> 5|N | AX8: =(Paramètres!$B$5+(1-Paramètres!$B$5)*((K8-Paramètres!$B$7)/(Paramètres!$B$8-Paramètres!$B$7))^Paramètres!$B$6) -> 0.070203814 | AY8: =MATCH(I8,Rôles!$A$5:$A$13,0) -> 7 | AZ8: =MATCH(H8,Rôles!$A$18:$A$22,0) -> 2
A9: MON-003 | B9: 5 | C9: {=INDEX(Zones!$B$6:$B$35,MATCH(B9,Zones!$A$6:$A$35,0))} -> Forêt de chasse | D9: {=INDEX(Éléments!$B$5:$B$14,MATCH(B9,Éléments!$C$5:$C$14,1))} -> Forêt | E9: {=INDEX(Éléments!$A$5:$A$14,MATCH(B9,Éléments!$C$5:$C$14,1))} -> Neutre | F9: Ours | G9: =IF(OR(H9="Boss",H9="Dragon"),"Oui","Non") -> Non | H9: Fort | I9: Brute | J9: Physique | K9: =IF($F$3="",B9,$F$3) -> 5 | L9: {=ROUND(Paramètres!$B$16*(Paramètres!$B$5+(1-Paramètres!$B$5)*((K9-Paramètres!$B$7)/(Paramètres!$B$8-Paramètres!$B$7))^Paramètres!$B$6)*INDEX(Rôles!$B$18:$B$22,AZ9)*INDEX(Rôles!$B$5:$B$13,AY9),0)} -> 232 | M9: {=ROUND(IF(J9="Physique",1,IF(J9="Mixte",Paramètres!$B$32,0))*Paramètres!$B$12*(Paramètres!$B$5+(1-Paramètres!$B$5)*((K9-Paramètres!$B$7)/(Paramètres!$B$8-Paramètres!$B$7))^Paramètres!$B$6)*INDEX(Rôles!$C$18:$C$22,AZ9)*INDEX(Rôles!$C$5:$C$13,AY9)/(Paramètres!$B$35*(1-Paramètres!$B$36)),0)} -> 29 | N9: {=ROUND(IF(J9="Magique",1,IF(J9="Mixte",Paramètres!$B$32,0))*Paramètres!$B$12*(Paramètres!$B$5+(1-Paramètres!$B$5)*((K9-Paramètres!$B$7)/(Paramètres!$B$8-Paramètres!$B$7))^Paramètres!$B$6)*INDEX(Rôles!$C$18:$C$22,AZ9)*INDEX(Rôles!$C$5:$C$13,AY9)/(Paramètres!$B$35*(1-Paramètres!$B$36)),0)} -> 0 | O9: {=ROUND(Paramètres!$B$18*(Paramètres!$B$5+(1-Paramètres!$B$5)*((K9-Paramètres!$B$7)/(Paramètres!$B$8-Paramètres!$B$7))^Paramètres!$B$6)*INDEX(Rôles!$D$5:$D$13,AY9)*INDEX(Rôles!$D$18:$D$22,AZ9),0)} -> 44 | P9: {=ROUND(Paramètres!$B$19*(Paramètres!$B$5+(1-Paramètres!$B$5)*((K9-Paramètres!$B$7)/(Paramètres!$B$8-Paramètres!$B$7))^Paramètres!$B$6)*INDEX(Rôles!$E$5:$E$13,AY9)*INDEX(Rôles!$D$18:$D$22,AZ9),0)} -> 48 | Q9: {=ROUND(Paramètres!$B$20*(Paramètres!$B$5+(1-Paramètres!$B$5)*((K9-Paramètres!$B$7)/(Paramètres!$B$8-Paramètres!$B$7))^Paramètres!$B$6)*INDEX(Rôles!$F$5:$F$13,AY9),0)} -> 5 | R9: =ROUND(Paramètres!$B$64*$AX9*INDEX(Rôles!$N$5:$N$13,$AY9)*INDEX(Rôles!$I$18:$I$22,$AZ9),0) -> 5 | S9: {=MIN(1,ROUND(Paramètres!$B$21*INDEX(Rôles!$G$5:$G$13,AY9),3))} -> 0.765 | T9: {=MIN(Paramètres!$B$28,ROUND(Paramètres!$B$22*INDEX(Rôles!$H$5:$H$13,AY9),3))} -> 0.03 | U9: {=ROUND(Paramètres!$B$23*INDEX(Rôles!$I$5:$I$13,AY9),3)} -> 0.5 | V9: {=MIN(Paramètres!$B$29,ROUND(Paramètres!$B$24*INDEX(Rôles!$J$5:$J$13,AY9),3))} -> 0.04 | W9: {=MIN(Paramètres!$B$27,ROUND((Paramètres!$B$25+(Paramètres!$B$26-Paramètres!$B$25)*(K9-Paramètres!$B$7)/(Paramètres!$B$8-Paramètres!$B$7))*INDEX(Rôles!$K$5:$K$13,AY9)+INDEX(Rôles!$G$18:$G$22,AZ9),3))} -> 0.072 | X9: =ROUND(1-(1-P9/(P9+(Paramètres!$B$19*(Paramètres!$B$5+(1-Paramètres!$B$5)*((K9-Paramètres!$B$7)/(Paramètres!$B$8-Paramètres!$B$7))^Paramètres!$B$6)*(1-Paramètres!$B$30)/Paramètres!$B$30)))*(1-O9/(O9+(Paramètres!$B$18*(Paramètres!$B$5+(1-Paramètres!$B$5)*((K9-Paramètres!$B$7)/(Paramètres!$B$8-Paramètres!$B$7))^Paramètres!$B$6)*(1-Paramètres!$B$31)/Paramètres!$B$31))),3) -> 0.438 | Y9: =ROUND(O9/(O9+(Paramètres!$B$18*(Paramètres!$B$5+(1-Paramètres!$B$5)*((K9-Paramètres!$B$7)/(Paramètres!$B$8-Paramètres!$B$7))^Paramètres!$B$6)*(1-Paramètres!$B$31)/Paramètres!$B$31)),3) -> 0.197 | Z9: {=IF(E9="Neutre",0,MIN(1,INDEX(Rôles!$L$5:$L$13,AY9)+INDEX(Rôles!$F$18:$F$22,AZ9)))} -> 0 | AA9: {=ROUND(INDEX(Rôles!$C$18:$C$22,AZ9)*INDEX(Rôles!$C$5:$C$13,AY9),4)} -> 0.0181 | AB9: {=ROUND(INDEX(Rôles!$B$18:$B$22,AZ9)*INDEX(Rôles!$B$5:$B$13,AY9),2)} -> 4.2 | AC9: {=INDEX(Rôles!$E$18:$E$22,AZ9)} -> 1.4 | AD9: {=INDEX(Éléments!$F$5:$F$14,MATCH(E9,Éléments!$A$5:$A$14,0))} -> — | AE9: {=INDEX(Éléments!$G$5:$G$14,MATCH(E9,Éléments!$A$5:$A$14,0))} -> — | AF9: Assommé | AG9: 0.15 | AH9: Saignement | AI9: 0.15 | AJ9: {=ROUND(ROUND(Paramètres!$B$49*K9^Paramètres!$B$50,0)*INDEX(Rôles!$E$18:$E$22,AZ9),0)} -> 63 | AK9: {=ROUND(ROUND(Paramètres!$B$53*K9^Paramètres!$B$54,0)*INDEX(Rôles!$E$18:$E$22,AZ9),0)} -> 36 | AL9: =INDEX(Butin!$B$7:$B$11,AZ9) -> 0.08 | AM9: =INDEX(Butin!$E$7:$E$11,AZ9) -> 0.08 | AN9: =IF($H9="Boss",INDEX(Butin!$E$28:$K$37,MATCH($B9,Éléments!$C$5:$C$14,1),1),IF($H9="Dragon",INDEX(Butin!$E$41:$K$50,MATCH($B9,Éléments!$C$5:$C$14,1),1),INDEX(Butin!$E$15:$K$24,MATCH($B9,Éléments!$C$5:$C$14,1),1))) -> 0.8 | AO9: =IF($H9="Boss",INDEX(Butin!$E$28:$K$37,MATCH($B9,Éléments!$C$5:$C$14,1),2),IF($H9="Dragon",INDEX(Butin!$E$41:$K$50,MATCH($B9,Éléments!$C$5:$C$14,1),2),INDEX(Butin!$E$15:$K$24,MATCH($B9,Éléments!$C$5:$C$14,1),2))) -> 0.2 | AP9: =IF($H9="Boss",INDEX(Butin!$E$28:$K$37,MATCH($B9,Éléments!$C$5:$C$14,1),3),IF($H9="Dragon",INDEX(Butin!$E$41:$K$50,MATCH($B9,Éléments!$C$5:$C$14,1),3),INDEX(Butin!$E$15:$K$24,MATCH($B9,Éléments!$C$5:$C$14,1),3))) -> 0 | AQ9: =IF($H9="Boss",INDEX(Butin!$E$28:$K$37,MATCH($B9,Éléments!$C$5:$C$14,1),4),IF($H9="Dragon",INDEX(Butin!$E$41:$K$50,MATCH($B9,Éléments!$C$5:$C$14,1),4),INDEX(Butin!$E$15:$K$24,MATCH($B9,Éléments!$C$5:$C$14,1),4))) -> 0 | AR9: =IF($H9="Boss",INDEX(Butin!$E$28:$K$37,MATCH($B9,Éléments!$C$5:$C$14,1),5),IF($H9="Dragon",INDEX(Butin!$E$41:$K$50,MATCH($B9,Éléments!$C$5:$C$14,1),5),INDEX(Butin!$E$15:$K$24,MATCH($B9,Éléments!$C$5:$C$14,1),5))) -> 0 | AS9: =IF($H9="Boss",INDEX(Butin!$E$28:$K$37,MATCH($B9,Éléments!$C$5:$C$14,1),6),IF($H9="Dragon",INDEX(Butin!$E$41:$K$50,MATCH($B9,Éléments!$C$5:$C$14,1),6),INDEX(Butin!$E$15:$K$24,MATCH($B9,Éléments!$C$5:$C$14,1),6))) -> 0 | AT9: =IF($H9="Boss",INDEX(Butin!$E$28:$K$37,MATCH($B9,Éléments!$C$5:$C$14,1),7),IF($H9="Dragon",INDEX(Butin!$E$41:$K$50,MATCH($B9,Éléments!$C$5:$C$14,1),7),INDEX(Butin!$E$15:$K$24,MATCH($B9,Éléments!$C$5:$C$14,1),7))) -> 0 | AU9: =IF(AT9=0,"—",INDEX(Butin!$D$54:$D$63,MATCH($B9,Éléments!$C$5:$C$14,1))&" · "&INDEX(Butin!$F$54:$F$63,MATCH($B9,Éléments!$C$5:$C$14,1))&" · "&INDEX(Butin!$H$54:$H$63,MATCH($B9,Éléments!$C$5:$C$14,1))) -> — | AV9: Ours | AW9: =B9&IF(G9="Oui","|B","|N") -> 5|N | AX9: =(Paramètres!$B$5+(1-Paramètres!$B$5)*((K9-Paramètres!$B$7)/(Paramètres!$B$8-Paramètres!$B$7))^Paramètres!$B$6) -> 0.070203814 | AY9: =MATCH(I9,Rôles!$A$5:$A$13,0) -> 2 | AZ9: =MATCH(H9,Rôles!$A$18:$A$22,0) -> 3
A10: MON-004 | B10: 5 | C10: {=INDEX(Zones!$B$6:$B$35,MATCH(B10,Zones!$A$6:$A$35,0))} -> Forêt de chasse | D10: {=INDEX(Éléments!$B$5:$B$14,MATCH(B10,Éléments!$C$5:$C$14,1))} -> Forêt | E10: {=INDEX(Éléments!$A$5:$A$14,MATCH(B10,Éléments!$C$5:$C$14,1))} -> Neutre | F10: Ours enragé | G10: =IF(OR(H10="Boss",H10="Dragon"),"Oui","Non") -> Oui | H10: Boss | I10: Brute | J10: Physique | K10: =IF($F$3="",B10,$F$3) -> 5 | L10: {=ROUND(Paramètres!$B$16*(Paramètres!$B$5+(1-Paramètres!$B$5)*((K10-Paramètres!$B$7)/(Paramètres!$B$8-Paramètres!$B$7))^Paramètres!$B$6)*INDEX(Rôles!$B$18:$B$22,AZ10)*INDEX(Rôles!$B$5:$B$13,AY10),0)} -> 995 | M10: {=ROUND(IF(J10="Physique",1,IF(J10="Mixte",Paramètres!$B$32,0))*Paramètres!$B$12*(Paramètres!$B$5+(1-Paramètres!$B$5)*((K10-Paramètres!$B$7)/(Paramètres!$B$8-Paramètres!$B$7))^Paramètres!$B$6)*INDEX(Rôles!$C$18:$C$22,AZ10)*INDEX(Rôles!$C$5:$C$13,AY10)/(Paramètres!$B$35*(1-Paramètres!$B$36)),0)} -> 46 | N10: {=ROUND(IF(J10="Magique",1,IF(J10="Mixte",Paramètres!$B$32,0))*Paramètres!$B$12*(Paramètres!$B$5+(1-Paramètres!$B$5)*((K10-Paramètres!$B$7)/(Paramètres!$B$8-Paramètres!$B$7))^Paramètres!$B$6)*INDEX(Rôles!$C$18:$C$22,AZ10)*INDEX(Rôles!$C$5:$C$13,AY10)/(Paramètres!$B$35*(1-Paramètres!$B$36)),0)} -> 0 | O10: {=ROUND(Paramètres!$B$18*(Paramètres!$B$5+(1-Paramètres!$B$5)*((K10-Paramètres!$B$7)/(Paramètres!$B$8-Paramètres!$B$7))^Paramètres!$B$6)*INDEX(Rôles!$D$5:$D$13,AY10)*INDEX(Rôles!$D$18:$D$22,AZ10),0)} -> 49 | P10: {=ROUND(Paramètres!$B$19*(Paramètres!$B$5+(1-Paramètres!$B$5)*((K10-Paramètres!$B$7)/(Paramètres!$B$8-Paramètres!$B$7))^Paramètres!$B$6)*INDEX(Rôles!$E$5:$E$13,AY10)*INDEX(Rôles!$D$18:$D$22,AZ10),0)} -> 55 | Q10: {=ROUND(Paramètres!$B$20*(Paramètres!$B$5+(1-Paramètres!$B$5)*((K10-Paramètres!$B$7)/(Paramètres!$B$8-Paramètres!$B$7))^Paramètres!$B$6)*INDEX(Rôles!$F$5:$F$13,AY10),0)} -> 5 | R10: =ROUND(Paramètres!$B$64*$AX10*INDEX(Rôles!$N$5:$N$13,$AY10)*INDEX(Rôles!$I$18:$I$22,$AZ10),0) -> 6 | S10: {=MIN(1,ROUND(Paramètres!$B$21*INDEX(Rôles!$G$5:$G$13,AY10),3))} -> 0.765 | T10: {=MIN(Paramètres!$B$28,ROUND(Paramètres!$B$22*INDEX(Rôles!$H$5:$H$13,AY10),3))} -> 0.03 | U10: {=ROUND(Paramètres!$B$23*INDEX(Rôles!$I$5:$I$13,AY10),3)} -> 0.5 | V10: {=MIN(Paramètres!$B$29,ROUND(Paramètres!$B$24*INDEX(Rôles!$J$5:$J$13,AY10),3))} -> 0.04 | W10: {=MIN(Paramètres!$B$27,ROUND((Paramètres!$B$25+(Paramètres!$B$26-Paramètres!$B$25)*(K10-Paramètres!$B$7)/(Paramètres!$B$8-Paramètres!$B$7))*INDEX(Rôles!$K$5:$K$13,AY10)+INDEX(Rôles!$G$18:$G$22,AZ10),3))} -> 0.272 | X10: =ROUND(1-(1-P10/(P10+(Paramètres!$B$19*(Paramètres!$B$5+(1-Paramètres!$B$5)*((K10-Paramètres!$B$7)/(Paramètres!$B$8-Paramètres!$B$7))^Paramètres!$B$6)*(1-Paramètres!$B$30)/Paramètres!$B$30)))*(1-O10/(O10+(Paramètres!$B$18*(Paramètres!$B$5+(1-Paramètres!$B$5)*((K10-Paramètres!$B$7)/(Paramètres!$B$8-Paramètres!$B$7))^Paramètres!$B$6)*(1-Paramètres!$B$31)/Paramètres!$B$31))),3) -> 0.473 | Y10: =ROUND(O10/(O10+(Paramètres!$B$18*(Paramètres!$B$5+(1-Paramètres!$B$5)*((K10-Paramètres!$B$7)/(Paramètres!$B$8-Paramètres!$B$7))^Paramètres!$B$6)*(1-Paramètres!$B$31)/Paramètres!$B$31)),3) -> 0.215 | Z10: {=IF(E10="Neutre",0,MIN(1,INDEX(Rôles!$L$5:$L$13,AY10)+INDEX(Rôles!$F$18:$F$22,AZ10)))} -> 0 | AA10: {=ROUND(INDEX(Rôles!$C$18:$C$22,AZ10)*INDEX(Rôles!$C$5:$C$13,AY10),4)} -> 0.0285 | AB10: {=ROUND(INDEX(Rôles!$B$18:$B$22,AZ10)*INDEX(Rôles!$B$5:$B$13,AY10),2)} -> 18 | AC10: {=INDEX(Rôles!$E$18:$E$22,AZ10)} -> 8 | AD10: {=INDEX(Éléments!$F$5:$F$14,MATCH(E10,Éléments!$A$5:$A$14,0))} -> — | AE10: {=INDEX(Éléments!$G$5:$G$14,MATCH(E10,Éléments!$A$5:$A$14,0))} -> — | AF10: Saignement | AG10: 0.35 | AH10: Assommé | AI10: 0.25 | AJ10: {=ROUND(ROUND(Paramètres!$B$49*K10^Paramètres!$B$50,0)*INDEX(Rôles!$E$18:$E$22,AZ10),0)} -> 360 | AK10: {=ROUND(ROUND(Paramètres!$B$53*K10^Paramètres!$B$54,0)*INDEX(Rôles!$E$18:$E$22,AZ10),0)} -> 208 | AL10: =INDEX(Butin!$B$7:$B$11,AZ10) -> 1 | AM10: =INDEX(Butin!$E$7:$E$11,AZ10) -> 1.4 | AN10: =IF($H10="Boss",INDEX(Butin!$E$28:$K$37,MATCH($B10,Éléments!$C$5:$C$14,1),1),IF($H10="Dragon",INDEX(Butin!$E$41:$K$50,MATCH($B10,Éléments!$C$5:$C$14,1),1),INDEX(Butin!$E$15:$K$24,MATCH($B10,Éléments!$C$5:$C$14,1),1))) -> 0.4 | AO10: =IF($H10="Boss",INDEX(Butin!$E$28:$K$37,MATCH($B10,Éléments!$C$5:$C$14,1),2),IF($H10="Dragon",INDEX(Butin!$E$41:$K$50,MATCH($B10,Éléments!$C$5:$C$14,1),2),INDEX(Butin!$E$15:$K$24,MATCH($B10,Éléments!$C$5:$C$14,1),2))) -> 0.4 | AP10: =IF($H10="Boss",INDEX(Butin!$E$28:$K$37,MATCH($B10,Éléments!$C$5:$C$14,1),3),IF($H10="Dragon",INDEX(Butin!$E$41:$K$50,MATCH($B10,Éléments!$C$5:$C$14,1),3),INDEX(Butin!$E$15:$K$24,MATCH($B10,Éléments!$C$5:$C$14,1),3))) -> 0.15 | AQ10: =IF($H10="Boss",INDEX(Butin!$E$28:$K$37,MATCH($B10,Éléments!$C$5:$C$14,1),4),IF($H10="Dragon",INDEX(Butin!$E$41:$K$50,MATCH($B10,Éléments!$C$5:$C$14,1),4),INDEX(Butin!$E$15:$K$24,MATCH($B10,Éléments!$C$5:$C$14,1),4))) -> 0.04 | AR10: =IF($H10="Boss",INDEX(Butin!$E$28:$K$37,MATCH($B10,Éléments!$C$5:$C$14,1),5),IF($H10="Dragon",INDEX(Butin!$E$41:$K$50,MATCH($B10,Éléments!$C$5:$C$14,1),5),INDEX(Butin!$E$15:$K$24,MATCH($B10,Éléments!$C$5:$C$14,1),5))) -> 0 | AS10: =IF($H10="Boss",INDEX(Butin!$E$28:$K$37,MATCH($B10,Éléments!$C$5:$C$14,1),6),IF($H10="Dragon",INDEX(Butin!$E$41:$K$50,MATCH($B10,Éléments!$C$5:$C$14,1),6),INDEX(Butin!$E$15:$K$24,MATCH($B10,Éléments!$C$5:$C$14,1),6))) -> 0 | AT10: =IF($H10="Boss",INDEX(Butin!$E$28:$K$37,MATCH($B10,Éléments!$C$5:$C$14,1),7),IF($H10="Dragon",INDEX(Butin!$E$41:$K$50,MATCH($B10,Éléments!$C$5:$C$14,1),7),INDEX(Butin!$E$15:$K$24,MATCH($B10,Éléments!$C$5:$C$14,1),7))) -> 0.01 | AU10: =IF(AT10=0,"—",INDEX(Butin!$D$54:$D$63,MATCH($B10,Éléments!$C$5:$C$14,1))&" · "&INDEX(Butin!$F$54:$F$63,MATCH($B10,Éléments!$C$5:$C$14,1))&" · "&INDEX(Butin!$H$54:$H$63,MATCH($B10,Éléments!$C$5:$C$14,1))) -> Heaume du Roi Déchu · Bâton de la Singularité · Bague du Dernier Souffle | AV10: Ours enragé (Boss) | AW10: =B10&IF(G10="Oui","|B","|N") -> 5|B | AX10: =(Paramètres!$B$5+(1-Paramètres!$B$5)*((K10-Paramètres!$B$7)/(Paramètres!$B$8-Paramètres!$B$7))^Paramètres!$B$6) -> 0.070203814 | AY10: =MATCH(I10,Rôles!$A$5:$A$13,0) -> 2 | AZ10: =MATCH(H10,Rôles!$A$18:$A$22,0) -> 4
A11: MON-005 | B11: 9 | C11: {=INDEX(Zones!$B$6:$B$35,MATCH(B11,Zones!$A$6:$A$35,0))} -> Tannière du dragon (9) | D11: {=INDEX(Éléments!$B$5:$B$14,MATCH(B11,Éléments!$C$5:$C$14,1))} -> Forêt | E11: {=INDEX(Éléments!$A$5:$A$14,MATCH(B11,Éléments!$C$5:$C$14,1))} -> Neutre | F11: Dragon (Neutre) | G11: =IF(OR(H11="Boss",H11="Dragon"),"Oui","Non") -> Oui | H11: Dragon | I11: Dragon | J11: Mixte | K11: =IF($F$3="",B11,$F$3) -> 9 | L11: {=ROUND(Paramètres!$B$16*(Paramètres!$B$5+(1-Paramètres!$B$5)*((K11-Paramètres!$B$7)/(Paramètres!$B$8-Paramètres!$B$7))^Paramètres!$B$6)*INDEX(Rôles!$B$18:$B$22,AZ11)*INDEX(Rôles!$B$5:$B$13,AY11),0)} -> 1519 | M11: {=ROUND(IF(J11="Physique",1,IF(J11="Mixte",Paramètres!$B$32,0))*Paramètres!$B$12*(Paramètres!$B$5+(1-Paramètres!$B$5)*((K11-Paramètres!$B$7)/(Paramètres!$B$8-Paramètres!$B$7))^Paramètres!$B$6)*INDEX(Rôles!$C$18:$C$22,AZ11)*INDEX(Rôles!$C$5:$C$13,AY11)/(Paramètres!$B$35*(1-Paramètres!$B$36)),0)} -> 50 | N11: {=ROUND(IF(J11="Magique",1,IF(J11="Mixte",Paramètres!$B$32,0))*Paramètres!$B$12*(Paramètres!$B$5+(1-Paramètres!$B$5)*((K11-Paramètres!$B$7)/(Paramètres!$B$8-Paramètres!$B$7))^Paramètres!$B$6)*INDEX(Rôles!$C$18:$C$22,AZ11)*INDEX(Rôles!$C$5:$C$13,AY11)/(Paramètres!$B$35*(1-Paramètres!$B$36)),0)} -> 50 | O11: {=ROUND(Paramètres!$B$18*(Paramètres!$B$5+(1-Paramètres!$B$5)*((K11-Paramètres!$B$7)/(Paramètres!$B$8-Paramètres!$B$7))^Paramètres!$B$6)*INDEX(Rôles!$D$5:$D$13,AY11)*INDEX(Rôles!$D$18:$D$22,AZ11),0)} -> 73 | P11: {=ROUND(Paramètres!$B$19*(Paramètres!$B$5+(1-Paramètres!$B$5)*((K11-Paramètres!$B$7)/(Paramètres!$B$8-Paramètres!$B$7))^Paramètres!$B$6)*INDEX(Rôles!$E$5:$E$13,AY11)*INDEX(Rôles!$D$18:$D$22,AZ11),0)} -> 70 | Q11: {=ROUND(Paramètres!$B$20*(Paramètres!$B$5+(1-Paramètres!$B$5)*((K11-Paramètres!$B$7)/(Paramètres!$B$8-Paramètres!$B$7))^Paramètres!$B$6)*INDEX(Rôles!$F$5:$F$13,AY11),0)} -> 9 | R11: =ROUND(Paramètres!$B$64*$AX11*INDEX(Rôles!$N$5:$N$13,$AY11)*INDEX(Rôles!$I$18:$I$22,$AZ11),0) -> 8 | S11: {=MIN(1,ROUND(Paramètres!$B$21*INDEX(Rôles!$G$5:$G$13,AY11),3))} -> 0.9 | T11: {=MIN(Paramètres!$B$28,ROUND(Paramètres!$B$22*INDEX(Rôles!$H$5:$H$13,AY11),3))} -> 0.05 | U11: {=ROUND(Paramètres!$B$23*INDEX(Rôles!$I$5:$I$13,AY11),3)} -> 0.5 | V11: {=MIN(Paramètres!$B$29,ROUND(Paramètres!$B$24*INDEX(Rôles!$J$5:$J$13,AY11),3))} -> 0.05 | W11: {=MIN(Paramètres!$B$27,ROUND((Paramètres!$B$25+(Paramètres!$B$26-Paramètres!$B$25)*(K11-Paramètres!$B$7)/(Paramètres!$B$8-Paramètres!$B$7))*INDEX(Rôles!$K$5:$K$13,AY11)+INDEX(Rôles!$G$18:$G$22,AZ11),3))} -> 0.291 | X11: =ROUND(1-(1-P11/(P11+(Paramètres!$B$19*(Paramètres!$B$5+(1-Paramètres!$B$5)*((K11-Paramètres!$B$7)/(Paramètres!$B$8-Paramètres!$B$7))^Paramètres!$B$6)*(1-Paramètres!$B$30)/Paramètres!$B$30)))*(1-O11/(O11+(Paramètres!$B$18*(Paramètres!$B$5+(1-Paramètres!$B$5)*((K11-Paramètres!$B$7)/(Paramètres!$B$8-Paramètres!$B$7))^Paramètres!$B$6)*(1-Paramètres!$B$31)/Paramètres!$B$31))),3) -> 0.47 | Y11: =ROUND(O11/(O11+(Paramètres!$B$18*(Paramètres!$B$5+(1-Paramètres!$B$5)*((K11-Paramètres!$B$7)/(Paramètres!$B$8-Paramètres!$B$7))^Paramètres!$B$6)*(1-Paramètres!$B$31)/Paramètres!$B$31)),3) -> 0.229 | Z11: {=IF(E11="Neutre",0,MIN(1,INDEX(Rôles!$L$5:$L$13,AY11)+INDEX(Rôles!$F$18:$F$22,AZ11)))} -> 0 | AA11: {=ROUND(INDEX(Rôles!$C$18:$C$22,AZ11)*INDEX(Rôles!$C$5:$C$13,AY11),4)} -> 0.03 | AB11: {=ROUND(INDEX(Rôles!$B$18:$B$22,AZ11)*INDEX(Rôles!$B$5:$B$13,AY11),2)} -> 20 | AC11: {=INDEX(Rôles!$E$18:$E$22,AZ11)} -> 12 | AD11: {=INDEX(Éléments!$F$5:$F$14,MATCH(E11,Éléments!$A$5:$A$14,0))} -> — | AE11: {=INDEX(Éléments!$G$5:$G$14,MATCH(E11,Éléments!$A$5:$A$14,0))} -> — | AF11: Assommé | AG11: 0.2 | AH11: Saignement | AI11: 0.2 | AJ11: {=ROUND(ROUND(Paramètres!$B$49*K11^Paramètres!$B$50,0)*INDEX(Rôles!$E$18:$E$22,AZ11),0)} -> 1128 | AK11: {=ROUND(ROUND(Paramètres!$B$53*K11^Paramètres!$B$54,0)*INDEX(Rôles!$E$18:$E$22,AZ11),0)} -> 696 | AL11: =INDEX(Butin!$B$7:$B$11,AZ11) -> 1 | AM11: =INDEX(Butin!$E$7:$E$11,AZ11) -> 2.5 | AN11: =IF($H11="Boss",INDEX(Butin!$E$28:$K$37,MATCH($B11,Éléments!$C$5:$C$14,1),1),IF($H11="Dragon",INDEX(Butin!$E$41:$K$50,MATCH($B11,Éléments!$C$5:$C$14,1),1),INDEX(Butin!$E$15:$K$24,MATCH($B11,Éléments!$C$5:$C$14,1),1))) -> 0.3 | AO11: =IF($H11="Boss",INDEX(Butin!$E$28:$K$37,MATCH($B11,Éléments!$C$5:$C$14,1),2),IF($H11="Dragon",INDEX(Butin!$E$41:$K$50,MATCH($B11,Éléments!$C$5:$C$14,1),2),INDEX(Butin!$E$15:$K$24,MATCH($B11,Éléments!$C$5:$C$14,1),2))) -> 0.4 | AP11: =IF($H11="Boss",INDEX(Butin!$E$28:$K$37,MATCH($B11,Éléments!$C$5:$C$14,1),3),IF($H11="Dragon",INDEX(Butin!$E$41:$K$50,MATCH($B11,Éléments!$C$5:$C$14,1),3),INDEX(Butin!$E$15:$K$24,MATCH($B11,Éléments!$C$5:$C$14,1),3))) -> 0.22 | AQ11: =IF($H11="Boss",INDEX(Butin!$E$28:$K$37,MATCH($B11,Éléments!$C$5:$C$14,1),4),IF($H11="Dragon",INDEX(Butin!$E$41:$K$50,MATCH($B11,Éléments!$C$5:$C$14,1),4),INDEX(Butin!$E$15:$K$24,MATCH($B11,Éléments!$C$5:$C$14,1),4))) -> 0.06 | AR11: =IF($H11="Boss",INDEX(Butin!$E$28:$K$37,MATCH($B11,Éléments!$C$5:$C$14,1),5),IF($H11="Dragon",INDEX(Butin!$E$41:$K$50,MATCH($B11,Éléments!$C$5:$C$14,1),5),INDEX(Butin!$E$15:$K$24,MATCH($B11,Éléments!$C$5:$C$14,1),5))) -> 0 | AS11: =IF($H11="Boss",INDEX(Butin!$E$28:$K$37,MATCH($B11,Éléments!$C$5:$C$14,1),6),IF($H11="Dragon",INDEX(Butin!$E$41:$K$50,MATCH($B11,Éléments!$C$5:$C$14,1),6),INDEX(Butin!$E$15:$K$24,MATCH($B11,Éléments!$C$5:$C$14,1),6))) -> 0 | AT11: =IF($H11="Boss",INDEX(Butin!$E$28:$K$37,MATCH($B11,Éléments!$C$5:$C$14,1),7),IF($H11="Dragon",INDEX(Butin!$E$41:$K$50,MATCH($B11,Éléments!$C$5:$C$14,1),7),INDEX(Butin!$E$15:$K$24,MATCH($B11,Éléments!$C$5:$C$14,1),7))) -> 0.02 | AU11: =IF(AT11=0,"—",INDEX(Butin!$D$54:$D$63,MATCH($B11,Éléments!$C$5:$C$14,1))&" · "&INDEX(Butin!$F$54:$F$63,MATCH($B11,Éléments!$C$5:$C$14,1))&" · "&INDEX(Butin!$H$54:$H$63,MATCH($B11,Éléments!$C$5:$C$14,1))) -> Heaume du Roi Déchu · Bâton de la Singularité · Bague du Dernier Souffle | AV11: Dragon (Neutre) | AW11: =B11&IF(G11="Oui","|B","|N") -> 9|B | AX11: =(Paramètres!$B$5+(1-Paramètres!$B$5)*((K11-Paramètres!$B$7)/(Paramètres!$B$8-Paramètres!$B$7))^Paramètres!$B$6) -> 0.096416176 | AY11: =MATCH(I11,Rôles!$A$5:$A$13,0) -> 9 | AZ11: =MATCH(H11,Rôles!$A$18:$A$22,0) -> 5
A12: MON-006 | B12: 10 | C12: {=INDEX(Zones!$B$6:$B$35,MATCH(B12,Zones!$A$6:$A$35,0))} -> Village gobelin | D12: {=INDEX(Éléments!$B$5:$B$14,MATCH(B12,Éléments!$C$5:$C$14,1))} -> Forêt | E12: {=INDEX(Éléments!$A$5:$A$14,MATCH(B12,Éléments!$C$5:$C$14,1))} -> Neutre | F12: Chef gobelin | G12: =IF(OR(H12="Boss",H12="Dragon"),"Oui","Non") -> Oui | H12: Boss | I12: Guerrier | J12: Physique | K12: =IF($F$3="",B12,$F$3) -> 10 | L12: {=ROUND(Paramètres!$B$16*(Paramètres!$B$5+(1-Paramètres!$B$5)*((K12-Paramètres!$B$7)/(Paramètres!$B$8-Paramètres!$B$7))^Paramètres!$B$6)*INDEX(Rôles!$B$18:$B$22,AZ12)*INDEX(Rôles!$B$5:$B$13,AY12),0)} -> 1124 | M12: {=ROUND(IF(J12="Physique",1,IF(J12="Mixte",Paramètres!$B$32,0))*Paramètres!$B$12*(Paramètres!$B$5+(1-Paramètres!$B$5)*((K12-Paramètres!$B$7)/(Paramètres!$B$8-Paramètres!$B$7))^Paramètres!$B$6)*INDEX(Rôles!$C$18:$C$22,AZ12)*INDEX(Rôles!$C$5:$C$13,AY12)/(Paramètres!$B$35*(1-Paramètres!$B$36)),0)} -> 71 | N12: {=ROUND(IF(J12="Magique",1,IF(J12="Mixte",Paramètres!$B$32,0))*Paramètres!$B$12*(Paramètres!$B$5+(1-Paramètres!$B$5)*((K12-Paramètres!$B$7)/(Paramètres!$B$8-Paramètres!$B$7))^Paramètres!$B$6)*INDEX(Rôles!$C$18:$C$22,AZ12)*INDEX(Rôles!$C$5:$C$13,AY12)/(Paramètres!$B$35*(1-Paramètres!$B$36)),0)} -> 0 | O12: {=ROUND(Paramètres!$B$18*(Paramètres!$B$5+(1-Paramètres!$B$5)*((K12-Paramètres!$B$7)/(Paramètres!$B$8-Paramètres!$B$7))^Paramètres!$B$6)*INDEX(Rôles!$D$5:$D$13,AY12)*INDEX(Rôles!$D$18:$D$22,AZ12),0)} -> 61 | P12: {=ROUND(Paramètres!$B$19*(Paramètres!$B$5+(1-Paramètres!$B$5)*((K12-Paramètres!$B$7)/(Paramètres!$B$8-Paramètres!$B$7))^Paramètres!$B$6)*INDEX(Rôles!$E$5:$E$13,AY12)*INDEX(Rôles!$D$18:$D$22,AZ12),0)} -> 65 | Q12: {=ROUND(Paramètres!$B$20*(Paramètres!$B$5+(1-Paramètres!$B$5)*((K12-Paramètres!$B$7)/(Paramètres!$B$8-Paramètres!$B$7))^Paramètres!$B$6)*INDEX(Rôles!$F$5:$F$13,AY12),0)} -> 11 | R12: =ROUND(Paramètres!$B$64*$AX12*INDEX(Rôles!$N$5:$N$13,$AY12)*INDEX(Rôles!$I$18:$I$22,$AZ12),0) -> 11 | S12: {=MIN(1,ROUND(Paramètres!$B$21*INDEX(Rôles!$G$5:$G$13,AY12),3))} -> 0.9 | T12: {=MIN(Paramètres!$B$28,ROUND(Paramètres!$B$22*INDEX(Rôles!$H$5:$H$13,AY12),3))} -> 0.05 | U12: {=ROUND(Paramètres!$B$23*INDEX(Rôles!$I$5:$I$13,AY12),3)} -> 0.5 | V12: {=MIN(Paramètres!$B$29,ROUND(Paramètres!$B$24*INDEX(Rôles!$J$5:$J$13,AY12),3))} -> 0.05 | W12: {=MIN(Paramètres!$B$27,ROUND((Paramètres!$B$25+(Paramètres!$B$26-Paramètres!$B$25)*(K12-Paramètres!$B$7)/(Paramètres!$B$8-Paramètres!$B$7))*INDEX(Rôles!$K$5:$K$13,AY12)+INDEX(Rôles!$G$18:$G$22,AZ12),3))} -> 0.273 | X12: =ROUND(1-(1-P12/(P12+(Paramètres!$B$19*(Paramètres!$B$5+(1-Paramètres!$B$5)*((K12-Paramètres!$B$7)/(Paramètres!$B$8-Paramètres!$B$7))^Paramètres!$B$6)*(1-Paramètres!$B$30)/Paramètres!$B$30)))*(1-O12/(O12+(Paramètres!$B$18*(Paramètres!$B$5+(1-Paramètres!$B$5)*((K12-Paramètres!$B$7)/(Paramètres!$B$8-Paramètres!$B$7))^Paramètres!$B$6)*(1-Paramètres!$B$31)/Paramètres!$B$31))),3) -> 0.417 | Y12: =ROUND(O12/(O12+(Paramètres!$B$18*(Paramètres!$B$5+(1-Paramètres!$B$5)*((K12-Paramètres!$B$7)/(Paramètres!$B$8-Paramètres!$B$7))^Paramètres!$B$6)*(1-Paramètres!$B$31)/Paramètres!$B$31)),3) -> 0.188 | Z12: {=IF(E12="Neutre",0,MIN(1,INDEX(Rôles!$L$5:$L$13,AY12)+INDEX(Rôles!$F$18:$F$22,AZ12)))} -> 0 | AA12: {=ROUND(INDEX(Rôles!$C$18:$C$22,AZ12)*INDEX(Rôles!$C$5:$C$13,AY12),4)} -> 0.03 | AB12: {=ROUND(INDEX(Rôles!$B$18:$B$22,AZ12)*INDEX(Rôles!$B$5:$B$13,AY12),2)} -> 13.8 | AC12: {=INDEX(Rôles!$E$18:$E$22,AZ12)} -> 8 | AD12: {=INDEX(Éléments!$F$5:$F$14,MATCH(E12,Éléments!$A$5:$A$14,0))} -> — | AE12: {=INDEX(Éléments!$G$5:$G$14,MATCH(E12,Éléments!$A$5:$A$14,0))} -> — | AF12: Assommé | AG12: 0.3 | AH12: Intimidé | AI12: 0.3 | AJ12: {=ROUND(ROUND(Paramètres!$B$49*K12^Paramètres!$B$50,0)*INDEX(Rôles!$E$18:$E$22,AZ12),0)} -> 856 | AK12: {=ROUND(ROUND(Paramètres!$B$53*K12^Paramètres!$B$54,0)*INDEX(Rôles!$E$18:$E$22,AZ12),0)} -> 536 | AL12: =INDEX(Butin!$B$7:$B$11,AZ12) -> 1 | AM12: =INDEX(Butin!$E$7:$E$11,AZ12) -> 1.4 | AN12: =IF($H12="Boss",INDEX(Butin!$E$28:$K$37,MATCH($B12,Éléments!$C$5:$C$14,1),1),IF($H12="Dragon",INDEX(Butin!$E$41:$K$50,MATCH($B12,Éléments!$C$5:$C$14,1),1),INDEX(Butin!$E$15:$K$24,MATCH($B12,Éléments!$C$5:$C$14,1),1))) -> 0.4 | AO12: =IF($H12="Boss",INDEX(Butin!$E$28:$K$37,MATCH($B12,Éléments!$C$5:$C$14,1),2),IF($H12="Dragon",INDEX(Butin!$E$41:$K$50,MATCH($B12,Éléments!$C$5:$C$14,1),2),INDEX(Butin!$E$15:$K$24,MATCH($B12,Éléments!$C$5:$C$14,1),2))) -> 0.4 | AP12: =IF($H12="Boss",INDEX(Butin!$E$28:$K$37,MATCH($B12,Éléments!$C$5:$C$14,1),3),IF($H12="Dragon",INDEX(Butin!$E$41:$K$50,MATCH($B12,Éléments!$C$5:$C$14,1),3),INDEX(Butin!$E$15:$K$24,MATCH($B12,Éléments!$C$5:$C$14,1),3))) -> 0.15 | AQ12: =IF($H12="Boss",INDEX(Butin!$E$28:$K$37,MATCH($B12,Éléments!$C$5:$C$14,1),4),IF($H12="Dragon",INDEX(Butin!$E$41:$K$50,MATCH($B12,Éléments!$C$5:$C$14,1),4),INDEX(Butin!$E$15:$K$24,MATCH($B12,Éléments!$C$5:$C$14,1),4))) -> 0.04 | AR12: =IF($H12="Boss",INDEX(Butin!$E$28:$K$37,MATCH($B12,Éléments!$C$5:$C$14,1),5),IF($H12="Dragon",INDEX(Butin!$E$41:$K$50,MATCH($B12,Éléments!$C$5:$C$14,1),5),INDEX(Butin!$E$15:$K$24,MATCH($B12,Éléments!$C$5:$C$14,1),5))) -> 0 | AS12: =IF($H12="Boss",INDEX(Butin!$E$28:$K$37,MATCH($B12,Éléments!$C$5:$C$14,1),6),IF($H12="Dragon",INDEX(Butin!$E$41:$K$50,MATCH($B12,Éléments!$C$5:$C$14,1),6),INDEX(Butin!$E$15:$K$24,MATCH($B12,Éléments!$C$5:$C$14,1),6))) -> 0 | AT12: =IF($H12="Boss",INDEX(Butin!$E$28:$K$37,MATCH($B12,Éléments!$C$5:$C$14,1),7),IF($H12="Dragon",INDEX(Butin!$E$41:$K$50,MATCH($B12,Éléments!$C$5:$C$14,1),7),INDEX(Butin!$E$15:$K$24,MATCH($B12,Éléments!$C$5:$C$14,1),7))) -> 0.01 | AU12: =IF(AT12=0,"—",INDEX(Butin!$D$54:$D$63,MATCH($B12,Éléments!$C$5:$C$14,1))&" · "&INDEX(Butin!$F$54:$F$63,MATCH($B12,Éléments!$C$5:$C$14,1))&" · "&INDEX(Butin!$H$54:$H$63,MATCH($B12,Éléments!$C$5:$C$14,1))) -> Heaume du Roi Déchu · Bâton de la Singularité · Bague du Dernier Souffle | AV12: Chef Gobbelin (Boss) | AW12: =B12&IF(G12="Oui","|B","|N") -> 10|B | AX12: =(Paramètres!$B$5+(1-Paramètres!$B$5)*((K12-Paramètres!$B$7)/(Paramètres!$B$8-Paramètres!$B$7))^Paramètres!$B$6) -> 0.10346288 | AY12: =MATCH(I12,Rôles!$A$5:$A$13,0) -> 3 | AZ12: =MATCH(H12,Rôles!$A$18:$A$22,0) -> 4
A13: MON-007 | B13: 10 | C13: {=INDEX(Zones!$B$6:$B$35,MATCH(B13,Zones!$A$6:$A$35,0))} -> Village gobelin | D13: {=INDEX(Éléments!$B$5:$B$14,MATCH(B13,Éléments!$C$5:$C$14,1))} -> Forêt | E13: {=INDEX(Éléments!$A$5:$A$14,MATCH(B13,Éléments!$C$5:$C$14,1))} -> Neutre | F13: Gobelin | G13: =IF(OR(H13="Boss",H13="Dragon"),"Oui","Non") -> Non | H13: Faible | I13: Assassin | J13: Physique | K13: =IF($F$3="",B13,$F$3) -> 10 | L13: {=ROUND(Paramètres!$B$16*(Paramètres!$B$5+(1-Paramètres!$B$5)*((K13-Paramètres!$B$7)/(Paramètres!$B$8-Paramètres!$B$7))^Paramètres!$B$6)*INDEX(Rôles!$B$18:$B$22,AZ13)*INDEX(Rôles!$B$5:$B$13,AY13),0)} -> 92 | M13: {=ROUND(IF(J13="Physique",1,IF(J13="Mixte",Paramètres!$B$32,0))*Paramètres!$B$12*(Paramètres!$B$5+(1-Paramètres!$B$5)*((K13-Paramètres!$B$7)/(Paramètres!$B$8-Paramètres!$B$7))^Paramètres!$B$6)*INDEX(Rôles!$C$18:$C$22,AZ13)*INDEX(Rôles!$C$5:$C$13,AY13)/(Paramètres!$B$35*(1-Paramètres!$B$36)),0)} -> 28 | N13: {=ROUND(IF(J13="Magique",1,IF(J13="Mixte",Paramètres!$B$32,0))*Paramètres!$B$12*(Paramètres!$B$5+(1-Paramètres!$B$5)*((K13-Paramètres!$B$7)/(Paramètres!$B$8-Paramètres!$B$7))^Paramètres!$B$6)*INDEX(Rôles!$C$18:$C$22,AZ13)*INDEX(Rôles!$C$5:$C$13,AY13)/(Paramètres!$B$35*(1-Paramètres!$B$36)),0)} -> 0 | O13: {=ROUND(Paramètres!$B$18*(Paramètres!$B$5+(1-Paramètres!$B$5)*((K13-Paramètres!$B$7)/(Paramètres!$B$8-Paramètres!$B$7))^Paramètres!$B$6)*INDEX(Rôles!$D$5:$D$13,AY13)*INDEX(Rôles!$D$18:$D$22,AZ13),0)} -> 22 | P13: {=ROUND(Paramètres!$B$19*(Paramètres!$B$5+(1-Paramètres!$B$5)*((K13-Paramètres!$B$7)/(Paramètres!$B$8-Paramètres!$B$7))^Paramètres!$B$6)*INDEX(Rôles!$E$5:$E$13,AY13)*INDEX(Rôles!$D$18:$D$22,AZ13),0)} -> 17 | Q13: {=ROUND(Paramètres!$B$20*(Paramètres!$B$5+(1-Paramètres!$B$5)*((K13-Paramètres!$B$7)/(Paramètres!$B$8-Paramètres!$B$7))^Paramètres!$B$6)*INDEX(Rôles!$F$5:$F$13,AY13),0)} -> 20 | R13: =ROUND(Paramètres!$B$64*$AX13*INDEX(Rôles!$N$5:$N$13,$AY13)*INDEX(Rôles!$I$18:$I$22,$AZ13),0) -> 14 | S13: {=MIN(1,ROUND(Paramètres!$B$21*INDEX(Rôles!$G$5:$G$13,AY13),3))} -> 1 | T13: {=MIN(Paramètres!$B$28,ROUND(Paramètres!$B$22*INDEX(Rôles!$H$5:$H$13,AY13),3))} -> 0.08 | U13: {=ROUND(Paramètres!$B$23*INDEX(Rôles!$I$5:$I$13,AY13),3)} -> 0.7 | V13: {=MIN(Paramètres!$B$29,ROUND(Paramètres!$B$24*INDEX(Rôles!$J$5:$J$13,AY13),3))} -> 0.06 | W13: {=MIN(Paramètres!$B$27,ROUND((Paramètres!$B$25+(Paramètres!$B$26-Paramètres!$B$25)*(K13-Paramètres!$B$7)/(Paramètres!$B$8-Paramètres!$B$7))*INDEX(Rôles!$K$5:$K$13,AY13)+INDEX(Rôles!$G$18:$G$22,AZ13),3))} -> 0.058 | X13: =ROUND(1-(1-P13/(P13+(Paramètres!$B$19*(Paramètres!$B$5+(1-Paramètres!$B$5)*((K13-Paramètres!$B$7)/(Paramètres!$B$8-Paramètres!$B$7))^Paramètres!$B$6)*(1-Paramètres!$B$30)/Paramètres!$B$30)))*(1-O13/(O13+(Paramètres!$B$18*(Paramètres!$B$5+(1-Paramètres!$B$5)*((K13-Paramètres!$B$7)/(Paramètres!$B$8-Paramètres!$B$7))^Paramètres!$B$6)*(1-Paramètres!$B$31)/Paramètres!$B$31))),3) -> 0.163 | Y13: =ROUND(O13/(O13+(Paramètres!$B$18*(Paramètres!$B$5+(1-Paramètres!$B$5)*((K13-Paramètres!$B$7)/(Paramètres!$B$8-Paramètres!$B$7))^Paramètres!$B$6)*(1-Paramètres!$B$31)/Paramètres!$B$31)),3) -> 0.077 | Z13: {=IF(E13="Neutre",0,MIN(1,INDEX(Rôles!$L$5:$L$13,AY13)+INDEX(Rôles!$F$18:$F$22,AZ13)))} -> 0 | AA13: {=ROUND(INDEX(Rôles!$C$18:$C$22,AZ13)*INDEX(Rôles!$C$5:$C$13,AY13),4)} -> 0.012 | AB13: {=ROUND(INDEX(Rôles!$B$18:$B$22,AZ13)*INDEX(Rôles!$B$5:$B$13,AY13),2)} -> 1.13 | AC13: {=INDEX(Rôles!$E$18:$E$22,AZ13)} -> 0.7 | AD13: {=INDEX(Éléments!$F$5:$F$14,MATCH(E13,Éléments!$A$5:$A$14,0))} -> — | AE13: {=INDEX(Éléments!$G$5:$G$14,MATCH(E13,Éléments!$A$5:$A$14,0))} -> — | AF13: Saignement | AG13: 0.15 | AJ13: {=ROUND(ROUND(Paramètres!$B$49*K13^Paramètres!$B$50,0)*INDEX(Rôles!$E$18:$E$22,AZ13),0)} -> 75 | AK13: {=ROUND(ROUND(Paramètres!$B$53*K13^Paramètres!$B$54,0)*INDEX(Rôles!$E$18:$E$22,AZ13),0)} -> 47 | AL13: =INDEX(Butin!$B$7:$B$11,AZ13) -> 0.03 | AM13: =INDEX(Butin!$E$7:$E$11,AZ13) -> 0.03 | AN13: =IF($H13="Boss",INDEX(Butin!$E$28:$K$37,MATCH($B13,Éléments!$C$5:$C$14,1),1),IF($H13="Dragon",INDEX(Butin!$E$41:$K$50,MATCH($B13,Éléments!$C$5:$C$14,1),1),INDEX(Butin!$E$15:$K$24,MATCH($B13,Éléments!$C$5:$C$14,1),1))) -> 0.8 | AO13: =IF($H13="Boss",INDEX(Butin!$E$28:$K$37,MATCH($B13,Éléments!$C$5:$C$14,1),2),IF($H13="Dragon",INDEX(Butin!$E$41:$K$50,MATCH($B13,Éléments!$C$5:$C$14,1),2),INDEX(Butin!$E$15:$K$24,MATCH($B13,Éléments!$C$5:$C$14,1),2))) -> 0.2 | AP13: =IF($H13="Boss",INDEX(Butin!$E$28:$K$37,MATCH($B13,Éléments!$C$5:$C$14,1),3),IF($H13="Dragon",INDEX(Butin!$E$41:$K$50,MATCH($B13,Éléments!$C$5:$C$14,1),3),INDEX(Butin!$E$15:$K$24,MATCH($B13,Éléments!$C$5:$C$14,1),3))) -> 0 | AQ13: =IF($H13="Boss",INDEX(Butin!$E$28:$K$37,MATCH($B13,Éléments!$C$5:$C$14,1),4),IF($H13="Dragon",INDEX(Butin!$E$41:$K$50,MATCH($B13,Éléments!$C$5:$C$14,1),4),INDEX(Butin!$E$15:$K$24,MATCH($B13,Éléments!$C$5:$C$14,1),4))) -> 0 | AR13: =IF($H13="Boss",INDEX(Butin!$E$28:$K$37,MATCH($B13,Éléments!$C$5:$C$14,1),5),IF($H13="Dragon",INDEX(Butin!$E$41:$K$50,MATCH($B13,Éléments!$C$5:$C$14,1),5),INDEX(Butin!$E$15:$K$24,MATCH($B13,Éléments!$C$5:$C$14,1),5))) -> 0 | AS13: =IF($H13="Boss",INDEX(Butin!$E$28:$K$37,MATCH($B13,Éléments!$C$5:$C$14,1),6),IF($H13="Dragon",INDEX(Butin!$E$41:$K$50,MATCH($B13,Éléments!$C$5:$C$14,1),6),INDEX(Butin!$E$15:$K$24,MATCH($B13,Éléments!$C$5:$C$14,1),6))) -> 0 | AT13: =IF($H13="Boss",INDEX(Butin!$E$28:$K$37,MATCH($B13,Éléments!$C$5:$C$14,1),7),IF($H13="Dragon",INDEX(Butin!$E$41:$K$50,MATCH($B13,Éléments!$C$5:$C$14,1),7),INDEX(Butin!$E$15:$K$24,MATCH($B13,Éléments!$C$5:$C$14,1),7))) -> 0 | AU13: =IF(AT13=0,"—",INDEX(Butin!$D$54:$D$63,MATCH($B13,Éléments!$C$5:$C$14,1))&" · "&INDEX(Butin!$F$54:$F$63,MATCH($B13,Éléments!$C$5:$C$14,1))&" · "&INDEX(Butin!$H$54:$H$63,MATCH($B13,Éléments!$C$5:$C$14,1))) -> — | AV13: Gobbelin | AW13: =B13&IF(G13="Oui","|B","|N") -> 10|N | AX13: =(Paramètres!$B$5+(1-Paramètres!$B$5)*((K13-Paramètres!$B$7)/(Paramètres!$B$8-Paramètres!$B$7))^Paramètres!$B$6) -> 0.10346288 | AY13: =MATCH(I13,Rôles!$A$5:$A$13,0) -> 7 | AZ13: =MATCH(H13,Rôles!$A$18:$A$22,0) -> 1
A14: MON-008 | B14: 10 | C14: {=INDEX(Zones!$B$6:$B$35,MATCH(B14,Zones!$A$6:$A$35,0))} -> Village gobelin | D14: {=INDEX(Éléments!$B$5:$B$14,MATCH(B14,Éléments!$C$5:$C$14,1))} -> Forêt | E14: {=INDEX(Éléments!$A$5:$A$14,MATCH(B14,Éléments!$C$5:$C$14,1))} -> Neutre | F14: Guerrier gobelin | G14: =IF(OR(H14="Boss",H14="Dragon"),"Oui","Non") -> Non | H14: Normal | I14: Guerrier | J14: Physique | K14: =IF($F$3="",B14,$F$3) -> 10 | L14: {=ROUND(Paramètres!$B$16*(Paramètres!$B$5+(1-Paramètres!$B$5)*((K14-Paramètres!$B$7)/(Paramètres!$B$8-Paramètres!$B$7))^Paramètres!$B$6)*INDEX(Rôles!$B$18:$B$22,AZ14)*INDEX(Rôles!$B$5:$B$13,AY14),0)} -> 187 | M14: {=ROUND(IF(J14="Physique",1,IF(J14="Mixte",Paramètres!$B$32,0))*Paramètres!$B$12*(Paramètres!$B$5+(1-Paramètres!$B$5)*((K14-Paramètres!$B$7)/(Paramètres!$B$8-Paramètres!$B$7))^Paramètres!$B$6)*INDEX(Rôles!$C$18:$C$22,AZ14)*INDEX(Rôles!$C$5:$C$13,AY14)/(Paramètres!$B$35*(1-Paramètres!$B$36)),0)} -> 35 | N14: {=ROUND(IF(J14="Magique",1,IF(J14="Mixte",Paramètres!$B$32,0))*Paramètres!$B$12*(Paramètres!$B$5+(1-Paramètres!$B$5)*((K14-Paramètres!$B$7)/(Paramètres!$B$8-Paramètres!$B$7))^Paramètres!$B$6)*INDEX(Rôles!$C$18:$C$22,AZ14)*INDEX(Rôles!$C$5:$C$13,AY14)/(Paramètres!$B$35*(1-Paramètres!$B$36)),0)} -> 0 | O14: {=ROUND(Paramètres!$B$18*(Paramètres!$B$5+(1-Paramètres!$B$5)*((K14-Paramètres!$B$7)/(Paramètres!$B$8-Paramètres!$B$7))^Paramètres!$B$6)*INDEX(Rôles!$D$5:$D$13,AY14)*INDEX(Rôles!$D$18:$D$22,AZ14),0)} -> 47 | P14: {=ROUND(Paramètres!$B$19*(Paramètres!$B$5+(1-Paramètres!$B$5)*((K14-Paramètres!$B$7)/(Paramètres!$B$8-Paramètres!$B$7))^Paramètres!$B$6)*INDEX(Rôles!$E$5:$E$13,AY14)*INDEX(Rôles!$D$18:$D$22,AZ14),0)} -> 50 | Q14: {=ROUND(Paramètres!$B$20*(Paramètres!$B$5+(1-Paramètres!$B$5)*((K14-Paramètres!$B$7)/(Paramètres!$B$8-Paramètres!$B$7))^Paramètres!$B$6)*INDEX(Rôles!$F$5:$F$13,AY14),0)} -> 11 | R14: =ROUND(Paramètres!$B$64*$AX14*INDEX(Rôles!$N$5:$N$13,$AY14)*INDEX(Rôles!$I$18:$I$22,$AZ14),0) -> 10 | S14: {=MIN(1,ROUND(Paramètres!$B$21*INDEX(Rôles!$G$5:$G$13,AY14),3))} -> 0.9 | T14: {=MIN(Paramètres!$B$28,ROUND(Paramètres!$B$22*INDEX(Rôles!$H$5:$H$13,AY14),3))} -> 0.05 | U14: {=ROUND(Paramètres!$B$23*INDEX(Rôles!$I$5:$I$13,AY14),3)} -> 0.5 | V14: {=MIN(Paramètres!$B$29,ROUND(Paramètres!$B$24*INDEX(Rôles!$J$5:$J$13,AY14),3))} -> 0.05 | W14: {=MIN(Paramètres!$B$27,ROUND((Paramètres!$B$25+(Paramètres!$B$26-Paramètres!$B$25)*(K14-Paramètres!$B$7)/(Paramètres!$B$8-Paramètres!$B$7))*INDEX(Rôles!$K$5:$K$13,AY14)+INDEX(Rôles!$G$18:$G$22,AZ14),3))} -> 0.073 | X14: =ROUND(1-(1-P14/(P14+(Paramètres!$B$19*(Paramètres!$B$5+(1-Paramètres!$B$5)*((K14-Paramètres!$B$7)/(Paramètres!$B$8-Paramètres!$B$7))^Paramètres!$B$6)*(1-Paramètres!$B$30)/Paramètres!$B$30)))*(1-O14/(O14+(Paramètres!$B$18*(Paramètres!$B$5+(1-Paramètres!$B$5)*((K14-Paramètres!$B$7)/(Paramètres!$B$8-Paramètres!$B$7))^Paramètres!$B$6)*(1-Paramètres!$B$31)/Paramètres!$B$31))),3) -> 0.348 | Y14: =ROUND(O14/(O14+(Paramètres!$B$18*(Paramètres!$B$5+(1-Paramètres!$B$5)*((K14-Paramètres!$B$7)/(Paramètres!$B$8-Paramètres!$B$7))^Paramètres!$B$6)*(1-Paramètres!$B$31)/Paramètres!$B$31)),3) -> 0.151 | Z14: {=IF(E14="Neutre",0,MIN(1,INDEX(Rôles!$L$5:$L$13,AY14)+INDEX(Rôles!$F$18:$F$22,AZ14)))} -> 0 | AA14: {=ROUND(INDEX(Rôles!$C$18:$C$22,AZ14)*INDEX(Rôles!$C$5:$C$13,AY14),4)} -> 0.015 | AB14: {=ROUND(INDEX(Rôles!$B$18:$B$22,AZ14)*INDEX(Rôles!$B$5:$B$13,AY14),2)} -> 2.3 | AC14: {=INDEX(Rôles!$E$18:$E$22,AZ14)} -> 1 | AD14: {=INDEX(Éléments!$F$5:$F$14,MATCH(E14,Éléments!$A$5:$A$14,0))} -> — | AE14: {=INDEX(Éléments!$G$5:$G$14,MATCH(E14,Éléments!$A$5:$A$14,0))} -> — | AF14: Saignement | AG14: 0.15 | AH14: Assommé | AI14: 0.1 | AJ14: {=ROUND(ROUND(Paramètres!$B$49*K14^Paramètres!$B$50,0)*INDEX(Rôles!$E$18:$E$22,AZ14),0)} -> 107 | AK14: {=ROUND(ROUND(Paramètres!$B$53*K14^Paramètres!$B$54,0)*INDEX(Rôles!$E$18:$E$22,AZ14),0)} -> 67 | AL14: =INDEX(Butin!$B$7:$B$11,AZ14) -> 0.05 | AM14: =INDEX(Butin!$E$7:$E$11,AZ14) -> 0.05 | AN14: =IF($H14="Boss",INDEX(Butin!$E$28:$K$37,MATCH($B14,Éléments!$C$5:$C$14,1),1),IF($H14="Dragon",INDEX(Butin!$E$41:$K$50,MATCH($B14,Éléments!$C$5:$C$14,1),1),INDEX(Butin!$E$15:$K$24,MATCH($B14,Éléments!$C$5:$C$14,1),1))) -> 0.8 | AO14: =IF($H14="Boss",INDEX(Butin!$E$28:$K$37,MATCH($B14,Éléments!$C$5:$C$14,1),2),IF($H14="Dragon",INDEX(Butin!$E$41:$K$50,MATCH($B14,Éléments!$C$5:$C$14,1),2),INDEX(Butin!$E$15:$K$24,MATCH($B14,Éléments!$C$5:$C$14,1),2))) -> 0.2 | AP14: =IF($H14="Boss",INDEX(Butin!$E$28:$K$37,MATCH($B14,Éléments!$C$5:$C$14,1),3),IF($H14="Dragon",INDEX(Butin!$E$41:$K$50,MATCH($B14,Éléments!$C$5:$C$14,1),3),INDEX(Butin!$E$15:$K$24,MATCH($B14,Éléments!$C$5:$C$14,1),3))) -> 0 | AQ14: =IF($H14="Boss",INDEX(Butin!$E$28:$K$37,MATCH($B14,Éléments!$C$5:$C$14,1),4),IF($H14="Dragon",INDEX(Butin!$E$41:$K$50,MATCH($B14,Éléments!$C$5:$C$14,1),4),INDEX(Butin!$E$15:$K$24,MATCH($B14,Éléments!$C$5:$C$14,1),4))) -> 0 | AR14: =IF($H14="Boss",INDEX(Butin!$E$28:$K$37,MATCH($B14,Éléments!$C$5:$C$14,1),5),IF($H14="Dragon",INDEX(Butin!$E$41:$K$50,MATCH($B14,Éléments!$C$5:$C$14,1),5),INDEX(Butin!$E$15:$K$24,MATCH($B14,Éléments!$C$5:$C$14,1),5))) -> 0 | AS14: =IF($H14="Boss",INDEX(Butin!$E$28:$K$37,MATCH($B14,Éléments!$C$5:$C$14,1),6),IF($H14="Dragon",INDEX(Butin!$E$41:$K$50,MATCH($B14,Éléments!$C$5:$C$14,1),6),INDEX(Butin!$E$15:$K$24,MATCH($B14,Éléments!$C$5:$C$14,1),6))) -> 0 | AT14: =IF($H14="Boss",INDEX(Butin!$E$28:$K$37,MATCH($B14,Éléments!$C$5:$C$14,1),7),IF($H14="Dragon",INDEX(Butin!$E$41:$K$50,MATCH($B14,Éléments!$C$5:$C$14,1),7),INDEX(Butin!$E$15:$K$24,MATCH($B14,Éléments!$C$5:$C$14,1),7))) -> 0 | AU14: =IF(AT14=0,"—",INDEX(Butin!$D$54:$D$63,MATCH($B14,Éléments!$C$5:$C$14,1))&" · "&INDEX(Butin!$F$54:$F$63,MATCH($B14,Éléments!$C$5:$C$14,1))&" · "&INDEX(Butin!$H$54:$H$63,MATCH($B14,Éléments!$C$5:$C$14,1))) -> — | AV14: Guerrier Gobbelin | AW14: =B14&IF(G14="Oui","|B","|N") -> 10|N | AX14: =(Paramètres!$B$5+(1-Paramètres!$B$5)*((K14-Paramètres!$B$7)/(Paramètres!$B$8-Paramètres!$B$7))^Paramètres!$B$6) -> 0.10346288 | AY14: =MATCH(I14,Rôles!$A$5:$A$13,0) -> 3 | AZ14: =MATCH(H14,Rôles!$A$18:$A$22,0) -> 2
A15: MON-009 | B15: 10 | C15: {=INDEX(Zones!$B$6:$B$35,MATCH(B15,Zones!$A$6:$A$35,0))} -> Village gobelin | D15: {=INDEX(Éléments!$B$5:$B$14,MATCH(B15,Éléments!$C$5:$C$14,1))} -> Forêt | E15: {=INDEX(Éléments!$A$5:$A$14,MATCH(B15,Éléments!$C$5:$C$14,1))} -> Neutre | F15: Chaman gobelin | G15: =IF(OR(H15="Boss",H15="Dragon"),"Oui","Non") -> Non | H15: Normal | I15: Soutien | J15: Magique | K15: =IF($F$3="",B15,$F$3) -> 10 | L15: {=ROUND(Paramètres!$B$16*(Paramètres!$B$5+(1-Paramètres!$B$5)*((K15-Paramètres!$B$7)/(Paramètres!$B$8-Paramètres!$B$7))^Paramètres!$B$6)*INDEX(Rôles!$B$18:$B$22,AZ15)*INDEX(Rôles!$B$5:$B$13,AY15),0)} -> 139 | M15: {=ROUND(IF(J15="Physique",1,IF(J15="Mixte",Paramètres!$B$32,0))*Paramètres!$B$12*(Paramètres!$B$5+(1-Paramètres!$B$5)*((K15-Paramètres!$B$7)/(Paramètres!$B$8-Paramètres!$B$7))^Paramètres!$B$6)*INDEX(Rôles!$C$18:$C$22,AZ15)*INDEX(Rôles!$C$5:$C$13,AY15)/(Paramètres!$B$35*(1-Paramètres!$B$36)),0)} -> 0 | N15: {=ROUND(IF(J15="Magique",1,IF(J15="Mixte",Paramètres!$B$32,0))*Paramètres!$B$12*(Paramètres!$B$5+(1-Paramètres!$B$5)*((K15-Paramètres!$B$7)/(Paramètres!$B$8-Paramètres!$B$7))^Paramètres!$B$6)*INDEX(Rôles!$C$18:$C$22,AZ15)*INDEX(Rôles!$C$5:$C$13,AY15)/(Paramètres!$B$35*(1-Paramètres!$B$36)),0)} -> 28 | O15: {=ROUND(Paramètres!$B$18*(Paramètres!$B$5+(1-Paramètres!$B$5)*((K15-Paramètres!$B$7)/(Paramètres!$B$8-Paramètres!$B$7))^Paramètres!$B$6)*INDEX(Rôles!$D$5:$D$13,AY15)*INDEX(Rôles!$D$18:$D$22,AZ15),0)} -> 56 | P15: {=ROUND(Paramètres!$B$19*(Paramètres!$B$5+(1-Paramètres!$B$5)*((K15-Paramètres!$B$7)/(Paramètres!$B$8-Paramètres!$B$7))^Paramètres!$B$6)*INDEX(Rôles!$E$5:$E$13,AY15)*INDEX(Rôles!$D$18:$D$22,AZ15),0)} -> 21 | Q15: {=ROUND(Paramètres!$B$20*(Paramètres!$B$5+(1-Paramètres!$B$5)*((K15-Paramètres!$B$7)/(Paramètres!$B$8-Paramètres!$B$7))^Paramètres!$B$6)*INDEX(Rôles!$F$5:$F$13,AY15),0)} -> 11 | R15: =ROUND(Paramètres!$B$64*$AX15*INDEX(Rôles!$N$5:$N$13,$AY15)*INDEX(Rôles!$I$18:$I$22,$AZ15),0) -> 10 | S15: {=MIN(1,ROUND(Paramètres!$B$21*INDEX(Rôles!$G$5:$G$13,AY15),3))} -> 0.9 | T15: {=MIN(Paramètres!$B$28,ROUND(Paramètres!$B$22*INDEX(Rôles!$H$5:$H$13,AY15),3))} -> 0.04 | U15: {=ROUND(Paramètres!$B$23*INDEX(Rôles!$I$5:$I$13,AY15),3)} -> 0.5 | V15: {=MIN(Paramètres!$B$29,ROUND(Paramètres!$B$24*INDEX(Rôles!$J$5:$J$13,AY15),3))} -> 0.04 | W15: {=MIN(Paramètres!$B$27,ROUND((Paramètres!$B$25+(Paramètres!$B$26-Paramètres!$B$25)*(K15-Paramètres!$B$7)/(Paramètres!$B$8-Paramètres!$B$7))*INDEX(Rôles!$K$5:$K$13,AY15)+INDEX(Rôles!$G$18:$G$22,AZ15),3))} -> 0.095 | X15: =ROUND(1-(1-P15/(P15+(Paramètres!$B$19*(Paramètres!$B$5+(1-Paramètres!$B$5)*((K15-Paramètres!$B$7)/(Paramètres!$B$8-Paramètres!$B$7))^Paramètres!$B$6)*(1-Paramètres!$B$30)/Paramètres!$B$30)))*(1-O15/(O15+(Paramètres!$B$18*(Paramètres!$B$5+(1-Paramètres!$B$5)*((K15-Paramètres!$B$7)/(Paramètres!$B$8-Paramètres!$B$7))^Paramètres!$B$6)*(1-Paramètres!$B$31)/Paramètres!$B$31))),3) -> 0.268 | Y15: =ROUND(O15/(O15+(Paramètres!$B$18*(Paramètres!$B$5+(1-Paramètres!$B$5)*((K15-Paramètres!$B$7)/(Paramètres!$B$8-Paramètres!$B$7))^Paramètres!$B$6)*(1-Paramètres!$B$31)/Paramètres!$B$31)),3) -> 0.175 | Z15: {=IF(E15="Neutre",0,MIN(1,INDEX(Rôles!$L$5:$L$13,AY15)+INDEX(Rôles!$F$18:$F$22,AZ15)))} -> 0 | AA15: {=ROUND(INDEX(Rôles!$C$18:$C$22,AZ15)*INDEX(Rôles!$C$5:$C$13,AY15),4)} -> 0.012 | AB15: {=ROUND(INDEX(Rôles!$B$18:$B$22,AZ15)*INDEX(Rôles!$B$5:$B$13,AY15),2)} -> 1.7 | AC15: {=INDEX(Rôles!$E$18:$E$22,AZ15)} -> 1 | AD15: {=INDEX(Éléments!$F$5:$F$14,MATCH(E15,Éléments!$A$5:$A$14,0))} -> — | AE15: {=INDEX(Éléments!$G$5:$G$14,MATCH(E15,Éléments!$A$5:$A$14,0))} -> — | AF15: Intimidé | AG15: 0.3 | AJ15: {=ROUND(ROUND(Paramètres!$B$49*K15^Paramètres!$B$50,0)*INDEX(Rôles!$E$18:$E$22,AZ15),0)} -> 107 | AK15: {=ROUND(ROUND(Paramètres!$B$53*K15^Paramètres!$B$54,0)*INDEX(Rôles!$E$18:$E$22,AZ15),0)} -> 67 | AL15: =INDEX(Butin!$B$7:$B$11,AZ15) -> 0.05 | AM15: =INDEX(Butin!$E$7:$E$11,AZ15) -> 0.05 | AN15: =IF($H15="Boss",INDEX(Butin!$E$28:$K$37,MATCH($B15,Éléments!$C$5:$C$14,1),1),IF($H15="Dragon",INDEX(Butin!$E$41:$K$50,MATCH($B15,Éléments!$C$5:$C$14,1),1),INDEX(Butin!$E$15:$K$24,MATCH($B15,Éléments!$C$5:$C$14,1),1))) -> 0.8 | AO15: =IF($H15="Boss",INDEX(Butin!$E$28:$K$37,MATCH($B15,Éléments!$C$5:$C$14,1),2),IF($H15="Dragon",INDEX(Butin!$E$41:$K$50,MATCH($B15,Éléments!$C$5:$C$14,1),2),INDEX(Butin!$E$15:$K$24,MATCH($B15,Éléments!$C$5:$C$14,1),2))) -> 0.2 | AP15: =IF($H15="Boss",INDEX(Butin!$E$28:$K$37,MATCH($B15,Éléments!$C$5:$C$14,1),3),IF($H15="Dragon",INDEX(Butin!$E$41:$K$50,MATCH($B15,Éléments!$C$5:$C$14,1),3),INDEX(Butin!$E$15:$K$24,MATCH($B15,Éléments!$C$5:$C$14,1),3))) -> 0 | AQ15: =IF($H15="Boss",INDEX(Butin!$E$28:$K$37,MATCH($B15,Éléments!$C$5:$C$14,1),4),IF($H15="Dragon",INDEX(Butin!$E$41:$K$50,MATCH($B15,Éléments!$C$5:$C$14,1),4),INDEX(Butin!$E$15:$K$24,MATCH($B15,Éléments!$C$5:$C$14,1),4))) -> 0 | AR15: =IF($H15="Boss",INDEX(Butin!$E$28:$K$37,MATCH($B15,Éléments!$C$5:$C$14,1),5),IF($H15="Dragon",INDEX(Butin!$E$41:$K$50,MATCH($B15,Éléments!$C$5:$C$14,1),5),INDEX(Butin!$E$15:$K$24,MATCH($B15,Éléments!$C$5:$C$14,1),5))) -> 0 | AS15: =IF($H15="Boss",INDEX(Butin!$E$28:$K$37,MATCH($B15,Éléments!$C$5:$C$14,1),6),IF($H15="Dragon",INDEX(Butin!$E$41:$K$50,MATCH($B15,Éléments!$C$5:$C$14,1),6),INDEX(Butin!$E$15:$K$24,MATCH($B15,Éléments!$C$5:$C$14,1),6))) -> 0 | AT15: =IF($H15="Boss",INDEX(Butin!$E$28:$K$37,MATCH($B15,Éléments!$C$5:$C$14,1),7),IF($H15="Dragon",INDEX(Butin!$E$41:$K$50,MATCH($B15,Éléments!$C$5:$C$14,1),7),INDEX(Butin!$E$15:$K$24,MATCH($B15,Éléments!$C$5:$C$14,1),7))) -> 0 | AU15: =IF(AT15=0,"—",INDEX(Butin!$D$54:$D$63,MATCH($B15,Éléments!$C$5:$C$14,1))&" · "&INDEX(Butin!$F$54:$F$63,MATCH($B15,Éléments!$C$5:$C$14,1))&" · "&INDEX(Butin!$H$54:$H$63,MATCH($B15,Éléments!$C$5:$C$14,1))) -> — | AV15: Chaman Gobbelin | AW15: =B15&IF(G15="Oui","|B","|N") -> 10|N | AX15: =(Paramètres!$B$5+(1-Paramètres!$B$5)*((K15-Paramètres!$B$7)/(Paramètres!$B$8-Paramètres!$B$7))^Paramètres!$B$6) -> 0.10346288 | AY15: =MATCH(I15,Rôles!$A$5:$A$13,0) -> 6 | AZ15: =MATCH(H15,Rôles!$A$18:$A$22,0) -> 2
A16: MON-010 | B16: 10 | C16: {=INDEX(Zones!$B$6:$B$35,MATCH(B16,Zones!$A$6:$A$35,0))} -> Village gobelin | D16: {=INDEX(Éléments!$B$5:$B$14,MATCH(B16,Éléments!$C$5:$C$14,1))} -> Forêt | E16: {=INDEX(Éléments!$A$5:$A$14,MATCH(B16,Éléments!$C$5:$C$14,1))} -> Neutre | F16: Archer gobelin | G16: =IF(OR(H16="Boss",H16="Dragon"),"Oui","Non") -> Non | H16: Normal | I16: Tireur | J16: Physique | K16: =IF($F$3="",B16,$F$3) -> 10 | L16: {=ROUND(Paramètres!$B$16*(Paramètres!$B$5+(1-Paramètres!$B$5)*((K16-Paramètres!$B$7)/(Paramètres!$B$8-Paramètres!$B$7))^Paramètres!$B$6)*INDEX(Rôles!$B$18:$B$22,AZ16)*INDEX(Rôles!$B$5:$B$13,AY16),0)} -> 130 | M16: {=ROUND(IF(J16="Physique",1,IF(J16="Mixte",Paramètres!$B$32,0))*Paramètres!$B$12*(Paramètres!$B$5+(1-Paramètres!$B$5)*((K16-Paramètres!$B$7)/(Paramètres!$B$8-Paramètres!$B$7))^Paramètres!$B$6)*INDEX(Rôles!$C$18:$C$22,AZ16)*INDEX(Rôles!$C$5:$C$13,AY16)/(Paramètres!$B$35*(1-Paramètres!$B$36)),0)} -> 39 | N16: {=ROUND(IF(J16="Magique",1,IF(J16="Mixte",Paramètres!$B$32,0))*Paramètres!$B$12*(Paramètres!$B$5+(1-Paramètres!$B$5)*((K16-Paramètres!$B$7)/(Paramètres!$B$8-Paramètres!$B$7))^Paramètres!$B$6)*INDEX(Rôles!$C$18:$C$22,AZ16)*INDEX(Rôles!$C$5:$C$13,AY16)/(Paramètres!$B$35*(1-Paramètres!$B$36)),0)} -> 0 | O16: {=ROUND(Paramètres!$B$18*(Paramètres!$B$5+(1-Paramètres!$B$5)*((K16-Paramètres!$B$7)/(Paramètres!$B$8-Paramètres!$B$7))^Paramètres!$B$6)*INDEX(Rôles!$D$5:$D$13,AY16)*INDEX(Rôles!$D$18:$D$22,AZ16),0)} -> 33 | P16: {=ROUND(Paramètres!$B$19*(Paramètres!$B$5+(1-Paramètres!$B$5)*((K16-Paramètres!$B$7)/(Paramètres!$B$8-Paramètres!$B$7))^Paramètres!$B$6)*INDEX(Rôles!$E$5:$E$13,AY16)*INDEX(Rôles!$D$18:$D$22,AZ16),0)} -> 25 | Q16: {=ROUND(Paramètres!$B$20*(Paramètres!$B$5+(1-Paramètres!$B$5)*((K16-Paramètres!$B$7)/(Paramètres!$B$8-Paramètres!$B$7))^Paramètres!$B$6)*INDEX(Rôles!$F$5:$F$13,AY16),0)} -> 14 | R16: =ROUND(Paramètres!$B$64*$AX16*INDEX(Rôles!$N$5:$N$13,$AY16)*INDEX(Rôles!$I$18:$I$22,$AZ16),0) -> 11 | S16: {=MIN(1,ROUND(Paramètres!$B$21*INDEX(Rôles!$G$5:$G$13,AY16),3))} -> 1 | T16: {=MIN(Paramètres!$B$28,ROUND(Paramètres!$B$22*INDEX(Rôles!$H$5:$H$13,AY16),3))} -> 0.075 | U16: {=ROUND(Paramètres!$B$23*INDEX(Rôles!$I$5:$I$13,AY16),3)} -> 0.65 | V16: {=MIN(Paramètres!$B$29,ROUND(Paramètres!$B$24*INDEX(Rôles!$J$5:$J$13,AY16),3))} -> 0.07 | W16: {=MIN(Paramètres!$B$27,ROUND((Paramètres!$B$25+(Paramètres!$B$26-Paramètres!$B$25)*(K16-Paramètres!$B$7)/(Paramètres!$B$8-Paramètres!$B$7))*INDEX(Rôles!$K$5:$K$13,AY16)+INDEX(Rôles!$G$18:$G$22,AZ16),3))} -> 0.058 | X16: =ROUND(1-(1-P16/(P16+(Paramètres!$B$19*(Paramètres!$B$5+(1-Paramètres!$B$5)*((K16-Paramètres!$B$7)/(Paramètres!$B$8-Paramètres!$B$7))^Paramètres!$B$6)*(1-Paramètres!$B$30)/Paramètres!$B$30)))*(1-O16/(O16+(Paramètres!$B$18*(Paramètres!$B$5+(1-Paramètres!$B$5)*((K16-Paramètres!$B$7)/(Paramètres!$B$8-Paramètres!$B$7))^Paramètres!$B$6)*(1-Paramètres!$B$31)/Paramètres!$B$31))),3) -> 0.228 | Y16: =ROUND(O16/(O16+(Paramètres!$B$18*(Paramètres!$B$5+(1-Paramètres!$B$5)*((K16-Paramètres!$B$7)/(Paramètres!$B$8-Paramètres!$B$7))^Paramètres!$B$6)*(1-Paramètres!$B$31)/Paramètres!$B$31)),3) -> 0.111 | Z16: {=IF(E16="Neutre",0,MIN(1,INDEX(Rôles!$L$5:$L$13,AY16)+INDEX(Rôles!$F$18:$F$22,AZ16)))} -> 0 | AA16: {=ROUND(INDEX(Rôles!$C$18:$C$22,AZ16)*INDEX(Rôles!$C$5:$C$13,AY16),4)} -> 0.0165 | AB16: {=ROUND(INDEX(Rôles!$B$18:$B$22,AZ16)*INDEX(Rôles!$B$5:$B$13,AY16),2)} -> 1.6 | AC16: {=INDEX(Rôles!$E$18:$E$22,AZ16)} -> 1 | AD16: {=INDEX(Éléments!$F$5:$F$14,MATCH(E16,Éléments!$A$5:$A$14,0))} -> — | AE16: {=INDEX(Éléments!$G$5:$G$14,MATCH(E16,Éléments!$A$5:$A$14,0))} -> — | AF16: Saignement | AG16: 0.2 | AJ16: {=ROUND(ROUND(Paramètres!$B$49*K16^Paramètres!$B$50,0)*INDEX(Rôles!$E$18:$E$22,AZ16),0)} -> 107 | AK16: {=ROUND(ROUND(Paramètres!$B$53*K16^Paramètres!$B$54,0)*INDEX(Rôles!$E$18:$E$22,AZ16),0)} -> 67 | AL16: =INDEX(Butin!$B$7:$B$11,AZ16) -> 0.05 | AM16: =INDEX(Butin!$E$7:$E$11,AZ16) -> 0.05 | AN16: =IF($H16="Boss",INDEX(Butin!$E$28:$K$37,MATCH($B16,Éléments!$C$5:$C$14,1),1),IF($H16="Dragon",INDEX(Butin!$E$41:$K$50,MATCH($B16,Éléments!$C$5:$C$14,1),1),INDEX(Butin!$E$15:$K$24,MATCH($B16,Éléments!$C$5:$C$14,1),1))) -> 0.8 | AO16: =IF($H16="Boss",INDEX(Butin!$E$28:$K$37,MATCH($B16,Éléments!$C$5:$C$14,1),2),IF($H16="Dragon",INDEX(Butin!$E$41:$K$50,MATCH($B16,Éléments!$C$5:$C$14,1),2),INDEX(Butin!$E$15:$K$24,MATCH($B16,Éléments!$C$5:$C$14,1),2))) -> 0.2 | AP16: =IF($H16="Boss",INDEX(Butin!$E$28:$K$37,MATCH($B16,Éléments!$C$5:$C$14,1),3),IF($H16="Dragon",INDEX(Butin!$E$41:$K$50,MATCH($B16,Éléments!$C$5:$C$14,1),3),INDEX(Butin!$E$15:$K$24,MATCH($B16,Éléments!$C$5:$C$14,1),3))) -> 0 | AQ16: =IF($H16="Boss",INDEX(Butin!$E$28:$K$37,MATCH($B16,Éléments!$C$5:$C$14,1),4),IF($H16="Dragon",INDEX(Butin!$E$41:$K$50,MATCH($B16,Éléments!$C$5:$C$14,1),4),INDEX(Butin!$E$15:$K$24,MATCH($B16,Éléments!$C$5:$C$14,1),4))) -> 0 | AR16: =IF($H16="Boss",INDEX(Butin!$E$28:$K$37,MATCH($B16,Éléments!$C$5:$C$14,1),5),IF($H16="Dragon",INDEX(Butin!$E$41:$K$50,MATCH($B16,Éléments!$C$5:$C$14,1),5),INDEX(Butin!$E$15:$K$24,MATCH($B16,Éléments!$C$5:$C$14,1),5))) -> 0 | AS16: =IF($H16="Boss",INDEX(Butin!$E$28:$K$37,MATCH($B16,Éléments!$C$5:$C$14,1),6),IF($H16="Dragon",INDEX(Butin!$E$41:$K$50,MATCH($B16,Éléments!$C$5:$C$14,1),6),INDEX(Butin!$E$15:$K$24,MATCH($B16,Éléments!$C$5:$C$14,1),6))) -> 0 | AT16: =IF($H16="Boss",INDEX(Butin!$E$28:$K$37,MATCH($B16,Éléments!$C$5:$C$14,1),7),IF($H16="Dragon",INDEX(Butin!$E$41:$K$50,MATCH($B16,Éléments!$C$5:$C$14,1),7),INDEX(Butin!$E$15:$K$24,MATCH($B16,Éléments!$C$5:$C$14,1),7))) -> 0 | AU16: =IF(AT16=0,"—",INDEX(Butin!$D$54:$D$63,MATCH($B16,Éléments!$C$5:$C$14,1))&" · "&INDEX(Butin!$F$54:$F$63,MATCH($B16,Éléments!$C$5:$C$14,1))&" · "&INDEX(Butin!$H$54:$H$63,MATCH($B16,Éléments!$C$5:$C$14,1))) -> — | AV16: Archer gobbelin | AW16: =B16&IF(G16="Oui","|B","|N") -> 10|N | AX16: =(Paramètres!$B$5+(1-Paramètres!$B$5)*((K16-Paramètres!$B$7)/(Paramètres!$B$8-Paramètres!$B$7))^Paramètres!$B$6) -> 0.10346288 | AY16: =MATCH(I16,Rôles!$A$5:$A$13,0) -> 4 | AZ16: =MATCH(H16,Rôles!$A$18:$A$22,0) -> 2
A17: MON-011 | B17: 15 | C17: {=INDEX(Zones!$B$6:$B$35,MATCH(B17,Zones!$A$6:$A$35,0))} -> Mine abandonnée | D17: {=INDEX(Éléments!$B$5:$B$14,MATCH(B17,Éléments!$C$5:$C$14,1))} -> Montagne | E17: {=INDEX(Éléments!$A$5:$A$14,MATCH(B17,Éléments!$C$5:$C$14,1))} -> Terre | F17: Haut chaman gobelin | G17: =IF(OR(H17="Boss",H17="Dragon"),"Oui","Non") -> Oui | H17: Boss | I17: Soutien | J17: Magique | K17: =IF($F$3="",B17,$F$3) -> 15 | L17: {=ROUND(Paramètres!$B$16*(Paramètres!$B$5+(1-Paramètres!$B$5)*((K17-Paramètres!$B$7)/(Paramètres!$B$8-Paramètres!$B$7))^Paramètres!$B$6)*INDEX(Rôles!$B$18:$B$22,AZ17)*INDEX(Rôles!$B$5:$B$13,AY17),0)} -> 1131 | M17: {=ROUND(IF(J17="Physique",1,IF(J17="Mixte",Paramètres!$B$32,0))*Paramètres!$B$12*(Paramètres!$B$5+(1-Paramètres!$B$5)*((K17-Paramètres!$B$7)/(Paramètres!$B$8-Paramètres!$B$7))^Paramètres!$B$6)*INDEX(Rôles!$C$18:$C$22,AZ17)*INDEX(Rôles!$C$5:$C$13,AY17)/(Paramètres!$B$35*(1-Paramètres!$B$36)),0)} -> 0 | N17: {=ROUND(IF(J17="Magique",1,IF(J17="Mixte",Paramètres!$B$32,0))*Paramètres!$B$12*(Paramètres!$B$5+(1-Paramètres!$B$5)*((K17-Paramètres!$B$7)/(Paramètres!$B$8-Paramètres!$B$7))^Paramètres!$B$6)*INDEX(Rôles!$C$18:$C$22,AZ17)*INDEX(Rôles!$C$5:$C$13,AY17)/(Paramètres!$B$35*(1-Paramètres!$B$36)),0)} -> 77 | O17: {=ROUND(Paramètres!$B$18*(Paramètres!$B$5+(1-Paramètres!$B$5)*((K17-Paramètres!$B$7)/(Paramètres!$B$8-Paramètres!$B$7))^Paramètres!$B$6)*INDEX(Rôles!$D$5:$D$13,AY17)*INDEX(Rôles!$D$18:$D$22,AZ17),0)} -> 99 | P17: {=ROUND(Paramètres!$B$19*(Paramètres!$B$5+(1-Paramètres!$B$5)*((K17-Paramètres!$B$7)/(Paramètres!$B$8-Paramètres!$B$7))^Paramètres!$B$6)*INDEX(Rôles!$E$5:$E$13,AY17)*INDEX(Rôles!$D$18:$D$22,AZ17),0)} -> 37 | Q17: {=ROUND(Paramètres!$B$20*(Paramètres!$B$5+(1-Paramètres!$B$5)*((K17-Paramètres!$B$7)/(Paramètres!$B$8-Paramètres!$B$7))^Paramètres!$B$6)*INDEX(Rôles!$F$5:$F$13,AY17),0)} -> 15 | R17: =ROUND(Paramètres!$B$64*$AX17*INDEX(Rôles!$N$5:$N$13,$AY17)*INDEX(Rôles!$I$18:$I$22,$AZ17),0) -> 16 | S17: {=MIN(1,ROUND(Paramètres!$B$21*INDEX(Rôles!$G$5:$G$13,AY17),3))} -> 0.9 | T17: {=MIN(Paramètres!$B$28,ROUND(Paramètres!$B$22*INDEX(Rôles!$H$5:$H$13,AY17),3))} -> 0.04 | U17: {=ROUND(Paramètres!$B$23*INDEX(Rôles!$I$5:$I$13,AY17),3)} -> 0.5 | V17: {=MIN(Paramètres!$B$29,ROUND(Paramètres!$B$24*INDEX(Rôles!$J$5:$J$13,AY17),3))} -> 0.04 | W17: {=MIN(Paramètres!$B$27,ROUND((Paramètres!$B$25+(Paramètres!$B$26-Paramètres!$B$25)*(K17-Paramètres!$B$7)/(Paramètres!$B$8-Paramètres!$B$7))*INDEX(Rôles!$K$5:$K$13,AY17)+INDEX(Rôles!$G$18:$G$22,AZ17),3))} -> 0.311 | X17: =ROUND(1-(1-P17/(P17+(Paramètres!$B$19*(Paramètres!$B$5+(1-Paramètres!$B$5)*((K17-Paramètres!$B$7)/(Paramètres!$B$8-Paramètres!$B$7))^Paramètres!$B$6)*(1-Paramètres!$B$30)/Paramètres!$B$30)))*(1-O17/(O17+(Paramètres!$B$18*(Paramètres!$B$5+(1-Paramètres!$B$5)*((K17-Paramètres!$B$7)/(Paramètres!$B$8-Paramètres!$B$7))^Paramètres!$B$6)*(1-Paramètres!$B$31)/Paramètres!$B$31))),3) -> 0.327 | Y17: =ROUND(O17/(O17+(Paramètres!$B$18*(Paramètres!$B$5+(1-Paramètres!$B$5)*((K17-Paramètres!$B$7)/(Paramètres!$B$8-Paramètres!$B$7))^Paramètres!$B$6)*(1-Paramètres!$B$31)/Paramètres!$B$31)),3) -> 0.216 | Z17: {=IF(E17="Neutre",0,MIN(1,INDEX(Rôles!$L$5:$L$13,AY17)+INDEX(Rôles!$F$18:$F$22,AZ17)))} -> 0.9 | AA17: {=ROUND(INDEX(Rôles!$C$18:$C$22,AZ17)*INDEX(Rôles!$C$5:$C$13,AY17),4)} -> 0.024 | AB17: {=ROUND(INDEX(Rôles!$B$18:$B$22,AZ17)*INDEX(Rôles!$B$5:$B$13,AY17),2)} -> 10.2 | AC17: {=INDEX(Rôles!$E$18:$E$22,AZ17)} -> 8 | AD17: {=INDEX(Éléments!$F$5:$F$14,MATCH(E17,Éléments!$A$5:$A$14,0))} -> Acide, Vent | AE17: {=INDEX(Éléments!$G$5:$G$14,MATCH(E17,Éléments!$A$5:$A$14,0))} -> Électricité | AF17: Garde brisée | AG17: 0.35 | AH17: Intimidé | AI17: 0.3 | AJ17: {=ROUND(ROUND(Paramètres!$B$49*K17^Paramètres!$B$50,0)*INDEX(Rôles!$E$18:$E$22,AZ17),0)} -> 1416 | AK17: {=ROUND(ROUND(Paramètres!$B$53*K17^Paramètres!$B$54,0)*INDEX(Rôles!$E$18:$E$22,AZ17),0)} -> 928 | AL17: =INDEX(Butin!$B$7:$B$11,AZ17) -> 1 | AM17: =INDEX(Butin!$E$7:$E$11,AZ17) -> 1.4 | AN17: =IF($H17="Boss",INDEX(Butin!$E$28:$K$37,MATCH($B17,Éléments!$C$5:$C$14,1),1),IF($H17="Dragon",INDEX(Butin!$E$41:$K$50,MATCH($B17,Éléments!$C$5:$C$14,1),1),INDEX(Butin!$E$15:$K$24,MATCH($B17,Éléments!$C$5:$C$14,1),1))) -> 0.28 | AO17: =IF($H17="Boss",INDEX(Butin!$E$28:$K$37,MATCH($B17,Éléments!$C$5:$C$14,1),2),IF($H17="Dragon",INDEX(Butin!$E$41:$K$50,MATCH($B17,Éléments!$C$5:$C$14,1),2),INDEX(Butin!$E$15:$K$24,MATCH($B17,Éléments!$C$5:$C$14,1),2))) -> 0.38 | AP17: =IF($H17="Boss",INDEX(Butin!$E$28:$K$37,MATCH($B17,Éléments!$C$5:$C$14,1),3),IF($H17="Dragon",INDEX(Butin!$E$41:$K$50,MATCH($B17,Éléments!$C$5:$C$14,1),3),INDEX(Butin!$E$15:$K$24,MATCH($B17,Éléments!$C$5:$C$14,1),3))) -> 0.24 | AQ17: =IF($H17="Boss",INDEX(Butin!$E$28:$K$37,MATCH($B17,Éléments!$C$5:$C$14,1),4),IF($H17="Dragon",INDEX(Butin!$E$41:$K$50,MATCH($B17,Éléments!$C$5:$C$14,1),4),INDEX(Butin!$E$15:$K$24,MATCH($B17,Éléments!$C$5:$C$14,1),4))) -> 0.08 | AR17: =IF($H17="Boss",INDEX(Butin!$E$28:$K$37,MATCH($B17,Éléments!$C$5:$C$14,1),5),IF($H17="Dragon",INDEX(Butin!$E$41:$K$50,MATCH($B17,Éléments!$C$5:$C$14,1),5),INDEX(Butin!$E$15:$K$24,MATCH($B17,Éléments!$C$5:$C$14,1),5))) -> 0 | AS17: =IF($H17="Boss",INDEX(Butin!$E$28:$K$37,MATCH($B17,Éléments!$C$5:$C$14,1),6),IF($H17="Dragon",INDEX(Butin!$E$41:$K$50,MATCH($B17,Éléments!$C$5:$C$14,1),6),INDEX(Butin!$E$15:$K$24,MATCH($B17,Éléments!$C$5:$C$14,1),6))) -> 0 | AT17: =IF($H17="Boss",INDEX(Butin!$E$28:$K$37,MATCH($B17,Éléments!$C$5:$C$14,1),7),IF($H17="Dragon",INDEX(Butin!$E$41:$K$50,MATCH($B17,Éléments!$C$5:$C$14,1),7),INDEX(Butin!$E$15:$K$24,MATCH($B17,Éléments!$C$5:$C$14,1),7))) -> 0.02 | AU17: =IF(AT17=0,"—",INDEX(Butin!$D$54:$D$63,MATCH($B17,Éléments!$C$5:$C$14,1))&" · "&INDEX(Butin!$F$54:$F$63,MATCH($B17,Éléments!$C$5:$C$14,1))&" · "&INDEX(Butin!$H$54:$H$63,MATCH($B17,Éléments!$C$5:$C$14,1))) -> Plastron du Titan de Pierre · Sceau de la Terre Ancestrale · Pendentif de la Sentinelle de Pierre | AV17: Haut Chaman Gobbelin (Boss) | AW17: =B17&IF(G17="Oui","|B","|N") -> 15|B | AX17: =(Paramètres!$B$5+(1-Paramètres!$B$5)*((K17-Paramètres!$B$7)/(Paramètres!$B$8-Paramètres!$B$7))^Paramètres!$B$6) -> 0.14084793 | AY17: =MATCH(I17,Rôles!$A$5:$A$13,0) -> 6 | AZ17: =MATCH(H17,Rôles!$A$18:$A$22,0) -> 4
A18: MON-012 | B18: 15 | C18: {=INDEX(Zones!$B$6:$B$35,MATCH(B18,Zones!$A$6:$A$35,0))} -> Mine abandonnée | D18: {=INDEX(Éléments!$B$5:$B$14,MATCH(B18,Éléments!$C$5:$C$14,1))} -> Montagne | E18: {=INDEX(Éléments!$A$5:$A$14,MATCH(B18,Éléments!$C$5:$C$14,1))} -> Terre | F18: Haut gobelin | G18: =IF(OR(H18="Boss",H18="Dragon"),"Oui","Non") -> Non | H18: Normal | I18: Guerrier | J18: Physique | K18: =IF($F$3="",B18,$F$3) -> 15 | L18: {=ROUND(Paramètres!$B$16*(Paramètres!$B$5+(1-Paramètres!$B$5)*((K18-Paramètres!$B$7)/(Paramètres!$B$8-Paramètres!$B$7))^Paramètres!$B$6)*INDEX(Rôles!$B$18:$B$22,AZ18)*INDEX(Rôles!$B$5:$B$13,AY18),0)} -> 255 | M18: {=ROUND(IF(J18="Physique",1,IF(J18="Mixte",Paramètres!$B$32,0))*Paramètres!$B$12*(Paramètres!$B$5+(1-Paramètres!$B$5)*((K18-Paramètres!$B$7)/(Paramètres!$B$8-Paramètres!$B$7))^Paramètres!$B$6)*INDEX(Rôles!$C$18:$C$22,AZ18)*INDEX(Rôles!$C$5:$C$13,AY18)/(Paramètres!$B$35*(1-Paramètres!$B$36)),0)} -> 48 | N18: {=ROUND(IF(J18="Magique",1,IF(J18="Mixte",Paramètres!$B$32,0))*Paramètres!$B$12*(Paramètres!$B$5+(1-Paramètres!$B$5)*((K18-Paramètres!$B$7)/(Paramètres!$B$8-Paramètres!$B$7))^Paramètres!$B$6)*INDEX(Rôles!$C$18:$C$22,AZ18)*INDEX(Rôles!$C$5:$C$13,AY18)/(Paramètres!$B$35*(1-Paramètres!$B$36)),0)} -> 0 | O18: {=ROUND(Paramètres!$B$18*(Paramètres!$B$5+(1-Paramètres!$B$5)*((K18-Paramètres!$B$7)/(Paramètres!$B$8-Paramètres!$B$7))^Paramètres!$B$6)*INDEX(Rôles!$D$5:$D$13,AY18)*INDEX(Rôles!$D$18:$D$22,AZ18),0)} -> 63 | P18: {=ROUND(Paramètres!$B$19*(Paramètres!$B$5+(1-Paramètres!$B$5)*((K18-Paramètres!$B$7)/(Paramètres!$B$8-Paramètres!$B$7))^Paramètres!$B$6)*INDEX(Rôles!$E$5:$E$13,AY18)*INDEX(Rôles!$D$18:$D$22,AZ18),0)} -> 68 | Q18: {=ROUND(Paramètres!$B$20*(Paramètres!$B$5+(1-Paramètres!$B$5)*((K18-Paramètres!$B$7)/(Paramètres!$B$8-Paramètres!$B$7))^Paramètres!$B$6)*INDEX(Rôles!$F$5:$F$13,AY18),0)} -> 15 | R18: =ROUND(Paramètres!$B$64*$AX18*INDEX(Rôles!$N$5:$N$13,$AY18)*INDEX(Rôles!$I$18:$I$22,$AZ18),0) -> 13 | S18: {=MIN(1,ROUND(Paramètres!$B$21*INDEX(Rôles!$G$5:$G$13,AY18),3))} -> 0.9 | T18: {=MIN(Paramètres!$B$28,ROUND(Paramètres!$B$22*INDEX(Rôles!$H$5:$H$13,AY18),3))} -> 0.05 | U18: {=ROUND(Paramètres!$B$23*INDEX(Rôles!$I$5:$I$13,AY18),3)} -> 0.5 | V18: {=MIN(Paramètres!$B$29,ROUND(Paramètres!$B$24*INDEX(Rôles!$J$5:$J$13,AY18),3))} -> 0.05 | W18: {=MIN(Paramètres!$B$27,ROUND((Paramètres!$B$25+(Paramètres!$B$26-Paramètres!$B$25)*(K18-Paramètres!$B$7)/(Paramètres!$B$8-Paramètres!$B$7))*INDEX(Rôles!$K$5:$K$13,AY18)+INDEX(Rôles!$G$18:$G$22,AZ18),3))} -> 0.085 | X18: =ROUND(1-(1-P18/(P18+(Paramètres!$B$19*(Paramètres!$B$5+(1-Paramètres!$B$5)*((K18-Paramètres!$B$7)/(Paramètres!$B$8-Paramètres!$B$7))^Paramètres!$B$6)*(1-Paramètres!$B$30)/Paramètres!$B$30)))*(1-O18/(O18+(Paramètres!$B$18*(Paramètres!$B$5+(1-Paramètres!$B$5)*((K18-Paramètres!$B$7)/(Paramètres!$B$8-Paramètres!$B$7))^Paramètres!$B$6)*(1-Paramètres!$B$31)/Paramètres!$B$31))),3) -> 0.346 | Y18: =ROUND(O18/(O18+(Paramètres!$B$18*(Paramètres!$B$5+(1-Paramètres!$B$5)*((K18-Paramètres!$B$7)/(Paramètres!$B$8-Paramètres!$B$7))^Paramètres!$B$6)*(1-Paramètres!$B$31)/Paramètres!$B$31)),3) -> 0.149 | Z18: {=IF(E18="Neutre",0,MIN(1,INDEX(Rôles!$L$5:$L$13,AY18)+INDEX(Rôles!$F$18:$F$22,AZ18)))} -> 0.5 | AA18: {=ROUND(INDEX(Rôles!$C$18:$C$22,AZ18)*INDEX(Rôles!$C$5:$C$13,AY18),4)} -> 0.015 | AB18: {=ROUND(INDEX(Rôles!$B$18:$B$22,AZ18)*INDEX(Rôles!$B$5:$B$13,AY18),2)} -> 2.3 | AC18: {=INDEX(Rôles!$E$18:$E$22,AZ18)} -> 1 | AD18: {=INDEX(Éléments!$F$5:$F$14,MATCH(E18,Éléments!$A$5:$A$14,0))} -> Acide, Vent | AE18: {=INDEX(Éléments!$G$5:$G$14,MATCH(E18,Éléments!$A$5:$A$14,0))} -> Électricité | AF18: Garde brisée | AG18: 0.2 | AH18: Saignement | AI18: 0.15 | AJ18: {=ROUND(ROUND(Paramètres!$B$49*K18^Paramètres!$B$50,0)*INDEX(Rôles!$E$18:$E$22,AZ18),0)} -> 177 | AK18: {=ROUND(ROUND(Paramètres!$B$53*K18^Paramètres!$B$54,0)*INDEX(Rôles!$E$18:$E$22,AZ18),0)} -> 116 | AL18: =INDEX(Butin!$B$7:$B$11,AZ18) -> 0.05 | AM18: =INDEX(Butin!$E$7:$E$11,AZ18) -> 0.05 | AN18: =IF($H18="Boss",INDEX(Butin!$E$28:$K$37,MATCH($B18,Éléments!$C$5:$C$14,1),1),IF($H18="Dragon",INDEX(Butin!$E$41:$K$50,MATCH($B18,Éléments!$C$5:$C$14,1),1),INDEX(Butin!$E$15:$K$24,MATCH($B18,Éléments!$C$5:$C$14,1),1))) -> 0.65 | AO18: =IF($H18="Boss",INDEX(Butin!$E$28:$K$37,MATCH($B18,Éléments!$C$5:$C$14,1),2),IF($H18="Dragon",INDEX(Butin!$E$41:$K$50,MATCH($B18,Éléments!$C$5:$C$14,1),2),INDEX(Butin!$E$15:$K$24,MATCH($B18,Éléments!$C$5:$C$14,1),2))) -> 0.28 | AP18: =IF($H18="Boss",INDEX(Butin!$E$28:$K$37,MATCH($B18,Éléments!$C$5:$C$14,1),3),IF($H18="Dragon",INDEX(Butin!$E$41:$K$50,MATCH($B18,Éléments!$C$5:$C$14,1),3),INDEX(Butin!$E$15:$K$24,MATCH($B18,Éléments!$C$5:$C$14,1),3))) -> 0.07 | AQ18: =IF($H18="Boss",INDEX(Butin!$E$28:$K$37,MATCH($B18,Éléments!$C$5:$C$14,1),4),IF($H18="Dragon",INDEX(Butin!$E$41:$K$50,MATCH($B18,Éléments!$C$5:$C$14,1),4),INDEX(Butin!$E$15:$K$24,MATCH($B18,Éléments!$C$5:$C$14,1),4))) -> 0 | AR18: =IF($H18="Boss",INDEX(Butin!$E$28:$K$37,MATCH($B18,Éléments!$C$5:$C$14,1),5),IF($H18="Dragon",INDEX(Butin!$E$41:$K$50,MATCH($B18,Éléments!$C$5:$C$14,1),5),INDEX(Butin!$E$15:$K$24,MATCH($B18,Éléments!$C$5:$C$14,1),5))) -> 0 | AS18: =IF($H18="Boss",INDEX(Butin!$E$28:$K$37,MATCH($B18,Éléments!$C$5:$C$14,1),6),IF($H18="Dragon",INDEX(Butin!$E$41:$K$50,MATCH($B18,Éléments!$C$5:$C$14,1),6),INDEX(Butin!$E$15:$K$24,MATCH($B18,Éléments!$C$5:$C$14,1),6))) -> 0 | AT18: =IF($H18="Boss",INDEX(Butin!$E$28:$K$37,MATCH($B18,Éléments!$C$5:$C$14,1),7),IF($H18="Dragon",INDEX(Butin!$E$41:$K$50,MATCH($B18,Éléments!$C$5:$C$14,1),7),INDEX(Butin!$E$15:$K$24,MATCH($B18,Éléments!$C$5:$C$14,1),7))) -> 0 | AU18: =IF(AT18=0,"—",INDEX(Butin!$D$54:$D$63,MATCH($B18,Éléments!$C$5:$C$14,1))&" · "&INDEX(Butin!$F$54:$F$63,MATCH($B18,Éléments!$C$5:$C$14,1))&" · "&INDEX(Butin!$H$54:$H$63,MATCH($B18,Éléments!$C$5:$C$14,1))) -> — | AV18: Haut Gobbelin | AW18: =B18&IF(G18="Oui","|B","|N") -> 15|N | AX18: =(Paramètres!$B$5+(1-Paramètres!$B$5)*((K18-Paramètres!$B$7)/(Paramètres!$B$8-Paramètres!$B$7))^Paramètres!$B$6) -> 0.14084793 | AY18: =MATCH(I18,Rôles!$A$5:$A$13,0) -> 3 | AZ18: =MATCH(H18,Rôles!$A$18:$A$22,0) -> 2
A19: MON-013 | B19: 15 | C19: {=INDEX(Zones!$B$6:$B$35,MATCH(B19,Zones!$A$6:$A$35,0))} -> Mine abandonnée | D19: {=INDEX(Éléments!$B$5:$B$14,MATCH(B19,Éléments!$C$5:$C$14,1))} -> Montagne | E19: {=INDEX(Éléments!$A$5:$A$14,MATCH(B19,Éléments!$C$5:$C$14,1))} -> Terre | F19: Haut archer gobelin | G19: =IF(OR(H19="Boss",H19="Dragon"),"Oui","Non") -> Non | H19: Normal | I19: Tireur | J19: Physique | K19: =IF($F$3="",B19,$F$3) -> 15 | L19: {=ROUND(Paramètres!$B$16*(Paramètres!$B$5+(1-Paramètres!$B$5)*((K19-Paramètres!$B$7)/(Paramètres!$B$8-Paramètres!$B$7))^Paramètres!$B$6)*INDEX(Rôles!$B$18:$B$22,AZ19)*INDEX(Rôles!$B$5:$B$13,AY19),0)} -> 177 | M19: {=ROUND(IF(J19="Physique",1,IF(J19="Mixte",Paramètres!$B$32,0))*Paramètres!$B$12*(Paramètres!$B$5+(1-Paramètres!$B$5)*((K19-Paramètres!$B$7)/(Paramètres!$B$8-Paramètres!$B$7))^Paramètres!$B$6)*INDEX(Rôles!$C$18:$C$22,AZ19)*INDEX(Rôles!$C$5:$C$13,AY19)/(Paramètres!$B$35*(1-Paramètres!$B$36)),0)} -> 53 | N19: {=ROUND(IF(J19="Magique",1,IF(J19="Mixte",Paramètres!$B$32,0))*Paramètres!$B$12*(Paramètres!$B$5+(1-Paramètres!$B$5)*((K19-Paramètres!$B$7)/(Paramètres!$B$8-Paramètres!$B$7))^Paramètres!$B$6)*INDEX(Rôles!$C$18:$C$22,AZ19)*INDEX(Rôles!$C$5:$C$13,AY19)/(Paramètres!$B$35*(1-Paramètres!$B$36)),0)} -> 0 | O19: {=ROUND(Paramètres!$B$18*(Paramètres!$B$5+(1-Paramètres!$B$5)*((K19-Paramètres!$B$7)/(Paramètres!$B$8-Paramètres!$B$7))^Paramètres!$B$6)*INDEX(Rôles!$D$5:$D$13,AY19)*INDEX(Rôles!$D$18:$D$22,AZ19),0)} -> 44 | P19: {=ROUND(Paramètres!$B$19*(Paramètres!$B$5+(1-Paramètres!$B$5)*((K19-Paramètres!$B$7)/(Paramètres!$B$8-Paramètres!$B$7))^Paramètres!$B$6)*INDEX(Rôles!$E$5:$E$13,AY19)*INDEX(Rôles!$D$18:$D$22,AZ19),0)} -> 34 | Q19: {=ROUND(Paramètres!$B$20*(Paramètres!$B$5+(1-Paramètres!$B$5)*((K19-Paramètres!$B$7)/(Paramètres!$B$8-Paramètres!$B$7))^Paramètres!$B$6)*INDEX(Rôles!$F$5:$F$13,AY19),0)} -> 19 | R19: =ROUND(Paramètres!$B$64*$AX19*INDEX(Rôles!$N$5:$N$13,$AY19)*INDEX(Rôles!$I$18:$I$22,$AZ19),0) -> 15 | S19: {=MIN(1,ROUND(Paramètres!$B$21*INDEX(Rôles!$G$5:$G$13,AY19),3))} -> 1 | T19: {=MIN(Paramètres!$B$28,ROUND(Paramètres!$B$22*INDEX(Rôles!$H$5:$H$13,AY19),3))} -> 0.075 | U19: {=ROUND(Paramètres!$B$23*INDEX(Rôles!$I$5:$I$13,AY19),3)} -> 0.65 | V19: {=MIN(Paramètres!$B$29,ROUND(Paramètres!$B$24*INDEX(Rôles!$J$5:$J$13,AY19),3))} -> 0.07 | W19: {=MIN(Paramètres!$B$27,ROUND((Paramètres!$B$25+(Paramètres!$B$26-Paramètres!$B$25)*(K19-Paramètres!$B$7)/(Paramètres!$B$8-Paramètres!$B$7))*INDEX(Rôles!$K$5:$K$13,AY19)+INDEX(Rôles!$G$18:$G$22,AZ19),3))} -> 0.068 | X19: =ROUND(1-(1-P19/(P19+(Paramètres!$B$19*(Paramètres!$B$5+(1-Paramètres!$B$5)*((K19-Paramètres!$B$7)/(Paramètres!$B$8-Paramètres!$B$7))^Paramètres!$B$6)*(1-Paramètres!$B$30)/Paramètres!$B$30)))*(1-O19/(O19+(Paramètres!$B$18*(Paramètres!$B$5+(1-Paramètres!$B$5)*((K19-Paramètres!$B$7)/(Paramètres!$B$8-Paramètres!$B$7))^Paramètres!$B$6)*(1-Paramètres!$B$31)/Paramètres!$B$31))),3) -> 0.226 | Y19: =ROUND(O19/(O19+(Paramètres!$B$18*(Paramètres!$B$5+(1-Paramètres!$B$5)*((K19-Paramètres!$B$7)/(Paramètres!$B$8-Paramètres!$B$7))^Paramètres!$B$6)*(1-Paramètres!$B$31)/Paramètres!$B$31)),3) -> 0.109 | Z19: {=IF(E19="Neutre",0,MIN(1,INDEX(Rôles!$L$5:$L$13,AY19)+INDEX(Rôles!$F$18:$F$22,AZ19)))} -> 0.6 | AA19: {=ROUND(INDEX(Rôles!$C$18:$C$22,AZ19)*INDEX(Rôles!$C$5:$C$13,AY19),4)} -> 0.0165 | AB19: {=ROUND(INDEX(Rôles!$B$18:$B$22,AZ19)*INDEX(Rôles!$B$5:$B$13,AY19),2)} -> 1.6 | AC19: {=INDEX(Rôles!$E$18:$E$22,AZ19)} -> 1 | AD19: {=INDEX(Éléments!$F$5:$F$14,MATCH(E19,Éléments!$A$5:$A$14,0))} -> Acide, Vent | AE19: {=INDEX(Éléments!$G$5:$G$14,MATCH(E19,Éléments!$A$5:$A$14,0))} -> Électricité | AF19: Enraciné | AG19: 0.2 | AH19: Saignement | AI19: 0.15 | AJ19: {=ROUND(ROUND(Paramètres!$B$49*K19^Paramètres!$B$50,0)*INDEX(Rôles!$E$18:$E$22,AZ19),0)} -> 177 | AK19: {=ROUND(ROUND(Paramètres!$B$53*K19^Paramètres!$B$54,0)*INDEX(Rôles!$E$18:$E$22,AZ19),0)} -> 116 | AL19: =INDEX(Butin!$B$7:$B$11,AZ19) -> 0.05 | AM19: =INDEX(Butin!$E$7:$E$11,AZ19) -> 0.05 | AN19: =IF($H19="Boss",INDEX(Butin!$E$28:$K$37,MATCH($B19,Éléments!$C$5:$C$14,1),1),IF($H19="Dragon",INDEX(Butin!$E$41:$K$50,MATCH($B19,Éléments!$C$5:$C$14,1),1),INDEX(Butin!$E$15:$K$24,MATCH($B19,Éléments!$C$5:$C$14,1),1))) -> 0.65 | AO19: =IF($H19="Boss",INDEX(Butin!$E$28:$K$37,MATCH($B19,Éléments!$C$5:$C$14,1),2),IF($H19="Dragon",INDEX(Butin!$E$41:$K$50,MATCH($B19,Éléments!$C$5:$C$14,1),2),INDEX(Butin!$E$15:$K$24,MATCH($B19,Éléments!$C$5:$C$14,1),2))) -> 0.28 | AP19: =IF($H19="Boss",INDEX(Butin!$E$28:$K$37,MATCH($B19,Éléments!$C$5:$C$14,1),3),IF($H19="Dragon",INDEX(Butin!$E$41:$K$50,MATCH($B19,Éléments!$C$5:$C$14,1),3),INDEX(Butin!$E$15:$K$24,MATCH($B19,Éléments!$C$5:$C$14,1),3))) -> 0.07 | AQ19: =IF($H19="Boss",INDEX(Butin!$E$28:$K$37,MATCH($B19,Éléments!$C$5:$C$14,1),4),IF($H19="Dragon",INDEX(Butin!$E$41:$K$50,MATCH($B19,Éléments!$C$5:$C$14,1),4),INDEX(Butin!$E$15:$K$24,MATCH($B19,Éléments!$C$5:$C$14,1),4))) -> 0 | AR19: =IF($H19="Boss",INDEX(Butin!$E$28:$K$37,MATCH($B19,Éléments!$C$5:$C$14,1),5),IF($H19="Dragon",INDEX(Butin!$E$41:$K$50,MATCH($B19,Éléments!$C$5:$C$14,1),5),INDEX(Butin!$E$15:$K$24,MATCH($B19,Éléments!$C$5:$C$14,1),5))) -> 0 | AS19: =IF($H19="Boss",INDEX(Butin!$E$28:$K$37,MATCH($B19,Éléments!$C$5:$C$14,1),6),IF($H19="Dragon",INDEX(Butin!$E$41:$K$50,MATCH($B19,Éléments!$C$5:$C$14,1),6),INDEX(Butin!$E$15:$K$24,MATCH($B19,Éléments!$C$5:$C$14,1),6))) -> 0 | AT19: =IF($H19="Boss",INDEX(Butin!$E$28:$K$37,MATCH($B19,Éléments!$C$5:$C$14,1),7),IF($H19="Dragon",INDEX(Butin!$E$41:$K$50,MATCH($B19,Éléments!$C$5:$C$14,1),7),INDEX(Butin!$E$15:$K$24,MATCH($B19,Éléments!$C$5:$C$14,1),7))) -> 0 | AU19: =IF(AT19=0,"—",INDEX(Butin!$D$54:$D$63,MATCH($B19,Éléments!$C$5:$C$14,1))&" · "&INDEX(Butin!$F$54:$F$63,MATCH($B19,Éléments!$C$5:$C$14,1))&" · "&INDEX(Butin!$H$54:$H$63,MATCH($B19,Éléments!$C$5:$C$14,1))) -> — | AV19: Haut Archer Bobbelin | AW19: =B19&IF(G19="Oui","|B","|N") -> 15|N | AX19: =(Paramètres!$B$5+(1-Paramètres!$B$5)*((K19-Paramètres!$B$7)/(Paramètres!$B$8-Paramètres!$B$7))^Paramètres!$B$6) -> 0.14084793 | AY19: =MATCH(I19,Rôles!$A$5:$A$13,0) -> 4 | AZ19: =MATCH(H19,Rôles!$A$18:$A$22,0) -> 2
A20: MON-014 | B20: 15 | C20: {=INDEX(Zones!$B$6:$B$35,MATCH(B20,Zones!$A$6:$A$35,0))} -> Mine abandonnée | D20: {=INDEX(Éléments!$B$5:$B$14,MATCH(B20,Éléments!$C$5:$C$14,1))} -> Montagne | E20: {=INDEX(Éléments!$A$5:$A$14,MATCH(B20,Éléments!$C$5:$C$14,1))} -> Terre | F20: Haut guerrier gobelin | G20: =IF(OR(H20="Boss",H20="Dragon"),"Oui","Non") -> Non | H20: Fort | I20: Guerrier | J20: Physique | K20: =IF($F$3="",B20,$F$3) -> 15 | L20: {=ROUND(Paramètres!$B$16*(Paramètres!$B$5+(1-Paramètres!$B$5)*((K20-Paramètres!$B$7)/(Paramètres!$B$8-Paramètres!$B$7))^Paramètres!$B$6)*INDEX(Rôles!$B$18:$B$22,AZ20)*INDEX(Rôles!$B$5:$B$13,AY20),0)} -> 357 | M20: {=ROUND(IF(J20="Physique",1,IF(J20="Mixte",Paramètres!$B$32,0))*Paramètres!$B$12*(Paramètres!$B$5+(1-Paramètres!$B$5)*((K20-Paramètres!$B$7)/(Paramètres!$B$8-Paramètres!$B$7))^Paramètres!$B$6)*INDEX(Rôles!$C$18:$C$22,AZ20)*INDEX(Rôles!$C$5:$C$13,AY20)/(Paramètres!$B$35*(1-Paramètres!$B$36)),0)} -> 61 | N20: {=ROUND(IF(J20="Magique",1,IF(J20="Mixte",Paramètres!$B$32,0))*Paramètres!$B$12*(Paramètres!$B$5+(1-Paramètres!$B$5)*((K20-Paramètres!$B$7)/(Paramètres!$B$8-Paramètres!$B$7))^Paramètres!$B$6)*INDEX(Rôles!$C$18:$C$22,AZ20)*INDEX(Rôles!$C$5:$C$13,AY20)/(Paramètres!$B$35*(1-Paramètres!$B$36)),0)} -> 0 | O20: {=ROUND(Paramètres!$B$18*(Paramètres!$B$5+(1-Paramètres!$B$5)*((K20-Paramètres!$B$7)/(Paramètres!$B$8-Paramètres!$B$7))^Paramètres!$B$6)*INDEX(Rôles!$D$5:$D$13,AY20)*INDEX(Rôles!$D$18:$D$22,AZ20),0)} -> 73 | P20: {=ROUND(Paramètres!$B$19*(Paramètres!$B$5+(1-Paramètres!$B$5)*((K20-Paramètres!$B$7)/(Paramètres!$B$8-Paramètres!$B$7))^Paramètres!$B$6)*INDEX(Rôles!$E$5:$E$13,AY20)*INDEX(Rôles!$D$18:$D$22,AZ20),0)} -> 78 | Q20: {=ROUND(Paramètres!$B$20*(Paramètres!$B$5+(1-Paramètres!$B$5)*((K20-Paramètres!$B$7)/(Paramètres!$B$8-Paramètres!$B$7))^Paramètres!$B$6)*INDEX(Rôles!$F$5:$F$13,AY20),0)} -> 15 | R20: =ROUND(Paramètres!$B$64*$AX20*INDEX(Rôles!$N$5:$N$13,$AY20)*INDEX(Rôles!$I$18:$I$22,$AZ20),0) -> 14 | S20: {=MIN(1,ROUND(Paramètres!$B$21*INDEX(Rôles!$G$5:$G$13,AY20),3))} -> 0.9 | T20: {=MIN(Paramètres!$B$28,ROUND(Paramètres!$B$22*INDEX(Rôles!$H$5:$H$13,AY20),3))} -> 0.05 | U20: {=ROUND(Paramètres!$B$23*INDEX(Rôles!$I$5:$I$13,AY20),3)} -> 0.5 | V20: {=MIN(Paramètres!$B$29,ROUND(Paramètres!$B$24*INDEX(Rôles!$J$5:$J$13,AY20),3))} -> 0.05 | W20: {=MIN(Paramètres!$B$27,ROUND((Paramètres!$B$25+(Paramètres!$B$26-Paramètres!$B$25)*(K20-Paramètres!$B$7)/(Paramètres!$B$8-Paramètres!$B$7))*INDEX(Rôles!$K$5:$K$13,AY20)+INDEX(Rôles!$G$18:$G$22,AZ20),3))} -> 0.085 | X20: =ROUND(1-(1-P20/(P20+(Paramètres!$B$19*(Paramètres!$B$5+(1-Paramètres!$B$5)*((K20-Paramètres!$B$7)/(Paramètres!$B$8-Paramètres!$B$7))^Paramètres!$B$6)*(1-Paramètres!$B$30)/Paramètres!$B$30)))*(1-O20/(O20+(Paramètres!$B$18*(Paramètres!$B$5+(1-Paramètres!$B$5)*((K20-Paramètres!$B$7)/(Paramètres!$B$8-Paramètres!$B$7))^Paramètres!$B$6)*(1-Paramètres!$B$31)/Paramètres!$B$31))),3) -> 0.383 | Y20: =ROUND(O20/(O20+(Paramètres!$B$18*(Paramètres!$B$5+(1-Paramètres!$B$5)*((K20-Paramètres!$B$7)/(Paramètres!$B$8-Paramètres!$B$7))^Paramètres!$B$6)*(1-Paramètres!$B$31)/Paramètres!$B$31)),3) -> 0.169 | Z20: {=IF(E20="Neutre",0,MIN(1,INDEX(Rôles!$L$5:$L$13,AY20)+INDEX(Rôles!$F$18:$F$22,AZ20)))} -> 0.5 | AA20: {=ROUND(INDEX(Rôles!$C$18:$C$22,AZ20)*INDEX(Rôles!$C$5:$C$13,AY20),4)} -> 0.019 | AB20: {=ROUND(INDEX(Rôles!$B$18:$B$22,AZ20)*INDEX(Rôles!$B$5:$B$13,AY20),2)} -> 3.22 | AC20: {=INDEX(Rôles!$E$18:$E$22,AZ20)} -> 1.4 | AD20: {=INDEX(Éléments!$F$5:$F$14,MATCH(E20,Éléments!$A$5:$A$14,0))} -> Acide, Vent | AE20: {=INDEX(Éléments!$G$5:$G$14,MATCH(E20,Éléments!$A$5:$A$14,0))} -> Électricité | AF20: Garde brisée | AG20: 0.25 | AH20: Assommé | AI20: 0.12 | AJ20: {=ROUND(ROUND(Paramètres!$B$49*K20^Paramètres!$B$50,0)*INDEX(Rôles!$E$18:$E$22,AZ20),0)} -> 248 | AK20: {=ROUND(ROUND(Paramètres!$B$53*K20^Paramètres!$B$54,0)*INDEX(Rôles!$E$18:$E$22,AZ20),0)} -> 162 | AL20: =INDEX(Butin!$B$7:$B$11,AZ20) -> 0.08 | AM20: =INDEX(Butin!$E$7:$E$11,AZ20) -> 0.08 | AN20: =IF($H20="Boss",INDEX(Butin!$E$28:$K$37,MATCH($B20,Éléments!$C$5:$C$14,1),1),IF($H20="Dragon",INDEX(Butin!$E$41:$K$50,MATCH($B20,Éléments!$C$5:$C$14,1),1),INDEX(Butin!$E$15:$K$24,MATCH($B20,Éléments!$C$5:$C$14,1),1))) -> 0.65 | AO20: =IF($H20="Boss",INDEX(Butin!$E$28:$K$37,MATCH($B20,Éléments!$C$5:$C$14,1),2),IF($H20="Dragon",INDEX(Butin!$E$41:$K$50,MATCH($B20,Éléments!$C$5:$C$14,1),2),INDEX(Butin!$E$15:$K$24,MATCH($B20,Éléments!$C$5:$C$14,1),2))) -> 0.28 | AP20: =IF($H20="Boss",INDEX(Butin!$E$28:$K$37,MATCH($B20,Éléments!$C$5:$C$14,1),3),IF($H20="Dragon",INDEX(Butin!$E$41:$K$50,MATCH($B20,Éléments!$C$5:$C$14,1),3),INDEX(Butin!$E$15:$K$24,MATCH($B20,Éléments!$C$5:$C$14,1),3))) -> 0.07 | AQ20: =IF($H20="Boss",INDEX(Butin!$E$28:$K$37,MATCH($B20,Éléments!$C$5:$C$14,1),4),IF($H20="Dragon",INDEX(Butin!$E$41:$K$50,MATCH($B20,Éléments!$C$5:$C$14,1),4),INDEX(Butin!$E$15:$K$24,MATCH($B20,Éléments!$C$5:$C$14,1),4))) -> 0 | AR20: =IF($H20="Boss",INDEX(Butin!$E$28:$K$37,MATCH($B20,Éléments!$C$5:$C$14,1),5),IF($H20="Dragon",INDEX(Butin!$E$41:$K$50,MATCH($B20,Éléments!$C$5:$C$14,1),5),INDEX(Butin!$E$15:$K$24,MATCH($B20,Éléments!$C$5:$C$14,1),5))) -> 0 | AS20: =IF($H20="Boss",INDEX(Butin!$E$28:$K$37,MATCH($B20,Éléments!$C$5:$C$14,1),6),IF($H20="Dragon",INDEX(Butin!$E$41:$K$50,MATCH($B20,Éléments!$C$5:$C$14,1),6),INDEX(Butin!$E$15:$K$24,MATCH($B20,Éléments!$C$5:$C$14,1),6))) -> 0 | AT20: =IF($H20="Boss",INDEX(Butin!$E$28:$K$37,MATCH($B20,Éléments!$C$5:$C$14,1),7),IF($H20="Dragon",INDEX(Butin!$E$41:$K$50,MATCH($B20,Éléments!$C$5:$C$14,1),7),INDEX(Butin!$E$15:$K$24,MATCH($B20,Éléments!$C$5:$C$14,1),7))) -> 0 | AU20: =IF(AT20=0,"—",INDEX(Butin!$D$54:$D$63,MATCH($B20,Éléments!$C$5:$C$14,1))&" · "&INDEX(Butin!$F$54:$F$63,MATCH($B20,Éléments!$C$5:$C$14,1))&" · "&INDEX(Butin!$H$54:$H$63,MATCH($B20,Éléments!$C$5:$C$14,1))) -> — | AV20: Haut guerrier Gobbelin | AW20: =B20&IF(G20="Oui","|B","|N") -> 15|N | AX20: =(Paramètres!$B$5+(1-Paramètres!$B$5)*((K20-Paramètres!$B$7)/(Paramètres!$B$8-Paramètres!$B$7))^Paramètres!$B$6) -> 0.14084793 | AY20: =MATCH(I20,Rôles!$A$5:$A$13,0) -> 3 | AZ20: =MATCH(H20,Rôles!$A$18:$A$22,0) -> 3
A21: MON-015 | B21: 15 | C21: {=INDEX(Zones!$B$6:$B$35,MATCH(B21,Zones!$A$6:$A$35,0))} -> Mine abandonnée | D21: {=INDEX(Éléments!$B$5:$B$14,MATCH(B21,Éléments!$C$5:$C$14,1))} -> Montagne | E21: {=INDEX(Éléments!$A$5:$A$14,MATCH(B21,Éléments!$C$5:$C$14,1))} -> Terre | F21: Haut shaman gobelin | G21: =IF(OR(H21="Boss",H21="Dragon"),"Oui","Non") -> Non | H21: Normal | I21: Mage | J21: Magique | K21: =IF($F$3="",B21,$F$3) -> 15 | L21: {=ROUND(Paramètres!$B$16*(Paramètres!$B$5+(1-Paramètres!$B$5)*((K21-Paramètres!$B$7)/(Paramètres!$B$8-Paramètres!$B$7))^Paramètres!$B$6)*INDEX(Rôles!$B$18:$B$22,AZ21)*INDEX(Rôles!$B$5:$B$13,AY21),0)} -> 155 | M21: {=ROUND(IF(J21="Physique",1,IF(J21="Mixte",Paramètres!$B$32,0))*Paramètres!$B$12*(Paramètres!$B$5+(1-Paramètres!$B$5)*((K21-Paramètres!$B$7)/(Paramètres!$B$8-Paramètres!$B$7))^Paramètres!$B$6)*INDEX(Rôles!$C$18:$C$22,AZ21)*INDEX(Rôles!$C$5:$C$13,AY21)/(Paramètres!$B$35*(1-Paramètres!$B$36)),0)} -> 0 | N21: {=ROUND(IF(J21="Magique",1,IF(J21="Mixte",Paramètres!$B$32,0))*Paramètres!$B$12*(Paramètres!$B$5+(1-Paramètres!$B$5)*((K21-Paramètres!$B$7)/(Paramètres!$B$8-Paramètres!$B$7))^Paramètres!$B$6)*INDEX(Rôles!$C$18:$C$22,AZ21)*INDEX(Rôles!$C$5:$C$13,AY21)/(Paramètres!$B$35*(1-Paramètres!$B$36)),0)} -> 60 | O21: {=ROUND(Paramètres!$B$18*(Paramètres!$B$5+(1-Paramètres!$B$5)*((K21-Paramètres!$B$7)/(Paramètres!$B$8-Paramètres!$B$7))^Paramètres!$B$6)*INDEX(Rôles!$D$5:$D$13,AY21)*INDEX(Rôles!$D$18:$D$22,AZ21),0)} -> 70 | P21: {=ROUND(Paramètres!$B$19*(Paramètres!$B$5+(1-Paramètres!$B$5)*((K21-Paramètres!$B$7)/(Paramètres!$B$8-Paramètres!$B$7))^Paramètres!$B$6)*INDEX(Rôles!$E$5:$E$13,AY21)*INDEX(Rôles!$D$18:$D$22,AZ21),0)} -> 23 | Q21: {=ROUND(Paramètres!$B$20*(Paramètres!$B$5+(1-Paramètres!$B$5)*((K21-Paramètres!$B$7)/(Paramètres!$B$8-Paramètres!$B$7))^Paramètres!$B$6)*INDEX(Rôles!$F$5:$F$13,AY21),0)} -> 15 | R21: =ROUND(Paramètres!$B$64*$AX21*INDEX(Rôles!$N$5:$N$13,$AY21)*INDEX(Rôles!$I$18:$I$22,$AZ21),0) -> 13 | S21: {=MIN(1,ROUND(Paramètres!$B$21*INDEX(Rôles!$G$5:$G$13,AY21),3))} -> 0.9 | T21: {=MIN(Paramètres!$B$28,ROUND(Paramètres!$B$22*INDEX(Rôles!$H$5:$H$13,AY21),3))} -> 0.05 | U21: {=ROUND(Paramètres!$B$23*INDEX(Rôles!$I$5:$I$13,AY21),3)} -> 0.5 | V21: {=MIN(Paramètres!$B$29,ROUND(Paramètres!$B$24*INDEX(Rôles!$J$5:$J$13,AY21),3))} -> 0.065 | W21: {=MIN(Paramètres!$B$27,ROUND((Paramètres!$B$25+(Paramètres!$B$26-Paramètres!$B$25)*(K21-Paramètres!$B$7)/(Paramètres!$B$8-Paramètres!$B$7))*INDEX(Rôles!$K$5:$K$13,AY21)+INDEX(Rôles!$G$18:$G$22,AZ21),3))} -> 0.102 | X21: =ROUND(1-(1-P21/(P21+(Paramètres!$B$19*(Paramètres!$B$5+(1-Paramètres!$B$5)*((K21-Paramètres!$B$7)/(Paramètres!$B$8-Paramètres!$B$7))^Paramètres!$B$6)*(1-Paramètres!$B$30)/Paramètres!$B$30)))*(1-O21/(O21+(Paramètres!$B$18*(Paramètres!$B$5+(1-Paramètres!$B$5)*((K21-Paramètres!$B$7)/(Paramètres!$B$8-Paramètres!$B$7))^Paramètres!$B$6)*(1-Paramètres!$B$31)/Paramètres!$B$31))),3) -> 0.241 | Y21: =ROUND(O21/(O21+(Paramètres!$B$18*(Paramètres!$B$5+(1-Paramètres!$B$5)*((K21-Paramètres!$B$7)/(Paramètres!$B$8-Paramètres!$B$7))^Paramètres!$B$6)*(1-Paramètres!$B$31)/Paramètres!$B$31)),3) -> 0.163 | Z21: {=IF(E21="Neutre",0,MIN(1,INDEX(Rôles!$L$5:$L$13,AY21)+INDEX(Rôles!$F$18:$F$22,AZ21)))} -> 1 | AA21: {=ROUND(INDEX(Rôles!$C$18:$C$22,AZ21)*INDEX(Rôles!$C$5:$C$13,AY21),4)} -> 0.0188 | AB21: {=ROUND(INDEX(Rôles!$B$18:$B$22,AZ21)*INDEX(Rôles!$B$5:$B$13,AY21),2)} -> 1.4 | AC21: {=INDEX(Rôles!$E$18:$E$22,AZ21)} -> 1 | AD21: {=INDEX(Éléments!$F$5:$F$14,MATCH(E21,Éléments!$A$5:$A$14,0))} -> Acide, Vent | AE21: {=INDEX(Éléments!$G$5:$G$14,MATCH(E21,Éléments!$A$5:$A$14,0))} -> Électricité | AF21: Garde brisée | AG21: 0.25 | AH21: Enraciné | AI21: 0.2 | AJ21: {=ROUND(ROUND(Paramètres!$B$49*K21^Paramètres!$B$50,0)*INDEX(Rôles!$E$18:$E$22,AZ21),0)} -> 177 | AK21: {=ROUND(ROUND(Paramètres!$B$53*K21^Paramètres!$B$54,0)*INDEX(Rôles!$E$18:$E$22,AZ21),0)} -> 116 | AL21: =INDEX(Butin!$B$7:$B$11,AZ21) -> 0.05 | AM21: =INDEX(Butin!$E$7:$E$11,AZ21) -> 0.05 | AN21: =IF($H21="Boss",INDEX(Butin!$E$28:$K$37,MATCH($B21,Éléments!$C$5:$C$14,1),1),IF($H21="Dragon",INDEX(Butin!$E$41:$K$50,MATCH($B21,Éléments!$C$5:$C$14,1),1),INDEX(Butin!$E$15:$K$24,MATCH($B21,Éléments!$C$5:$C$14,1),1))) -> 0.65 | AO21: =IF($H21="Boss",INDEX(Butin!$E$28:$K$37,MATCH($B21,Éléments!$C$5:$C$14,1),2),IF($H21="Dragon",INDEX(Butin!$E$41:$K$50,MATCH($B21,Éléments!$C$5:$C$14,1),2),INDEX(Butin!$E$15:$K$24,MATCH($B21,Éléments!$C$5:$C$14,1),2))) -> 0.28 | AP21: =IF($H21="Boss",INDEX(Butin!$E$28:$K$37,MATCH($B21,Éléments!$C$5:$C$14,1),3),IF($H21="Dragon",INDEX(Butin!$E$41:$K$50,MATCH($B21,Éléments!$C$5:$C$14,1),3),INDEX(Butin!$E$15:$K$24,MATCH($B21,Éléments!$C$5:$C$14,1),3))) -> 0.07 | AQ21: =IF($H21="Boss",INDEX(Butin!$E$28:$K$37,MATCH($B21,Éléments!$C$5:$C$14,1),4),IF($H21="Dragon",INDEX(Butin!$E$41:$K$50,MATCH($B21,Éléments!$C$5:$C$14,1),4),INDEX(Butin!$E$15:$K$24,MATCH($B21,Éléments!$C$5:$C$14,1),4))) -> 0 | AR21: =IF($H21="Boss",INDEX(Butin!$E$28:$K$37,MATCH($B21,Éléments!$C$5:$C$14,1),5),IF($H21="Dragon",INDEX(Butin!$E$41:$K$50,MATCH($B21,Éléments!$C$5:$C$14,1),5),INDEX(Butin!$E$15:$K$24,MATCH($B21,Éléments!$C$5:$C$14,1),5))) -> 0 | AS21: =IF($H21="Boss",INDEX(Butin!$E$28:$K$37,MATCH($B21,Éléments!$C$5:$C$14,1),6),IF($H21="Dragon",INDEX(Butin!$E$41:$K$50,MATCH($B21,Éléments!$C$5:$C$14,1),6),INDEX(Butin!$E$15:$K$24,MATCH($B21,Éléments!$C$5:$C$14,1),6))) -> 0 | AT21: =IF($H21="Boss",INDEX(Butin!$E$28:$K$37,MATCH($B21,Éléments!$C$5:$C$14,1),7),IF($H21="Dragon",INDEX(Butin!$E$41:$K$50,MATCH($B21,Éléments!$C$5:$C$14,1),7),INDEX(Butin!$E$15:$K$24,MATCH($B21,Éléments!$C$5:$C$14,1),7))) -> 0 | AU21: =IF(AT21=0,"—",INDEX(Butin!$D$54:$D$63,MATCH($B21,Éléments!$C$5:$C$14,1))&" · "&INDEX(Butin!$F$54:$F$63,MATCH($B21,Éléments!$C$5:$C$14,1))&" · "&INDEX(Butin!$H$54:$H$63,MATCH($B21,Éléments!$C$5:$C$14,1))) -> — | AV21: Haut Shaman Bobbelin | AW21: =B21&IF(G21="Oui","|B","|N") -> 15|N | AX21: =(Paramètres!$B$5+(1-Paramètres!$B$5)*((K21-Paramètres!$B$7)/(Paramètres!$B$8-Paramètres!$B$7))^Paramètres!$B$6) -> 0.14084793 | AY21: =MATCH(I21,Rôles!$A$5:$A$13,0) -> 5 | AZ21: =MATCH(H21,Rôles!$A$18:$A$22,0) -> 2
A22: MON-016 | B22: 19 | C22: {=INDEX(Zones!$B$6:$B$35,MATCH(B22,Zones!$A$6:$A$35,0))} -> Tannière du dragon (19) | D22: {=INDEX(Éléments!$B$5:$B$14,MATCH(B22,Éléments!$C$5:$C$14,1))} -> Montagne | E22: {=INDEX(Éléments!$A$5:$A$14,MATCH(B22,Éléments!$C$5:$C$14,1))} -> Terre | F22: Dragon (Terre) | G22: =IF(OR(H22="Boss",H22="Dragon"),"Oui","Non") -> Oui | H22: Dragon | I22: Dragon | J22: Mixte | K22: =IF($F$3="",B22,$F$3) -> 19 | L22: {=ROUND(Paramètres!$B$16*(Paramètres!$B$5+(1-Paramètres!$B$5)*((K22-Paramètres!$B$7)/(Paramètres!$B$8-Paramètres!$B$7))^Paramètres!$B$6)*INDEX(Rôles!$B$18:$B$22,AZ22)*INDEX(Rôles!$B$5:$B$13,AY22),0)} -> 2722 | M22: {=ROUND(IF(J22="Physique",1,IF(J22="Mixte",Paramètres!$B$32,0))*Paramètres!$B$12*(Paramètres!$B$5+(1-Paramètres!$B$5)*((K22-Paramètres!$B$7)/(Paramètres!$B$8-Paramètres!$B$7))^Paramètres!$B$6)*INDEX(Rôles!$C$18:$C$22,AZ22)*INDEX(Rôles!$C$5:$C$13,AY22)/(Paramètres!$B$35*(1-Paramètres!$B$36)),0)} -> 89 | N22: {=ROUND(IF(J22="Magique",1,IF(J22="Mixte",Paramètres!$B$32,0))*Paramètres!$B$12*(Paramètres!$B$5+(1-Paramètres!$B$5)*((K22-Paramètres!$B$7)/(Paramètres!$B$8-Paramètres!$B$7))^Paramètres!$B$6)*INDEX(Rôles!$C$18:$C$22,AZ22)*INDEX(Rôles!$C$5:$C$13,AY22)/(Paramètres!$B$35*(1-Paramètres!$B$36)),0)} -> 89 | O22: {=ROUND(Paramètres!$B$18*(Paramètres!$B$5+(1-Paramètres!$B$5)*((K22-Paramètres!$B$7)/(Paramètres!$B$8-Paramètres!$B$7))^Paramètres!$B$6)*INDEX(Rôles!$D$5:$D$13,AY22)*INDEX(Rôles!$D$18:$D$22,AZ22),0)} -> 131 | P22: {=ROUND(Paramètres!$B$19*(Paramètres!$B$5+(1-Paramètres!$B$5)*((K22-Paramètres!$B$7)/(Paramètres!$B$8-Paramètres!$B$7))^Paramètres!$B$6)*INDEX(Rôles!$E$5:$E$13,AY22)*INDEX(Rôles!$D$18:$D$22,AZ22),0)} -> 126 | Q22: {=ROUND(Paramètres!$B$20*(Paramètres!$B$5+(1-Paramètres!$B$5)*((K22-Paramètres!$B$7)/(Paramètres!$B$8-Paramètres!$B$7))^Paramètres!$B$6)*INDEX(Rôles!$F$5:$F$13,AY22),0)} -> 17 | R22: =ROUND(Paramètres!$B$64*$AX22*INDEX(Rôles!$N$5:$N$13,$AY22)*INDEX(Rôles!$I$18:$I$22,$AZ22),0) -> 14 | S22: {=MIN(1,ROUND(Paramètres!$B$21*INDEX(Rôles!$G$5:$G$13,AY22),3))} -> 0.9 | T22: {=MIN(Paramètres!$B$28,ROUND(Paramètres!$B$22*INDEX(Rôles!$H$5:$H$13,AY22),3))} -> 0.05 | U22: {=ROUND(Paramètres!$B$23*INDEX(Rôles!$I$5:$I$13,AY22),3)} -> 0.5 | V22: {=MIN(Paramètres!$B$29,ROUND(Paramètres!$B$24*INDEX(Rôles!$J$5:$J$13,AY22),3))} -> 0.05 | W22: {=MIN(Paramètres!$B$27,ROUND((Paramètres!$B$25+(Paramètres!$B$26-Paramètres!$B$25)*(K22-Paramètres!$B$7)/(Paramètres!$B$8-Paramètres!$B$7))*INDEX(Rôles!$K$5:$K$13,AY22)+INDEX(Rôles!$G$18:$G$22,AZ22),3))} -> 0.324 | X22: =ROUND(1-(1-P22/(P22+(Paramètres!$B$19*(Paramètres!$B$5+(1-Paramètres!$B$5)*((K22-Paramètres!$B$7)/(Paramètres!$B$8-Paramètres!$B$7))^Paramètres!$B$6)*(1-Paramètres!$B$30)/Paramètres!$B$30)))*(1-O22/(O22+(Paramètres!$B$18*(Paramètres!$B$5+(1-Paramètres!$B$5)*((K22-Paramètres!$B$7)/(Paramètres!$B$8-Paramètres!$B$7))^Paramètres!$B$6)*(1-Paramètres!$B$31)/Paramètres!$B$31))),3) -> 0.47 | Y22: =ROUND(O22/(O22+(Paramètres!$B$18*(Paramètres!$B$5+(1-Paramètres!$B$5)*((K22-Paramètres!$B$7)/(Paramètres!$B$8-Paramètres!$B$7))^Paramètres!$B$6)*(1-Paramètres!$B$31)/Paramètres!$B$31)),3) -> 0.229 | Z22: {=IF(E22="Neutre",0,MIN(1,INDEX(Rôles!$L$5:$L$13,AY22)+INDEX(Rôles!$F$18:$F$22,AZ22)))} -> 1 | AA22: {=ROUND(INDEX(Rôles!$C$18:$C$22,AZ22)*INDEX(Rôles!$C$5:$C$13,AY22),4)} -> 0.03 | AB22: {=ROUND(INDEX(Rôles!$B$18:$B$22,AZ22)*INDEX(Rôles!$B$5:$B$13,AY22),2)} -> 20 | AC22: {=INDEX(Rôles!$E$18:$E$22,AZ22)} -> 12 | AD22: {=INDEX(Éléments!$F$5:$F$14,MATCH(E22,Éléments!$A$5:$A$14,0))} -> Acide, Vent | AE22: {=INDEX(Éléments!$G$5:$G$14,MATCH(E22,Éléments!$A$5:$A$14,0))} -> Électricité | AF22: Garde brisée | AG22: 0.25 | AH22: Enraciné | AI22: 0.2 | AJ22: {=ROUND(ROUND(Paramètres!$B$49*K22^Paramètres!$B$50,0)*INDEX(Rôles!$E$18:$E$22,AZ22),0)} -> 2856 | AK22: {=ROUND(ROUND(Paramètres!$B$53*K22^Paramètres!$B$54,0)*INDEX(Rôles!$E$18:$E$22,AZ22),0)} -> 1920 | AL22: =INDEX(Butin!$B$7:$B$11,AZ22) -> 1 | AM22: =INDEX(Butin!$E$7:$E$11,AZ22) -> 2.5 | AN22: =IF($H22="Boss",INDEX(Butin!$E$28:$K$37,MATCH($B22,Éléments!$C$5:$C$14,1),1),IF($H22="Dragon",INDEX(Butin!$E$41:$K$50,MATCH($B22,Éléments!$C$5:$C$14,1),1),INDEX(Butin!$E$15:$K$24,MATCH($B22,Éléments!$C$5:$C$14,1),1))) -> 0.2 | AO22: =IF($H22="Boss",INDEX(Butin!$E$28:$K$37,MATCH($B22,Éléments!$C$5:$C$14,1),2),IF($H22="Dragon",INDEX(Butin!$E$41:$K$50,MATCH($B22,Éléments!$C$5:$C$14,1),2),INDEX(Butin!$E$15:$K$24,MATCH($B22,Éléments!$C$5:$C$14,1),2))) -> 0.36 | AP22: =IF($H22="Boss",INDEX(Butin!$E$28:$K$37,MATCH($B22,Éléments!$C$5:$C$14,1),3),IF($H22="Dragon",INDEX(Butin!$E$41:$K$50,MATCH($B22,Éléments!$C$5:$C$14,1),3),INDEX(Butin!$E$15:$K$24,MATCH($B22,Éléments!$C$5:$C$14,1),3))) -> 0.28 | AQ22: =IF($H22="Boss",INDEX(Butin!$E$28:$K$37,MATCH($B22,Éléments!$C$5:$C$14,1),4),IF($H22="Dragon",INDEX(Butin!$E$41:$K$50,MATCH($B22,Éléments!$C$5:$C$14,1),4),INDEX(Butin!$E$15:$K$24,MATCH($B22,Éléments!$C$5:$C$14,1),4))) -> 0.12 | AR22: =IF($H22="Boss",INDEX(Butin!$E$28:$K$37,MATCH($B22,Éléments!$C$5:$C$14,1),5),IF($H22="Dragon",INDEX(Butin!$E$41:$K$50,MATCH($B22,Éléments!$C$5:$C$14,1),5),INDEX(Butin!$E$15:$K$24,MATCH($B22,Éléments!$C$5:$C$14,1),5))) -> 0.01 | AS22: =IF($H22="Boss",INDEX(Butin!$E$28:$K$37,MATCH($B22,Éléments!$C$5:$C$14,1),6),IF($H22="Dragon",INDEX(Butin!$E$41:$K$50,MATCH($B22,Éléments!$C$5:$C$14,1),6),INDEX(Butin!$E$15:$K$24,MATCH($B22,Éléments!$C$5:$C$14,1),6))) -> 0 | AT22: =IF($H22="Boss",INDEX(Butin!$E$28:$K$37,MATCH($B22,Éléments!$C$5:$C$14,1),7),IF($H22="Dragon",INDEX(Butin!$E$41:$K$50,MATCH($B22,Éléments!$C$5:$C$14,1),7),INDEX(Butin!$E$15:$K$24,MATCH($B22,Éléments!$C$5:$C$14,1),7))) -> 0.03 | AU22: =IF(AT22=0,"—",INDEX(Butin!$D$54:$D$63,MATCH($B22,Éléments!$C$5:$C$14,1))&" · "&INDEX(Butin!$F$54:$F$63,MATCH($B22,Éléments!$C$5:$C$14,1))&" · "&INDEX(Butin!$H$54:$H$63,MATCH($B22,Éléments!$C$5:$C$14,1))) -> Plastron du Titan de Pierre · Sceau de la Terre Ancestrale · Pendentif de la Sentinelle de Pierre | AV22: Dragon (Terre) | AW22: =B22&IF(G22="Oui","|B","|N") -> 19|B | AX22: =(Paramètres!$B$5+(1-Paramètres!$B$5)*((K22-Paramètres!$B$7)/(Paramètres!$B$8-Paramètres!$B$7))^Paramètres!$B$6) -> 0.17282545 | AY22: =MATCH(I22,Rôles!$A$5:$A$13,0) -> 9 | AZ22: =MATCH(H22,Rôles!$A$18:$A$22,0) -> 5
A23: MON-017 | B23: 20 | C23: {=INDEX(Zones!$B$6:$B$35,MATCH(B23,Zones!$A$6:$A$35,0))} -> Grotte profonde | D23: {=INDEX(Éléments!$B$5:$B$14,MATCH(B23,Éléments!$C$5:$C$14,1))} -> Montagne | E23: {=INDEX(Éléments!$A$5:$A$14,MATCH(B23,Éléments!$C$5:$C$14,1))} -> Terre | F23: Chef orc | G23: =IF(OR(H23="Boss",H23="Dragon"),"Oui","Non") -> Oui | H23: Boss | I23: Brute | J23: Physique | K23: =IF($F$3="",B23,$F$3) -> 20 | L23: {=ROUND(Paramètres!$B$16*(Paramètres!$B$5+(1-Paramètres!$B$5)*((K23-Paramètres!$B$7)/(Paramètres!$B$8-Paramètres!$B$7))^Paramètres!$B$6)*INDEX(Rôles!$B$18:$B$22,AZ23)*INDEX(Rôles!$B$5:$B$13,AY23),0)} -> 2567 | M23: {=ROUND(IF(J23="Physique",1,IF(J23="Mixte",Paramètres!$B$32,0))*Paramètres!$B$12*(Paramètres!$B$5+(1-Paramètres!$B$5)*((K23-Paramètres!$B$7)/(Paramètres!$B$8-Paramètres!$B$7))^Paramètres!$B$6)*INDEX(Rôles!$C$18:$C$22,AZ23)*INDEX(Rôles!$C$5:$C$13,AY23)/(Paramètres!$B$35*(1-Paramètres!$B$36)),0)} -> 118 | N23: {=ROUND(IF(J23="Magique",1,IF(J23="Mixte",Paramètres!$B$32,0))*Paramètres!$B$12*(Paramètres!$B$5+(1-Paramètres!$B$5)*((K23-Paramètres!$B$7)/(Paramètres!$B$8-Paramètres!$B$7))^Paramètres!$B$6)*INDEX(Rôles!$C$18:$C$22,AZ23)*INDEX(Rôles!$C$5:$C$13,AY23)/(Paramètres!$B$35*(1-Paramètres!$B$36)),0)} -> 0 | O23: {=ROUND(Paramètres!$B$18*(Paramètres!$B$5+(1-Paramètres!$B$5)*((K23-Paramètres!$B$7)/(Paramètres!$B$8-Paramètres!$B$7))^Paramètres!$B$6)*INDEX(Rôles!$D$5:$D$13,AY23)*INDEX(Rôles!$D$18:$D$22,AZ23),0)} -> 127 | P23: {=ROUND(Paramètres!$B$19*(Paramètres!$B$5+(1-Paramètres!$B$5)*((K23-Paramètres!$B$7)/(Paramètres!$B$8-Paramètres!$B$7))^Paramètres!$B$6)*INDEX(Rôles!$E$5:$E$13,AY23)*INDEX(Rôles!$D$18:$D$22,AZ23),0)} -> 141 | Q23: {=ROUND(Paramètres!$B$20*(Paramètres!$B$5+(1-Paramètres!$B$5)*((K23-Paramètres!$B$7)/(Paramètres!$B$8-Paramètres!$B$7))^Paramètres!$B$6)*INDEX(Rôles!$F$5:$F$13,AY23),0)} -> 13 | R23: =ROUND(Paramètres!$B$64*$AX23*INDEX(Rôles!$N$5:$N$13,$AY23)*INDEX(Rôles!$I$18:$I$22,$AZ23),0) -> 15 | S23: {=MIN(1,ROUND(Paramètres!$B$21*INDEX(Rôles!$G$5:$G$13,AY23),3))} -> 0.765 | T23: {=MIN(Paramètres!$B$28,ROUND(Paramètres!$B$22*INDEX(Rôles!$H$5:$H$13,AY23),3))} -> 0.03 | U23: {=ROUND(Paramètres!$B$23*INDEX(Rôles!$I$5:$I$13,AY23),3)} -> 0.5 | V23: {=MIN(Paramètres!$B$29,ROUND(Paramètres!$B$24*INDEX(Rôles!$J$5:$J$13,AY23),3))} -> 0.04 | W23: {=MIN(Paramètres!$B$27,ROUND((Paramètres!$B$25+(Paramètres!$B$26-Paramètres!$B$25)*(K23-Paramètres!$B$7)/(Paramètres!$B$8-Paramètres!$B$7))*INDEX(Rôles!$K$5:$K$13,AY23)+INDEX(Rôles!$G$18:$G$22,AZ23),3))} -> 0.318 | X23: =ROUND(1-(1-P23/(P23+(Paramètres!$B$19*(Paramètres!$B$5+(1-Paramètres!$B$5)*((K23-Paramètres!$B$7)/(Paramètres!$B$8-Paramètres!$B$7))^Paramètres!$B$6)*(1-Paramètres!$B$30)/Paramètres!$B$30)))*(1-O23/(O23+(Paramètres!$B$18*(Paramètres!$B$5+(1-Paramètres!$B$5)*((K23-Paramètres!$B$7)/(Paramètres!$B$8-Paramètres!$B$7))^Paramètres!$B$6)*(1-Paramètres!$B$31)/Paramètres!$B$31))),3) -> 0.472 | Y23: =ROUND(O23/(O23+(Paramètres!$B$18*(Paramètres!$B$5+(1-Paramètres!$B$5)*((K23-Paramètres!$B$7)/(Paramètres!$B$8-Paramètres!$B$7))^Paramètres!$B$6)*(1-Paramètres!$B$31)/Paramètres!$B$31)),3) -> 0.216 | Z23: {=IF(E23="Neutre",0,MIN(1,INDEX(Rôles!$L$5:$L$13,AY23)+INDEX(Rôles!$F$18:$F$22,AZ23)))} -> 0.6 | AA23: {=ROUND(INDEX(Rôles!$C$18:$C$22,AZ23)*INDEX(Rôles!$C$5:$C$13,AY23),4)} -> 0.0285 | AB23: {=ROUND(INDEX(Rôles!$B$18:$B$22,AZ23)*INDEX(Rôles!$B$5:$B$13,AY23),2)} -> 18 | AC23: {=INDEX(Rôles!$E$18:$E$22,AZ23)} -> 8 | AD23: {=INDEX(Éléments!$F$5:$F$14,MATCH(E23,Éléments!$A$5:$A$14,0))} -> Acide, Vent | AE23: {=INDEX(Éléments!$G$5:$G$14,MATCH(E23,Éléments!$A$5:$A$14,0))} -> Électricité | AF23: Garde brisée | AG23: 0.35 | AH23: Assommé | AI23: 0.25 | AJ23: {=ROUND(ROUND(Paramètres!$B$49*K23^Paramètres!$B$50,0)*INDEX(Rôles!$E$18:$E$22,AZ23),0)} -> 2032 | AK23: {=ROUND(ROUND(Paramètres!$B$53*K23^Paramètres!$B$54,0)*INDEX(Rôles!$E$18:$E$22,AZ23),0)} -> 1368 | AL23: =INDEX(Butin!$B$7:$B$11,AZ23) -> 1 | AM23: =INDEX(Butin!$E$7:$E$11,AZ23) -> 1.4 | AN23: =IF($H23="Boss",INDEX(Butin!$E$28:$K$37,MATCH($B23,Éléments!$C$5:$C$14,1),1),IF($H23="Dragon",INDEX(Butin!$E$41:$K$50,MATCH($B23,Éléments!$C$5:$C$14,1),1),INDEX(Butin!$E$15:$K$24,MATCH($B23,Éléments!$C$5:$C$14,1),1))) -> 0.28 | AO23: =IF($H23="Boss",INDEX(Butin!$E$28:$K$37,MATCH($B23,Éléments!$C$5:$C$14,1),2),IF($H23="Dragon",INDEX(Butin!$E$41:$K$50,MATCH($B23,Éléments!$C$5:$C$14,1),2),INDEX(Butin!$E$15:$K$24,MATCH($B23,Éléments!$C$5:$C$14,1),2))) -> 0.38 | AP23: =IF($H23="Boss",INDEX(Butin!$E$28:$K$37,MATCH($B23,Éléments!$C$5:$C$14,1),3),IF($H23="Dragon",INDEX(Butin!$E$41:$K$50,MATCH($B23,Éléments!$C$5:$C$14,1),3),INDEX(Butin!$E$15:$K$24,MATCH($B23,Éléments!$C$5:$C$14,1),3))) -> 0.24 | AQ23: =IF($H23="Boss",INDEX(Butin!$E$28:$K$37,MATCH($B23,Éléments!$C$5:$C$14,1),4),IF($H23="Dragon",INDEX(Butin!$E$41:$K$50,MATCH($B23,Éléments!$C$5:$C$14,1),4),INDEX(Butin!$E$15:$K$24,MATCH($B23,Éléments!$C$5:$C$14,1),4))) -> 0.08 | AR23: =IF($H23="Boss",INDEX(Butin!$E$28:$K$37,MATCH($B23,Éléments!$C$5:$C$14,1),5),IF($H23="Dragon",INDEX(Butin!$E$41:$K$50,MATCH($B23,Éléments!$C$5:$C$14,1),5),INDEX(Butin!$E$15:$K$24,MATCH($B23,Éléments!$C$5:$C$14,1),5))) -> 0 | AS23: =IF($H23="Boss",INDEX(Butin!$E$28:$K$37,MATCH($B23,Éléments!$C$5:$C$14,1),6),IF($H23="Dragon",INDEX(Butin!$E$41:$K$50,MATCH($B23,Éléments!$C$5:$C$14,1),6),INDEX(Butin!$E$15:$K$24,MATCH($B23,Éléments!$C$5:$C$14,1),6))) -> 0 | AT23: =IF($H23="Boss",INDEX(Butin!$E$28:$K$37,MATCH($B23,Éléments!$C$5:$C$14,1),7),IF($H23="Dragon",INDEX(Butin!$E$41:$K$50,MATCH($B23,Éléments!$C$5:$C$14,1),7),INDEX(Butin!$E$15:$K$24,MATCH($B23,Éléments!$C$5:$C$14,1),7))) -> 0.02 | AU23: =IF(AT23=0,"—",INDEX(Butin!$D$54:$D$63,MATCH($B23,Éléments!$C$5:$C$14,1))&" · "&INDEX(Butin!$F$54:$F$63,MATCH($B23,Éléments!$C$5:$C$14,1))&" · "&INDEX(Butin!$H$54:$H$63,MATCH($B23,Éléments!$C$5:$C$14,1))) -> Plastron du Titan de Pierre · Sceau de la Terre Ancestrale · Pendentif de la Sentinelle de Pierre | AV23: Chef orc | AW23: =B23&IF(G23="Oui","|B","|N") -> 20|B | AX23: =(Paramètres!$B$5+(1-Paramètres!$B$5)*((K23-Paramètres!$B$7)/(Paramètres!$B$8-Paramètres!$B$7))^Paramètres!$B$6) -> 0.18105865 | AY23: =MATCH(I23,Rôles!$A$5:$A$13,0) -> 2 | AZ23: =MATCH(H23,Rôles!$A$18:$A$22,0) -> 4
A24: MON-018 | B24: 20 | C24: {=INDEX(Zones!$B$6:$B$35,MATCH(B24,Zones!$A$6:$A$35,0))} -> Grotte profonde | D24: {=INDEX(Éléments!$B$5:$B$14,MATCH(B24,Éléments!$C$5:$C$14,1))} -> Montagne | E24: {=INDEX(Éléments!$A$5:$A$14,MATCH(B24,Éléments!$C$5:$C$14,1))} -> Terre | F24: Orc | G24: =IF(OR(H24="Boss",H24="Dragon"),"Oui","Non") -> Non | H24: Normal | I24: Guerrier | J24: Physique | K24: =IF($F$3="",B24,$F$3) -> 20 | L24: {=ROUND(Paramètres!$B$16*(Paramètres!$B$5+(1-Paramètres!$B$5)*((K24-Paramètres!$B$7)/(Paramètres!$B$8-Paramètres!$B$7))^Paramètres!$B$6)*INDEX(Rôles!$B$18:$B$22,AZ24)*INDEX(Rôles!$B$5:$B$13,AY24),0)} -> 328 | M24: {=ROUND(IF(J24="Physique",1,IF(J24="Mixte",Paramètres!$B$32,0))*Paramètres!$B$12*(Paramètres!$B$5+(1-Paramètres!$B$5)*((K24-Paramètres!$B$7)/(Paramètres!$B$8-Paramètres!$B$7))^Paramètres!$B$6)*INDEX(Rôles!$C$18:$C$22,AZ24)*INDEX(Rôles!$C$5:$C$13,AY24)/(Paramètres!$B$35*(1-Paramètres!$B$36)),0)} -> 62 | N24: {=ROUND(IF(J24="Magique",1,IF(J24="Mixte",Paramètres!$B$32,0))*Paramètres!$B$12*(Paramètres!$B$5+(1-Paramètres!$B$5)*((K24-Paramètres!$B$7)/(Paramètres!$B$8-Paramètres!$B$7))^Paramètres!$B$6)*INDEX(Rôles!$C$18:$C$22,AZ24)*INDEX(Rôles!$C$5:$C$13,AY24)/(Paramètres!$B$35*(1-Paramètres!$B$36)),0)} -> 0 | O24: {=ROUND(Paramètres!$B$18*(Paramètres!$B$5+(1-Paramètres!$B$5)*((K24-Paramètres!$B$7)/(Paramètres!$B$8-Paramètres!$B$7))^Paramètres!$B$6)*INDEX(Rôles!$D$5:$D$13,AY24)*INDEX(Rôles!$D$18:$D$22,AZ24),0)} -> 81 | P24: {=ROUND(Paramètres!$B$19*(Paramètres!$B$5+(1-Paramètres!$B$5)*((K24-Paramètres!$B$7)/(Paramètres!$B$8-Paramètres!$B$7))^Paramètres!$B$6)*INDEX(Rôles!$E$5:$E$13,AY24)*INDEX(Rôles!$D$18:$D$22,AZ24),0)} -> 87 | Q24: {=ROUND(Paramètres!$B$20*(Paramètres!$B$5+(1-Paramètres!$B$5)*((K24-Paramètres!$B$7)/(Paramètres!$B$8-Paramètres!$B$7))^Paramètres!$B$6)*INDEX(Rôles!$F$5:$F$13,AY24),0)} -> 20 | R24: =ROUND(Paramètres!$B$64*$AX24*INDEX(Rôles!$N$5:$N$13,$AY24)*INDEX(Rôles!$I$18:$I$22,$AZ24),0) -> 17 | S24: {=MIN(1,ROUND(Paramètres!$B$21*INDEX(Rôles!$G$5:$G$13,AY24),3))} -> 0.9 | T24: {=MIN(Paramètres!$B$28,ROUND(Paramètres!$B$22*INDEX(Rôles!$H$5:$H$13,AY24),3))} -> 0.05 | U24: {=ROUND(Paramètres!$B$23*INDEX(Rôles!$I$5:$I$13,AY24),3)} -> 0.5 | V24: {=MIN(Paramètres!$B$29,ROUND(Paramètres!$B$24*INDEX(Rôles!$J$5:$J$13,AY24),3))} -> 0.05 | W24: {=MIN(Paramètres!$B$27,ROUND((Paramètres!$B$25+(Paramètres!$B$26-Paramètres!$B$25)*(K24-Paramètres!$B$7)/(Paramètres!$B$8-Paramètres!$B$7))*INDEX(Rôles!$K$5:$K$13,AY24)+INDEX(Rôles!$G$18:$G$22,AZ24),3))} -> 0.098 | X24: =ROUND(1-(1-P24/(P24+(Paramètres!$B$19*(Paramètres!$B$5+(1-Paramètres!$B$5)*((K24-Paramètres!$B$7)/(Paramètres!$B$8-Paramètres!$B$7))^Paramètres!$B$6)*(1-Paramètres!$B$30)/Paramètres!$B$30)))*(1-O24/(O24+(Paramètres!$B$18*(Paramètres!$B$5+(1-Paramètres!$B$5)*((K24-Paramètres!$B$7)/(Paramètres!$B$8-Paramètres!$B$7))^Paramètres!$B$6)*(1-Paramètres!$B$31)/Paramètres!$B$31))),3) -> 0.346 | Y24: =ROUND(O24/(O24+(Paramètres!$B$18*(Paramètres!$B$5+(1-Paramètres!$B$5)*((K24-Paramètres!$B$7)/(Paramètres!$B$8-Paramètres!$B$7))^Paramètres!$B$6)*(1-Paramètres!$B$31)/Paramètres!$B$31)),3) -> 0.149 | Z24: {=IF(E24="Neutre",0,MIN(1,INDEX(Rôles!$L$5:$L$13,AY24)+INDEX(Rôles!$F$18:$F$22,AZ24)))} -> 0.5 | AA24: {=ROUND(INDEX(Rôles!$C$18:$C$22,AZ24)*INDEX(Rôles!$C$5:$C$13,AY24),4)} -> 0.015 | AB24: {=ROUND(INDEX(Rôles!$B$18:$B$22,AZ24)*INDEX(Rôles!$B$5:$B$13,AY24),2)} -> 2.3 | AC24: {=INDEX(Rôles!$E$18:$E$22,AZ24)} -> 1 | AD24: {=INDEX(Éléments!$F$5:$F$14,MATCH(E24,Éléments!$A$5:$A$14,0))} -> Acide, Vent | AE24: {=INDEX(Éléments!$G$5:$G$14,MATCH(E24,Éléments!$A$5:$A$14,0))} -> Électricité | AF24: Garde brisée | AG24: 0.2 | AH24: Saignement | AI24: 0.15 | AJ24: {=ROUND(ROUND(Paramètres!$B$49*K24^Paramètres!$B$50,0)*INDEX(Rôles!$E$18:$E$22,AZ24),0)} -> 254 | AK24: {=ROUND(ROUND(Paramètres!$B$53*K24^Paramètres!$B$54,0)*INDEX(Rôles!$E$18:$E$22,AZ24),0)} -> 171 | AL24: =INDEX(Butin!$B$7:$B$11,AZ24) -> 0.05 | AM24: =INDEX(Butin!$E$7:$E$11,AZ24) -> 0.05 | AN24: =IF($H24="Boss",INDEX(Butin!$E$28:$K$37,MATCH($B24,Éléments!$C$5:$C$14,1),1),IF($H24="Dragon",INDEX(Butin!$E$41:$K$50,MATCH($B24,Éléments!$C$5:$C$14,1),1),INDEX(Butin!$E$15:$K$24,MATCH($B24,Éléments!$C$5:$C$14,1),1))) -> 0.65 | AO24: =IF($H24="Boss",INDEX(Butin!$E$28:$K$37,MATCH($B24,Éléments!$C$5:$C$14,1),2),IF($H24="Dragon",INDEX(Butin!$E$41:$K$50,MATCH($B24,Éléments!$C$5:$C$14,1),2),INDEX(Butin!$E$15:$K$24,MATCH($B24,Éléments!$C$5:$C$14,1),2))) -> 0.28 | AP24: =IF($H24="Boss",INDEX(Butin!$E$28:$K$37,MATCH($B24,Éléments!$C$5:$C$14,1),3),IF($H24="Dragon",INDEX(Butin!$E$41:$K$50,MATCH($B24,Éléments!$C$5:$C$14,1),3),INDEX(Butin!$E$15:$K$24,MATCH($B24,Éléments!$C$5:$C$14,1),3))) -> 0.07 | AQ24: =IF($H24="Boss",INDEX(Butin!$E$28:$K$37,MATCH($B24,Éléments!$C$5:$C$14,1),4),IF($H24="Dragon",INDEX(Butin!$E$41:$K$50,MATCH($B24,Éléments!$C$5:$C$14,1),4),INDEX(Butin!$E$15:$K$24,MATCH($B24,Éléments!$C$5:$C$14,1),4))) -> 0 | AR24: =IF($H24="Boss",INDEX(Butin!$E$28:$K$37,MATCH($B24,Éléments!$C$5:$C$14,1),5),IF($H24="Dragon",INDEX(Butin!$E$41:$K$50,MATCH($B24,Éléments!$C$5:$C$14,1),5),INDEX(Butin!$E$15:$K$24,MATCH($B24,Éléments!$C$5:$C$14,1),5))) -> 0 | AS24: =IF($H24="Boss",INDEX(Butin!$E$28:$K$37,MATCH($B24,Éléments!$C$5:$C$14,1),6),IF($H24="Dragon",INDEX(Butin!$E$41:$K$50,MATCH($B24,Éléments!$C$5:$C$14,1),6),INDEX(Butin!$E$15:$K$24,MATCH($B24,Éléments!$C$5:$C$14,1),6))) -> 0 | AT24: =IF($H24="Boss",INDEX(Butin!$E$28:$K$37,MATCH($B24,Éléments!$C$5:$C$14,1),7),IF($H24="Dragon",INDEX(Butin!$E$41:$K$50,MATCH($B24,Éléments!$C$5:$C$14,1),7),INDEX(Butin!$E$15:$K$24,MATCH($B24,Éléments!$C$5:$C$14,1),7))) -> 0 | AU24: =IF(AT24=0,"—",INDEX(Butin!$D$54:$D$63,MATCH($B24,Éléments!$C$5:$C$14,1))&" · "&INDEX(Butin!$F$54:$F$63,MATCH($B24,Éléments!$C$5:$C$14,1))&" · "&INDEX(Butin!$H$54:$H$63,MATCH($B24,Éléments!$C$5:$C$14,1))) -> — | AV24: Orc | AW24: =B24&IF(G24="Oui","|B","|N") -> 20|N | AX24: =(Paramètres!$B$5+(1-Paramètres!$B$5)*((K24-Paramètres!$B$7)/(Paramètres!$B$8-Paramètres!$B$7))^Paramètres!$B$6) -> 0.18105865 | AY24: =MATCH(I24,Rôles!$A$5:$A$13,0) -> 3 | AZ24: =MATCH(H24,Rôles!$A$18:$A$22,0) -> 2
A25: MON-019 | B25: 20 | C25: {=INDEX(Zones!$B$6:$B$35,MATCH(B25,Zones!$A$6:$A$35,0))} -> Grotte profonde | D25: {=INDEX(Éléments!$B$5:$B$14,MATCH(B25,Éléments!$C$5:$C$14,1))} -> Montagne | E25: {=INDEX(Éléments!$A$5:$A$14,MATCH(B25,Éléments!$C$5:$C$14,1))} -> Terre | F25: Guerrier orc | G25: =IF(OR(H25="Boss",H25="Dragon"),"Oui","Non") -> Non | H25: Fort | I25: Guerrier | J25: Physique | K25: =IF($F$3="",B25,$F$3) -> 20 | L25: {=ROUND(Paramètres!$B$16*(Paramètres!$B$5+(1-Paramètres!$B$5)*((K25-Paramètres!$B$7)/(Paramètres!$B$8-Paramètres!$B$7))^Paramètres!$B$6)*INDEX(Rôles!$B$18:$B$22,AZ25)*INDEX(Rôles!$B$5:$B$13,AY25),0)} -> 459 | M25: {=ROUND(IF(J25="Physique",1,IF(J25="Mixte",Paramètres!$B$32,0))*Paramètres!$B$12*(Paramètres!$B$5+(1-Paramètres!$B$5)*((K25-Paramètres!$B$7)/(Paramètres!$B$8-Paramètres!$B$7))^Paramètres!$B$6)*INDEX(Rôles!$C$18:$C$22,AZ25)*INDEX(Rôles!$C$5:$C$13,AY25)/(Paramètres!$B$35*(1-Paramètres!$B$36)),0)} -> 79 | N25: {=ROUND(IF(J25="Magique",1,IF(J25="Mixte",Paramètres!$B$32,0))*Paramètres!$B$12*(Paramètres!$B$5+(1-Paramètres!$B$5)*((K25-Paramètres!$B$7)/(Paramètres!$B$8-Paramètres!$B$7))^Paramètres!$B$6)*INDEX(Rôles!$C$18:$C$22,AZ25)*INDEX(Rôles!$C$5:$C$13,AY25)/(Paramètres!$B$35*(1-Paramètres!$B$36)),0)} -> 0 | O25: {=ROUND(Paramètres!$B$18*(Paramètres!$B$5+(1-Paramètres!$B$5)*((K25-Paramètres!$B$7)/(Paramètres!$B$8-Paramètres!$B$7))^Paramètres!$B$6)*INDEX(Rôles!$D$5:$D$13,AY25)*INDEX(Rôles!$D$18:$D$22,AZ25),0)} -> 94 | P25: {=ROUND(Paramètres!$B$19*(Paramètres!$B$5+(1-Paramètres!$B$5)*((K25-Paramètres!$B$7)/(Paramètres!$B$8-Paramètres!$B$7))^Paramètres!$B$6)*INDEX(Rôles!$E$5:$E$13,AY25)*INDEX(Rôles!$D$18:$D$22,AZ25),0)} -> 100 | Q25: {=ROUND(Paramètres!$B$20*(Paramètres!$B$5+(1-Paramètres!$B$5)*((K25-Paramètres!$B$7)/(Paramètres!$B$8-Paramètres!$B$7))^Paramètres!$B$6)*INDEX(Rôles!$F$5:$F$13,AY25),0)} -> 20 | R25: =ROUND(Paramètres!$B$64*$AX25*INDEX(Rôles!$N$5:$N$13,$AY25)*INDEX(Rôles!$I$18:$I$22,$AZ25),0) -> 18 | S25: {=MIN(1,ROUND(Paramètres!$B$21*INDEX(Rôles!$G$5:$G$13,AY25),3))} -> 0.9 | T25: {=MIN(Paramètres!$B$28,ROUND(Paramètres!$B$22*INDEX(Rôles!$H$5:$H$13,AY25),3))} -> 0.05 | U25: {=ROUND(Paramètres!$B$23*INDEX(Rôles!$I$5:$I$13,AY25),3)} -> 0.5 | V25: {=MIN(Paramètres!$B$29,ROUND(Paramètres!$B$24*INDEX(Rôles!$J$5:$J$13,AY25),3))} -> 0.05 | W25: {=MIN(Paramètres!$B$27,ROUND((Paramètres!$B$25+(Paramètres!$B$26-Paramètres!$B$25)*(K25-Paramètres!$B$7)/(Paramètres!$B$8-Paramètres!$B$7))*INDEX(Rôles!$K$5:$K$13,AY25)+INDEX(Rôles!$G$18:$G$22,AZ25),3))} -> 0.098 | X25: =ROUND(1-(1-P25/(P25+(Paramètres!$B$19*(Paramètres!$B$5+(1-Paramètres!$B$5)*((K25-Paramètres!$B$7)/(Paramètres!$B$8-Paramètres!$B$7))^Paramètres!$B$6)*(1-Paramètres!$B$30)/Paramètres!$B$30)))*(1-O25/(O25+(Paramètres!$B$18*(Paramètres!$B$5+(1-Paramètres!$B$5)*((K25-Paramètres!$B$7)/(Paramètres!$B$8-Paramètres!$B$7))^Paramètres!$B$6)*(1-Paramètres!$B$31)/Paramètres!$B$31))),3) -> 0.382 | Y25: =ROUND(O25/(O25+(Paramètres!$B$18*(Paramètres!$B$5+(1-Paramètres!$B$5)*((K25-Paramètres!$B$7)/(Paramètres!$B$8-Paramètres!$B$7))^Paramètres!$B$6)*(1-Paramètres!$B$31)/Paramètres!$B$31)),3) -> 0.169 | Z25: {=IF(E25="Neutre",0,MIN(1,INDEX(Rôles!$L$5:$L$13,AY25)+INDEX(Rôles!$F$18:$F$22,AZ25)))} -> 0.5 | AA25: {=ROUND(INDEX(Rôles!$C$18:$C$22,AZ25)*INDEX(Rôles!$C$5:$C$13,AY25),4)} -> 0.019 | AB25: {=ROUND(INDEX(Rôles!$B$18:$B$22,AZ25)*INDEX(Rôles!$B$5:$B$13,AY25),2)} -> 3.22 | AC25: {=INDEX(Rôles!$E$18:$E$22,AZ25)} -> 1.4 | AD25: {=INDEX(Éléments!$F$5:$F$14,MATCH(E25,Éléments!$A$5:$A$14,0))} -> Acide, Vent | AE25: {=INDEX(Éléments!$G$5:$G$14,MATCH(E25,Éléments!$A$5:$A$14,0))} -> Électricité | AF25: Garde brisée | AG25: 0.25 | AH25: Assommé | AI25: 0.12 | AJ25: {=ROUND(ROUND(Paramètres!$B$49*K25^Paramètres!$B$50,0)*INDEX(Rôles!$E$18:$E$22,AZ25),0)} -> 356 | AK25: {=ROUND(ROUND(Paramètres!$B$53*K25^Paramètres!$B$54,0)*INDEX(Rôles!$E$18:$E$22,AZ25),0)} -> 239 | AL25: =INDEX(Butin!$B$7:$B$11,AZ25) -> 0.08 | AM25: =INDEX(Butin!$E$7:$E$11,AZ25) -> 0.08 | AN25: =IF($H25="Boss",INDEX(Butin!$E$28:$K$37,MATCH($B25,Éléments!$C$5:$C$14,1),1),IF($H25="Dragon",INDEX(Butin!$E$41:$K$50,MATCH($B25,Éléments!$C$5:$C$14,1),1),INDEX(Butin!$E$15:$K$24,MATCH($B25,Éléments!$C$5:$C$14,1),1))) -> 0.65 | AO25: =IF($H25="Boss",INDEX(Butin!$E$28:$K$37,MATCH($B25,Éléments!$C$5:$C$14,1),2),IF($H25="Dragon",INDEX(Butin!$E$41:$K$50,MATCH($B25,Éléments!$C$5:$C$14,1),2),INDEX(Butin!$E$15:$K$24,MATCH($B25,Éléments!$C$5:$C$14,1),2))) -> 0.28 | AP25: =IF($H25="Boss",INDEX(Butin!$E$28:$K$37,MATCH($B25,Éléments!$C$5:$C$14,1),3),IF($H25="Dragon",INDEX(Butin!$E$41:$K$50,MATCH($B25,Éléments!$C$5:$C$14,1),3),INDEX(Butin!$E$15:$K$24,MATCH($B25,Éléments!$C$5:$C$14,1),3))) -> 0.07 | AQ25: =IF($H25="Boss",INDEX(Butin!$E$28:$K$37,MATCH($B25,Éléments!$C$5:$C$14,1),4),IF($H25="Dragon",INDEX(Butin!$E$41:$K$50,MATCH($B25,Éléments!$C$5:$C$14,1),4),INDEX(Butin!$E$15:$K$24,MATCH($B25,Éléments!$C$5:$C$14,1),4))) -> 0 | AR25: =IF($H25="Boss",INDEX(Butin!$E$28:$K$37,MATCH($B25,Éléments!$C$5:$C$14,1),5),IF($H25="Dragon",INDEX(Butin!$E$41:$K$50,MATCH($B25,Éléments!$C$5:$C$14,1),5),INDEX(Butin!$E$15:$K$24,MATCH($B25,Éléments!$C$5:$C$14,1),5))) -> 0 | AS25: =IF($H25="Boss",INDEX(Butin!$E$28:$K$37,MATCH($B25,Éléments!$C$5:$C$14,1),6),IF($H25="Dragon",INDEX(Butin!$E$41:$K$50,MATCH($B25,Éléments!$C$5:$C$14,1),6),INDEX(Butin!$E$15:$K$24,MATCH($B25,Éléments!$C$5:$C$14,1),6))) -> 0 | AT25: =IF($H25="Boss",INDEX(Butin!$E$28:$K$37,MATCH($B25,Éléments!$C$5:$C$14,1),7),IF($H25="Dragon",INDEX(Butin!$E$41:$K$50,MATCH($B25,Éléments!$C$5:$C$14,1),7),INDEX(Butin!$E$15:$K$24,MATCH($B25,Éléments!$C$5:$C$14,1),7))) -> 0 | AU25: =IF(AT25=0,"—",INDEX(Butin!$D$54:$D$63,MATCH($B25,Éléments!$C$5:$C$14,1))&" · "&INDEX(Butin!$F$54:$F$63,MATCH($B25,Éléments!$C$5:$C$14,1))&" · "&INDEX(Butin!$H$54:$H$63,MATCH($B25,Éléments!$C$5:$C$14,1))) -> — | AV25: Guerrier orc | AW25: =B25&IF(G25="Oui","|B","|N") -> 20|N | AX25: =(Paramètres!$B$5+(1-Paramètres!$B$5)*((K25-Paramètres!$B$7)/(Paramètres!$B$8-Paramètres!$B$7))^Paramètres!$B$6) -> 0.18105865 | AY25: =MATCH(I25,Rôles!$A$5:$A$13,0) -> 3 | AZ25: =MATCH(H25,Rôles!$A$18:$A$22,0) -> 3
A26: MON-020 | B26: 20 | C26: {=INDEX(Zones!$B$6:$B$35,MATCH(B26,Zones!$A$6:$A$35,0))} -> Grotte profonde | D26: {=INDEX(Éléments!$B$5:$B$14,MATCH(B26,Éléments!$C$5:$C$14,1))} -> Montagne | E26: {=INDEX(Éléments!$A$5:$A$14,MATCH(B26,Éléments!$C$5:$C$14,1))} -> Terre | F26: Chaman orc | G26: =IF(OR(H26="Boss",H26="Dragon"),"Oui","Non") -> Non | H26: Normal | I26: Mage | J26: Magique | K26: =IF($F$3="",B26,$F$3) -> 20 | L26: {=ROUND(Paramètres!$B$16*(Paramètres!$B$5+(1-Paramètres!$B$5)*((K26-Paramètres!$B$7)/(Paramètres!$B$8-Paramètres!$B$7))^Paramètres!$B$6)*INDEX(Rôles!$B$18:$B$22,AZ26)*INDEX(Rôles!$B$5:$B$13,AY26),0)} -> 200 | M26: {=ROUND(IF(J26="Physique",1,IF(J26="Mixte",Paramètres!$B$32,0))*Paramètres!$B$12*(Paramètres!$B$5+(1-Paramètres!$B$5)*((K26-Paramètres!$B$7)/(Paramètres!$B$8-Paramètres!$B$7))^Paramètres!$B$6)*INDEX(Rôles!$C$18:$C$22,AZ26)*INDEX(Rôles!$C$5:$C$13,AY26)/(Paramètres!$B$35*(1-Paramètres!$B$36)),0)} -> 0 | N26: {=ROUND(IF(J26="Magique",1,IF(J26="Mixte",Paramètres!$B$32,0))*Paramètres!$B$12*(Paramètres!$B$5+(1-Paramètres!$B$5)*((K26-Paramètres!$B$7)/(Paramètres!$B$8-Paramètres!$B$7))^Paramètres!$B$6)*INDEX(Rôles!$C$18:$C$22,AZ26)*INDEX(Rôles!$C$5:$C$13,AY26)/(Paramètres!$B$35*(1-Paramètres!$B$36)),0)} -> 78 | O26: {=ROUND(Paramètres!$B$18*(Paramètres!$B$5+(1-Paramètres!$B$5)*((K26-Paramètres!$B$7)/(Paramètres!$B$8-Paramètres!$B$7))^Paramètres!$B$6)*INDEX(Rôles!$D$5:$D$13,AY26)*INDEX(Rôles!$D$18:$D$22,AZ26),0)} -> 90 | P26: {=ROUND(Paramètres!$B$19*(Paramètres!$B$5+(1-Paramètres!$B$5)*((K26-Paramètres!$B$7)/(Paramètres!$B$8-Paramètres!$B$7))^Paramètres!$B$6)*INDEX(Rôles!$E$5:$E$13,AY26)*INDEX(Rôles!$D$18:$D$22,AZ26),0)} -> 29 | Q26: {=ROUND(Paramètres!$B$20*(Paramètres!$B$5+(1-Paramètres!$B$5)*((K26-Paramètres!$B$7)/(Paramètres!$B$8-Paramètres!$B$7))^Paramètres!$B$6)*INDEX(Rôles!$F$5:$F$13,AY26),0)} -> 20 | R26: =ROUND(Paramètres!$B$64*$AX26*INDEX(Rôles!$N$5:$N$13,$AY26)*INDEX(Rôles!$I$18:$I$22,$AZ26),0) -> 16 | S26: {=MIN(1,ROUND(Paramètres!$B$21*INDEX(Rôles!$G$5:$G$13,AY26),3))} -> 0.9 | T26: {=MIN(Paramètres!$B$28,ROUND(Paramètres!$B$22*INDEX(Rôles!$H$5:$H$13,AY26),3))} -> 0.05 | U26: {=ROUND(Paramètres!$B$23*INDEX(Rôles!$I$5:$I$13,AY26),3)} -> 0.5 | V26: {=MIN(Paramètres!$B$29,ROUND(Paramètres!$B$24*INDEX(Rôles!$J$5:$J$13,AY26),3))} -> 0.065 | W26: {=MIN(Paramètres!$B$27,ROUND((Paramètres!$B$25+(Paramètres!$B$26-Paramètres!$B$25)*(K26-Paramètres!$B$7)/(Paramètres!$B$8-Paramètres!$B$7))*INDEX(Rôles!$K$5:$K$13,AY26)+INDEX(Rôles!$G$18:$G$22,AZ26),3))} -> 0.118 | X26: =ROUND(1-(1-P26/(P26+(Paramètres!$B$19*(Paramètres!$B$5+(1-Paramètres!$B$5)*((K26-Paramètres!$B$7)/(Paramètres!$B$8-Paramètres!$B$7))^Paramètres!$B$6)*(1-Paramètres!$B$30)/Paramètres!$B$30)))*(1-O26/(O26+(Paramètres!$B$18*(Paramètres!$B$5+(1-Paramètres!$B$5)*((K26-Paramètres!$B$7)/(Paramètres!$B$8-Paramètres!$B$7))^Paramètres!$B$6)*(1-Paramètres!$B$31)/Paramètres!$B$31))),3) -> 0.239 | Y26: =ROUND(O26/(O26+(Paramètres!$B$18*(Paramètres!$B$5+(1-Paramètres!$B$5)*((K26-Paramètres!$B$7)/(Paramètres!$B$8-Paramètres!$B$7))^Paramètres!$B$6)*(1-Paramètres!$B$31)/Paramètres!$B$31)),3) -> 0.163 | Z26: {=IF(E26="Neutre",0,MIN(1,INDEX(Rôles!$L$5:$L$13,AY26)+INDEX(Rôles!$F$18:$F$22,AZ26)))} -> 1 | AA26: {=ROUND(INDEX(Rôles!$C$18:$C$22,AZ26)*INDEX(Rôles!$C$5:$C$13,AY26),4)} -> 0.0188 | AB26: {=ROUND(INDEX(Rôles!$B$18:$B$22,AZ26)*INDEX(Rôles!$B$5:$B$13,AY26),2)} -> 1.4 | AC26: {=INDEX(Rôles!$E$18:$E$22,AZ26)} -> 1 | AD26: {=INDEX(Éléments!$F$5:$F$14,MATCH(E26,Éléments!$A$5:$A$14,0))} -> Acide, Vent | AE26: {=INDEX(Éléments!$G$5:$G$14,MATCH(E26,Éléments!$A$5:$A$14,0))} -> Électricité | AF26: Enraciné | AG26: 0.25 | AH26: Intimidé | AI26: 0.2 | AJ26: {=ROUND(ROUND(Paramètres!$B$49*K26^Paramètres!$B$50,0)*INDEX(Rôles!$E$18:$E$22,AZ26),0)} -> 254 | AK26: {=ROUND(ROUND(Paramètres!$B$53*K26^Paramètres!$B$54,0)*INDEX(Rôles!$E$18:$E$22,AZ26),0)} -> 171 | AL26: =INDEX(Butin!$B$7:$B$11,AZ26) -> 0.05 | AM26: =INDEX(Butin!$E$7:$E$11,AZ26) -> 0.05 | AN26: =IF($H26="Boss",INDEX(Butin!$E$28:$K$37,MATCH($B26,Éléments!$C$5:$C$14,1),1),IF($H26="Dragon",INDEX(Butin!$E$41:$K$50,MATCH($B26,Éléments!$C$5:$C$14,1),1),INDEX(Butin!$E$15:$K$24,MATCH($B26,Éléments!$C$5:$C$14,1),1))) -> 0.65 | AO26: =IF($H26="Boss",INDEX(Butin!$E$28:$K$37,MATCH($B26,Éléments!$C$5:$C$14,1),2),IF($H26="Dragon",INDEX(Butin!$E$41:$K$50,MATCH($B26,Éléments!$C$5:$C$14,1),2),INDEX(Butin!$E$15:$K$24,MATCH($B26,Éléments!$C$5:$C$14,1),2))) -> 0.28 | AP26: =IF($H26="Boss",INDEX(Butin!$E$28:$K$37,MATCH($B26,Éléments!$C$5:$C$14,1),3),IF($H26="Dragon",INDEX(Butin!$E$41:$K$50,MATCH($B26,Éléments!$C$5:$C$14,1),3),INDEX(Butin!$E$15:$K$24,MATCH($B26,Éléments!$C$5:$C$14,1),3))) -> 0.07 | AQ26: =IF($H26="Boss",INDEX(Butin!$E$28:$K$37,MATCH($B26,Éléments!$C$5:$C$14,1),4),IF($H26="Dragon",INDEX(Butin!$E$41:$K$50,MATCH($B26,Éléments!$C$5:$C$14,1),4),INDEX(Butin!$E$15:$K$24,MATCH($B26,Éléments!$C$5:$C$14,1),4))) -> 0 | AR26: =IF($H26="Boss",INDEX(Butin!$E$28:$K$37,MATCH($B26,Éléments!$C$5:$C$14,1),5),IF($H26="Dragon",INDEX(Butin!$E$41:$K$50,MATCH($B26,Éléments!$C$5:$C$14,1),5),INDEX(Butin!$E$15:$K$24,MATCH($B26,Éléments!$C$5:$C$14,1),5))) -> 0 | AS26: =IF($H26="Boss",INDEX(Butin!$E$28:$K$37,MATCH($B26,Éléments!$C$5:$C$14,1),6),IF($H26="Dragon",INDEX(Butin!$E$41:$K$50,MATCH($B26,Éléments!$C$5:$C$14,1),6),INDEX(Butin!$E$15:$K$24,MATCH($B26,Éléments!$C$5:$C$14,1),6))) -> 0 | AT26: =IF($H26="Boss",INDEX(Butin!$E$28:$K$37,MATCH($B26,Éléments!$C$5:$C$14,1),7),IF($H26="Dragon",INDEX(Butin!$E$41:$K$50,MATCH($B26,Éléments!$C$5:$C$14,1),7),INDEX(Butin!$E$15:$K$24,MATCH($B26,Éléments!$C$5:$C$14,1),7))) -> 0 | AU26: =IF(AT26=0,"—",INDEX(Butin!$D$54:$D$63,MATCH($B26,Éléments!$C$5:$C$14,1))&" · "&INDEX(Butin!$F$54:$F$63,MATCH($B26,Éléments!$C$5:$C$14,1))&" · "&INDEX(Butin!$H$54:$H$63,MATCH($B26,Éléments!$C$5:$C$14,1))) -> — | AV26: Chaman orc | AW26: =B26&IF(G26="Oui","|B","|N") -> 20|N | AX26: =(Paramètres!$B$5+(1-Paramètres!$B$5)*((K26-Paramètres!$B$7)/(Paramètres!$B$8-Paramètres!$B$7))^Paramètres!$B$6) -> 0.18105865 | AY26: =MATCH(I26,Rôles!$A$5:$A$13,0) -> 5 | AZ26: =MATCH(H26,Rôles!$A$18:$A$22,0) -> 2
A27: MON-021 | B27: 25 | C27: {=INDEX(Zones!$B$6:$B$35,MATCH(B27,Zones!$A$6:$A$35,0))} -> Océan de lave | D27: {=INDEX(Éléments!$B$5:$B$14,MATCH(B27,Éléments!$C$5:$C$14,1))} -> Volcan | E27: {=INDEX(Éléments!$A$5:$A$14,MATCH(B27,Éléments!$C$5:$C$14,1))} -> Feu | F27: Salamandre | G27: =IF(OR(H27="Boss",H27="Dragon"),"Oui","Non") -> Non | H27: Normal | I27: Bête | J27: Physique | K27: =IF($F$3="",B27,$F$3) -> 25 | L27: {=ROUND(Paramètres!$B$16*(Paramètres!$B$5+(1-Paramètres!$B$5)*((K27-Paramètres!$B$7)/(Paramètres!$B$8-Paramètres!$B$7))^Paramètres!$B$6)*INDEX(Rôles!$B$18:$B$22,AZ27)*INDEX(Rôles!$B$5:$B$13,AY27),0)} -> 334 | M27: {=ROUND(IF(J27="Physique",1,IF(J27="Mixte",Paramètres!$B$32,0))*Paramètres!$B$12*(Paramètres!$B$5+(1-Paramètres!$B$5)*((K27-Paramètres!$B$7)/(Paramètres!$B$8-Paramètres!$B$7))^Paramètres!$B$6)*INDEX(Rôles!$C$18:$C$22,AZ27)*INDEX(Rôles!$C$5:$C$13,AY27)/(Paramètres!$B$35*(1-Paramètres!$B$36)),0)} -> 80 | N27: {=ROUND(IF(J27="Magique",1,IF(J27="Mixte",Paramètres!$B$32,0))*Paramètres!$B$12*(Paramètres!$B$5+(1-Paramètres!$B$5)*((K27-Paramètres!$B$7)/(Paramètres!$B$8-Paramètres!$B$7))^Paramètres!$B$6)*INDEX(Rôles!$C$18:$C$22,AZ27)*INDEX(Rôles!$C$5:$C$13,AY27)/(Paramètres!$B$35*(1-Paramètres!$B$36)),0)} -> 0 | O27: {=ROUND(Paramètres!$B$18*(Paramètres!$B$5+(1-Paramètres!$B$5)*((K27-Paramètres!$B$7)/(Paramètres!$B$8-Paramètres!$B$7))^Paramètres!$B$6)*INDEX(Rôles!$D$5:$D$13,AY27)*INDEX(Rôles!$D$18:$D$22,AZ27),0)} -> 60 | P27: {=ROUND(Paramètres!$B$19*(Paramètres!$B$5+(1-Paramètres!$B$5)*((K27-Paramètres!$B$7)/(Paramètres!$B$8-Paramètres!$B$7))^Paramètres!$B$6)*INDEX(Rôles!$E$5:$E$13,AY27)*INDEX(Rôles!$D$18:$D$22,AZ27),0)} -> 63 | Q27: {=ROUND(Paramètres!$B$20*(Paramètres!$B$5+(1-Paramètres!$B$5)*((K27-Paramètres!$B$7)/(Paramètres!$B$8-Paramètres!$B$7))^Paramètres!$B$6)*INDEX(Rôles!$F$5:$F$13,AY27),0)} -> 32 | R27: =ROUND(Paramètres!$B$64*$AX27*INDEX(Rôles!$N$5:$N$13,$AY27)*INDEX(Rôles!$I$18:$I$22,$AZ27),0) -> 27 | S27: {=MIN(1,ROUND(Paramètres!$B$21*INDEX(Rôles!$G$5:$G$13,AY27),3))} -> 0.9 | T27: {=MIN(Paramètres!$B$28,ROUND(Paramètres!$B$22*INDEX(Rôles!$H$5:$H$13,AY27),3))} -> 0.05 | U27: {=ROUND(Paramètres!$B$23*INDEX(Rôles!$I$5:$I$13,AY27),3)} -> 0.5 | V27: {=MIN(Paramètres!$B$29,ROUND(Paramètres!$B$24*INDEX(Rôles!$J$5:$J$13,AY27),3))} -> 0.025 | W27: {=MIN(Paramètres!$B$27,ROUND((Paramètres!$B$25+(Paramètres!$B$26-Paramètres!$B$25)*(K27-Paramètres!$B$7)/(Paramètres!$B$8-Paramètres!$B$7))*INDEX(Rôles!$K$5:$K$13,AY27)+INDEX(Rôles!$G$18:$G$22,AZ27),3))} -> 0.088 | X27: =ROUND(1-(1-P27/(P27+(Paramètres!$B$19*(Paramètres!$B$5+(1-Paramètres!$B$5)*((K27-Paramètres!$B$7)/(Paramètres!$B$8-Paramètres!$B$7))^Paramètres!$B$6)*(1-Paramètres!$B$30)/Paramètres!$B$30)))*(1-O27/(O27+(Paramètres!$B$18*(Paramètres!$B$5+(1-Paramètres!$B$5)*((K27-Paramètres!$B$7)/(Paramètres!$B$8-Paramètres!$B$7))^Paramètres!$B$6)*(1-Paramètres!$B$31)/Paramètres!$B$31))),3) -> 0.231 | Y27: =ROUND(O27/(O27+(Paramètres!$B$18*(Paramètres!$B$5+(1-Paramètres!$B$5)*((K27-Paramètres!$B$7)/(Paramètres!$B$8-Paramètres!$B$7))^Paramètres!$B$6)*(1-Paramètres!$B$31)/Paramètres!$B$31)),3) -> 0.095 | Z27: {=IF(E27="Neutre",0,MIN(1,INDEX(Rôles!$L$5:$L$13,AY27)+INDEX(Rôles!$F$18:$F$22,AZ27)))} -> 0.5 | AA27: {=ROUND(INDEX(Rôles!$C$18:$C$22,AZ27)*INDEX(Rôles!$C$5:$C$13,AY27),4)} -> 0.0158 | AB27: {=ROUND(INDEX(Rôles!$B$18:$B$22,AZ27)*INDEX(Rôles!$B$5:$B$13,AY27),2)} -> 1.9 | AC27: {=INDEX(Rôles!$E$18:$E$22,AZ27)} -> 1 | AD27: {=INDEX(Éléments!$F$5:$F$14,MATCH(E27,Éléments!$A$5:$A$14,0))} -> Eau | AE27: {=INDEX(Éléments!$G$5:$G$14,MATCH(E27,Éléments!$A$5:$A$14,0))} -> Glace | AF27: Brûlure | AG27: 0.3 | AH27: Saignement | AI27: 0.1 | AJ27: {=ROUND(ROUND(Paramètres!$B$49*K27^Paramètres!$B$50,0)*INDEX(Rôles!$E$18:$E$22,AZ27),0)} -> 335 | AK27: {=ROUND(ROUND(Paramètres!$B$53*K27^Paramètres!$B$54,0)*INDEX(Rôles!$E$18:$E$22,AZ27),0)} -> 231 | AL27: =INDEX(Butin!$B$7:$B$11,AZ27) -> 0.05 | AM27: =INDEX(Butin!$E$7:$E$11,AZ27) -> 0.05 | AN27: =IF($H27="Boss",INDEX(Butin!$E$28:$K$37,MATCH($B27,Éléments!$C$5:$C$14,1),1),IF($H27="Dragon",INDEX(Butin!$E$41:$K$50,MATCH($B27,Éléments!$C$5:$C$14,1),1),INDEX(Butin!$E$15:$K$24,MATCH($B27,Éléments!$C$5:$C$14,1),1))) -> 0.52 | AO27: =IF($H27="Boss",INDEX(Butin!$E$28:$K$37,MATCH($B27,Éléments!$C$5:$C$14,1),2),IF($H27="Dragon",INDEX(Butin!$E$41:$K$50,MATCH($B27,Éléments!$C$5:$C$14,1),2),INDEX(Butin!$E$15:$K$24,MATCH($B27,Éléments!$C$5:$C$14,1),2))) -> 0.32 | AP27: =IF($H27="Boss",INDEX(Butin!$E$28:$K$37,MATCH($B27,Éléments!$C$5:$C$14,1),3),IF($H27="Dragon",INDEX(Butin!$E$41:$K$50,MATCH($B27,Éléments!$C$5:$C$14,1),3),INDEX(Butin!$E$15:$K$24,MATCH($B27,Éléments!$C$5:$C$14,1),3))) -> 0.13 | AQ27: =IF($H27="Boss",INDEX(Butin!$E$28:$K$37,MATCH($B27,Éléments!$C$5:$C$14,1),4),IF($H27="Dragon",INDEX(Butin!$E$41:$K$50,MATCH($B27,Éléments!$C$5:$C$14,1),4),INDEX(Butin!$E$15:$K$24,MATCH($B27,Éléments!$C$5:$C$14,1),4))) -> 0.03 | AR27: =IF($H27="Boss",INDEX(Butin!$E$28:$K$37,MATCH($B27,Éléments!$C$5:$C$14,1),5),IF($H27="Dragon",INDEX(Butin!$E$41:$K$50,MATCH($B27,Éléments!$C$5:$C$14,1),5),INDEX(Butin!$E$15:$K$24,MATCH($B27,Éléments!$C$5:$C$14,1),5))) -> 0 | AS27: =IF($H27="Boss",INDEX(Butin!$E$28:$K$37,MATCH($B27,Éléments!$C$5:$C$14,1),6),IF($H27="Dragon",INDEX(Butin!$E$41:$K$50,MATCH($B27,Éléments!$C$5:$C$14,1),6),INDEX(Butin!$E$15:$K$24,MATCH($B27,Éléments!$C$5:$C$14,1),6))) -> 0 | AT27: =IF($H27="Boss",INDEX(Butin!$E$28:$K$37,MATCH($B27,Éléments!$C$5:$C$14,1),7),IF($H27="Dragon",INDEX(Butin!$E$41:$K$50,MATCH($B27,Éléments!$C$5:$C$14,1),7),INDEX(Butin!$E$15:$K$24,MATCH($B27,Éléments!$C$5:$C$14,1),7))) -> 0 | AU27: =IF(AT27=0,"—",INDEX(Butin!$D$54:$D$63,MATCH($B27,Éléments!$C$5:$C$14,1))&" · "&INDEX(Butin!$F$54:$F$63,MATCH($B27,Éléments!$C$5:$C$14,1))&" · "&INDEX(Butin!$H$54:$H$63,MATCH($B27,Éléments!$C$5:$C$14,1))) -> — | AV27: Salamandre | AW27: =B27&IF(G27="Oui","|B","|N") -> 25|N | AX27: =(Paramètres!$B$5+(1-Paramètres!$B$5)*((K27-Paramètres!$B$7)/(Paramètres!$B$8-Paramètres!$B$7))^Paramètres!$B$6) -> 0.2234662 | AY27: =MATCH(I27,Rôles!$A$5:$A$13,0) -> 1 | AZ27: =MATCH(H27,Rôles!$A$18:$A$22,0) -> 2
A28: MON-022 | B28: 25 | C28: {=INDEX(Zones!$B$6:$B$35,MATCH(B28,Zones!$A$6:$A$35,0))} -> Océan de lave | D28: {=INDEX(Éléments!$B$5:$B$14,MATCH(B28,Éléments!$C$5:$C$14,1))} -> Volcan | E28: {=INDEX(Éléments!$A$5:$A$14,MATCH(B28,Éléments!$C$5:$C$14,1))} -> Feu | F28: Malphite | G28: =IF(OR(H28="Boss",H28="Dragon"),"Oui","Non") -> Oui | H28: Boss | I28: Brute | J28: Physique | K28: =IF($F$3="",B28,$F$3) -> 25 | L28: {=ROUND(Paramètres!$B$16*(Paramètres!$B$5+(1-Paramètres!$B$5)*((K28-Paramètres!$B$7)/(Paramètres!$B$8-Paramètres!$B$7))^Paramètres!$B$6)*INDEX(Rôles!$B$18:$B$22,AZ28)*INDEX(Rôles!$B$5:$B$13,AY28),0)} -> 3168 | M28: {=ROUND(IF(J28="Physique",1,IF(J28="Mixte",Paramètres!$B$32,0))*Paramètres!$B$12*(Paramètres!$B$5+(1-Paramètres!$B$5)*((K28-Paramètres!$B$7)/(Paramètres!$B$8-Paramètres!$B$7))^Paramètres!$B$6)*INDEX(Rôles!$C$18:$C$22,AZ28)*INDEX(Rôles!$C$5:$C$13,AY28)/(Paramètres!$B$35*(1-Paramètres!$B$36)),0)} -> 146 | N28: {=ROUND(IF(J28="Magique",1,IF(J28="Mixte",Paramètres!$B$32,0))*Paramètres!$B$12*(Paramètres!$B$5+(1-Paramètres!$B$5)*((K28-Paramètres!$B$7)/(Paramètres!$B$8-Paramètres!$B$7))^Paramètres!$B$6)*INDEX(Rôles!$C$18:$C$22,AZ28)*INDEX(Rôles!$C$5:$C$13,AY28)/(Paramètres!$B$35*(1-Paramètres!$B$36)),0)} -> 0 | O28: {=ROUND(Paramètres!$B$18*(Paramètres!$B$5+(1-Paramètres!$B$5)*((K28-Paramètres!$B$7)/(Paramètres!$B$8-Paramètres!$B$7))^Paramètres!$B$6)*INDEX(Rôles!$D$5:$D$13,AY28)*INDEX(Rôles!$D$18:$D$22,AZ28),0)} -> 157 | P28: {=ROUND(Paramètres!$B$19*(Paramètres!$B$5+(1-Paramètres!$B$5)*((K28-Paramètres!$B$7)/(Paramètres!$B$8-Paramètres!$B$7))^Paramètres!$B$6)*INDEX(Rôles!$E$5:$E$13,AY28)*INDEX(Rôles!$D$18:$D$22,AZ28),0)} -> 174 | Q28: {=ROUND(Paramètres!$B$20*(Paramètres!$B$5+(1-Paramètres!$B$5)*((K28-Paramètres!$B$7)/(Paramètres!$B$8-Paramètres!$B$7))^Paramètres!$B$6)*INDEX(Rôles!$F$5:$F$13,AY28),0)} -> 16 | R28: =ROUND(Paramètres!$B$64*$AX28*INDEX(Rôles!$N$5:$N$13,$AY28)*INDEX(Rôles!$I$18:$I$22,$AZ28),0) -> 18 | S28: {=MIN(1,ROUND(Paramètres!$B$21*INDEX(Rôles!$G$5:$G$13,AY28),3))} -> 0.765 | T28: {=MIN(Paramètres!$B$28,ROUND(Paramètres!$B$22*INDEX(Rôles!$H$5:$H$13,AY28),3))} -> 0.03 | U28: {=ROUND(Paramètres!$B$23*INDEX(Rôles!$I$5:$I$13,AY28),3)} -> 0.5 | V28: {=MIN(Paramètres!$B$29,ROUND(Paramètres!$B$24*INDEX(Rôles!$J$5:$J$13,AY28),3))} -> 0.04 | W28: {=MIN(Paramètres!$B$27,ROUND((Paramètres!$B$25+(Paramètres!$B$26-Paramètres!$B$25)*(K28-Paramètres!$B$7)/(Paramètres!$B$8-Paramètres!$B$7))*INDEX(Rôles!$K$5:$K$13,AY28)+INDEX(Rôles!$G$18:$G$22,AZ28),3))} -> 0.333 | X28: =ROUND(1-(1-P28/(P28+(Paramètres!$B$19*(Paramètres!$B$5+(1-Paramètres!$B$5)*((K28-Paramètres!$B$7)/(Paramètres!$B$8-Paramètres!$B$7))^Paramètres!$B$6)*(1-Paramètres!$B$30)/Paramètres!$B$30)))*(1-O28/(O28+(Paramètres!$B$18*(Paramètres!$B$5+(1-Paramètres!$B$5)*((K28-Paramètres!$B$7)/(Paramètres!$B$8-Paramètres!$B$7))^Paramètres!$B$6)*(1-Paramètres!$B$31)/Paramètres!$B$31))),3) -> 0.473 | Y28: =ROUND(O28/(O28+(Paramètres!$B$18*(Paramètres!$B$5+(1-Paramètres!$B$5)*((K28-Paramètres!$B$7)/(Paramètres!$B$8-Paramètres!$B$7))^Paramètres!$B$6)*(1-Paramètres!$B$31)/Paramètres!$B$31)),3) -> 0.216 | Z28: {=IF(E28="Neutre",0,MIN(1,INDEX(Rôles!$L$5:$L$13,AY28)+INDEX(Rôles!$F$18:$F$22,AZ28)))} -> 0.6 | AA28: {=ROUND(INDEX(Rôles!$C$18:$C$22,AZ28)*INDEX(Rôles!$C$5:$C$13,AY28),4)} -> 0.0285 | AB28: {=ROUND(INDEX(Rôles!$B$18:$B$22,AZ28)*INDEX(Rôles!$B$5:$B$13,AY28),2)} -> 18 | AC28: {=INDEX(Rôles!$E$18:$E$22,AZ28)} -> 8 | AD28: {=INDEX(Éléments!$F$5:$F$14,MATCH(E28,Éléments!$A$5:$A$14,0))} -> Eau | AE28: {=INDEX(Éléments!$G$5:$G$14,MATCH(E28,Éléments!$A$5:$A$14,0))} -> Glace | AF28: Brûlure | AG28: 0.35 | AH28: Assommé | AI28: 0.3 | AJ28: {=ROUND(ROUND(Paramètres!$B$49*K28^Paramètres!$B$50,0)*INDEX(Rôles!$E$18:$E$22,AZ28),0)} -> 2680 | AK28: {=ROUND(ROUND(Paramètres!$B$53*K28^Paramètres!$B$54,0)*INDEX(Rôles!$E$18:$E$22,AZ28),0)} -> 1848 | AL28: =INDEX(Butin!$B$7:$B$11,AZ28) -> 1 | AM28: =INDEX(Butin!$E$7:$E$11,AZ28) -> 1.4 | AN28: =IF($H28="Boss",INDEX(Butin!$E$28:$K$37,MATCH($B28,Éléments!$C$5:$C$14,1),1),IF($H28="Dragon",INDEX(Butin!$E$41:$K$50,MATCH($B28,Éléments!$C$5:$C$14,1),1),INDEX(Butin!$E$15:$K$24,MATCH($B28,Éléments!$C$5:$C$14,1),1))) -> 0.18 | AO28: =IF($H28="Boss",INDEX(Butin!$E$28:$K$37,MATCH($B28,Éléments!$C$5:$C$14,1),2),IF($H28="Dragon",INDEX(Butin!$E$41:$K$50,MATCH($B28,Éléments!$C$5:$C$14,1),2),INDEX(Butin!$E$15:$K$24,MATCH($B28,Éléments!$C$5:$C$14,1),2))) -> 0.32 | AP28: =IF($H28="Boss",INDEX(Butin!$E$28:$K$37,MATCH($B28,Éléments!$C$5:$C$14,1),3),IF($H28="Dragon",INDEX(Butin!$E$41:$K$50,MATCH($B28,Éléments!$C$5:$C$14,1),3),INDEX(Butin!$E$15:$K$24,MATCH($B28,Éléments!$C$5:$C$14,1),3))) -> 0.3 | AQ28: =IF($H28="Boss",INDEX(Butin!$E$28:$K$37,MATCH($B28,Éléments!$C$5:$C$14,1),4),IF($H28="Dragon",INDEX(Butin!$E$41:$K$50,MATCH($B28,Éléments!$C$5:$C$14,1),4),INDEX(Butin!$E$15:$K$24,MATCH($B28,Éléments!$C$5:$C$14,1),4))) -> 0.14 | AR28: =IF($H28="Boss",INDEX(Butin!$E$28:$K$37,MATCH($B28,Éléments!$C$5:$C$14,1),5),IF($H28="Dragon",INDEX(Butin!$E$41:$K$50,MATCH($B28,Éléments!$C$5:$C$14,1),5),INDEX(Butin!$E$15:$K$24,MATCH($B28,Éléments!$C$5:$C$14,1),5))) -> 0.03 | AS28: =IF($H28="Boss",INDEX(Butin!$E$28:$K$37,MATCH($B28,Éléments!$C$5:$C$14,1),6),IF($H28="Dragon",INDEX(Butin!$E$41:$K$50,MATCH($B28,Éléments!$C$5:$C$14,1),6),INDEX(Butin!$E$15:$K$24,MATCH($B28,Éléments!$C$5:$C$14,1),6))) -> 0 | AT28: =IF($H28="Boss",INDEX(Butin!$E$28:$K$37,MATCH($B28,Éléments!$C$5:$C$14,1),7),IF($H28="Dragon",INDEX(Butin!$E$41:$K$50,MATCH($B28,Éléments!$C$5:$C$14,1),7),INDEX(Butin!$E$15:$K$24,MATCH($B28,Éléments!$C$5:$C$14,1),7))) -> 0.03 | AU28: =IF(AT28=0,"—",INDEX(Butin!$D$54:$D$63,MATCH($B28,Éléments!$C$5:$C$14,1))&" · "&INDEX(Butin!$F$54:$F$63,MATCH($B28,Éléments!$C$5:$C$14,1))&" · "&INDEX(Butin!$H$54:$H$63,MATCH($B28,Éléments!$C$5:$C$14,1))) -> Jambières du Brasier Marchant · Ceinture du Feu Intérieur · Anneau des Flèches Ardentes | AV28: Malphite | AW28: =B28&IF(G28="Oui","|B","|N") -> 25|B | AX28: =(Paramètres!$B$5+(1-Paramètres!$B$5)*((K28-Paramètres!$B$7)/(Paramètres!$B$8-Paramètres!$B$7))^Paramètres!$B$6) -> 0.2234662 | AY28: =MATCH(I28,Rôles!$A$5:$A$13,0) -> 2 | AZ28: =MATCH(H28,Rôles!$A$18:$A$22,0) -> 4
... A31: MON-025 | B31: 30 | C31: {=INDEX(Zones!$B$6:$B$35,MATCH(B31,Zones!$A$6:$A$35,0))} -> Cœur du volcan | D31: {=INDEX(Éléments!$B$5:$B$14,MATCH(B31,Éléments!$C$5:$C$14,1))} -> Volcan | E31: {=INDEX(Éléments!$A$5:$A$14,MATCH(B31,Éléments!$C$5:$C$14,1))} -> Feu | F31: Ifrit | G31: =IF(OR(H31="Boss",H31="Dragon"),"Oui","Non") -> Oui | H31: Boss | I31: Mage | J31: Magique | K31: =IF($F$3="",B31,$F$3) -> 30 | L31: {=ROUND(Paramètres!$B$16*(Paramètres!$B$5+(1-Paramètres!$B$5)*((K31-Paramètres!$B$7)/(Paramètres!$B$8-Paramètres!$B$7))^Paramètres!$B$6)*INDEX(Rôles!$B$18:$B$22,AZ31)*INDEX(Rôles!$B$5:$B$13,AY31),0)} -> 1771 | M31: {=ROUND(IF(J31="Physique",1,IF(J31="Mixte",Paramètres!$B$32,0))*Paramètres!$B$12*(Paramètres!$B$5+(1-Paramètres!$B$5)*((K31-Paramètres!$B$7)/(Paramètres!$B$8-Paramètres!$B$7))^Paramètres!$B$6)*INDEX(Rôles!$C$18:$C$22,AZ31)*INDEX(Rôles!$C$5:$C$13,AY31)/(Paramètres!$B$35*(1-Paramètres!$B$36)),0)} -> 0 | N31: {=ROUND(IF(J31="Magique",1,IF(J31="Mixte",Paramètres!$B$32,0))*Paramètres!$B$12*(Paramètres!$B$5+(1-Paramètres!$B$5)*((K31-Paramètres!$B$7)/(Paramètres!$B$8-Paramètres!$B$7))^Paramètres!$B$6)*INDEX(Rôles!$C$18:$C$22,AZ31)*INDEX(Rôles!$C$5:$C$13,AY31)/(Paramètres!$B$35*(1-Paramètres!$B$36)),0)} -> 229 | O31: {=ROUND(Paramètres!$B$18*(Paramètres!$B$5+(1-Paramètres!$B$5)*((K31-Paramètres!$B$7)/(Paramètres!$B$8-Paramètres!$B$7))^Paramètres!$B$6)*INDEX(Rôles!$D$5:$D$13,AY31)*INDEX(Rôles!$D$18:$D$22,AZ31),0)} -> 172 | P31: {=ROUND(Paramètres!$B$19*(Paramètres!$B$5+(1-Paramètres!$B$5)*((K31-Paramètres!$B$7)/(Paramètres!$B$8-Paramètres!$B$7))^Paramètres!$B$6)*INDEX(Rôles!$E$5:$E$13,AY31)*INDEX(Rôles!$D$18:$D$22,AZ31),0)} -> 56 | Q31: {=ROUND(Paramètres!$B$20*(Paramètres!$B$5+(1-Paramètres!$B$5)*((K31-Paramètres!$B$7)/(Paramètres!$B$8-Paramètres!$B$7))^Paramètres!$B$6)*INDEX(Rôles!$F$5:$F$13,AY31),0)} -> 29 | R31: =ROUND(Paramètres!$B$64*$AX31*INDEX(Rôles!$N$5:$N$13,$AY31)*INDEX(Rôles!$I$18:$I$22,$AZ31),0) -> 28 | S31: {=MIN(1,ROUND(Paramètres!$B$21*INDEX(Rôles!$G$5:$G$13,AY31),3))} -> 0.9 | T31: {=MIN(Paramètres!$B$28,ROUND(Paramètres!$B$22*INDEX(Rôles!$H$5:$H$13,AY31),3))} -> 0.05 | U31: {=ROUND(Paramètres!$B$23*INDEX(Rôles!$I$5:$I$13,AY31),3)} -> 0.5 | V31: {=MIN(Paramètres!$B$29,ROUND(Paramètres!$B$24*INDEX(Rôles!$J$5:$J$13,AY31),3))} -> 0.065 | W31: {=MIN(Paramètres!$B$27,ROUND((Paramètres!$B$25+(Paramètres!$B$26-Paramètres!$B$25)*(K31-Paramètres!$B$7)/(Paramètres!$B$8-Paramètres!$B$7))*INDEX(Rôles!$K$5:$K$13,AY31)+INDEX(Rôles!$G$18:$G$22,AZ31),3))} -> 0.348 | X31: =ROUND(1-(1-P31/(P31+(Paramètres!$B$19*(Paramètres!$B$5+(1-Paramètres!$B$5)*((K31-Paramètres!$B$7)/(Paramètres!$B$8-Paramètres!$B$7))^Paramètres!$B$6)*(1-Paramètres!$B$30)/Paramètres!$B$30)))*(1-O31/(O31+(Paramètres!$B$18*(Paramètres!$B$5+(1-Paramètres!$B$5)*((K31-Paramètres!$B$7)/(Paramètres!$B$8-Paramètres!$B$7))^Paramètres!$B$6)*(1-Paramètres!$B$31)/Paramètres!$B$31))),3) -> 0.294 | Y31: =ROUND(O31/(O31+(Paramètres!$B$18*(Paramètres!$B$5+(1-Paramètres!$B$5)*((K31-Paramètres!$B$7)/(Paramètres!$B$8-Paramètres!$B$7))^Paramètres!$B$6)*(1-Paramètres!$B$31)/Paramètres!$B$31)),3) -> 0.201 | Z31: {=IF(E31="Neutre",0,MIN(1,INDEX(Rôles!$L$5:$L$13,AY31)+INDEX(Rôles!$F$18:$F$22,AZ31)))} -> 1 | AA31: {=ROUND(INDEX(Rôles!$C$18:$C$22,AZ31)*INDEX(Rôles!$C$5:$C$13,AY31),4)} -> 0.0375 | AB31: {=ROUND(INDEX(Rôles!$B$18:$B$22,AZ31)*INDEX(Rôles!$B$5:$B$13,AY31),2)} -> 8.4 | AC31: {=INDEX(Rôles!$E$18:$E$22,AZ31)} -> 8 | AD31: {=INDEX(Éléments!$F$5:$F$14,MATCH(E31,Éléments!$A$5:$A$14,0))} -> Eau | AE31: {=INDEX(Éléments!$G$5:$G$14,MATCH(E31,Éléments!$A$5:$A$14,0))} -> Glace | AF31: Brûlure | AG31: 0.45 | AH31: Assommé | AI31: 0.15 | AJ31: {=ROUND(ROUND(Paramètres!$B$49*K31^Paramètres!$B$50,0)*INDEX(Rôles!$E$18:$E$22,AZ31),0)} -> 3368 | AK31: {=ROUND(ROUND(Paramètres!$B$53*K31^Paramètres!$B$54,0)*INDEX(Rôles!$E$18:$E$22,AZ31),0)} -> 2368 | AL31: =INDEX(Butin!$B$7:$B$11,AZ31) -> 1 | AM31: =INDEX(Butin!$E$7:$E$11,AZ31) -> 1.4 | AN31: =IF($H31="Boss",INDEX(Butin!$E$28:$K$37,MATCH($B31,Éléments!$C$5:$C$14,1),1),IF($H31="Dragon",INDEX(Butin!$E$41:$K$50,MATCH($B31,Éléments!$C$5:$C$14,1),1),INDEX(Butin!$E$15:$K$24,MATCH($B31,Éléments!$C$5:$C$14,1),1))) -> 0.18 | AO31: =IF($H31="Boss",INDEX(Butin!$E$28:$K$37,MATCH($B31,Éléments!$C$5:$C$14,1),2),IF($H31="Dragon",INDEX(Butin!$E$41:$K$50,MATCH($B31,Éléments!$C$5:$C$14,1),2),INDEX(Butin!$E$15:$K$24,MATCH($B31,Éléments!$C$5:$C$14,1),2))) -> 0.32 | AP31: =IF($H31="Boss",INDEX(Butin!$E$28:$K$37,MATCH($B31,Éléments!$C$5:$C$14,1),3),IF($H31="Dragon",INDEX(Butin!$E$41:$K$50,MATCH($B31,Éléments!$C$5:$C$14,1),3),INDEX(Butin!$E$15:$K$24,MATCH($B31,Éléments!$C$5:$C$14,1),3))) -> 0.3 | AQ31: =IF($H31="Boss",INDEX(Butin!$E$28:$K$37,MATCH($B31,Éléments!$C$5:$C$14,1),4),IF($H31="Dragon",INDEX(Butin!$E$41:$K$50,MATCH($B31,Éléments!$C$5:$C$14,1),4),INDEX(Butin!$E$15:$K$24,MATCH($B31,Éléments!$C$5:$C$14,1),4))) -> 0.14 | AR31: =IF($H31="Boss",INDEX(Butin!$E$28:$K$37,MATCH($B31,Éléments!$C$5:$C$14,1),5),IF($H31="Dragon",INDEX(Butin!$E$41:$K$50,MATCH($B31,Éléments!$C$5:$C$14,1),5),INDEX(Butin!$E$15:$K$24,MATCH($B31,Éléments!$C$5:$C$14,1),5))) -> 0.03 | AS31: =IF($H31="Boss",INDEX(Butin!$E$28:$K$37,MATCH($B31,Éléments!$C$5:$C$14,1),6),IF($H31="Dragon",INDEX(Butin!$E$41:$K$50,MATCH($B31,Éléments!$C$5:$C$14,1),6),INDEX(Butin!$E$15:$K$24,MATCH($B31,Éléments!$C$5:$C$14,1),6))) -> 0 | AT31: =IF($H31="Boss",INDEX(Butin!$E$28:$K$37,MATCH($B31,Éléments!$C$5:$C$14,1),7),IF($H31="Dragon",INDEX(Butin!$E$41:$K$50,MATCH($B31,Éléments!$C$5:$C$14,1),7),INDEX(Butin!$E$15:$K$24,MATCH($B31,Éléments!$C$5:$C$14,1),7))) -> 0.03 | AU31: =IF(AT31=0,"—",INDEX(Butin!$D$54:$D$63,MATCH($B31,Éléments!$C$5:$C$14,1))&" · "&INDEX(Butin!$F$54:$F$63,MATCH($B31,Éléments!$C$5:$C$14,1))&" · "&INDEX(Butin!$H$54:$H$63,MATCH($B31,Éléments!$C$5:$C$14,1))) -> Jambières du Brasier Marchant · Ceinture du Feu Intérieur · Anneau des Flèches Ardentes | AV31: Ifrit | AW31: =B31&IF(G31="Oui","|B","|N") -> 30|B | AX31: =(Paramètres!$B$5+(1-Paramètres!$B$5)*((K31-Paramètres!$B$7)/(Paramètres!$B$8-Paramètres!$B$7))^Paramètres!$B$6) -> 0.26769025 | AY31: =MATCH(I31,Rôles!$A$5:$A$13,0) -> 5 | AZ31: =MATCH(H31,Rôles!$A$18:$A$22,0) -> 4
A32: MON-026 | B32: 30 | C32: {=INDEX(Zones!$B$6:$B$35,MATCH(B32,Zones!$A$6:$A$35,0))} -> Cœur du volcan | D32: {=INDEX(Éléments!$B$5:$B$14,MATCH(B32,Éléments!$C$5:$C$14,1))} -> Volcan | E32: {=INDEX(Éléments!$A$5:$A$14,MATCH(B32,Éléments!$C$5:$C$14,1))} -> Feu | F32: Diablotin | G32: =IF(OR(H32="Boss",H32="Dragon"),"Oui","Non") -> Non | H32: Faible | I32: Assassin | J32: Magique | K32: =IF($F$3="",B32,$F$3) -> 30 | L32: {=ROUND(Paramètres!$B$16*(Paramètres!$B$5+(1-Paramètres!$B$5)*((K32-Paramètres!$B$7)/(Paramètres!$B$8-Paramètres!$B$7))^Paramètres!$B$6)*INDEX(Rôles!$B$18:$B$22,AZ32)*INDEX(Rôles!$B$5:$B$13,AY32),0)} -> 237 | M32: {=ROUND(IF(J32="Physique",1,IF(J32="Mixte",Paramètres!$B$32,0))*Paramètres!$B$12*(Paramètres!$B$5+(1-Paramètres!$B$5)*((K32-Paramètres!$B$7)/(Paramètres!$B$8-Paramètres!$B$7))^Paramètres!$B$6)*INDEX(Rôles!$C$18:$C$22,AZ32)*INDEX(Rôles!$C$5:$C$13,AY32)/(Paramètres!$B$35*(1-Paramètres!$B$36)),0)} -> 0 | N32: {=ROUND(IF(J32="Magique",1,IF(J32="Mixte",Paramètres!$B$32,0))*Paramètres!$B$12*(Paramètres!$B$5+(1-Paramètres!$B$5)*((K32-Paramètres!$B$7)/(Paramètres!$B$8-Paramètres!$B$7))^Paramètres!$B$6)*INDEX(Rôles!$C$18:$C$22,AZ32)*INDEX(Rôles!$C$5:$C$13,AY32)/(Paramètres!$B$35*(1-Paramètres!$B$36)),0)} -> 73 | O32: {=ROUND(Paramètres!$B$18*(Paramètres!$B$5+(1-Paramètres!$B$5)*((K32-Paramètres!$B$7)/(Paramètres!$B$8-Paramètres!$B$7))^Paramètres!$B$6)*INDEX(Rôles!$D$5:$D$13,AY32)*INDEX(Rôles!$D$18:$D$22,AZ32),0)} -> 58 | P32: {=ROUND(Paramètres!$B$19*(Paramètres!$B$5+(1-Paramètres!$B$5)*((K32-Paramètres!$B$7)/(Paramètres!$B$8-Paramètres!$B$7))^Paramètres!$B$6)*INDEX(Rôles!$E$5:$E$13,AY32)*INDEX(Rôles!$D$18:$D$22,AZ32),0)} -> 43 | Q32: {=ROUND(Paramètres!$B$20*(Paramètres!$B$5+(1-Paramètres!$B$5)*((K32-Paramètres!$B$7)/(Paramètres!$B$8-Paramètres!$B$7))^Paramètres!$B$6)*INDEX(Rôles!$F$5:$F$13,AY32),0)} -> 51 | R32: =ROUND(Paramètres!$B$64*$AX32*INDEX(Rôles!$N$5:$N$13,$AY32)*INDEX(Rôles!$I$18:$I$22,$AZ32),0) -> 36 | S32: {=MIN(1,ROUND(Paramètres!$B$21*INDEX(Rôles!$G$5:$G$13,AY32),3))} -> 1 | T32: {=MIN(Paramètres!$B$28,ROUND(Paramètres!$B$22*INDEX(Rôles!$H$5:$H$13,AY32),3))} -> 0.08 | U32: {=ROUND(Paramètres!$B$23*INDEX(Rôles!$I$5:$I$13,AY32),3)} -> 0.7 | V32: {=MIN(Paramètres!$B$29,ROUND(Paramètres!$B$24*INDEX(Rôles!$J$5:$J$13,AY32),3))} -> 0.06 | W32: {=MIN(Paramètres!$B$27,ROUND((Paramètres!$B$25+(Paramètres!$B$26-Paramètres!$B$25)*(K32-Paramètres!$B$7)/(Paramètres!$B$8-Paramètres!$B$7))*INDEX(Rôles!$K$5:$K$13,AY32)+INDEX(Rôles!$G$18:$G$22,AZ32),3))} -> 0.099 | X32: =ROUND(1-(1-P32/(P32+(Paramètres!$B$19*(Paramètres!$B$5+(1-Paramètres!$B$5)*((K32-Paramètres!$B$7)/(Paramètres!$B$8-Paramètres!$B$7))^Paramètres!$B$6)*(1-Paramètres!$B$30)/Paramètres!$B$30)))*(1-O32/(O32+(Paramètres!$B$18*(Paramètres!$B$5+(1-Paramètres!$B$5)*((K32-Paramètres!$B$7)/(Paramètres!$B$8-Paramètres!$B$7))^Paramètres!$B$6)*(1-Paramètres!$B$31)/Paramètres!$B$31))),3) -> 0.162 | Y32: =ROUND(O32/(O32+(Paramètres!$B$18*(Paramètres!$B$5+(1-Paramètres!$B$5)*((K32-Paramètres!$B$7)/(Paramètres!$B$8-Paramètres!$B$7))^Paramètres!$B$6)*(1-Paramètres!$B$31)/Paramètres!$B$31)),3) -> 0.078 | Z32: {=IF(E32="Neutre",0,MIN(1,INDEX(Rôles!$L$5:$L$13,AY32)+INDEX(Rôles!$F$18:$F$22,AZ32)))} -> 0.5 | AA32: {=ROUND(INDEX(Rôles!$C$18:$C$22,AZ32)*INDEX(Rôles!$C$5:$C$13,AY32),4)} -> 0.012 | AB32: {=ROUND(INDEX(Rôles!$B$18:$B$22,AZ32)*INDEX(Rôles!$B$5:$B$13,AY32),2)} -> 1.13 | AC32: {=INDEX(Rôles!$E$18:$E$22,AZ32)} -> 0.7 | AD32: {=INDEX(Éléments!$F$5:$F$14,MATCH(E32,Éléments!$A$5:$A$14,0))} -> Eau | AE32: {=INDEX(Éléments!$G$5:$G$14,MATCH(E32,Éléments!$A$5:$A$14,0))} -> Glace | AF32: Brûlure | AG32: 0.25 | AJ32: {=ROUND(ROUND(Paramètres!$B$49*K32^Paramètres!$B$50,0)*INDEX(Rôles!$E$18:$E$22,AZ32),0)} -> 295 | AK32: {=ROUND(ROUND(Paramètres!$B$53*K32^Paramètres!$B$54,0)*INDEX(Rôles!$E$18:$E$22,AZ32),0)} -> 207 | AL32: =INDEX(Butin!$B$7:$B$11,AZ32) -> 0.03 | AM32: =INDEX(Butin!$E$7:$E$11,AZ32) -> 0.03 | AN32: =IF($H32="Boss",INDEX(Butin!$E$28:$K$37,MATCH($B32,Éléments!$C$5:$C$14,1),1),IF($H32="Dragon",INDEX(Butin!$E$41:$K$50,MATCH($B32,Éléments!$C$5:$C$14,1),1),INDEX(Butin!$E$15:$K$24,MATCH($B32,Éléments!$C$5:$C$14,1),1))) -> 0.52 | AO32: =IF($H32="Boss",INDEX(Butin!$E$28:$K$37,MATCH($B32,Éléments!$C$5:$C$14,1),2),IF($H32="Dragon",INDEX(Butin!$E$41:$K$50,MATCH($B32,Éléments!$C$5:$C$14,1),2),INDEX(Butin!$E$15:$K$24,MATCH($B32,Éléments!$C$5:$C$14,1),2))) -> 0.32 | AP32: =IF($H32="Boss",INDEX(Butin!$E$28:$K$37,MATCH($B32,Éléments!$C$5:$C$14,1),3),IF($H32="Dragon",INDEX(Butin!$E$41:$K$50,MATCH($B32,Éléments!$C$5:$C$14,1),3),INDEX(Butin!$E$15:$K$24,MATCH($B32,Éléments!$C$5:$C$14,1),3))) -> 0.13 | AQ32: =IF($H32="Boss",INDEX(Butin!$E$28:$K$37,MATCH($B32,Éléments!$C$5:$C$14,1),4),IF($H32="Dragon",INDEX(Butin!$E$41:$K$50,MATCH($B32,Éléments!$C$5:$C$14,1),4),INDEX(Butin!$E$15:$K$24,MATCH($B32,Éléments!$C$5:$C$14,1),4))) -> 0.03 | AR32: =IF($H32="Boss",INDEX(Butin!$E$28:$K$37,MATCH($B32,Éléments!$C$5:$C$14,1),5),IF($H32="Dragon",INDEX(Butin!$E$41:$K$50,MATCH($B32,Éléments!$C$5:$C$14,1),5),INDEX(Butin!$E$15:$K$24,MATCH($B32,Éléments!$C$5:$C$14,1),5))) -> 0 | AS32: =IF($H32="Boss",INDEX(Butin!$E$28:$K$37,MATCH($B32,Éléments!$C$5:$C$14,1),6),IF($H32="Dragon",INDEX(Butin!$E$41:$K$50,MATCH($B32,Éléments!$C$5:$C$14,1),6),INDEX(Butin!$E$15:$K$24,MATCH($B32,Éléments!$C$5:$C$14,1),6))) -> 0 | AT32: =IF($H32="Boss",INDEX(Butin!$E$28:$K$37,MATCH($B32,Éléments!$C$5:$C$14,1),7),IF($H32="Dragon",INDEX(Butin!$E$41:$K$50,MATCH($B32,Éléments!$C$5:$C$14,1),7),INDEX(Butin!$E$15:$K$24,MATCH($B32,Éléments!$C$5:$C$14,1),7))) -> 0 | AU32: =IF(AT32=0,"—",INDEX(Butin!$D$54:$D$63,MATCH($B32,Éléments!$C$5:$C$14,1))&" · "&INDEX(Butin!$F$54:$F$63,MATCH($B32,Éléments!$C$5:$C$14,1))&" · "&INDEX(Butin!$H$54:$H$63,MATCH($B32,Éléments!$C$5:$C$14,1))) -> — | AV32: Diablotin | AW32: =B32&IF(G32="Oui","|B","|N") -> 30|N | AX32: =(Paramètres!$B$5+(1-Paramètres!$B$5)*((K32-Paramètres!$B$7)/(Paramètres!$B$8-Paramètres!$B$7))^Paramètres!$B$6) -> 0.26769025 | AY32: =MATCH(I32,Rôles!$A$5:$A$13,0) -> 7 | AZ32: =MATCH(H32,Rôles!$A$18:$A$22,0) -> 1
A33: MON-027 | B33: 30 | C33: {=INDEX(Zones!$B$6:$B$35,MATCH(B33,Zones!$A$6:$A$35,0))} -> Cœur du volcan | D33: {=INDEX(Éléments!$B$5:$B$14,MATCH(B33,Éléments!$C$5:$C$14,1))} -> Volcan | E33: {=INDEX(Éléments!$A$5:$A$14,MATCH(B33,Éléments!$C$5:$C$14,1))} -> Feu | F33: Chien des enfers | G33: =IF(OR(H33="Boss",H33="Dragon"),"Oui","Non") -> Non | H33: Normal | I33: Bête | J33: Physique | K33: =IF($F$3="",B33,$F$3) -> 30 | L33: {=ROUND(Paramètres!$B$16*(Paramètres!$B$5+(1-Paramètres!$B$5)*((K33-Paramètres!$B$7)/(Paramètres!$B$8-Paramètres!$B$7))^Paramètres!$B$6)*INDEX(Rôles!$B$18:$B$22,AZ33)*INDEX(Rôles!$B$5:$B$13,AY33),0)} -> 401 | M33: {=ROUND(IF(J33="Physique",1,IF(J33="Mixte",Paramètres!$B$32,0))*Paramètres!$B$12*(Paramètres!$B$5+(1-Paramètres!$B$5)*((K33-Paramètres!$B$7)/(Paramètres!$B$8-Paramètres!$B$7))^Paramètres!$B$6)*INDEX(Rôles!$C$18:$C$22,AZ33)*INDEX(Rôles!$C$5:$C$13,AY33)/(Paramètres!$B$35*(1-Paramètres!$B$36)),0)} -> 96 | N33: {=ROUND(IF(J33="Magique",1,IF(J33="Mixte",Paramètres!$B$32,0))*Paramètres!$B$12*(Paramètres!$B$5+(1-Paramètres!$B$5)*((K33-Paramètres!$B$7)/(Paramètres!$B$8-Paramètres!$B$7))^Paramètres!$B$6)*INDEX(Rôles!$C$18:$C$22,AZ33)*INDEX(Rôles!$C$5:$C$13,AY33)/(Paramètres!$B$35*(1-Paramètres!$B$36)),0)} -> 0 | O33: {=ROUND(Paramètres!$B$18*(Paramètres!$B$5+(1-Paramètres!$B$5)*((K33-Paramètres!$B$7)/(Paramètres!$B$8-Paramètres!$B$7))^Paramètres!$B$6)*INDEX(Rôles!$D$5:$D$13,AY33)*INDEX(Rôles!$D$18:$D$22,AZ33),0)} -> 72 | P33: {=ROUND(Paramètres!$B$19*(Paramètres!$B$5+(1-Paramètres!$B$5)*((K33-Paramètres!$B$7)/(Paramètres!$B$8-Paramètres!$B$7))^Paramètres!$B$6)*INDEX(Rôles!$E$5:$E$13,AY33)*INDEX(Rôles!$D$18:$D$22,AZ33),0)} -> 75 | Q33: {=ROUND(Paramètres!$B$20*(Paramètres!$B$5+(1-Paramètres!$B$5)*((K33-Paramètres!$B$7)/(Paramètres!$B$8-Paramètres!$B$7))^Paramètres!$B$6)*INDEX(Rôles!$F$5:$F$13,AY33),0)} -> 39 | R33: =ROUND(Paramètres!$B$64*$AX33*INDEX(Rôles!$N$5:$N$13,$AY33)*INDEX(Rôles!$I$18:$I$22,$AZ33),0) -> 32 | S33: {=MIN(1,ROUND(Paramètres!$B$21*INDEX(Rôles!$G$5:$G$13,AY33),3))} -> 0.9 | T33: {=MIN(Paramètres!$B$28,ROUND(Paramètres!$B$22*INDEX(Rôles!$H$5:$H$13,AY33),3))} -> 0.05 | U33: {=ROUND(Paramètres!$B$23*INDEX(Rôles!$I$5:$I$13,AY33),3)} -> 0.5 | V33: {=MIN(Paramètres!$B$29,ROUND(Paramètres!$B$24*INDEX(Rôles!$J$5:$J$13,AY33),3))} -> 0.025 | W33: {=MIN(Paramètres!$B$27,ROUND((Paramètres!$B$25+(Paramètres!$B$26-Paramètres!$B$25)*(K33-Paramètres!$B$7)/(Paramètres!$B$8-Paramètres!$B$7))*INDEX(Rôles!$K$5:$K$13,AY33)+INDEX(Rôles!$G$18:$G$22,AZ33),3))} -> 0.099 | X33: =ROUND(1-(1-P33/(P33+(Paramètres!$B$19*(Paramètres!$B$5+(1-Paramètres!$B$5)*((K33-Paramètres!$B$7)/(Paramètres!$B$8-Paramètres!$B$7))^Paramètres!$B$6)*(1-Paramètres!$B$30)/Paramètres!$B$30)))*(1-O33/(O33+(Paramètres!$B$18*(Paramètres!$B$5+(1-Paramètres!$B$5)*((K33-Paramètres!$B$7)/(Paramètres!$B$8-Paramètres!$B$7))^Paramètres!$B$6)*(1-Paramètres!$B$31)/Paramètres!$B$31))),3) -> 0.23 | Y33: =ROUND(O33/(O33+(Paramètres!$B$18*(Paramètres!$B$5+(1-Paramètres!$B$5)*((K33-Paramètres!$B$7)/(Paramètres!$B$8-Paramètres!$B$7))^Paramètres!$B$6)*(1-Paramètres!$B$31)/Paramètres!$B$31)),3) -> 0.095 | Z33: {=IF(E33="Neutre",0,MIN(1,INDEX(Rôles!$L$5:$L$13,AY33)+INDEX(Rôles!$F$18:$F$22,AZ33)))} -> 0.5 | AA33: {=ROUND(INDEX(Rôles!$C$18:$C$22,AZ33)*INDEX(Rôles!$C$5:$C$13,AY33),4)} -> 0.0158 | AB33: {=ROUND(INDEX(Rôles!$B$18:$B$22,AZ33)*INDEX(Rôles!$B$5:$B$13,AY33),2)} -> 1.9 | AC33: {=INDEX(Rôles!$E$18:$E$22,AZ33)} -> 1 | AD33: {=INDEX(Éléments!$F$5:$F$14,MATCH(E33,Éléments!$A$5:$A$14,0))} -> Eau | AE33: {=INDEX(Éléments!$G$5:$G$14,MATCH(E33,Éléments!$A$5:$A$14,0))} -> Glace | AF33: Brûlure | AG33: 0.3 | AH33: Saignement | AI33: 0.2 | AJ33: {=ROUND(ROUND(Paramètres!$B$49*K33^Paramètres!$B$50,0)*INDEX(Rôles!$E$18:$E$22,AZ33),0)} -> 421 | AK33: {=ROUND(ROUND(Paramètres!$B$53*K33^Paramètres!$B$54,0)*INDEX(Rôles!$E$18:$E$22,AZ33),0)} -> 296 | AL33: =INDEX(Butin!$B$7:$B$11,AZ33) -> 0.05 | AM33: =INDEX(Butin!$E$7:$E$11,AZ33) -> 0.05 | AN33: =IF($H33="Boss",INDEX(Butin!$E$28:$K$37,MATCH($B33,Éléments!$C$5:$C$14,1),1),IF($H33="Dragon",INDEX(Butin!$E$41:$K$50,MATCH($B33,Éléments!$C$5:$C$14,1),1),INDEX(Butin!$E$15:$K$24,MATCH($B33,Éléments!$C$5:$C$14,1),1))) -> 0.52 | AO33: =IF($H33="Boss",INDEX(Butin!$E$28:$K$37,MATCH($B33,Éléments!$C$5:$C$14,1),2),IF($H33="Dragon",INDEX(Butin!$E$41:$K$50,MATCH($B33,Éléments!$C$5:$C$14,1),2),INDEX(Butin!$E$15:$K$24,MATCH($B33,Éléments!$C$5:$C$14,1),2))) -> 0.32 | AP33: =IF($H33="Boss",INDEX(Butin!$E$28:$K$37,MATCH($B33,Éléments!$C$5:$C$14,1),3),IF($H33="Dragon",INDEX(Butin!$E$41:$K$50,MATCH($B33,Éléments!$C$5:$C$14,1),3),INDEX(Butin!$E$15:$K$24,MATCH($B33,Éléments!$C$5:$C$14,1),3))) -> 0.13 | AQ33: =IF($H33="Boss",INDEX(Butin!$E$28:$K$37,MATCH($B33,Éléments!$C$5:$C$14,1),4),IF($H33="Dragon",INDEX(Butin!$E$41:$K$50,MATCH($B33,Éléments!$C$5:$C$14,1),4),INDEX(Butin!$E$15:$K$24,MATCH($B33,Éléments!$C$5:$C$14,1),4))) -> 0.03 | AR33: =IF($H33="Boss",INDEX(Butin!$E$28:$K$37,MATCH($B33,Éléments!$C$5:$C$14,1),5),IF($H33="Dragon",INDEX(Butin!$E$41:$K$50,MATCH($B33,Éléments!$C$5:$C$14,1),5),INDEX(Butin!$E$15:$K$24,MATCH($B33,Éléments!$C$5:$C$14,1),5))) -> 0 | AS33: =IF($H33="Boss",INDEX(Butin!$E$28:$K$37,MATCH($B33,Éléments!$C$5:$C$14,1),6),IF($H33="Dragon",INDEX(Butin!$E$41:$K$50,MATCH($B33,Éléments!$C$5:$C$14,1),6),INDEX(Butin!$E$15:$K$24,MATCH($B33,Éléments!$C$5:$C$14,1),6))) -> 0 | AT33: =IF($H33="Boss",INDEX(Butin!$E$28:$K$37,MATCH($B33,Éléments!$C$5:$C$14,1),7),IF($H33="Dragon",INDEX(Butin!$E$41:$K$50,MATCH($B33,Éléments!$C$5:$C$14,1),7),INDEX(Butin!$E$15:$K$24,MATCH($B33,Éléments!$C$5:$C$14,1),7))) -> 0 | AU33: =IF(AT33=0,"—",INDEX(Butin!$D$54:$D$63,MATCH($B33,Éléments!$C$5:$C$14,1))&" · "&INDEX(Butin!$F$54:$F$63,MATCH($B33,Éléments!$C$5:$C$14,1))&" · "&INDEX(Butin!$H$54:$H$63,MATCH($B33,Éléments!$C$5:$C$14,1))) -> — | AV33: Chien des enfers | AW33: =B33&IF(G33="Oui","|B","|N") -> 30|N | AX33: =(Paramètres!$B$5+(1-Paramètres!$B$5)*((K33-Paramètres!$B$7)/(Paramètres!$B$8-Paramètres!$B$7))^Paramètres!$B$6) -> 0.26769025 | AY33: =MATCH(I33,Rôles!$A$5:$A$13,0) -> 1 | AZ33: =MATCH(H33,Rôles!$A$18:$A$22,0) -> 2
A34: MON-028 | B34: 30 | C34: {=INDEX(Zones!$B$6:$B$35,MATCH(B34,Zones!$A$6:$A$35,0))} -> Cœur du volcan | D34: {=INDEX(Éléments!$B$5:$B$14,MATCH(B34,Éléments!$C$5:$C$14,1))} -> Volcan | E34: {=INDEX(Éléments!$A$5:$A$14,MATCH(B34,Éléments!$C$5:$C$14,1))} -> Feu | F34: Élémentaire de feu | G34: =IF(OR(H34="Boss",H34="Dragon"),"Oui","Non") -> Non | H34: Normal | I34: Élémentaire | J34: Magique | K34: =IF($F$3="",B34,$F$3) -> 30 | L34: {=ROUND(Paramètres!$B$16*(Paramètres!$B$5+(1-Paramètres!$B$5)*((K34-Paramètres!$B$7)/(Paramètres!$B$8-Paramètres!$B$7))^Paramètres!$B$6)*INDEX(Rôles!$B$18:$B$22,AZ34)*INDEX(Rôles!$B$5:$B$13,AY34),0)} -> 422 | M34: {=ROUND(IF(J34="Physique",1,IF(J34="Mixte",Paramètres!$B$32,0))*Paramètres!$B$12*(Paramètres!$B$5+(1-Paramètres!$B$5)*((K34-Paramètres!$B$7)/(Paramètres!$B$8-Paramètres!$B$7))^Paramètres!$B$6)*INDEX(Rôles!$C$18:$C$22,AZ34)*INDEX(Rôles!$C$5:$C$13,AY34)/(Paramètres!$B$35*(1-Paramètres!$B$36)),0)} -> 0 | N34: {=ROUND(IF(J34="Magique",1,IF(J34="Mixte",Paramètres!$B$32,0))*Paramètres!$B$12*(Paramètres!$B$5+(1-Paramètres!$B$5)*((K34-Paramètres!$B$7)/(Paramètres!$B$8-Paramètres!$B$7))^Paramètres!$B$6)*INDEX(Rôles!$C$18:$C$22,AZ34)*INDEX(Rôles!$C$5:$C$13,AY34)/(Paramètres!$B$35*(1-Paramètres!$B$36)),0)} -> 110 | O34: {=ROUND(Paramètres!$B$18*(Paramètres!$B$5+(1-Paramètres!$B$5)*((K34-Paramètres!$B$7)/(Paramètres!$B$8-Paramètres!$B$7))^Paramètres!$B$6)*INDEX(Rôles!$D$5:$D$13,AY34)*INDEX(Rôles!$D$18:$D$22,AZ34),0)} -> 157 | P34: {=ROUND(Paramètres!$B$19*(Paramètres!$B$5+(1-Paramètres!$B$5)*((K34-Paramètres!$B$7)/(Paramètres!$B$8-Paramètres!$B$7))^Paramètres!$B$6)*INDEX(Rôles!$E$5:$E$13,AY34)*INDEX(Rôles!$D$18:$D$22,AZ34),0)} -> 75 | Q34: {=ROUND(Paramètres!$B$20*(Paramètres!$B$5+(1-Paramètres!$B$5)*((K34-Paramètres!$B$7)/(Paramètres!$B$8-Paramètres!$B$7))^Paramètres!$B$6)*INDEX(Rôles!$F$5:$F$13,AY34),0)} -> 32 | R34: =ROUND(Paramètres!$B$64*$AX34*INDEX(Rôles!$N$5:$N$13,$AY34)*INDEX(Rôles!$I$18:$I$22,$AZ34),0) -> 27 | S34: {=MIN(1,ROUND(Paramètres!$B$21*INDEX(Rôles!$G$5:$G$13,AY34),3))} -> 0.9 | T34: {=MIN(Paramètres!$B$28,ROUND(Paramètres!$B$22*INDEX(Rôles!$H$5:$H$13,AY34),3))} -> 0.05 | U34: {=ROUND(Paramètres!$B$23*INDEX(Rôles!$I$5:$I$13,AY34),3)} -> 0.5 | V34: {=MIN(Paramètres!$B$29,ROUND(Paramètres!$B$24*INDEX(Rôles!$J$5:$J$13,AY34),3))} -> 0.05 | W34: {=MIN(Paramètres!$B$27,ROUND((Paramètres!$B$25+(Paramètres!$B$26-Paramètres!$B$25)*(K34-Paramètres!$B$7)/(Paramètres!$B$8-Paramètres!$B$7))*INDEX(Rôles!$K$5:$K$13,AY34)+INDEX(Rôles!$G$18:$G$22,AZ34),3))} -> 0.185 | X34: =ROUND(1-(1-P34/(P34+(Paramètres!$B$19*(Paramètres!$B$5+(1-Paramètres!$B$5)*((K34-Paramètres!$B$7)/(Paramètres!$B$8-Paramètres!$B$7))^Paramètres!$B$6)*(1-Paramètres!$B$30)/Paramètres!$B$30)))*(1-O34/(O34+(Paramètres!$B$18*(Paramètres!$B$5+(1-Paramètres!$B$5)*((K34-Paramètres!$B$7)/(Paramètres!$B$8-Paramètres!$B$7))^Paramètres!$B$6)*(1-Paramètres!$B$31)/Paramètres!$B$31))),3) -> 0.308 | Y34: =ROUND(O34/(O34+(Paramètres!$B$18*(Paramètres!$B$5+(1-Paramètres!$B$5)*((K34-Paramètres!$B$7)/(Paramètres!$B$8-Paramètres!$B$7))^Paramètres!$B$6)*(1-Paramètres!$B$31)/Paramètres!$B$31)),3) -> 0.187 | Z34: {=IF(E34="Neutre",0,MIN(1,INDEX(Rôles!$L$5:$L$13,AY34)+INDEX(Rôles!$F$18:$F$22,AZ34)))} -> 1 | AA34: {=ROUND(INDEX(Rôles!$C$18:$C$22,AZ34)*INDEX(Rôles!$C$5:$C$13,AY34),4)} -> 0.018 | AB34: {=ROUND(INDEX(Rôles!$B$18:$B$22,AZ34)*INDEX(Rôles!$B$5:$B$13,AY34),2)} -> 2 | AC34: {=INDEX(Rôles!$E$18:$E$22,AZ34)} -> 1 | AD34: {=INDEX(Éléments!$F$5:$F$14,MATCH(E34,Éléments!$A$5:$A$14,0))} -> Eau | AE34: {=INDEX(Éléments!$G$5:$G$14,MATCH(E34,Éléments!$A$5:$A$14,0))} -> Glace | AF34: Brûlure | AG34: 0.4 | AJ34: {=ROUND(ROUND(Paramètres!$B$49*K34^Paramètres!$B$50,0)*INDEX(Rôles!$E$18:$E$22,AZ34),0)} -> 421 | AK34: {=ROUND(ROUND(Paramètres!$B$53*K34^Paramètres!$B$54,0)*INDEX(Rôles!$E$18:$E$22,AZ34),0)} -> 296 | AL34: =INDEX(Butin!$B$7:$B$11,AZ34) -> 0.05 | AM34: =INDEX(Butin!$E$7:$E$11,AZ34) -> 0.05 | AN34: =IF($H34="Boss",INDEX(Butin!$E$28:$K$37,MATCH($B34,Éléments!$C$5:$C$14,1),1),IF($H34="Dragon",INDEX(Butin!$E$41:$K$50,MATCH($B34,Éléments!$C$5:$C$14,1),1),INDEX(Butin!$E$15:$K$24,MATCH($B34,Éléments!$C$5:$C$14,1),1))) -> 0.52 | AO34: =IF($H34="Boss",INDEX(Butin!$E$28:$K$37,MATCH($B34,Éléments!$C$5:$C$14,1),2),IF($H34="Dragon",INDEX(Butin!$E$41:$K$50,MATCH($B34,Éléments!$C$5:$C$14,1),2),INDEX(Butin!$E$15:$K$24,MATCH($B34,Éléments!$C$5:$C$14,1),2))) -> 0.32 | AP34: =IF($H34="Boss",INDEX(Butin!$E$28:$K$37,MATCH($B34,Éléments!$C$5:$C$14,1),3),IF($H34="Dragon",INDEX(Butin!$E$41:$K$50,MATCH($B34,Éléments!$C$5:$C$14,1),3),INDEX(Butin!$E$15:$K$24,MATCH($B34,Éléments!$C$5:$C$14,1),3))) -> 0.13 | AQ34: =IF($H34="Boss",INDEX(Butin!$E$28:$K$37,MATCH($B34,Éléments!$C$5:$C$14,1),4),IF($H34="Dragon",INDEX(Butin!$E$41:$K$50,MATCH($B34,Éléments!$C$5:$C$14,1),4),INDEX(Butin!$E$15:$K$24,MATCH($B34,Éléments!$C$5:$C$14,1),4))) -> 0.03 | AR34: =IF($H34="Boss",INDEX(Butin!$E$28:$K$37,MATCH($B34,Éléments!$C$5:$C$14,1),5),IF($H34="Dragon",INDEX(Butin!$E$41:$K$50,MATCH($B34,Éléments!$C$5:$C$14,1),5),INDEX(Butin!$E$15:$K$24,MATCH($B34,Éléments!$C$5:$C$14,1),5))) -> 0 | AS34: =IF($H34="Boss",INDEX(Butin!$E$28:$K$37,MATCH($B34,Éléments!$C$5:$C$14,1),6),IF($H34="Dragon",INDEX(Butin!$E$41:$K$50,MATCH($B34,Éléments!$C$5:$C$14,1),6),INDEX(Butin!$E$15:$K$24,MATCH($B34,Éléments!$C$5:$C$14,1),6))) -> 0 | AT34: =IF($H34="Boss",INDEX(Butin!$E$28:$K$37,MATCH($B34,Éléments!$C$5:$C$14,1),7),IF($H34="Dragon",INDEX(Butin!$E$41:$K$50,MATCH($B34,Éléments!$C$5:$C$14,1),7),INDEX(Butin!$E$15:$K$24,MATCH($B34,Éléments!$C$5:$C$14,1),7))) -> 0 | AU34: =IF(AT34=0,"—",INDEX(Butin!$D$54:$D$63,MATCH($B34,Éléments!$C$5:$C$14,1))&" · "&INDEX(Butin!$F$54:$F$63,MATCH($B34,Éléments!$C$5:$C$14,1))&" · "&INDEX(Butin!$H$54:$H$63,MATCH($B34,Éléments!$C$5:$C$14,1))) -> — | AV34: Élémentaire de feu | AW34: =B34&IF(G34="Oui","|B","|N") -> 30|N | AX34: =(Paramètres!$B$5+(1-Paramètres!$B$5)*((K34-Paramètres!$B$7)/(Paramètres!$B$8-Paramètres!$B$7))^Paramètres!$B$6) -> 0.26769025 | AY34: =MATCH(I34,Rôles!$A$5:$A$13,0) -> 8 | AZ34: =MATCH(H34,Rôles!$A$18:$A$22,0) -> 2
A35: MON-029 | B35: 35 | C35: {=INDEX(Zones!$B$6:$B$35,MATCH(B35,Zones!$A$6:$A$35,0))} -> Désert d'Arrakis | D35: {=INDEX(Éléments!$B$5:$B$14,MATCH(B35,Éléments!$C$5:$C$14,1))} -> Désert | E35: {=INDEX(Éléments!$A$5:$A$14,MATCH(B35,Éléments!$C$5:$C$14,1))} -> Vent | F35: Ver des sables | G35: =IF(OR(H35="Boss",H35="Dragon"),"Oui","Non") -> Oui | H35: Boss | I35: Brute | J35: Physique | K35: =IF($F$3="",B35,$F$3) -> 35 | L35: {=ROUND(Paramètres!$B$16*(Paramètres!$B$5+(1-Paramètres!$B$5)*((K35-Paramètres!$B$7)/(Paramètres!$B$8-Paramètres!$B$7))^Paramètres!$B$6)*INDEX(Rôles!$B$18:$B$22,AZ35)*INDEX(Rôles!$B$5:$B$13,AY35),0)} -> 4443 | M35: {=ROUND(IF(J35="Physique",1,IF(J35="Mixte",Paramètres!$B$32,0))*Paramètres!$B$12*(Paramètres!$B$5+(1-Paramètres!$B$5)*((K35-Paramètres!$B$7)/(Paramètres!$B$8-Paramètres!$B$7))^Paramètres!$B$6)*INDEX(Rôles!$C$18:$C$22,AZ35)*INDEX(Rôles!$C$5:$C$13,AY35)/(Paramètres!$B$35*(1-Paramètres!$B$36)),0)} -> 204 | N35: {=ROUND(IF(J35="Magique",1,IF(J35="Mixte",Paramètres!$B$32,0))*Paramètres!$B$12*(Paramètres!$B$5+(1-Paramètres!$B$5)*((K35-Paramètres!$B$7)/(Paramètres!$B$8-Paramètres!$B$7))^Paramètres!$B$6)*INDEX(Rôles!$C$18:$C$22,AZ35)*INDEX(Rôles!$C$5:$C$13,AY35)/(Paramètres!$B$35*(1-Paramètres!$B$36)),0)} -> 0 | O35: {=ROUND(Paramètres!$B$18*(Paramètres!$B$5+(1-Paramètres!$B$5)*((K35-Paramètres!$B$7)/(Paramètres!$B$8-Paramètres!$B$7))^Paramètres!$B$6)*INDEX(Rôles!$D$5:$D$13,AY35)*INDEX(Rôles!$D$18:$D$22,AZ35),0)} -> 220 | P35: {=ROUND(Paramètres!$B$19*(Paramètres!$B$5+(1-Paramètres!$B$5)*((K35-Paramètres!$B$7)/(Paramètres!$B$8-Paramètres!$B$7))^Paramètres!$B$6)*INDEX(Rôles!$E$5:$E$13,AY35)*INDEX(Rôles!$D$18:$D$22,AZ35),0)} -> 245 | Q35: {=ROUND(Paramètres!$B$20*(Paramètres!$B$5+(1-Paramètres!$B$5)*((K35-Paramètres!$B$7)/(Paramètres!$B$8-Paramètres!$B$7))^Paramètres!$B$6)*INDEX(Rôles!$F$5:$F$13,AY35),0)} -> 23 | R35: =ROUND(Paramètres!$B$64*$AX35*INDEX(Rôles!$N$5:$N$13,$AY35)*INDEX(Rôles!$I$18:$I$22,$AZ35),0) -> 25 | S35: {=MIN(1,ROUND(Paramètres!$B$21*INDEX(Rôles!$G$5:$G$13,AY35),3))} -> 0.765 | T35: {=MIN(Paramètres!$B$28,ROUND(Paramètres!$B$22*INDEX(Rôles!$H$5:$H$13,AY35),3))} -> 0.03 | U35: {=ROUND(Paramètres!$B$23*INDEX(Rôles!$I$5:$I$13,AY35),3)} -> 0.5 | V35: {=MIN(Paramètres!$B$29,ROUND(Paramètres!$B$24*INDEX(Rôles!$J$5:$J$13,AY35),3))} -> 0.04 | W35: {=MIN(Paramètres!$B$27,ROUND((Paramètres!$B$25+(Paramètres!$B$26-Paramètres!$B$25)*(K35-Paramètres!$B$7)/(Paramètres!$B$8-Paramètres!$B$7))*INDEX(Rôles!$K$5:$K$13,AY35)+INDEX(Rôles!$G$18:$G$22,AZ35),3))} -> 0.363 | X35: =ROUND(1-(1-P35/(P35+(Paramètres!$B$19*(Paramètres!$B$5+(1-Paramètres!$B$5)*((K35-Paramètres!$B$7)/(Paramètres!$B$8-Paramètres!$B$7))^Paramètres!$B$6)*(1-Paramètres!$B$30)/Paramètres!$B$30)))*(1-O35/(O35+(Paramètres!$B$18*(Paramètres!$B$5+(1-Paramètres!$B$5)*((K35-Paramètres!$B$7)/(Paramètres!$B$8-Paramètres!$B$7))^Paramètres!$B$6)*(1-Paramètres!$B$31)/Paramètres!$B$31))),3) -> 0.473 | Y35: =ROUND(O35/(O35+(Paramètres!$B$18*(Paramètres!$B$5+(1-Paramètres!$B$5)*((K35-Paramètres!$B$7)/(Paramètres!$B$8-Paramètres!$B$7))^Paramètres!$B$6)*(1-Paramètres!$B$31)/Paramètres!$B$31)),3) -> 0.216 | Z35: {=IF(E35="Neutre",0,MIN(1,INDEX(Rôles!$L$5:$L$13,AY35)+INDEX(Rôles!$F$18:$F$22,AZ35)))} -> 0.6 | AA35: {=ROUND(INDEX(Rôles!$C$18:$C$22,AZ35)*INDEX(Rôles!$C$5:$C$13,AY35),4)} -> 0.0285 | AB35: {=ROUND(INDEX(Rôles!$B$18:$B$22,AZ35)*INDEX(Rôles!$B$5:$B$13,AY35),2)} -> 18 | AC35: {=INDEX(Rôles!$E$18:$E$22,AZ35)} -> 8 | AD35: {=INDEX(Éléments!$F$5:$F$14,MATCH(E35,Éléments!$A$5:$A$14,0))} -> Glace | AE35: {=INDEX(Éléments!$G$5:$G$14,MATCH(E35,Éléments!$A$5:$A$14,0))} -> Terre | AF35: Désorienté | AG35: 0.3 | AH35: Assommé | AI35: 0.3 | AJ35: {=ROUND(ROUND(Paramètres!$B$49*K35^Paramètres!$B$50,0)*INDEX(Rôles!$E$18:$E$22,AZ35),0)} -> 4088 | AK35: {=ROUND(ROUND(Paramètres!$B$53*K35^Paramètres!$B$54,0)*INDEX(Rôles!$E$18:$E$22,AZ35),0)} -> 2912 | AL35: =INDEX(Butin!$B$7:$B$11,AZ35) -> 1 | AM35: =INDEX(Butin!$E$7:$E$11,AZ35) -> 1.4 | AN35: =IF($H35="Boss",INDEX(Butin!$E$28:$K$37,MATCH($B35,Éléments!$C$5:$C$14,1),1),IF($H35="Dragon",INDEX(Butin!$E$41:$K$50,MATCH($B35,Éléments!$C$5:$C$14,1),1),INDEX(Butin!$E$15:$K$24,MATCH($B35,Éléments!$C$5:$C$14,1),1))) -> 0.12 | AO35: =IF($H35="Boss",INDEX(Butin!$E$28:$K$37,MATCH($B35,Éléments!$C$5:$C$14,1),2),IF($H35="Dragon",INDEX(Butin!$E$41:$K$50,MATCH($B35,Éléments!$C$5:$C$14,1),2),INDEX(Butin!$E$15:$K$24,MATCH($B35,Éléments!$C$5:$C$14,1),2))) -> 0.26 | AP35: =IF($H35="Boss",INDEX(Butin!$E$28:$K$37,MATCH($B35,Éléments!$C$5:$C$14,1),3),IF($H35="Dragon",INDEX(Butin!$E$41:$K$50,MATCH($B35,Éléments!$C$5:$C$14,1),3),INDEX(Butin!$E$15:$K$24,MATCH($B35,Éléments!$C$5:$C$14,1),3))) -> 0.32 | AQ35: =IF($H35="Boss",INDEX(Butin!$E$28:$K$37,MATCH($B35,Éléments!$C$5:$C$14,1),4),IF($H35="Dragon",INDEX(Butin!$E$41:$K$50,MATCH($B35,Éléments!$C$5:$C$14,1),4),INDEX(Butin!$E$15:$K$24,MATCH($B35,Éléments!$C$5:$C$14,1),4))) -> 0.19 | AR35: =IF($H35="Boss",INDEX(Butin!$E$28:$K$37,MATCH($B35,Éléments!$C$5:$C$14,1),5),IF($H35="Dragon",INDEX(Butin!$E$41:$K$50,MATCH($B35,Éléments!$C$5:$C$14,1),5),INDEX(Butin!$E$15:$K$24,MATCH($B35,Éléments!$C$5:$C$14,1),5))) -> 0.06 | AS35: =IF($H35="Boss",INDEX(Butin!$E$28:$K$37,MATCH($B35,Éléments!$C$5:$C$14,1),6),IF($H35="Dragon",INDEX(Butin!$E$41:$K$50,MATCH($B35,Éléments!$C$5:$C$14,1),6),INDEX(Butin!$E$15:$K$24,MATCH($B35,Éléments!$C$5:$C$14,1),6))) -> 0.01 | AT35: =IF($H35="Boss",INDEX(Butin!$E$28:$K$37,MATCH($B35,Éléments!$C$5:$C$14,1),7),IF($H35="Dragon",INDEX(Butin!$E$41:$K$50,MATCH($B35,Éléments!$C$5:$C$14,1),7),INDEX(Butin!$E$15:$K$24,MATCH($B35,Éléments!$C$5:$C$14,1),7))) -> 0.04 | AU35: =IF(AT35=0,"—",INDEX(Butin!$D$54:$D$63,MATCH($B35,Éléments!$C$5:$C$14,1))&" · "&INDEX(Butin!$F$54:$F$63,MATCH($B35,Éléments!$C$5:$C$14,1))&" · "&INDEX(Butin!$H$54:$H$63,MATCH($B35,Éléments!$C$5:$C$14,1))) -> Médaillon du Serment Brisé * · Chapeau du Sage des Cieux · Arc des Mille Tempêtes | AV35: Ver des sable (Boss) | AW35: =B35&IF(G35="Oui","|B","|N") -> 35|B | AX35: =(Paramètres!$B$5+(1-Paramètres!$B$5)*((K35-Paramètres!$B$7)/(Paramètres!$B$8-Paramètres!$B$7))^Paramètres!$B$6) -> 0.31347297 | AY35: =MATCH(I35,Rôles!$A$5:$A$13,0) -> 2 | AZ35: =MATCH(H35,Rôles!$A$18:$A$22,0) -> 4
A36: MON-030 | B36: 35 | C36: {=INDEX(Zones!$B$6:$B$35,MATCH(B36,Zones!$A$6:$A$35,0))} -> Désert d'Arrakis | D36: {=INDEX(Éléments!$B$5:$B$14,MATCH(B36,Éléments!$C$5:$C$14,1))} -> Désert | E36: {=INDEX(Éléments!$A$5:$A$14,MATCH(B36,Éléments!$C$5:$C$14,1))} -> Vent | F36: Djin | G36: =IF(OR(H36="Boss",H36="Dragon"),"Oui","Non") -> Non | H36: Normal | I36: Mage | J36: Magique | K36: =IF($F$3="",B36,$F$3) -> 35 | L36: {=ROUND(Paramètres!$B$16*(Paramètres!$B$5+(1-Paramètres!$B$5)*((K36-Paramètres!$B$7)/(Paramètres!$B$8-Paramètres!$B$7))^Paramètres!$B$6)*INDEX(Rôles!$B$18:$B$22,AZ36)*INDEX(Rôles!$B$5:$B$13,AY36),0)} -> 346 | M36: {=ROUND(IF(J36="Physique",1,IF(J36="Mixte",Paramètres!$B$32,0))*Paramètres!$B$12*(Paramètres!$B$5+(1-Paramètres!$B$5)*((K36-Paramètres!$B$7)/(Paramètres!$B$8-Paramètres!$B$7))^Paramètres!$B$6)*INDEX(Rôles!$C$18:$C$22,AZ36)*INDEX(Rôles!$C$5:$C$13,AY36)/(Paramètres!$B$35*(1-Paramètres!$B$36)),0)} -> 0 | N36: {=ROUND(IF(J36="Magique",1,IF(J36="Mixte",Paramètres!$B$32,0))*Paramètres!$B$12*(Paramètres!$B$5+(1-Paramètres!$B$5)*((K36-Paramètres!$B$7)/(Paramètres!$B$8-Paramètres!$B$7))^Paramètres!$B$6)*INDEX(Rôles!$C$18:$C$22,AZ36)*INDEX(Rôles!$C$5:$C$13,AY36)/(Paramètres!$B$35*(1-Paramètres!$B$36)),0)} -> 134 | O36: {=ROUND(Paramètres!$B$18*(Paramètres!$B$5+(1-Paramètres!$B$5)*((K36-Paramètres!$B$7)/(Paramètres!$B$8-Paramètres!$B$7))^Paramètres!$B$6)*INDEX(Rôles!$D$5:$D$13,AY36)*INDEX(Rôles!$D$18:$D$22,AZ36),0)} -> 155 | P36: {=ROUND(Paramètres!$B$19*(Paramètres!$B$5+(1-Paramètres!$B$5)*((K36-Paramètres!$B$7)/(Paramètres!$B$8-Paramètres!$B$7))^Paramètres!$B$6)*INDEX(Rôles!$E$5:$E$13,AY36)*INDEX(Rôles!$D$18:$D$22,AZ36),0)} -> 50 | Q36: {=ROUND(Paramètres!$B$20*(Paramètres!$B$5+(1-Paramètres!$B$5)*((K36-Paramètres!$B$7)/(Paramètres!$B$8-Paramètres!$B$7))^Paramètres!$B$6)*INDEX(Rôles!$F$5:$F$13,AY36),0)} -> 34 | R36: =ROUND(Paramètres!$B$64*$AX36*INDEX(Rôles!$N$5:$N$13,$AY36)*INDEX(Rôles!$I$18:$I$22,$AZ36),0) -> 28 | S36: {=MIN(1,ROUND(Paramètres!$B$21*INDEX(Rôles!$G$5:$G$13,AY36),3))} -> 0.9 | T36: {=MIN(Paramètres!$B$28,ROUND(Paramètres!$B$22*INDEX(Rôles!$H$5:$H$13,AY36),3))} -> 0.05 | U36: {=ROUND(Paramètres!$B$23*INDEX(Rôles!$I$5:$I$13,AY36),3)} -> 0.5 | V36: {=MIN(Paramètres!$B$29,ROUND(Paramètres!$B$24*INDEX(Rôles!$J$5:$J$13,AY36),3))} -> 0.065 | W36: {=MIN(Paramètres!$B$27,ROUND((Paramètres!$B$25+(Paramètres!$B$26-Paramètres!$B$25)*(K36-Paramètres!$B$7)/(Paramètres!$B$8-Paramètres!$B$7))*INDEX(Rôles!$K$5:$K$13,AY36)+INDEX(Rôles!$G$18:$G$22,AZ36),3))} -> 0.163 | X36: =ROUND(1-(1-P36/(P36+(Paramètres!$B$19*(Paramètres!$B$5+(1-Paramètres!$B$5)*((K36-Paramètres!$B$7)/(Paramètres!$B$8-Paramètres!$B$7))^Paramètres!$B$6)*(1-Paramètres!$B$30)/Paramètres!$B$30)))*(1-O36/(O36+(Paramètres!$B$18*(Paramètres!$B$5+(1-Paramètres!$B$5)*((K36-Paramètres!$B$7)/(Paramètres!$B$8-Paramètres!$B$7))^Paramètres!$B$6)*(1-Paramètres!$B$31)/Paramètres!$B$31))),3) -> 0.238 | Y36: =ROUND(O36/(O36+(Paramètres!$B$18*(Paramètres!$B$5+(1-Paramètres!$B$5)*((K36-Paramètres!$B$7)/(Paramètres!$B$8-Paramètres!$B$7))^Paramètres!$B$6)*(1-Paramètres!$B$31)/Paramètres!$B$31)),3) -> 0.162 | Z36: {=IF(E36="Neutre",0,MIN(1,INDEX(Rôles!$L$5:$L$13,AY36)+INDEX(Rôles!$F$18:$F$22,AZ36)))} -> 1 | AA36: {=ROUND(INDEX(Rôles!$C$18:$C$22,AZ36)*INDEX(Rôles!$C$5:$C$13,AY36),4)} -> 0.0188 | AB36: {=ROUND(INDEX(Rôles!$B$18:$B$22,AZ36)*INDEX(Rôles!$B$5:$B$13,AY36),2)} -> 1.4 | AC36: {=INDEX(Rôles!$E$18:$E$22,AZ36)} -> 1 | AD36: {=INDEX(Éléments!$F$5:$F$14,MATCH(E36,Éléments!$A$5:$A$14,0))} -> Glace | AE36: {=INDEX(Éléments!$G$5:$G$14,MATCH(E36,Éléments!$A$5:$A$14,0))} -> Terre | AF36: Désorienté | AG36: 0.3 | AH36: Intimidé | AI36: 0.15 | AJ36: {=ROUND(ROUND(Paramètres!$B$49*K36^Paramètres!$B$50,0)*INDEX(Rôles!$E$18:$E$22,AZ36),0)} -> 511 | AK36: {=ROUND(ROUND(Paramètres!$B$53*K36^Paramètres!$B$54,0)*INDEX(Rôles!$E$18:$E$22,AZ36),0)} -> 364 | AL36: =INDEX(Butin!$B$7:$B$11,AZ36) -> 0.05 | AM36: =INDEX(Butin!$E$7:$E$11,AZ36) -> 0.05 | AN36: =IF($H36="Boss",INDEX(Butin!$E$28:$K$37,MATCH($B36,Éléments!$C$5:$C$14,1),1),IF($H36="Dragon",INDEX(Butin!$E$41:$K$50,MATCH($B36,Éléments!$C$5:$C$14,1),1),INDEX(Butin!$E$15:$K$24,MATCH($B36,Éléments!$C$5:$C$14,1),1))) -> 0.42 | AO36: =IF($H36="Boss",INDEX(Butin!$E$28:$K$37,MATCH($B36,Éléments!$C$5:$C$14,1),2),IF($H36="Dragon",INDEX(Butin!$E$41:$K$50,MATCH($B36,Éléments!$C$5:$C$14,1),2),INDEX(Butin!$E$15:$K$24,MATCH($B36,Éléments!$C$5:$C$14,1),2))) -> 0.33 | AP36: =IF($H36="Boss",INDEX(Butin!$E$28:$K$37,MATCH($B36,Éléments!$C$5:$C$14,1),3),IF($H36="Dragon",INDEX(Butin!$E$41:$K$50,MATCH($B36,Éléments!$C$5:$C$14,1),3),INDEX(Butin!$E$15:$K$24,MATCH($B36,Éléments!$C$5:$C$14,1),3))) -> 0.18 | AQ36: =IF($H36="Boss",INDEX(Butin!$E$28:$K$37,MATCH($B36,Éléments!$C$5:$C$14,1),4),IF($H36="Dragon",INDEX(Butin!$E$41:$K$50,MATCH($B36,Éléments!$C$5:$C$14,1),4),INDEX(Butin!$E$15:$K$24,MATCH($B36,Éléments!$C$5:$C$14,1),4))) -> 0.06 | AR36: =IF($H36="Boss",INDEX(Butin!$E$28:$K$37,MATCH($B36,Éléments!$C$5:$C$14,1),5),IF($H36="Dragon",INDEX(Butin!$E$41:$K$50,MATCH($B36,Éléments!$C$5:$C$14,1),5),INDEX(Butin!$E$15:$K$24,MATCH($B36,Éléments!$C$5:$C$14,1),5))) -> 0.01 | AS36: =IF($H36="Boss",INDEX(Butin!$E$28:$K$37,MATCH($B36,Éléments!$C$5:$C$14,1),6),IF($H36="Dragon",INDEX(Butin!$E$41:$K$50,MATCH($B36,Éléments!$C$5:$C$14,1),6),INDEX(Butin!$E$15:$K$24,MATCH($B36,Éléments!$C$5:$C$14,1),6))) -> 0 | AT36: =IF($H36="Boss",INDEX(Butin!$E$28:$K$37,MATCH($B36,Éléments!$C$5:$C$14,1),7),IF($H36="Dragon",INDEX(Butin!$E$41:$K$50,MATCH($B36,Éléments!$C$5:$C$14,1),7),INDEX(Butin!$E$15:$K$24,MATCH($B36,Éléments!$C$5:$C$14,1),7))) -> 0 | AU36: =IF(AT36=0,"—",INDEX(Butin!$D$54:$D$63,MATCH($B36,Éléments!$C$5:$C$14,1))&" · "&INDEX(Butin!$F$54:$F$63,MATCH($B36,Éléments!$C$5:$C$14,1))&" · "&INDEX(Butin!$H$54:$H$63,MATCH($B36,Éléments!$C$5:$C$14,1))) -> — | AV36: Djin | AW36: =B36&IF(G36="Oui","|B","|N") -> 35|N | AX36: =(Paramètres!$B$5+(1-Paramètres!$B$5)*((K36-Paramètres!$B$7)/(Paramètres!$B$8-Paramètres!$B$7))^Paramètres!$B$6) -> 0.31347297 | AY36: =MATCH(I36,Rôles!$A$5:$A$13,0) -> 5 | AZ36: =MATCH(H36,Rôles!$A$18:$A$22,0) -> 2
A37: MON-031 | B37: 35 | C37: {=INDEX(Zones!$B$6:$B$35,MATCH(B37,Zones!$A$6:$A$35,0))} -> Désert d'Arrakis | D37: {=INDEX(Éléments!$B$5:$B$14,MATCH(B37,Éléments!$C$5:$C$14,1))} -> Désert | E37: {=INDEX(Éléments!$A$5:$A$14,MATCH(B37,Éléments!$C$5:$C$14,1))} -> Vent | F37: Souffleur | G37: =IF(OR(H37="Boss",H37="Dragon"),"Oui","Non") -> Non | H37: Normal | I37: Mage | J37: Magique | K37: =IF($F$3="",B37,$F$3) -> 35 | L37: {=ROUND(Paramètres!$B$16*(Paramètres!$B$5+(1-Paramètres!$B$5)*((K37-Paramètres!$B$7)/(Paramètres!$B$8-Paramètres!$B$7))^Paramètres!$B$6)*INDEX(Rôles!$B$18:$B$22,AZ37)*INDEX(Rôles!$B$5:$B$13,AY37),0)} -> 346 | M37: {=ROUND(IF(J37="Physique",1,IF(J37="Mixte",Paramètres!$B$32,0))*Paramètres!$B$12*(Paramètres!$B$5+(1-Paramètres!$B$5)*((K37-Paramètres!$B$7)/(Paramètres!$B$8-Paramètres!$B$7))^Paramètres!$B$6)*INDEX(Rôles!$C$18:$C$22,AZ37)*INDEX(Rôles!$C$5:$C$13,AY37)/(Paramètres!$B$35*(1-Paramètres!$B$36)),0)} -> 0 | N37: {=ROUND(IF(J37="Magique",1,IF(J37="Mixte",Paramètres!$B$32,0))*Paramètres!$B$12*(Paramètres!$B$5+(1-Paramètres!$B$5)*((K37-Paramètres!$B$7)/(Paramètres!$B$8-Paramètres!$B$7))^Paramètres!$B$6)*INDEX(Rôles!$C$18:$C$22,AZ37)*INDEX(Rôles!$C$5:$C$13,AY37)/(Paramètres!$B$35*(1-Paramètres!$B$36)),0)} -> 134 | O37: {=ROUND(Paramètres!$B$18*(Paramètres!$B$5+(1-Paramètres!$B$5)*((K37-Paramètres!$B$7)/(Paramètres!$B$8-Paramètres!$B$7))^Paramètres!$B$6)*INDEX(Rôles!$D$5:$D$13,AY37)*INDEX(Rôles!$D$18:$D$22,AZ37),0)} -> 155 | P37: {=ROUND(Paramètres!$B$19*(Paramètres!$B$5+(1-Paramètres!$B$5)*((K37-Paramètres!$B$7)/(Paramètres!$B$8-Paramètres!$B$7))^Paramètres!$B$6)*INDEX(Rôles!$E$5:$E$13,AY37)*INDEX(Rôles!$D$18:$D$22,AZ37),0)} -> 50 | Q37: {=ROUND(Paramètres!$B$20*(Paramètres!$B$5+(1-Paramètres!$B$5)*((K37-Paramètres!$B$7)/(Paramètres!$B$8-Paramètres!$B$7))^Paramètres!$B$6)*INDEX(Rôles!$F$5:$F$13,AY37),0)} -> 34 | R37: =ROUND(Paramètres!$B$64*$AX37*INDEX(Rôles!$N$5:$N$13,$AY37)*INDEX(Rôles!$I$18:$I$22,$AZ37),0) -> 28 | S37: {=MIN(1,ROUND(Paramètres!$B$21*INDEX(Rôles!$G$5:$G$13,AY37),3))} -> 0.9 | T37: {=MIN(Paramètres!$B$28,ROUND(Paramètres!$B$22*INDEX(Rôles!$H$5:$H$13,AY37),3))} -> 0.05 | U37: {=ROUND(Paramètres!$B$23*INDEX(Rôles!$I$5:$I$13,AY37),3)} -> 0.5 | V37: {=MIN(Paramètres!$B$29,ROUND(Paramètres!$B$24*INDEX(Rôles!$J$5:$J$13,AY37),3))} -> 0.065 | W37: {=MIN(Paramètres!$B$27,ROUND((Paramètres!$B$25+(Paramètres!$B$26-Paramètres!$B$25)*(K37-Paramètres!$B$7)/(Paramètres!$B$8-Paramètres!$B$7))*INDEX(Rôles!$K$5:$K$13,AY37)+INDEX(Rôles!$G$18:$G$22,AZ37),3))} -> 0.163 | X37: =ROUND(1-(1-P37/(P37+(Paramètres!$B$19*(Paramètres!$B$5+(1-Paramètres!$B$5)*((K37-Paramètres!$B$7)/(Paramètres!$B$8-Paramètres!$B$7))^Paramètres!$B$6)*(1-Paramètres!$B$30)/Paramètres!$B$30)))*(1-O37/(O37+(Paramètres!$B$18*(Paramètres!$B$5+(1-Paramètres!$B$5)*((K37-Paramètres!$B$7)/(Paramètres!$B$8-Paramètres!$B$7))^Paramètres!$B$6)*(1-Paramètres!$B$31)/Paramètres!$B$31))),3) -> 0.238 | Y37: =ROUND(O37/(O37+(Paramètres!$B$18*(Paramètres!$B$5+(1-Paramètres!$B$5)*((K37-Paramètres!$B$7)/(Paramètres!$B$8-Paramètres!$B$7))^Paramètres!$B$6)*(1-Paramètres!$B$31)/Paramètres!$B$31)),3) -> 0.162 | Z37: {=IF(E37="Neutre",0,MIN(1,INDEX(Rôles!$L$5:$L$13,AY37)+INDEX(Rôles!$F$18:$F$22,AZ37)))} -> 1 | AA37: {=ROUND(INDEX(Rôles!$C$18:$C$22,AZ37)*INDEX(Rôles!$C$5:$C$13,AY37),4)} -> 0.0188 | AB37: {=ROUND(INDEX(Rôles!$B$18:$B$22,AZ37)*INDEX(Rôles!$B$5:$B$13,AY37),2)} -> 1.4 | AC37: {=INDEX(Rôles!$E$18:$E$22,AZ37)} -> 1 | AD37: {=INDEX(Éléments!$F$5:$F$14,MATCH(E37,Éléments!$A$5:$A$14,0))} -> Glace | AE37: {=INDEX(Éléments!$G$5:$G$14,MATCH(E37,Éléments!$A$5:$A$14,0))} -> Terre | AF37: Désorienté | AG37: 0.35 | AJ37: {=ROUND(ROUND(Paramètres!$B$49*K37^Paramètres!$B$50,0)*INDEX(Rôles!$E$18:$E$22,AZ37),0)} -> 511 | AK37: {=ROUND(ROUND(Paramètres!$B$53*K37^Paramètres!$B$54,0)*INDEX(Rôles!$E$18:$E$22,AZ37),0)} -> 364 | AL37: =INDEX(Butin!$B$7:$B$11,AZ37) -> 0.05 | AM37: =INDEX(Butin!$E$7:$E$11,AZ37) -> 0.05 | AN37: =IF($H37="Boss",INDEX(Butin!$E$28:$K$37,MATCH($B37,Éléments!$C$5:$C$14,1),1),IF($H37="Dragon",INDEX(Butin!$E$41:$K$50,MATCH($B37,Éléments!$C$5:$C$14,1),1),INDEX(Butin!$E$15:$K$24,MATCH($B37,Éléments!$C$5:$C$14,1),1))) -> 0.42 | AO37: =IF($H37="Boss",INDEX(Butin!$E$28:$K$37,MATCH($B37,Éléments!$C$5:$C$14,1),2),IF($H37="Dragon",INDEX(Butin!$E$41:$K$50,MATCH($B37,Éléments!$C$5:$C$14,1),2),INDEX(Butin!$E$15:$K$24,MATCH($B37,Éléments!$C$5:$C$14,1),2))) -> 0.33 | AP37: =IF($H37="Boss",INDEX(Butin!$E$28:$K$37,MATCH($B37,Éléments!$C$5:$C$14,1),3),IF($H37="Dragon",INDEX(Butin!$E$41:$K$50,MATCH($B37,Éléments!$C$5:$C$14,1),3),INDEX(Butin!$E$15:$K$24,MATCH($B37,Éléments!$C$5:$C$14,1),3))) -> 0.18 | AQ37: =IF($H37="Boss",INDEX(Butin!$E$28:$K$37,MATCH($B37,Éléments!$C$5:$C$14,1),4),IF($H37="Dragon",INDEX(Butin!$E$41:$K$50,MATCH($B37,Éléments!$C$5:$C$14,1),4),INDEX(Butin!$E$15:$K$24,MATCH($B37,Éléments!$C$5:$C$14,1),4))) -> 0.06 | AR37: =IF($H37="Boss",INDEX(Butin!$E$28:$K$37,MATCH($B37,Éléments!$C$5:$C$14,1),5),IF($H37="Dragon",INDEX(Butin!$E$41:$K$50,MATCH($B37,Éléments!$C$5:$C$14,1),5),INDEX(Butin!$E$15:$K$24,MATCH($B37,Éléments!$C$5:$C$14,1),5))) -> 0.01 | AS37: =IF($H37="Boss",INDEX(Butin!$E$28:$K$37,MATCH($B37,Éléments!$C$5:$C$14,1),6),IF($H37="Dragon",INDEX(Butin!$E$41:$K$50,MATCH($B37,Éléments!$C$5:$C$14,1),6),INDEX(Butin!$E$15:$K$24,MATCH($B37,Éléments!$C$5:$C$14,1),6))) -> 0 | AT37: =IF($H37="Boss",INDEX(Butin!$E$28:$K$37,MATCH($B37,Éléments!$C$5:$C$14,1),7),IF($H37="Dragon",INDEX(Butin!$E$41:$K$50,MATCH($B37,Éléments!$C$5:$C$14,1),7),INDEX(Butin!$E$15:$K$24,MATCH($B37,Éléments!$C$5:$C$14,1),7))) -> 0 | AU37: =IF(AT37=0,"—",INDEX(Butin!$D$54:$D$63,MATCH($B37,Éléments!$C$5:$C$14,1))&" · "&INDEX(Butin!$F$54:$F$63,MATCH($B37,Éléments!$C$5:$C$14,1))&" · "&INDEX(Butin!$H$54:$H$63,MATCH($B37,Éléments!$C$5:$C$14,1))) -> — | AV37: Souffleur | AW37: =B37&IF(G37="Oui","|B","|N") -> 35|N | AX37: =(Paramètres!$B$5+(1-Paramètres!$B$5)*((K37-Paramètres!$B$7)/(Paramètres!$B$8-Paramètres!$B$7))^Paramètres!$B$6) -> 0.31347297 | AY37: =MATCH(I37,Rôles!$A$5:$A$13,0) -> 5 | AZ37: =MATCH(H37,Rôles!$A$18:$A$22,0) -> 2
A38: MON-032 | B38: 35 | C38: {=INDEX(Zones!$B$6:$B$35,MATCH(B38,Zones!$A$6:$A$35,0))} -> Désert d'Arrakis | D38: {=INDEX(Éléments!$B$5:$B$14,MATCH(B38,Éléments!$C$5:$C$14,1))} -> Désert | E38: {=INDEX(Éléments!$A$5:$A$14,MATCH(B38,Éléments!$C$5:$C$14,1))} -> Vent | F38: Harpie | G38: =IF(OR(H38="Boss",H38="Dragon"),"Oui","Non") -> Non | H38: Normal | I38: Assassin | J38: Physique | K38: =IF($F$3="",B38,$F$3) -> 35 | L38: {=ROUND(Paramètres!$B$16*(Paramètres!$B$5+(1-Paramètres!$B$5)*((K38-Paramètres!$B$7)/(Paramètres!$B$8-Paramètres!$B$7))^Paramètres!$B$6)*INDEX(Rôles!$B$18:$B$22,AZ38)*INDEX(Rôles!$B$5:$B$13,AY38),0)} -> 370 | M38: {=ROUND(IF(J38="Physique",1,IF(J38="Mixte",Paramètres!$B$32,0))*Paramètres!$B$12*(Paramètres!$B$5+(1-Paramètres!$B$5)*((K38-Paramètres!$B$7)/(Paramètres!$B$8-Paramètres!$B$7))^Paramètres!$B$6)*INDEX(Rôles!$C$18:$C$22,AZ38)*INDEX(Rôles!$C$5:$C$13,AY38)/(Paramètres!$B$35*(1-Paramètres!$B$36)),0)} -> 129 | N38: {=ROUND(IF(J38="Magique",1,IF(J38="Mixte",Paramètres!$B$32,0))*Paramètres!$B$12*(Paramètres!$B$5+(1-Paramètres!$B$5)*((K38-Paramètres!$B$7)/(Paramètres!$B$8-Paramètres!$B$7))^Paramètres!$B$6)*INDEX(Rôles!$C$18:$C$22,AZ38)*INDEX(Rôles!$C$5:$C$13,AY38)/(Paramètres!$B$35*(1-Paramètres!$B$36)),0)} -> 0 | O38: {=ROUND(Paramètres!$B$18*(Paramètres!$B$5+(1-Paramètres!$B$5)*((K38-Paramètres!$B$7)/(Paramètres!$B$8-Paramètres!$B$7))^Paramètres!$B$6)*INDEX(Rôles!$D$5:$D$13,AY38)*INDEX(Rôles!$D$18:$D$22,AZ38),0)} -> 85 | P38: {=ROUND(Paramètres!$B$19*(Paramètres!$B$5+(1-Paramètres!$B$5)*((K38-Paramètres!$B$7)/(Paramètres!$B$8-Paramètres!$B$7))^Paramètres!$B$6)*INDEX(Rôles!$E$5:$E$13,AY38)*INDEX(Rôles!$D$18:$D$22,AZ38),0)} -> 63 | Q38: {=ROUND(Paramètres!$B$20*(Paramètres!$B$5+(1-Paramètres!$B$5)*((K38-Paramètres!$B$7)/(Paramètres!$B$8-Paramètres!$B$7))^Paramètres!$B$6)*INDEX(Rôles!$F$5:$F$13,AY38),0)} -> 60 | R38: =ROUND(Paramètres!$B$64*$AX38*INDEX(Rôles!$N$5:$N$13,$AY38)*INDEX(Rôles!$I$18:$I$22,$AZ38),0) -> 47 | S38: {=MIN(1,ROUND(Paramètres!$B$21*INDEX(Rôles!$G$5:$G$13,AY38),3))} -> 1 | T38: {=MIN(Paramètres!$B$28,ROUND(Paramètres!$B$22*INDEX(Rôles!$H$5:$H$13,AY38),3))} -> 0.08 | U38: {=ROUND(Paramètres!$B$23*INDEX(Rôles!$I$5:$I$13,AY38),3)} -> 0.7 | V38: {=MIN(Paramètres!$B$29,ROUND(Paramètres!$B$24*INDEX(Rôles!$J$5:$J$13,AY38),3))} -> 0.06 | W38: {=MIN(Paramètres!$B$27,ROUND((Paramètres!$B$25+(Paramètres!$B$26-Paramètres!$B$25)*(K38-Paramètres!$B$7)/(Paramètres!$B$8-Paramètres!$B$7))*INDEX(Rôles!$K$5:$K$13,AY38)+INDEX(Rôles!$G$18:$G$22,AZ38),3))} -> 0.109 | X38: =ROUND(1-(1-P38/(P38+(Paramètres!$B$19*(Paramètres!$B$5+(1-Paramètres!$B$5)*((K38-Paramètres!$B$7)/(Paramètres!$B$8-Paramètres!$B$7))^Paramètres!$B$6)*(1-Paramètres!$B$30)/Paramètres!$B$30)))*(1-O38/(O38+(Paramètres!$B$18*(Paramètres!$B$5+(1-Paramètres!$B$5)*((K38-Paramètres!$B$7)/(Paramètres!$B$8-Paramètres!$B$7))^Paramètres!$B$6)*(1-Paramètres!$B$31)/Paramètres!$B$31))),3) -> 0.197 | Y38: =ROUND(O38/(O38+(Paramètres!$B$18*(Paramètres!$B$5+(1-Paramètres!$B$5)*((K38-Paramètres!$B$7)/(Paramètres!$B$8-Paramètres!$B$7))^Paramètres!$B$6)*(1-Paramètres!$B$31)/Paramètres!$B$31)),3) -> 0.096 | Z38: {=IF(E38="Neutre",0,MIN(1,INDEX(Rôles!$L$5:$L$13,AY38)+INDEX(Rôles!$F$18:$F$22,AZ38)))} -> 0.5 | AA38: {=ROUND(INDEX(Rôles!$C$18:$C$22,AZ38)*INDEX(Rôles!$C$5:$C$13,AY38),4)} -> 0.018 | AB38: {=ROUND(INDEX(Rôles!$B$18:$B$22,AZ38)*INDEX(Rôles!$B$5:$B$13,AY38),2)} -> 1.5 | AC38: {=INDEX(Rôles!$E$18:$E$22,AZ38)} -> 1 | AD38: {=INDEX(Éléments!$F$5:$F$14,MATCH(E38,Éléments!$A$5:$A$14,0))} -> Glace | AE38: {=INDEX(Éléments!$G$5:$G$14,MATCH(E38,Éléments!$A$5:$A$14,0))} -> Terre | AF38: Saignement | AG38: 0.2 | AH38: Désorienté | AI38: 0.2 | AJ38: {=ROUND(ROUND(Paramètres!$B$49*K38^Paramètres!$B$50,0)*INDEX(Rôles!$E$18:$E$22,AZ38),0)} -> 511 | AK38: {=ROUND(ROUND(Paramètres!$B$53*K38^Paramètres!$B$54,0)*INDEX(Rôles!$E$18:$E$22,AZ38),0)} -> 364 | AL38: =INDEX(Butin!$B$7:$B$11,AZ38) -> 0.05 | AM38: =INDEX(Butin!$E$7:$E$11,AZ38) -> 0.05 | AN38: =IF($H38="Boss",INDEX(Butin!$E$28:$K$37,MATCH($B38,Éléments!$C$5:$C$14,1),1),IF($H38="Dragon",INDEX(Butin!$E$41:$K$50,MATCH($B38,Éléments!$C$5:$C$14,1),1),INDEX(Butin!$E$15:$K$24,MATCH($B38,Éléments!$C$5:$C$14,1),1))) -> 0.42 | AO38: =IF($H38="Boss",INDEX(Butin!$E$28:$K$37,MATCH($B38,Éléments!$C$5:$C$14,1),2),IF($H38="Dragon",INDEX(Butin!$E$41:$K$50,MATCH($B38,Éléments!$C$5:$C$14,1),2),INDEX(Butin!$E$15:$K$24,MATCH($B38,Éléments!$C$5:$C$14,1),2))) -> 0.33 | AP38: =IF($H38="Boss",INDEX(Butin!$E$28:$K$37,MATCH($B38,Éléments!$C$5:$C$14,1),3),IF($H38="Dragon",INDEX(Butin!$E$41:$K$50,MATCH($B38,Éléments!$C$5:$C$14,1),3),INDEX(Butin!$E$15:$K$24,MATCH($B38,Éléments!$C$5:$C$14,1),3))) -> 0.18 | AQ38: =IF($H38="Boss",INDEX(Butin!$E$28:$K$37,MATCH($B38,Éléments!$C$5:$C$14,1),4),IF($H38="Dragon",INDEX(Butin!$E$41:$K$50,MATCH($B38,Éléments!$C$5:$C$14,1),4),INDEX(Butin!$E$15:$K$24,MATCH($B38,Éléments!$C$5:$C$14,1),4))) -> 0.06 | AR38: =IF($H38="Boss",INDEX(Butin!$E$28:$K$37,MATCH($B38,Éléments!$C$5:$C$14,1),5),IF($H38="Dragon",INDEX(Butin!$E$41:$K$50,MATCH($B38,Éléments!$C$5:$C$14,1),5),INDEX(Butin!$E$15:$K$24,MATCH($B38,Éléments!$C$5:$C$14,1),5))) -> 0.01 | AS38: =IF($H38="Boss",INDEX(Butin!$E$28:$K$37,MATCH($B38,Éléments!$C$5:$C$14,1),6),IF($H38="Dragon",INDEX(Butin!$E$41:$K$50,MATCH($B38,Éléments!$C$5:$C$14,1),6),INDEX(Butin!$E$15:$K$24,MATCH($B38,Éléments!$C$5:$C$14,1),6))) -> 0 | AT38: =IF($H38="Boss",INDEX(Butin!$E$28:$K$37,MATCH($B38,Éléments!$C$5:$C$14,1),7),IF($H38="Dragon",INDEX(Butin!$E$41:$K$50,MATCH($B38,Éléments!$C$5:$C$14,1),7),INDEX(Butin!$E$15:$K$24,MATCH($B38,Éléments!$C$5:$C$14,1),7))) -> 0 | AU38: =IF(AT38=0,"—",INDEX(Butin!$D$54:$D$63,MATCH($B38,Éléments!$C$5:$C$14,1))&" · "&INDEX(Butin!$F$54:$F$63,MATCH($B38,Éléments!$C$5:$C$14,1))&" · "&INDEX(Butin!$H$54:$H$63,MATCH($B38,Éléments!$C$5:$C$14,1))) -> — | AV38: Harpie | AW38: =B38&IF(G38="Oui","|B","|N") -> 35|N | AX38: =(Paramètres!$B$5+(1-Paramètres!$B$5)*((K38-Paramètres!$B$7)/(Paramètres!$B$8-Paramètres!$B$7))^Paramètres!$B$6) -> 0.31347297 | AY38: =MATCH(I38,Rôles!$A$5:$A$13,0) -> 7 | AZ38: =MATCH(H38,Rôles!$A$18:$A$22,0) -> 2
A39: MON-033 | B39: 39 | C39: {=INDEX(Zones!$B$6:$B$35,MATCH(B39,Zones!$A$6:$A$35,0))} -> Tannière du dragon (39) | D39: {=INDEX(Éléments!$B$5:$B$14,MATCH(B39,Éléments!$C$5:$C$14,1))} -> Désert | E39: {=INDEX(Éléments!$A$5:$A$14,MATCH(B39,Éléments!$C$5:$C$14,1))} -> Vent | F39: Dragon (Vent) | G39: =IF(OR(H39="Boss",H39="Dragon"),"Oui","Non") -> Oui | H39: Dragon | I39: Dragon | J39: Mixte | K39: =IF($F$3="",B39,$F$3) -> 39 | L39: {=ROUND(Paramètres!$B$16*(Paramètres!$B$5+(1-Paramètres!$B$5)*((K39-Paramètres!$B$7)/(Paramètres!$B$8-Paramètres!$B$7))^Paramètres!$B$6)*INDEX(Rôles!$B$18:$B$22,AZ39)*INDEX(Rôles!$B$5:$B$13,AY39),0)} -> 5530 | M39: {=ROUND(IF(J39="Physique",1,IF(J39="Mixte",Paramètres!$B$32,0))*Paramètres!$B$12*(Paramètres!$B$5+(1-Paramètres!$B$5)*((K39-Paramètres!$B$7)/(Paramètres!$B$8-Paramètres!$B$7))^Paramètres!$B$6)*INDEX(Rôles!$C$18:$C$22,AZ39)*INDEX(Rôles!$C$5:$C$13,AY39)/(Paramètres!$B$35*(1-Paramètres!$B$36)),0)} -> 181 | N39: {=ROUND(IF(J39="Magique",1,IF(J39="Mixte",Paramètres!$B$32,0))*Paramètres!$B$12*(Paramètres!$B$5+(1-Paramètres!$B$5)*((K39-Paramètres!$B$7)/(Paramètres!$B$8-Paramètres!$B$7))^Paramètres!$B$6)*INDEX(Rôles!$C$18:$C$22,AZ39)*INDEX(Rôles!$C$5:$C$13,AY39)/(Paramètres!$B$35*(1-Paramètres!$B$36)),0)} -> 181 | O39: {=ROUND(Paramètres!$B$18*(Paramètres!$B$5+(1-Paramètres!$B$5)*((K39-Paramètres!$B$7)/(Paramètres!$B$8-Paramètres!$B$7))^Paramètres!$B$6)*INDEX(Rôles!$D$5:$D$13,AY39)*INDEX(Rôles!$D$18:$D$22,AZ39),0)} -> 267 | P39: {=ROUND(Paramètres!$B$19*(Paramètres!$B$5+(1-Paramètres!$B$5)*((K39-Paramètres!$B$7)/(Paramètres!$B$8-Paramètres!$B$7))^Paramètres!$B$6)*INDEX(Rôles!$E$5:$E$13,AY39)*INDEX(Rôles!$D$18:$D$22,AZ39),0)} -> 256 | Q39: {=ROUND(Paramètres!$B$20*(Paramètres!$B$5+(1-Paramètres!$B$5)*((K39-Paramètres!$B$7)/(Paramètres!$B$8-Paramètres!$B$7))^Paramètres!$B$6)*INDEX(Rôles!$F$5:$F$13,AY39),0)} -> 34 | R39: =ROUND(Paramètres!$B$64*$AX39*INDEX(Rôles!$N$5:$N$13,$AY39)*INDEX(Rôles!$I$18:$I$22,$AZ39),0) -> 28 | S39: {=MIN(1,ROUND(Paramètres!$B$21*INDEX(Rôles!$G$5:$G$13,AY39),3))} -> 0.9 | T39: {=MIN(Paramètres!$B$28,ROUND(Paramètres!$B$22*INDEX(Rôles!$H$5:$H$13,AY39),3))} -> 0.05 | U39: {=ROUND(Paramètres!$B$23*INDEX(Rôles!$I$5:$I$13,AY39),3)} -> 0.5 | V39: {=MIN(Paramètres!$B$29,ROUND(Paramètres!$B$24*INDEX(Rôles!$J$5:$J$13,AY39),3))} -> 0.05 | W39: {=MIN(Paramètres!$B$27,ROUND((Paramètres!$B$25+(Paramètres!$B$26-Paramètres!$B$25)*(K39-Paramètres!$B$7)/(Paramètres!$B$8-Paramètres!$B$7))*INDEX(Rôles!$K$5:$K$13,AY39)+INDEX(Rôles!$G$18:$G$22,AZ39),3))} -> 0.39 | X39: =ROUND(1-(1-P39/(P39+(Paramètres!$B$19*(Paramètres!$B$5+(1-Paramètres!$B$5)*((K39-Paramètres!$B$7)/(Paramètres!$B$8-Paramètres!$B$7))^Paramètres!$B$6)*(1-Paramètres!$B$30)/Paramètres!$B$30)))*(1-O39/(O39+(Paramètres!$B$18*(Paramètres!$B$5+(1-Paramètres!$B$5)*((K39-Paramètres!$B$7)/(Paramètres!$B$8-Paramètres!$B$7))^Paramètres!$B$6)*(1-Paramètres!$B$31)/Paramètres!$B$31))),3) -> 0.471 | Y39: =ROUND(O39/(O39+(Paramètres!$B$18*(Paramètres!$B$5+(1-Paramètres!$B$5)*((K39-Paramètres!$B$7)/(Paramètres!$B$8-Paramètres!$B$7))^Paramètres!$B$6)*(1-Paramètres!$B$31)/Paramètres!$B$31)),3) -> 0.23 | Z39: {=IF(E39="Neutre",0,MIN(1,INDEX(Rôles!$L$5:$L$13,AY39)+INDEX(Rôles!$F$18:$F$22,AZ39)))} -> 1 | AA39: {=ROUND(INDEX(Rôles!$C$18:$C$22,AZ39)*INDEX(Rôles!$C$5:$C$13,AY39),4)} -> 0.03 | AB39: {=ROUND(INDEX(Rôles!$B$18:$B$22,AZ39)*INDEX(Rôles!$B$5:$B$13,AY39),2)} -> 20 | AC39: {=INDEX(Rôles!$E$18:$E$22,AZ39)} -> 12 | AD39: {=INDEX(Éléments!$F$5:$F$14,MATCH(E39,Éléments!$A$5:$A$14,0))} -> Glace | AE39: {=INDEX(Éléments!$G$5:$G$14,MATCH(E39,Éléments!$A$5:$A$14,0))} -> Terre | AF39: Désorienté | AG39: 0.35 | AH39: Assommé | AI39: 0.15 | AJ39: {=ROUND(ROUND(Paramètres!$B$49*K39^Paramètres!$B$50,0)*INDEX(Rôles!$E$18:$E$22,AZ39),0)} -> 7020 | AK39: {=ROUND(ROUND(Paramètres!$B$53*K39^Paramètres!$B$54,0)*INDEX(Rôles!$E$18:$E$22,AZ39),0)} -> 5064 | AL39: =INDEX(Butin!$B$7:$B$11,AZ39) -> 1 | AM39: =INDEX(Butin!$E$7:$E$11,AZ39) -> 2.5 | AN39: =IF($H39="Boss",INDEX(Butin!$E$28:$K$37,MATCH($B39,Éléments!$C$5:$C$14,1),1),IF($H39="Dragon",INDEX(Butin!$E$41:$K$50,MATCH($B39,Éléments!$C$5:$C$14,1),1),INDEX(Butin!$E$15:$K$24,MATCH($B39,Éléments!$C$5:$C$14,1),1))) -> 0.07 | AO39: =IF($H39="Boss",INDEX(Butin!$E$28:$K$37,MATCH($B39,Éléments!$C$5:$C$14,1),2),IF($H39="Dragon",INDEX(Butin!$E$41:$K$50,MATCH($B39,Éléments!$C$5:$C$14,1),2),INDEX(Butin!$E$15:$K$24,MATCH($B39,Éléments!$C$5:$C$14,1),2))) -> 0.24 | AP39: =IF($H39="Boss",INDEX(Butin!$E$28:$K$37,MATCH($B39,Éléments!$C$5:$C$14,1),3),IF($H39="Dragon",INDEX(Butin!$E$41:$K$50,MATCH($B39,Éléments!$C$5:$C$14,1),3),INDEX(Butin!$E$15:$K$24,MATCH($B39,Éléments!$C$5:$C$14,1),3))) -> 0.31 | AQ39: =IF($H39="Boss",INDEX(Butin!$E$28:$K$37,MATCH($B39,Éléments!$C$5:$C$14,1),4),IF($H39="Dragon",INDEX(Butin!$E$41:$K$50,MATCH($B39,Éléments!$C$5:$C$14,1),4),INDEX(Butin!$E$15:$K$24,MATCH($B39,Éléments!$C$5:$C$14,1),4))) -> 0.23 | AR39: =IF($H39="Boss",INDEX(Butin!$E$28:$K$37,MATCH($B39,Éléments!$C$5:$C$14,1),5),IF($H39="Dragon",INDEX(Butin!$E$41:$K$50,MATCH($B39,Éléments!$C$5:$C$14,1),5),INDEX(Butin!$E$15:$K$24,MATCH($B39,Éléments!$C$5:$C$14,1),5))) -> 0.08 | AS39: =IF($H39="Boss",INDEX(Butin!$E$28:$K$37,MATCH($B39,Éléments!$C$5:$C$14,1),6),IF($H39="Dragon",INDEX(Butin!$E$41:$K$50,MATCH($B39,Éléments!$C$5:$C$14,1),6),INDEX(Butin!$E$15:$K$24,MATCH($B39,Éléments!$C$5:$C$14,1),6))) -> 0.015 | AT39: =IF($H39="Boss",INDEX(Butin!$E$28:$K$37,MATCH($B39,Éléments!$C$5:$C$14,1),7),IF($H39="Dragon",INDEX(Butin!$E$41:$K$50,MATCH($B39,Éléments!$C$5:$C$14,1),7),INDEX(Butin!$E$15:$K$24,MATCH($B39,Éléments!$C$5:$C$14,1),7))) -> 0.055 | AU39: =IF(AT39=0,"—",INDEX(Butin!$D$54:$D$63,MATCH($B39,Éléments!$C$5:$C$14,1))&" · "&INDEX(Butin!$F$54:$F$63,MATCH($B39,Éléments!$C$5:$C$14,1))&" · "&INDEX(Butin!$H$54:$H$63,MATCH($B39,Éléments!$C$5:$C$14,1))) -> Médaillon du Serment Brisé * · Chapeau du Sage des Cieux · Arc des Mille Tempêtes | AV39: Dragon (Vent) | AW39: =B39&IF(G39="Oui","|B","|N") -> 39|B | AX39: =(Paramètres!$B$5+(1-Paramètres!$B$5)*((K39-Paramètres!$B$7)/(Paramètres!$B$8-Paramètres!$B$7))^Paramètres!$B$6) -> 0.35109371 | AY39: =MATCH(I39,Rôles!$A$5:$A$13,0) -> 9 | AZ39: =MATCH(H39,Rôles!$A$18:$A$22,0) -> 5
