Workbook

Sheet Guide
A1: RPG tour par tour : village
A2: Bâtiments, production idle, coûts d'amélioration et bonus permanents.
A4: PRINCIPE
A5: Production idle | B5: Les bâtiments de production produisent en continu, même hors ligne, pendant 8 h maximum (Paramètres). Le stock de chaque ressource est plafonné par l'Entrepôt.
A6: Améliorer | B6: Chaque niveau coûte de l'or + un matériau de construction (bois, fer, acier, mithril, adamantite selon l'étage) + du charbon dès l'étage 15. Pas de temps de construction : instantané.
A7: Effet | B7: Un niveau augmente la production des ressources déjà débloquées (+12 %) et, à certains niveaux, débloque la ressource suivante (ex. Scierie niv. 6 : chêne et frêne).
A8: Étage requis | B8: Un niveau demande d'avoir atteint l'étage de sa tranche (Paramètres §3) et celui de la ressource qu'il débloque : on ne peut pas produire d'acier avant l'étage 30.
A9: Héritage | B9: Tout le village est conservé : niveaux, stocks et bâtiments débloqués.
A10: ONGLETS
A11: Bâtiments | B11: Les 10 bâtiments : image, étage de déblocage, niveau max, coût et rôle.
A12: Production | B12: Production par heure de chaque ressource à chaque niveau, plus un repère de cohérence avec le coût d'amélioration des objets.
A13: Améliorations | B13: Une ligne par niveau : étage requis, or, matériau, quantité, charbon, temps de chasse équivalent et effet. C'est l'info à afficher au survol du bouton « Améliorer ».
A14: Tour d'amélioration | B14: 6 branches de bonus permanents (dégâts, PV, défense, production, durée hors ligne, or et XP) et leur coût par niveau.
A15: Paramètres | B15: Tous les réglages : production de base, hausse par niveau, coûts, tranches, entrepôt, taverne et repère d'or par heure.
A16: LIENS AVEC LES AUTRES FICHIERS
A17: Équipements | B17: Les ressources produites sont les matériaux d'amélioration des objets (onglet Matériaux). Repère : une nuit de production ≈ un objet Commun monté au maximum.
A18: Bestiaire | B18: L'or demandé est calé sur l'or gagné en chasse (onglet Zones) : une amélioration coûte de quelques minutes à ~45 minutes de chasse. La boutique est dans l'onglet Boutique du bestiaire.
A19: À VALIDER
A20: Atelier à l'étage 15 | B20: Le diagramme place l'Atelier à l'étage 15 : avant, on ne peut ni fabriquer ni améliorer d'objet. Mettre 0 dans Bâtiments si tu veux l'ouvrir dès le début.
A21: Charbon | B21: Présent dans le diagramme et les assets mais pas dans les objets : utilisé ici comme matériau de construction.
A22: LÉGENDE
A23: Cellule jaune, texte bleu | B23: Valeur modifiable. Les autres cellules sont calculées : ne pas les écraser.

Sheet Bâtiments
A1: Bâtiments du village
A2: Déblocage, niveau maximum, coût et rôle de chaque bâtiment. Les noms d'images suivent le dossier assets_rpg_tour/village.
A5: Bâtiment | B5: Image | C5: Type | D5: Débloqué à l'étage | E5: Niveau max | F5: Coût en or (coefficient) | G5: Multiplicateur de matériaux | H5: Rôle
A6: Taverne | B6: village/taverne.png | C6: Commerce | D6: 0 | E6: 10 | F6: 800 | G6: 1 | H6: Marchand : objets (Commun → Épique), lots de ressources et personnages. Renouvellement toutes les heures. Les niveaux ajoutent des offres et une remise.
A7: Entrepôt | B7: village/entrepot.png | C7: Stockage | D7: 0 | E7: 25 | F7: 400 | G7: 1 | H7: Capacité maximale de chaque ressource. Au-delà, la production s'arrête.
A8: Scierie | B8: village/scierie.png | C8: Production | D8: 0 | E8: 15 | F8: 500 | G8: 1 | H8: Bois, chêne, frêne, ébène, if (armes de bois, bâtons, arcs).
A9: Champs | B9: village/champs.png | C9: Production | D9: 0 | E9: 25 | F9: 500 | G9: 1 | H9: Lin, laine, soie, velours enchanté, étoffe astrale (tissus du Mage).
A10: Terrain de chasse | B10: village/terrain_de_chasse.png | C10: Production | D10: 0 | E10: 20 | F10: 500 | G10: 1 | H10: Cuir, cuir clouté, écailles, peau et os de dragon (Guerrier palier 1, Tireur).
A11: Mine | B11: village/mine.png | C11: Production | D11: 15 | E11: 20 | F11: 600 | G11: 1 | H11: Charbon et métaux : fer, acier, mithril, adamantite, gemmes et métaux précieux (bijoux, orbes).
A12: Atelier de fabrication | B12: village/atelier_fabrication.png | C12: Artisanat | D12: 15 | E12: 5 | F12: 10000 | G12: 4 | H12: Forge : fabrication d’équipement Commun +0 et amélioration des objets. Niveau 1 : paliers 1 et 2 ; chaque niveau suivant ouvre un palier (voir Améliorations).
A13: Tour d'alchimie | B13: village/tour_alchimie.png | C13: Magie | D13: 85 | E13: 5 | F13: 50000 | G13: 6 | H13: Fusion de deux éléments sur une compétence, infusion d'élément ; produit l'éther.
A14: Tour d'amélioration | B14: village/tour_amelioration.png | C14: Bonus | D14: 100 | E14: 20 | F14: — | G14: — | H14: Bonus permanents en % (dégâts, PV, défense, production, durée hors ligne, or et XP) : voir son onglet.
A15: Tour | B15: village/tour.png | C15: Accès | D15: 0 | E15: — | F15: — | G15: — | H15: Entrée de la tour (étages, boss, dragons) et des zones de chasse débloquées. Pas d'amélioration.
A17: Ressources vendues seulement à la taverne : toile, verre, cuivre (palier 1). Héritage : le village (niveaux, stocks, déblocages) est conservé ; les bâtiments débloqués par un étage restent débloqués même si la tour est réinitialisée.

Sheet Production
A1: Production par heure, niveau par niveau
A2: Chaque ressource démarre à sa production de base au niveau qui la débloque, puis +12 % par niveau. Cases vides = pas encore débloquée ou au-delà du niveau max.
A5: Bâtiment | B5: Ressource | C5: Palier | D5: Niveau du bâtiment requis | E5: Étage requis | F5: Image | G5: Production de base (/h) | H5: Niv. 1 | I5: Niv. 2 | J5: Niv. 3 | K5: Niv. 4 | L5: Niv. 5 | M5: Niv. 6 | N5: Niv. 7 | O5: Niv. 8 | P5: Niv. 9 | Q5: Niv. 10 | R5: Niv. 11 | S5: Niv. 12 | T5: Niv. 13 | U5: Niv. 14 | V5: Niv. 15 | W5: Niv. 16 | X5: Niv. 17 | Y5: Niv. 18 | Z5: Niv. 19 | AA5: Niv. 20 | AB5: Niv. 21 | AC5: Niv. 22 | AD5: Niv. 23 | AE5: Niv. 24 | AF5: Niv. 25 | AG5: Niveau max | AH5: Production au niveau max (/h) | AI5: Stock en 8 h au niveau max
A6: Scierie | B6: bois | C6: 1 | D6: 1 | E6: 0 | F6: ressources/bois.png | G6: =INDEX(Paramètres!$B$5:$B$9,$C6) -> 60 | H6: =IF(OR(1<$D6,1>INDEX(Bâtiments!$E$6:$E$15,MATCH($A6,Bâtiments!$A$6:$A$15,0))),"",ROUND($G6*(1+Paramètres!$B$10)^(1-$D6),0)) -> 60 | I6: =IF(OR(2<$D6,2>INDEX(Bâtiments!$E$6:$E$15,MATCH($A6,Bâtiments!$A$6:$A$15,0))),"",ROUND($G6*(1+Paramètres!$B$10)^(2-$D6),0)) -> 67 | J6: =IF(OR(3<$D6,3>INDEX(Bâtiments!$E$6:$E$15,MATCH($A6,Bâtiments!$A$6:$A$15,0))),"",ROUND($G6*(1+Paramètres!$B$10)^(3-$D6),0)) -> 75 | K6: =IF(OR(4<$D6,4>INDEX(Bâtiments!$E$6:$E$15,MATCH($A6,Bâtiments!$A$6:$A$15,0))),"",ROUND($G6*(1+Paramètres!$B$10)^(4-$D6),0)) -> 84 | L6: =IF(OR(5<$D6,5>INDEX(Bâtiments!$E$6:$E$15,MATCH($A6,Bâtiments!$A$6:$A$15,0))),"",ROUND($G6*(1+Paramètres!$B$10)^(5-$D6),0)) -> 94 | M6: =IF(OR(6<$D6,6>INDEX(Bâtiments!$E$6:$E$15,MATCH($A6,Bâtiments!$A$6:$A$15,0))),"",ROUND($G6*(1+Paramètres!$B$10)^(6-$D6),0)) -> 106 | N6: =IF(OR(7<$D6,7>INDEX(Bâtiments!$E$6:$E$15,MATCH($A6,Bâtiments!$A$6:$A$15,0))),"",ROUND($G6*(1+Paramètres!$B$10)^(7-$D6),0)) -> 118 | O6: =IF(OR(8<$D6,8>INDEX(Bâtiments!$E$6:$E$15,MATCH($A6,Bâtiments!$A$6:$A$15,0))),"",ROUND($G6*(1+Paramètres!$B$10)^(8-$D6),0)) -> 133 | P6: =IF(OR(9<$D6,9>INDEX(Bâtiments!$E$6:$E$15,MATCH($A6,Bâtiments!$A$6:$A$15,0))),"",ROUND($G6*(1+Paramètres!$B$10)^(9-$D6),0)) -> 149 | Q6: =IF(OR(10<$D6,10>INDEX(Bâtiments!$E$6:$E$15,MATCH($A6,Bâtiments!$A$6:$A$15,0))),"",ROUND($G6*(1+Paramètres!$B$10)^(10-$D6),0)) -> 166 | R6: =IF(OR(11<$D6,11>INDEX(Bâtiments!$E$6:$E$15,MATCH($A6,Bâtiments!$A$6:$A$15,0))),"",ROUND($G6*(1+Paramètres!$B$10)^(11-$D6),0)) -> 186 | S6: =IF(OR(12<$D6,12>INDEX(Bâtiments!$E$6:$E$15,MATCH($A6,Bâtiments!$A$6:$A$15,0))),"",ROUND($G6*(1+Paramètres!$B$10)^(12-$D6),0)) -> 209 | T6: =IF(OR(13<$D6,13>INDEX(Bâtiments!$E$6:$E$15,MATCH($A6,Bâtiments!$A$6:$A$15,0))),"",ROUND($G6*(1+Paramètres!$B$10)^(13-$D6),0)) -> 234 | U6: =IF(OR(14<$D6,14>INDEX(Bâtiments!$E$6:$E$15,MATCH($A6,Bâtiments!$A$6:$A$15,0))),"",ROUND($G6*(1+Paramètres!$B$10)^(14-$D6),0)) -> 262 | V6: =IF(OR(15<$D6,15>INDEX(Bâtiments!$E$6:$E$15,MATCH($A6,Bâtiments!$A$6:$A$15,0))),"",ROUND($G6*(1+Paramètres!$B$10)^(15-$D6),0)) -> 293 | W6: =IF(OR(16<$D6,16>INDEX(Bâtiments!$E$6:$E$15,MATCH($A6,Bâtiments!$A$6:$A$15,0))),"",ROUND($G6*(1+Paramètres!$B$10)^(16-$D6),0)) | X6: =IF(OR(17<$D6,17>INDEX(Bâtiments!$E$6:$E$15,MATCH($A6,Bâtiments!$A$6:$A$15,0))),"",ROUND($G6*(1+Paramètres!$B$10)^(17-$D6),0)) | Y6: =IF(OR(18<$D6,18>INDEX(Bâtiments!$E$6:$E$15,MATCH($A6,Bâtiments!$A$6:$A$15,0))),"",ROUND($G6*(1+Paramètres!$B$10)^(18-$D6),0)) | Z6: =IF(OR(19<$D6,19>INDEX(Bâtiments!$E$6:$E$15,MATCH($A6,Bâtiments!$A$6:$A$15,0))),"",ROUND($G6*(1+Paramètres!$B$10)^(19-$D6),0)) | AA6: =IF(OR(20<$D6,20>INDEX(Bâtiments!$E$6:$E$15,MATCH($A6,Bâtiments!$A$6:$A$15,0))),"",ROUND($G6*(1+Paramètres!$B$10)^(20-$D6),0)) | AB6: =IF(OR(21<$D6,21>INDEX(Bâtiments!$E$6:$E$15,MATCH($A6,Bâtiments!$A$6:$A$15,0))),"",ROUND($G6*(1+Paramètres!$B$10)^(21-$D6),0)) | AC6: =IF(OR(22<$D6,22>INDEX(Bâtiments!$E$6:$E$15,MATCH($A6,Bâtiments!$A$6:$A$15,0))),"",ROUND($G6*(1+Paramètres!$B$10)^(22-$D6),0)) | AD6: =IF(OR(23<$D6,23>INDEX(Bâtiments!$E$6:$E$15,MATCH($A6,Bâtiments!$A$6:$A$15,0))),"",ROUND($G6*(1+Paramètres!$B$10)^(23-$D6),0)) | AE6: =IF(OR(24<$D6,24>INDEX(Bâtiments!$E$6:$E$15,MATCH($A6,Bâtiments!$A$6:$A$15,0))),"",ROUND($G6*(1+Paramètres!$B$10)^(24-$D6),0)) | AF6: =IF(OR(25<$D6,25>INDEX(Bâtiments!$E$6:$E$15,MATCH($A6,Bâtiments!$A$6:$A$15,0))),"",ROUND($G6*(1+Paramètres!$B$10)^(25-$D6),0)) | AG6: =INDEX(Bâtiments!$E$6:$E$15,MATCH($A6,Bâtiments!$A$6:$A$15,0)) -> 15 | AH6: =ROUND($G6*(1+Paramètres!$B$10)^(AG6-$D6),0) -> 293 | AI6: =AH6*Paramètres!$B$11 -> 2344
A7: Scierie | B7: chêne | C7: 2 | D7: 6 | E7: 15 | F7: ressources/chene.png | G7: =INDEX(Paramètres!$B$5:$B$9,$C7) -> 90 | H7: =IF(OR(1<$D7,1>INDEX(Bâtiments!$E$6:$E$15,MATCH($A7,Bâtiments!$A$6:$A$15,0))),"",ROUND($G7*(1+Paramètres!$B$10)^(1-$D7),0)) | I7: =IF(OR(2<$D7,2>INDEX(Bâtiments!$E$6:$E$15,MATCH($A7,Bâtiments!$A$6:$A$15,0))),"",ROUND($G7*(1+Paramètres!$B$10)^(2-$D7),0)) | J7: =IF(OR(3<$D7,3>INDEX(Bâtiments!$E$6:$E$15,MATCH($A7,Bâtiments!$A$6:$A$15,0))),"",ROUND($G7*(1+Paramètres!$B$10)^(3-$D7),0)) | K7: =IF(OR(4<$D7,4>INDEX(Bâtiments!$E$6:$E$15,MATCH($A7,Bâtiments!$A$6:$A$15,0))),"",ROUND($G7*(1+Paramètres!$B$10)^(4-$D7),0)) | L7: =IF(OR(5<$D7,5>INDEX(Bâtiments!$E$6:$E$15,MATCH($A7,Bâtiments!$A$6:$A$15,0))),"",ROUND($G7*(1+Paramètres!$B$10)^(5-$D7),0)) | M7: =IF(OR(6<$D7,6>INDEX(Bâtiments!$E$6:$E$15,MATCH($A7,Bâtiments!$A$6:$A$15,0))),"",ROUND($G7*(1+Paramètres!$B$10)^(6-$D7),0)) -> 90 | N7: =IF(OR(7<$D7,7>INDEX(Bâtiments!$E$6:$E$15,MATCH($A7,Bâtiments!$A$6:$A$15,0))),"",ROUND($G7*(1+Paramètres!$B$10)^(7-$D7),0)) -> 101 | O7: =IF(OR(8<$D7,8>INDEX(Bâtiments!$E$6:$E$15,MATCH($A7,Bâtiments!$A$6:$A$15,0))),"",ROUND($G7*(1+Paramètres!$B$10)^(8-$D7),0)) -> 113 | P7: =IF(OR(9<$D7,9>INDEX(Bâtiments!$E$6:$E$15,MATCH($A7,Bâtiments!$A$6:$A$15,0))),"",ROUND($G7*(1+Paramètres!$B$10)^(9-$D7),0)) -> 126 | Q7: =IF(OR(10<$D7,10>INDEX(Bâtiments!$E$6:$E$15,MATCH($A7,Bâtiments!$A$6:$A$15,0))),"",ROUND($G7*(1+Paramètres!$B$10)^(10-$D7),0)) -> 142 | R7: =IF(OR(11<$D7,11>INDEX(Bâtiments!$E$6:$E$15,MATCH($A7,Bâtiments!$A$6:$A$15,0))),"",ROUND($G7*(1+Paramètres!$B$10)^(11-$D7),0)) -> 159 | S7: =IF(OR(12<$D7,12>INDEX(Bâtiments!$E$6:$E$15,MATCH($A7,Bâtiments!$A$6:$A$15,0))),"",ROUND($G7*(1+Paramètres!$B$10)^(12-$D7),0)) -> 178 | T7: =IF(OR(13<$D7,13>INDEX(Bâtiments!$E$6:$E$15,MATCH($A7,Bâtiments!$A$6:$A$15,0))),"",ROUND($G7*(1+Paramètres!$B$10)^(13-$D7),0)) -> 199 | U7: =IF(OR(14<$D7,14>INDEX(Bâtiments!$E$6:$E$15,MATCH($A7,Bâtiments!$A$6:$A$15,0))),"",ROUND($G7*(1+Paramètres!$B$10)^(14-$D7),0)) -> 223 | V7: =IF(OR(15<$D7,15>INDEX(Bâtiments!$E$6:$E$15,MATCH($A7,Bâtiments!$A$6:$A$15,0))),"",ROUND($G7*(1+Paramètres!$B$10)^(15-$D7),0)) -> 250 | W7: =IF(OR(16<$D7,16>INDEX(Bâtiments!$E$6:$E$15,MATCH($A7,Bâtiments!$A$6:$A$15,0))),"",ROUND($G7*(1+Paramètres!$B$10)^(16-$D7),0)) | X7: =IF(OR(17<$D7,17>INDEX(Bâtiments!$E$6:$E$15,MATCH($A7,Bâtiments!$A$6:$A$15,0))),"",ROUND($G7*(1+Paramètres!$B$10)^(17-$D7),0)) | Y7: =IF(OR(18<$D7,18>INDEX(Bâtiments!$E$6:$E$15,MATCH($A7,Bâtiments!$A$6:$A$15,0))),"",ROUND($G7*(1+Paramètres!$B$10)^(18-$D7),0)) | Z7: =IF(OR(19<$D7,19>INDEX(Bâtiments!$E$6:$E$15,MATCH($A7,Bâtiments!$A$6:$A$15,0))),"",ROUND($G7*(1+Paramètres!$B$10)^(19-$D7),0)) | AA7: =IF(OR(20<$D7,20>INDEX(Bâtiments!$E$6:$E$15,MATCH($A7,Bâtiments!$A$6:$A$15,0))),"",ROUND($G7*(1+Paramètres!$B$10)^(20-$D7),0)) | AB7: =IF(OR(21<$D7,21>INDEX(Bâtiments!$E$6:$E$15,MATCH($A7,Bâtiments!$A$6:$A$15,0))),"",ROUND($G7*(1+Paramètres!$B$10)^(21-$D7),0)) | AC7: =IF(OR(22<$D7,22>INDEX(Bâtiments!$E$6:$E$15,MATCH($A7,Bâtiments!$A$6:$A$15,0))),"",ROUND($G7*(1+Paramètres!$B$10)^(22-$D7),0)) | AD7: =IF(OR(23<$D7,23>INDEX(Bâtiments!$E$6:$E$15,MATCH($A7,Bâtiments!$A$6:$A$15,0))),"",ROUND($G7*(1+Paramètres!$B$10)^(23-$D7),0)) | AE7: =IF(OR(24<$D7,24>INDEX(Bâtiments!$E$6:$E$15,MATCH($A7,Bâtiments!$A$6:$A$15,0))),"",ROUND($G7*(1+Paramètres!$B$10)^(24-$D7),0)) | AF7: =IF(OR(25<$D7,25>INDEX(Bâtiments!$E$6:$E$15,MATCH($A7,Bâtiments!$A$6:$A$15,0))),"",ROUND($G7*(1+Paramètres!$B$10)^(25-$D7),0)) | AG7: =INDEX(Bâtiments!$E$6:$E$15,MATCH($A7,Bâtiments!$A$6:$A$15,0)) -> 15 | AH7: =ROUND($G7*(1+Paramètres!$B$10)^(AG7-$D7),0) -> 250 | AI7: =AH7*Paramètres!$B$11 -> 2000
A8: Scierie | B8: frêne | C8: 2 | D8: 6 | E8: 15 | F8: ressources/frene.png | G8: =INDEX(Paramètres!$B$5:$B$9,$C8) -> 90 | H8: =IF(OR(1<$D8,1>INDEX(Bâtiments!$E$6:$E$15,MATCH($A8,Bâtiments!$A$6:$A$15,0))),"",ROUND($G8*(1+Paramètres!$B$10)^(1-$D8),0)) | I8: =IF(OR(2<$D8,2>INDEX(Bâtiments!$E$6:$E$15,MATCH($A8,Bâtiments!$A$6:$A$15,0))),"",ROUND($G8*(1+Paramètres!$B$10)^(2-$D8),0)) | J8: =IF(OR(3<$D8,3>INDEX(Bâtiments!$E$6:$E$15,MATCH($A8,Bâtiments!$A$6:$A$15,0))),"",ROUND($G8*(1+Paramètres!$B$10)^(3-$D8),0)) | K8: =IF(OR(4<$D8,4>INDEX(Bâtiments!$E$6:$E$15,MATCH($A8,Bâtiments!$A$6:$A$15,0))),"",ROUND($G8*(1+Paramètres!$B$10)^(4-$D8),0)) | L8: =IF(OR(5<$D8,5>INDEX(Bâtiments!$E$6:$E$15,MATCH($A8,Bâtiments!$A$6:$A$15,0))),"",ROUND($G8*(1+Paramètres!$B$10)^(5-$D8),0)) | M8: =IF(OR(6<$D8,6>INDEX(Bâtiments!$E$6:$E$15,MATCH($A8,Bâtiments!$A$6:$A$15,0))),"",ROUND($G8*(1+Paramètres!$B$10)^(6-$D8),0)) -> 90 | N8: =IF(OR(7<$D8,7>INDEX(Bâtiments!$E$6:$E$15,MATCH($A8,Bâtiments!$A$6:$A$15,0))),"",ROUND($G8*(1+Paramètres!$B$10)^(7-$D8),0)) -> 101 | O8: =IF(OR(8<$D8,8>INDEX(Bâtiments!$E$6:$E$15,MATCH($A8,Bâtiments!$A$6:$A$15,0))),"",ROUND($G8*(1+Paramètres!$B$10)^(8-$D8),0)) -> 113 | P8: =IF(OR(9<$D8,9>INDEX(Bâtiments!$E$6:$E$15,MATCH($A8,Bâtiments!$A$6:$A$15,0))),"",ROUND($G8*(1+Paramètres!$B$10)^(9-$D8),0)) -> 126 | Q8: =IF(OR(10<$D8,10>INDEX(Bâtiments!$E$6:$E$15,MATCH($A8,Bâtiments!$A$6:$A$15,0))),"",ROUND($G8*(1+Paramètres!$B$10)^(10-$D8),0)) -> 142 | R8: =IF(OR(11<$D8,11>INDEX(Bâtiments!$E$6:$E$15,MATCH($A8,Bâtiments!$A$6:$A$15,0))),"",ROUND($G8*(1+Paramètres!$B$10)^(11-$D8),0)) -> 159 | S8: =IF(OR(12<$D8,12>INDEX(Bâtiments!$E$6:$E$15,MATCH($A8,Bâtiments!$A$6:$A$15,0))),"",ROUND($G8*(1+Paramètres!$B$10)^(12-$D8),0)) -> 178 | T8: =IF(OR(13<$D8,13>INDEX(Bâtiments!$E$6:$E$15,MATCH($A8,Bâtiments!$A$6:$A$15,0))),"",ROUND($G8*(1+Paramètres!$B$10)^(13-$D8),0)) -> 199 | U8: =IF(OR(14<$D8,14>INDEX(Bâtiments!$E$6:$E$15,MATCH($A8,Bâtiments!$A$6:$A$15,0))),"",ROUND($G8*(1+Paramètres!$B$10)^(14-$D8),0)) -> 223 | V8: =IF(OR(15<$D8,15>INDEX(Bâtiments!$E$6:$E$15,MATCH($A8,Bâtiments!$A$6:$A$15,0))),"",ROUND($G8*(1+Paramètres!$B$10)^(15-$D8),0)) -> 250 | W8: =IF(OR(16<$D8,16>INDEX(Bâtiments!$E$6:$E$15,MATCH($A8,Bâtiments!$A$6:$A$15,0))),"",ROUND($G8*(1+Paramètres!$B$10)^(16-$D8),0)) | X8: =IF(OR(17<$D8,17>INDEX(Bâtiments!$E$6:$E$15,MATCH($A8,Bâtiments!$A$6:$A$15,0))),"",ROUND($G8*(1+Paramètres!$B$10)^(17-$D8),0)) | Y8: =IF(OR(18<$D8,18>INDEX(Bâtiments!$E$6:$E$15,MATCH($A8,Bâtiments!$A$6:$A$15,0))),"",ROUND($G8*(1+Paramètres!$B$10)^(18-$D8),0)) | Z8: =IF(OR(19<$D8,19>INDEX(Bâtiments!$E$6:$E$15,MATCH($A8,Bâtiments!$A$6:$A$15,0))),"",ROUND($G8*(1+Paramètres!$B$10)^(19-$D8),0)) | AA8: =IF(OR(20<$D8,20>INDEX(Bâtiments!$E$6:$E$15,MATCH($A8,Bâtiments!$A$6:$A$15,0))),"",ROUND($G8*(1+Paramètres!$B$10)^(20-$D8),0)) | AB8: =IF(OR(21<$D8,21>INDEX(Bâtiments!$E$6:$E$15,MATCH($A8,Bâtiments!$A$6:$A$15,0))),"",ROUND($G8*(1+Paramètres!$B$10)^(21-$D8),0)) | AC8: =IF(OR(22<$D8,22>INDEX(Bâtiments!$E$6:$E$15,MATCH($A8,Bâtiments!$A$6:$A$15,0))),"",ROUND($G8*(1+Paramètres!$B$10)^(22-$D8),0)) | AD8: =IF(OR(23<$D8,23>INDEX(Bâtiments!$E$6:$E$15,MATCH($A8,Bâtiments!$A$6:$A$15,0))),"",ROUND($G8*(1+Paramètres!$B$10)^(23-$D8),0)) | AE8: =IF(OR(24<$D8,24>INDEX(Bâtiments!$E$6:$E$15,MATCH($A8,Bâtiments!$A$6:$A$15,0))),"",ROUND($G8*(1+Paramètres!$B$10)^(24-$D8),0)) | AF8: =IF(OR(25<$D8,25>INDEX(Bâtiments!$E$6:$E$15,MATCH($A8,Bâtiments!$A$6:$A$15,0))),"",ROUND($G8*(1+Paramètres!$B$10)^(25-$D8),0)) | AG8: =INDEX(Bâtiments!$E$6:$E$15,MATCH($A8,Bâtiments!$A$6:$A$15,0)) -> 15 | AH8: =ROUND($G8*(1+Paramètres!$B$10)^(AG8-$D8),0) -> 250 | AI8: =AH8*Paramètres!$B$11 -> 2000
A9: Scierie | B9: ébène | C9: 3 | D9: 11 | E9: 30 | F9: ressources/ebene.png | G9: =INDEX(Paramètres!$B$5:$B$9,$C9) -> 135 | H9: =IF(OR(1<$D9,1>INDEX(Bâtiments!$E$6:$E$15,MATCH($A9,Bâtiments!$A$6:$A$15,0))),"",ROUND($G9*(1+Paramètres!$B$10)^(1-$D9),0)) | I9: =IF(OR(2<$D9,2>INDEX(Bâtiments!$E$6:$E$15,MATCH($A9,Bâtiments!$A$6:$A$15,0))),"",ROUND($G9*(1+Paramètres!$B$10)^(2-$D9),0)) | J9: =IF(OR(3<$D9,3>INDEX(Bâtiments!$E$6:$E$15,MATCH($A9,Bâtiments!$A$6:$A$15,0))),"",ROUND($G9*(1+Paramètres!$B$10)^(3-$D9),0)) | K9: =IF(OR(4<$D9,4>INDEX(Bâtiments!$E$6:$E$15,MATCH($A9,Bâtiments!$A$6:$A$15,0))),"",ROUND($G9*(1+Paramètres!$B$10)^(4-$D9),0)) | L9: =IF(OR(5<$D9,5>INDEX(Bâtiments!$E$6:$E$15,MATCH($A9,Bâtiments!$A$6:$A$15,0))),"",ROUND($G9*(1+Paramètres!$B$10)^(5-$D9),0)) | M9: =IF(OR(6<$D9,6>INDEX(Bâtiments!$E$6:$E$15,MATCH($A9,Bâtiments!$A$6:$A$15,0))),"",ROUND($G9*(1+Paramètres!$B$10)^(6-$D9),0)) | N9: =IF(OR(7<$D9,7>INDEX(Bâtiments!$E$6:$E$15,MATCH($A9,Bâtiments!$A$6:$A$15,0))),"",ROUND($G9*(1+Paramètres!$B$10)^(7-$D9),0)) | O9: =IF(OR(8<$D9,8>INDEX(Bâtiments!$E$6:$E$15,MATCH($A9,Bâtiments!$A$6:$A$15,0))),"",ROUND($G9*(1+Paramètres!$B$10)^(8-$D9),0)) | P9: =IF(OR(9<$D9,9>INDEX(Bâtiments!$E$6:$E$15,MATCH($A9,Bâtiments!$A$6:$A$15,0))),"",ROUND($G9*(1+Paramètres!$B$10)^(9-$D9),0)) | Q9: =IF(OR(10<$D9,10>INDEX(Bâtiments!$E$6:$E$15,MATCH($A9,Bâtiments!$A$6:$A$15,0))),"",ROUND($G9*(1+Paramètres!$B$10)^(10-$D9),0)) | R9: =IF(OR(11<$D9,11>INDEX(Bâtiments!$E$6:$E$15,MATCH($A9,Bâtiments!$A$6:$A$15,0))),"",ROUND($G9*(1+Paramètres!$B$10)^(11-$D9),0)) -> 135 | S9: =IF(OR(12<$D9,12>INDEX(Bâtiments!$E$6:$E$15,MATCH($A9,Bâtiments!$A$6:$A$15,0))),"",ROUND($G9*(1+Paramètres!$B$10)^(12-$D9),0)) -> 151 | T9: =IF(OR(13<$D9,13>INDEX(Bâtiments!$E$6:$E$15,MATCH($A9,Bâtiments!$A$6:$A$15,0))),"",ROUND($G9*(1+Paramètres!$B$10)^(13-$D9),0)) -> 169 | U9: =IF(OR(14<$D9,14>INDEX(Bâtiments!$E$6:$E$15,MATCH($A9,Bâtiments!$A$6:$A$15,0))),"",ROUND($G9*(1+Paramètres!$B$10)^(14-$D9),0)) -> 190 | V9: =IF(OR(15<$D9,15>INDEX(Bâtiments!$E$6:$E$15,MATCH($A9,Bâtiments!$A$6:$A$15,0))),"",ROUND($G9*(1+Paramètres!$B$10)^(15-$D9),0)) -> 212 | W9: =IF(OR(16<$D9,16>INDEX(Bâtiments!$E$6:$E$15,MATCH($A9,Bâtiments!$A$6:$A$15,0))),"",ROUND($G9*(1+Paramètres!$B$10)^(16-$D9),0)) | X9: =IF(OR(17<$D9,17>INDEX(Bâtiments!$E$6:$E$15,MATCH($A9,Bâtiments!$A$6:$A$15,0))),"",ROUND($G9*(1+Paramètres!$B$10)^(17-$D9),0)) | Y9: =IF(OR(18<$D9,18>INDEX(Bâtiments!$E$6:$E$15,MATCH($A9,Bâtiments!$A$6:$A$15,0))),"",ROUND($G9*(1+Paramètres!$B$10)^(18-$D9),0)) | Z9: =IF(OR(19<$D9,19>INDEX(Bâtiments!$E$6:$E$15,MATCH($A9,Bâtiments!$A$6:$A$15,0))),"",ROUND($G9*(1+Paramètres!$B$10)^(19-$D9),0)) | AA9: =IF(OR(20<$D9,20>INDEX(Bâtiments!$E$6:$E$15,MATCH($A9,Bâtiments!$A$6:$A$15,0))),"",ROUND($G9*(1+Paramètres!$B$10)^(20-$D9),0)) | AB9: =IF(OR(21<$D9,21>INDEX(Bâtiments!$E$6:$E$15,MATCH($A9,Bâtiments!$A$6:$A$15,0))),"",ROUND($G9*(1+Paramètres!$B$10)^(21-$D9),0)) | AC9: =IF(OR(22<$D9,22>INDEX(Bâtiments!$E$6:$E$15,MATCH($A9,Bâtiments!$A$6:$A$15,0))),"",ROUND($G9*(1+Paramètres!$B$10)^(22-$D9),0)) | AD9: =IF(OR(23<$D9,23>INDEX(Bâtiments!$E$6:$E$15,MATCH($A9,Bâtiments!$A$6:$A$15,0))),"",ROUND($G9*(1+Paramètres!$B$10)^(23-$D9),0)) | AE9: =IF(OR(24<$D9,24>INDEX(Bâtiments!$E$6:$E$15,MATCH($A9,Bâtiments!$A$6:$A$15,0))),"",ROUND($G9*(1+Paramètres!$B$10)^(24-$D9),0)) | AF9: =IF(OR(25<$D9,25>INDEX(Bâtiments!$E$6:$E$15,MATCH($A9,Bâtiments!$A$6:$A$15,0))),"",ROUND($G9*(1+Paramètres!$B$10)^(25-$D9),0)) | AG9: =INDEX(Bâtiments!$E$6:$E$15,MATCH($A9,Bâtiments!$A$6:$A$15,0)) -> 15 | AH9: =ROUND($G9*(1+Paramètres!$B$10)^(AG9-$D9),0) -> 212 | AI9: =AH9*Paramètres!$B$11 -> 1696
A10: Scierie | B10: if | C10: 3 | D10: 11 | E10: 30 | F10: ressources/if.png | G10: =INDEX(Paramètres!$B$5:$B$9,$C10) -> 135 | H10: =IF(OR(1<$D10,1>INDEX(Bâtiments!$E$6:$E$15,MATCH($A10,Bâtiments!$A$6:$A$15,0))),"",ROUND($G10*(1+Paramètres!$B$10)^(1-$D10),0)) | I10: =IF(OR(2<$D10,2>INDEX(Bâtiments!$E$6:$E$15,MATCH($A10,Bâtiments!$A$6:$A$15,0))),"",ROUND($G10*(1+Paramètres!$B$10)^(2-$D10),0)) | J10: =IF(OR(3<$D10,3>INDEX(Bâtiments!$E$6:$E$15,MATCH($A10,Bâtiments!$A$6:$A$15,0))),"",ROUND($G10*(1+Paramètres!$B$10)^(3-$D10),0)) | K10: =IF(OR(4<$D10,4>INDEX(Bâtiments!$E$6:$E$15,MATCH($A10,Bâtiments!$A$6:$A$15,0))),"",ROUND($G10*(1+Paramètres!$B$10)^(4-$D10),0)) | L10: =IF(OR(5<$D10,5>INDEX(Bâtiments!$E$6:$E$15,MATCH($A10,Bâtiments!$A$6:$A$15,0))),"",ROUND($G10*(1+Paramètres!$B$10)^(5-$D10),0)) | M10: =IF(OR(6<$D10,6>INDEX(Bâtiments!$E$6:$E$15,MATCH($A10,Bâtiments!$A$6:$A$15,0))),"",ROUND($G10*(1+Paramètres!$B$10)^(6-$D10),0)) | N10: =IF(OR(7<$D10,7>INDEX(Bâtiments!$E$6:$E$15,MATCH($A10,Bâtiments!$A$6:$A$15,0))),"",ROUND($G10*(1+Paramètres!$B$10)^(7-$D10),0)) | O10: =IF(OR(8<$D10,8>INDEX(Bâtiments!$E$6:$E$15,MATCH($A10,Bâtiments!$A$6:$A$15,0))),"",ROUND($G10*(1+Paramètres!$B$10)^(8-$D10),0)) | P10: =IF(OR(9<$D10,9>INDEX(Bâtiments!$E$6:$E$15,MATCH($A10,Bâtiments!$A$6:$A$15,0))),"",ROUND($G10*(1+Paramètres!$B$10)^(9-$D10),0)) | Q10: =IF(OR(10<$D10,10>INDEX(Bâtiments!$E$6:$E$15,MATCH($A10,Bâtiments!$A$6:$A$15,0))),"",ROUND($G10*(1+Paramètres!$B$10)^(10-$D10),0)) | R10: =IF(OR(11<$D10,11>INDEX(Bâtiments!$E$6:$E$15,MATCH($A10,Bâtiments!$A$6:$A$15,0))),"",ROUND($G10*(1+Paramètres!$B$10)^(11-$D10),0)) -> 135 | S10: =IF(OR(12<$D10,12>INDEX(Bâtiments!$E$6:$E$15,MATCH($A10,Bâtiments!$A$6:$A$15,0))),"",ROUND($G10*(1+Paramètres!$B$10)^(12-$D10),0)) -> 151 | T10: =IF(OR(13<$D10,13>INDEX(Bâtiments!$E$6:$E$15,MATCH($A10,Bâtiments!$A$6:$A$15,0))),"",ROUND($G10*(1+Paramètres!$B$10)^(13-$D10),0)) -> 169 | U10: =IF(OR(14<$D10,14>INDEX(Bâtiments!$E$6:$E$15,MATCH($A10,Bâtiments!$A$6:$A$15,0))),"",ROUND($G10*(1+Paramètres!$B$10)^(14-$D10),0)) -> 190 | V10: =IF(OR(15<$D10,15>INDEX(Bâtiments!$E$6:$E$15,MATCH($A10,Bâtiments!$A$6:$A$15,0))),"",ROUND($G10*(1+Paramètres!$B$10)^(15-$D10),0)) -> 212 | W10: =IF(OR(16<$D10,16>INDEX(Bâtiments!$E$6:$E$15,MATCH($A10,Bâtiments!$A$6:$A$15,0))),"",ROUND($G10*(1+Paramètres!$B$10)^(16-$D10),0)) | X10: =IF(OR(17<$D10,17>INDEX(Bâtiments!$E$6:$E$15,MATCH($A10,Bâtiments!$A$6:$A$15,0))),"",ROUND($G10*(1+Paramètres!$B$10)^(17-$D10),0)) | Y10: =IF(OR(18<$D10,18>INDEX(Bâtiments!$E$6:$E$15,MATCH($A10,Bâtiments!$A$6:$A$15,0))),"",ROUND($G10*(1+Paramètres!$B$10)^(18-$D10),0)) | Z10: =IF(OR(19<$D10,19>INDEX(Bâtiments!$E$6:$E$15,MATCH($A10,Bâtiments!$A$6:$A$15,0))),"",ROUND($G10*(1+Paramètres!$B$10)^(19-$D10),0)) | AA10: =IF(OR(20<$D10,20>INDEX(Bâtiments!$E$6:$E$15,MATCH($A10,Bâtiments!$A$6:$A$15,0))),"",ROUND($G10*(1+Paramètres!$B$10)^(20-$D10),0)) | AB10: =IF(OR(21<$D10,21>INDEX(Bâtiments!$E$6:$E$15,MATCH($A10,Bâtiments!$A$6:$A$15,0))),"",ROUND($G10*(1+Paramètres!$B$10)^(21-$D10),0)) | AC10: =IF(OR(22<$D10,22>INDEX(Bâtiments!$E$6:$E$15,MATCH($A10,Bâtiments!$A$6:$A$15,0))),"",ROUND($G10*(1+Paramètres!$B$10)^(22-$D10),0)) | AD10: =IF(OR(23<$D10,23>INDEX(Bâtiments!$E$6:$E$15,MATCH($A10,Bâtiments!$A$6:$A$15,0))),"",ROUND($G10*(1+Paramètres!$B$10)^(23-$D10),0)) | AE10: =IF(OR(24<$D10,24>INDEX(Bâtiments!$E$6:$E$15,MATCH($A10,Bâtiments!$A$6:$A$15,0))),"",ROUND($G10*(1+Paramètres!$B$10)^(24-$D10),0)) | AF10: =IF(OR(25<$D10,25>INDEX(Bâtiments!$E$6:$E$15,MATCH($A10,Bâtiments!$A$6:$A$15,0))),"",ROUND($G10*(1+Paramètres!$B$10)^(25-$D10),0)) | AG10: =INDEX(Bâtiments!$E$6:$E$15,MATCH($A10,Bâtiments!$A$6:$A$15,0)) -> 15 | AH10: =ROUND($G10*(1+Paramètres!$B$10)^(AG10-$D10),0) -> 212 | AI10: =AH10*Paramètres!$B$11 -> 1696
A11: Champs | B11: lin | C11: 1 | D11: 1 | E11: 0 | F11: ressources/lin.png | G11: =INDEX(Paramètres!$B$5:$B$9,$C11) -> 60 | H11: =IF(OR(1<$D11,1>INDEX(Bâtiments!$E$6:$E$15,MATCH($A11,Bâtiments!$A$6:$A$15,0))),"",ROUND($G11*(1+Paramètres!$B$10)^(1-$D11),0)) -> 60 | I11: =IF(OR(2<$D11,2>INDEX(Bâtiments!$E$6:$E$15,MATCH($A11,Bâtiments!$A$6:$A$15,0))),"",ROUND($G11*(1+Paramètres!$B$10)^(2-$D11),0)) -> 67 | J11: =IF(OR(3<$D11,3>INDEX(Bâtiments!$E$6:$E$15,MATCH($A11,Bâtiments!$A$6:$A$15,0))),"",ROUND($G11*(1+Paramètres!$B$10)^(3-$D11),0)) -> 75 | K11: =IF(OR(4<$D11,4>INDEX(Bâtiments!$E$6:$E$15,MATCH($A11,Bâtiments!$A$6:$A$15,0))),"",ROUND($G11*(1+Paramètres!$B$10)^(4-$D11),0)) -> 84 | L11: =IF(OR(5<$D11,5>INDEX(Bâtiments!$E$6:$E$15,MATCH($A11,Bâtiments!$A$6:$A$15,0))),"",ROUND($G11*(1+Paramètres!$B$10)^(5-$D11),0)) -> 94 | M11: =IF(OR(6<$D11,6>INDEX(Bâtiments!$E$6:$E$15,MATCH($A11,Bâtiments!$A$6:$A$15,0))),"",ROUND($G11*(1+Paramètres!$B$10)^(6-$D11),0)) -> 106 | N11: =IF(OR(7<$D11,7>INDEX(Bâtiments!$E$6:$E$15,MATCH($A11,Bâtiments!$A$6:$A$15,0))),"",ROUND($G11*(1+Paramètres!$B$10)^(7-$D11),0)) -> 118 | O11: =IF(OR(8<$D11,8>INDEX(Bâtiments!$E$6:$E$15,MATCH($A11,Bâtiments!$A$6:$A$15,0))),"",ROUND($G11*(1+Paramètres!$B$10)^(8-$D11),0)) -> 133 | P11: =IF(OR(9<$D11,9>INDEX(Bâtiments!$E$6:$E$15,MATCH($A11,Bâtiments!$A$6:$A$15,0))),"",ROUND($G11*(1+Paramètres!$B$10)^(9-$D11),0)) -> 149 | Q11: =IF(OR(10<$D11,10>INDEX(Bâtiments!$E$6:$E$15,MATCH($A11,Bâtiments!$A$6:$A$15,0))),"",ROUND($G11*(1+Paramètres!$B$10)^(10-$D11),0)) -> 166 | R11: =IF(OR(11<$D11,11>INDEX(Bâtiments!$E$6:$E$15,MATCH($A11,Bâtiments!$A$6:$A$15,0))),"",ROUND($G11*(1+Paramètres!$B$10)^(11-$D11),0)) -> 186 | S11: =IF(OR(12<$D11,12>INDEX(Bâtiments!$E$6:$E$15,MATCH($A11,Bâtiments!$A$6:$A$15,0))),"",ROUND($G11*(1+Paramètres!$B$10)^(12-$D11),0)) -> 209 | T11: =IF(OR(13<$D11,13>INDEX(Bâtiments!$E$6:$E$15,MATCH($A11,Bâtiments!$A$6:$A$15,0))),"",ROUND($G11*(1+Paramètres!$B$10)^(13-$D11),0)) -> 234 | U11: =IF(OR(14<$D11,14>INDEX(Bâtiments!$E$6:$E$15,MATCH($A11,Bâtiments!$A$6:$A$15,0))),"",ROUND($G11*(1+Paramètres!$B$10)^(14-$D11),0)) -> 262 | V11: =IF(OR(15<$D11,15>INDEX(Bâtiments!$E$6:$E$15,MATCH($A11,Bâtiments!$A$6:$A$15,0))),"",ROUND($G11*(1+Paramètres!$B$10)^(15-$D11),0)) -> 293 | W11: =IF(OR(16<$D11,16>INDEX(Bâtiments!$E$6:$E$15,MATCH($A11,Bâtiments!$A$6:$A$15,0))),"",ROUND($G11*(1+Paramètres!$B$10)^(16-$D11),0)) -> 328 | X11: =IF(OR(17<$D11,17>INDEX(Bâtiments!$E$6:$E$15,MATCH($A11,Bâtiments!$A$6:$A$15,0))),"",ROUND($G11*(1+Paramètres!$B$10)^(17-$D11),0)) -> 368 | Y11: =IF(OR(18<$D11,18>INDEX(Bâtiments!$E$6:$E$15,MATCH($A11,Bâtiments!$A$6:$A$15,0))),"",ROUND($G11*(1+Paramètres!$B$10)^(18-$D11),0)) -> 412 | Z11: =IF(OR(19<$D11,19>INDEX(Bâtiments!$E$6:$E$15,MATCH($A11,Bâtiments!$A$6:$A$15,0))),"",ROUND($G11*(1+Paramètres!$B$10)^(19-$D11),0)) -> 461 | AA11: =IF(OR(20<$D11,20>INDEX(Bâtiments!$E$6:$E$15,MATCH($A11,Bâtiments!$A$6:$A$15,0))),"",ROUND($G11*(1+Paramètres!$B$10)^(20-$D11),0)) -> 517 | AB11: =IF(OR(21<$D11,21>INDEX(Bâtiments!$E$6:$E$15,MATCH($A11,Bâtiments!$A$6:$A$15,0))),"",ROUND($G11*(1+Paramètres!$B$10)^(21-$D11),0)) -> 579 | AC11: =IF(OR(22<$D11,22>INDEX(Bâtiments!$E$6:$E$15,MATCH($A11,Bâtiments!$A$6:$A$15,0))),"",ROUND($G11*(1+Paramètres!$B$10)^(22-$D11),0)) -> 648 | AD11: =IF(OR(23<$D11,23>INDEX(Bâtiments!$E$6:$E$15,MATCH($A11,Bâtiments!$A$6:$A$15,0))),"",ROUND($G11*(1+Paramètres!$B$10)^(23-$D11),0)) -> 726 | AE11: =IF(OR(24<$D11,24>INDEX(Bâtiments!$E$6:$E$15,MATCH($A11,Bâtiments!$A$6:$A$15,0))),"",ROUND($G11*(1+Paramètres!$B$10)^(24-$D11),0)) -> 813 | AF11: =IF(OR(25<$D11,25>INDEX(Bâtiments!$E$6:$E$15,MATCH($A11,Bâtiments!$A$6:$A$15,0))),"",ROUND($G11*(1+Paramètres!$B$10)^(25-$D11),0)) -> 911 | AG11: =INDEX(Bâtiments!$E$6:$E$15,MATCH($A11,Bâtiments!$A$6:$A$15,0)) -> 25 | AH11: =ROUND($G11*(1+Paramètres!$B$10)^(AG11-$D11),0) -> 911 | AI11: =AH11*Paramètres!$B$11 -> 7288
A12: Champs | B12: laine | C12: 2 | D12: 6 | E12: 15 | F12: ressources/laine.png | G12: =INDEX(Paramètres!$B$5:$B$9,$C12) -> 90 | H12: =IF(OR(1<$D12,1>INDEX(Bâtiments!$E$6:$E$15,MATCH($A12,Bâtiments!$A$6:$A$15,0))),"",ROUND($G12*(1+Paramètres!$B$10)^(1-$D12),0)) | I12: =IF(OR(2<$D12,2>INDEX(Bâtiments!$E$6:$E$15,MATCH($A12,Bâtiments!$A$6:$A$15,0))),"",ROUND($G12*(1+Paramètres!$B$10)^(2-$D12),0)) | J12: =IF(OR(3<$D12,3>INDEX(Bâtiments!$E$6:$E$15,MATCH($A12,Bâtiments!$A$6:$A$15,0))),"",ROUND($G12*(1+Paramètres!$B$10)^(3-$D12),0)) | K12: =IF(OR(4<$D12,4>INDEX(Bâtiments!$E$6:$E$15,MATCH($A12,Bâtiments!$A$6:$A$15,0))),"",ROUND($G12*(1+Paramètres!$B$10)^(4-$D12),0)) | L12: =IF(OR(5<$D12,5>INDEX(Bâtiments!$E$6:$E$15,MATCH($A12,Bâtiments!$A$6:$A$15,0))),"",ROUND($G12*(1+Paramètres!$B$10)^(5-$D12),0)) | M12: =IF(OR(6<$D12,6>INDEX(Bâtiments!$E$6:$E$15,MATCH($A12,Bâtiments!$A$6:$A$15,0))),"",ROUND($G12*(1+Paramètres!$B$10)^(6-$D12),0)) -> 90 | N12: =IF(OR(7<$D12,7>INDEX(Bâtiments!$E$6:$E$15,MATCH($A12,Bâtiments!$A$6:$A$15,0))),"",ROUND($G12*(1+Paramètres!$B$10)^(7-$D12),0)) -> 101 | O12: =IF(OR(8<$D12,8>INDEX(Bâtiments!$E$6:$E$15,MATCH($A12,Bâtiments!$A$6:$A$15,0))),"",ROUND($G12*(1+Paramètres!$B$10)^(8-$D12),0)) -> 113 | P12: =IF(OR(9<$D12,9>INDEX(Bâtiments!$E$6:$E$15,MATCH($A12,Bâtiments!$A$6:$A$15,0))),"",ROUND($G12*(1+Paramètres!$B$10)^(9-$D12),0)) -> 126 | Q12: =IF(OR(10<$D12,10>INDEX(Bâtiments!$E$6:$E$15,MATCH($A12,Bâtiments!$A$6:$A$15,0))),"",ROUND($G12*(1+Paramètres!$B$10)^(10-$D12),0)) -> 142 | R12: =IF(OR(11<$D12,11>INDEX(Bâtiments!$E$6:$E$15,MATCH($A12,Bâtiments!$A$6:$A$15,0))),"",ROUND($G12*(1+Paramètres!$B$10)^(11-$D12),0)) -> 159 | S12: =IF(OR(12<$D12,12>INDEX(Bâtiments!$E$6:$E$15,MATCH($A12,Bâtiments!$A$6:$A$15,0))),"",ROUND($G12*(1+Paramètres!$B$10)^(12-$D12),0)) -> 178 | T12: =IF(OR(13<$D12,13>INDEX(Bâtiments!$E$6:$E$15,MATCH($A12,Bâtiments!$A$6:$A$15,0))),"",ROUND($G12*(1+Paramètres!$B$10)^(13-$D12),0)) -> 199 | U12: =IF(OR(14<$D12,14>INDEX(Bâtiments!$E$6:$E$15,MATCH($A12,Bâtiments!$A$6:$A$15,0))),"",ROUND($G12*(1+Paramètres!$B$10)^(14-$D12),0)) -> 223 | V12: =IF(OR(15<$D12,15>INDEX(Bâtiments!$E$6:$E$15,MATCH($A12,Bâtiments!$A$6:$A$15,0))),"",ROUND($G12*(1+Paramètres!$B$10)^(15-$D12),0)) -> 250 | W12: =IF(OR(16<$D12,16>INDEX(Bâtiments!$E$6:$E$15,MATCH($A12,Bâtiments!$A$6:$A$15,0))),"",ROUND($G12*(1+Paramètres!$B$10)^(16-$D12),0)) -> 280 | X12: =IF(OR(17<$D12,17>INDEX(Bâtiments!$E$6:$E$15,MATCH($A12,Bâtiments!$A$6:$A$15,0))),"",ROUND($G12*(1+Paramètres!$B$10)^(17-$D12),0)) -> 313 | Y12: =IF(OR(18<$D12,18>INDEX(Bâtiments!$E$6:$E$15,MATCH($A12,Bâtiments!$A$6:$A$15,0))),"",ROUND($G12*(1+Paramètres!$B$10)^(18-$D12),0)) -> 351 | Z12: =IF(OR(19<$D12,19>INDEX(Bâtiments!$E$6:$E$15,MATCH($A12,Bâtiments!$A$6:$A$15,0))),"",ROUND($G12*(1+Paramètres!$B$10)^(19-$D12),0)) -> 393 | AA12: =IF(OR(20<$D12,20>INDEX(Bâtiments!$E$6:$E$15,MATCH($A12,Bâtiments!$A$6:$A$15,0))),"",ROUND($G12*(1+Paramètres!$B$10)^(20-$D12),0)) -> 440 | AB12: =IF(OR(21<$D12,21>INDEX(Bâtiments!$E$6:$E$15,MATCH($A12,Bâtiments!$A$6:$A$15,0))),"",ROUND($G12*(1+Paramètres!$B$10)^(21-$D12),0)) -> 493 | AC12: =IF(OR(22<$D12,22>INDEX(Bâtiments!$E$6:$E$15,MATCH($A12,Bâtiments!$A$6:$A$15,0))),"",ROUND($G12*(1+Paramètres!$B$10)^(22-$D12),0)) -> 552 | AD12: =IF(OR(23<$D12,23>INDEX(Bâtiments!$E$6:$E$15,MATCH($A12,Bâtiments!$A$6:$A$15,0))),"",ROUND($G12*(1+Paramètres!$B$10)^(23-$D12),0)) -> 618 | AE12: =IF(OR(24<$D12,24>INDEX(Bâtiments!$E$6:$E$15,MATCH($A12,Bâtiments!$A$6:$A$15,0))),"",ROUND($G12*(1+Paramètres!$B$10)^(24-$D12),0)) -> 692 | AF12: =IF(OR(25<$D12,25>INDEX(Bâtiments!$E$6:$E$15,MATCH($A12,Bâtiments!$A$6:$A$15,0))),"",ROUND($G12*(1+Paramètres!$B$10)^(25-$D12),0)) -> 775 | AG12: =INDEX(Bâtiments!$E$6:$E$15,MATCH($A12,Bâtiments!$A$6:$A$15,0)) -> 25 | AH12: =ROUND($G12*(1+Paramètres!$B$10)^(AG12-$D12),0) -> 775 | AI12: =AH12*Paramètres!$B$11 -> 6200
A13: Champs | B13: soie | C13: 3 | D13: 11 | E13: 30 | F13: ressources/soie.png | G13: =INDEX(Paramètres!$B$5:$B$9,$C13) -> 135 | H13: =IF(OR(1<$D13,1>INDEX(Bâtiments!$E$6:$E$15,MATCH($A13,Bâtiments!$A$6:$A$15,0))),"",ROUND($G13*(1+Paramètres!$B$10)^(1-$D13),0)) | I13: =IF(OR(2<$D13,2>INDEX(Bâtiments!$E$6:$E$15,MATCH($A13,Bâtiments!$A$6:$A$15,0))),"",ROUND($G13*(1+Paramètres!$B$10)^(2-$D13),0)) | J13: =IF(OR(3<$D13,3>INDEX(Bâtiments!$E$6:$E$15,MATCH($A13,Bâtiments!$A$6:$A$15,0))),"",ROUND($G13*(1+Paramètres!$B$10)^(3-$D13),0)) | K13: =IF(OR(4<$D13,4>INDEX(Bâtiments!$E$6:$E$15,MATCH($A13,Bâtiments!$A$6:$A$15,0))),"",ROUND($G13*(1+Paramètres!$B$10)^(4-$D13),0)) | L13: =IF(OR(5<$D13,5>INDEX(Bâtiments!$E$6:$E$15,MATCH($A13,Bâtiments!$A$6:$A$15,0))),"",ROUND($G13*(1+Paramètres!$B$10)^(5-$D13),0)) | M13: =IF(OR(6<$D13,6>INDEX(Bâtiments!$E$6:$E$15,MATCH($A13,Bâtiments!$A$6:$A$15,0))),"",ROUND($G13*(1+Paramètres!$B$10)^(6-$D13),0)) | N13: =IF(OR(7<$D13,7>INDEX(Bâtiments!$E$6:$E$15,MATCH($A13,Bâtiments!$A$6:$A$15,0))),"",ROUND($G13*(1+Paramètres!$B$10)^(7-$D13),0)) | O13: =IF(OR(8<$D13,8>INDEX(Bâtiments!$E$6:$E$15,MATCH($A13,Bâtiments!$A$6:$A$15,0))),"",ROUND($G13*(1+Paramètres!$B$10)^(8-$D13),0)) | P13: =IF(OR(9<$D13,9>INDEX(Bâtiments!$E$6:$E$15,MATCH($A13,Bâtiments!$A$6:$A$15,0))),"",ROUND($G13*(1+Paramètres!$B$10)^(9-$D13),0)) | Q13: =IF(OR(10<$D13,10>INDEX(Bâtiments!$E$6:$E$15,MATCH($A13,Bâtiments!$A$6:$A$15,0))),"",ROUND($G13*(1+Paramètres!$B$10)^(10-$D13),0)) | R13: =IF(OR(11<$D13,11>INDEX(Bâtiments!$E$6:$E$15,MATCH($A13,Bâtiments!$A$6:$A$15,0))),"",ROUND($G13*(1+Paramètres!$B$10)^(11-$D13),0)) -> 135 | S13: =IF(OR(12<$D13,12>INDEX(Bâtiments!$E$6:$E$15,MATCH($A13,Bâtiments!$A$6:$A$15,0))),"",ROUND($G13*(1+Paramètres!$B$10)^(12-$D13),0)) -> 151 | T13: =IF(OR(13<$D13,13>INDEX(Bâtiments!$E$6:$E$15,MATCH($A13,Bâtiments!$A$6:$A$15,0))),"",ROUND($G13*(1+Paramètres!$B$10)^(13-$D13),0)) -> 169 | U13: =IF(OR(14<$D13,14>INDEX(Bâtiments!$E$6:$E$15,MATCH($A13,Bâtiments!$A$6:$A$15,0))),"",ROUND($G13*(1+Paramètres!$B$10)^(14-$D13),0)) -> 190 | V13: =IF(OR(15<$D13,15>INDEX(Bâtiments!$E$6:$E$15,MATCH($A13,Bâtiments!$A$6:$A$15,0))),"",ROUND($G13*(1+Paramètres!$B$10)^(15-$D13),0)) -> 212 | W13: =IF(OR(16<$D13,16>INDEX(Bâtiments!$E$6:$E$15,MATCH($A13,Bâtiments!$A$6:$A$15,0))),"",ROUND($G13*(1+Paramètres!$B$10)^(16-$D13),0)) -> 238 | X13: =IF(OR(17<$D13,17>INDEX(Bâtiments!$E$6:$E$15,MATCH($A13,Bâtiments!$A$6:$A$15,0))),"",ROUND($G13*(1+Paramètres!$B$10)^(17-$D13),0)) -> 266 | Y13: =IF(OR(18<$D13,18>INDEX(Bâtiments!$E$6:$E$15,MATCH($A13,Bâtiments!$A$6:$A$15,0))),"",ROUND($G13*(1+Paramètres!$B$10)^(18-$D13),0)) -> 298 | Z13: =IF(OR(19<$D13,19>INDEX(Bâtiments!$E$6:$E$15,MATCH($A13,Bâtiments!$A$6:$A$15,0))),"",ROUND($G13*(1+Paramètres!$B$10)^(19-$D13),0)) -> 334 | AA13: =IF(OR(20<$D13,20>INDEX(Bâtiments!$E$6:$E$15,MATCH($A13,Bâtiments!$A$6:$A$15,0))),"",ROUND($G13*(1+Paramètres!$B$10)^(20-$D13),0)) -> 374 | AB13: =IF(OR(21<$D13,21>INDEX(Bâtiments!$E$6:$E$15,MATCH($A13,Bâtiments!$A$6:$A$15,0))),"",ROUND($G13*(1+Paramètres!$B$10)^(21-$D13),0)) -> 419 | AC13: =IF(OR(22<$D13,22>INDEX(Bâtiments!$E$6:$E$15,MATCH($A13,Bâtiments!$A$6:$A$15,0))),"",ROUND($G13*(1+Paramètres!$B$10)^(22-$D13),0)) -> 470 | AD13: =IF(OR(23<$D13,23>INDEX(Bâtiments!$E$6:$E$15,MATCH($A13,Bâtiments!$A$6:$A$15,0))),"",ROUND($G13*(1+Paramètres!$B$10)^(23-$D13),0)) -> 526 | AE13: =IF(OR(24<$D13,24>INDEX(Bâtiments!$E$6:$E$15,MATCH($A13,Bâtiments!$A$6:$A$15,0))),"",ROUND($G13*(1+Paramètres!$B$10)^(24-$D13),0)) -> 589 | AF13: =IF(OR(25<$D13,25>INDEX(Bâtiments!$E$6:$E$15,MATCH($A13,Bâtiments!$A$6:$A$15,0))),"",ROUND($G13*(1+Paramètres!$B$10)^(25-$D13),0)) -> 660 | AG13: =INDEX(Bâtiments!$E$6:$E$15,MATCH($A13,Bâtiments!$A$6:$A$15,0)) -> 25 | AH13: =ROUND($G13*(1+Paramètres!$B$10)^(AG13-$D13),0) -> 660 | AI13: =AH13*Paramètres!$B$11 -> 5280
A14: Champs | B14: velours enchanté | C14: 4 | D14: 16 | E14: 50 | F14: ressources/velours_enchante.png | G14: =INDEX(Paramètres!$B$5:$B$9,$C14) -> 200 | H14: =IF(OR(1<$D14,1>INDEX(Bâtiments!$E$6:$E$15,MATCH($A14,Bâtiments!$A$6:$A$15,0))),"",ROUND($G14*(1+Paramètres!$B$10)^(1-$D14),0)) | I14: =IF(OR(2<$D14,2>INDEX(Bâtiments!$E$6:$E$15,MATCH($A14,Bâtiments!$A$6:$A$15,0))),"",ROUND($G14*(1+Paramètres!$B$10)^(2-$D14),0)) | J14: =IF(OR(3<$D14,3>INDEX(Bâtiments!$E$6:$E$15,MATCH($A14,Bâtiments!$A$6:$A$15,0))),"",ROUND($G14*(1+Paramètres!$B$10)^(3-$D14),0)) | K14: =IF(OR(4<$D14,4>INDEX(Bâtiments!$E$6:$E$15,MATCH($A14,Bâtiments!$A$6:$A$15,0))),"",ROUND($G14*(1+Paramètres!$B$10)^(4-$D14),0)) | L14: =IF(OR(5<$D14,5>INDEX(Bâtiments!$E$6:$E$15,MATCH($A14,Bâtiments!$A$6:$A$15,0))),"",ROUND($G14*(1+Paramètres!$B$10)^(5-$D14),0)) | M14: =IF(OR(6<$D14,6>INDEX(Bâtiments!$E$6:$E$15,MATCH($A14,Bâtiments!$A$6:$A$15,0))),"",ROUND($G14*(1+Paramètres!$B$10)^(6-$D14),0)) | N14: =IF(OR(7<$D14,7>INDEX(Bâtiments!$E$6:$E$15,MATCH($A14,Bâtiments!$A$6:$A$15,0))),"",ROUND($G14*(1+Paramètres!$B$10)^(7-$D14),0)) | O14: =IF(OR(8<$D14,8>INDEX(Bâtiments!$E$6:$E$15,MATCH($A14,Bâtiments!$A$6:$A$15,0))),"",ROUND($G14*(1+Paramètres!$B$10)^(8-$D14),0)) | P14: =IF(OR(9<$D14,9>INDEX(Bâtiments!$E$6:$E$15,MATCH($A14,Bâtiments!$A$6:$A$15,0))),"",ROUND($G14*(1+Paramètres!$B$10)^(9-$D14),0)) | Q14: =IF(OR(10<$D14,10>INDEX(Bâtiments!$E$6:$E$15,MATCH($A14,Bâtiments!$A$6:$A$15,0))),"",ROUND($G14*(1+Paramètres!$B$10)^(10-$D14),0)) | R14: =IF(OR(11<$D14,11>INDEX(Bâtiments!$E$6:$E$15,MATCH($A14,Bâtiments!$A$6:$A$15,0))),"",ROUND($G14*(1+Paramètres!$B$10)^(11-$D14),0)) | S14: =IF(OR(12<$D14,12>INDEX(Bâtiments!$E$6:$E$15,MATCH($A14,Bâtiments!$A$6:$A$15,0))),"",ROUND($G14*(1+Paramètres!$B$10)^(12-$D14),0)) | T14: =IF(OR(13<$D14,13>INDEX(Bâtiments!$E$6:$E$15,MATCH($A14,Bâtiments!$A$6:$A$15,0))),"",ROUND($G14*(1+Paramètres!$B$10)^(13-$D14),0)) | U14: =IF(OR(14<$D14,14>INDEX(Bâtiments!$E$6:$E$15,MATCH($A14,Bâtiments!$A$6:$A$15,0))),"",ROUND($G14*(1+Paramètres!$B$10)^(14-$D14),0)) | V14: =IF(OR(15<$D14,15>INDEX(Bâtiments!$E$6:$E$15,MATCH($A14,Bâtiments!$A$6:$A$15,0))),"",ROUND($G14*(1+Paramètres!$B$10)^(15-$D14),0)) | W14: =IF(OR(16<$D14,16>INDEX(Bâtiments!$E$6:$E$15,MATCH($A14,Bâtiments!$A$6:$A$15,0))),"",ROUND($G14*(1+Paramètres!$B$10)^(16-$D14),0)) -> 200 | X14: =IF(OR(17<$D14,17>INDEX(Bâtiments!$E$6:$E$15,MATCH($A14,Bâtiments!$A$6:$A$15,0))),"",ROUND($G14*(1+Paramètres!$B$10)^(17-$D14),0)) -> 224 | Y14: =IF(OR(18<$D14,18>INDEX(Bâtiments!$E$6:$E$15,MATCH($A14,Bâtiments!$A$6:$A$15,0))),"",ROUND($G14*(1+Paramètres!$B$10)^(18-$D14),0)) -> 251 | Z14: =IF(OR(19<$D14,19>INDEX(Bâtiments!$E$6:$E$15,MATCH($A14,Bâtiments!$A$6:$A$15,0))),"",ROUND($G14*(1+Paramètres!$B$10)^(19-$D14),0)) -> 281 | AA14: =IF(OR(20<$D14,20>INDEX(Bâtiments!$E$6:$E$15,MATCH($A14,Bâtiments!$A$6:$A$15,0))),"",ROUND($G14*(1+Paramètres!$B$10)^(20-$D14),0)) -> 315 | AB14: =IF(OR(21<$D14,21>INDEX(Bâtiments!$E$6:$E$15,MATCH($A14,Bâtiments!$A$6:$A$15,0))),"",ROUND($G14*(1+Paramètres!$B$10)^(21-$D14),0)) -> 352 | AC14: =IF(OR(22<$D14,22>INDEX(Bâtiments!$E$6:$E$15,MATCH($A14,Bâtiments!$A$6:$A$15,0))),"",ROUND($G14*(1+Paramètres!$B$10)^(22-$D14),0)) -> 395 | AD14: =IF(OR(23<$D14,23>INDEX(Bâtiments!$E$6:$E$15,MATCH($A14,Bâtiments!$A$6:$A$15,0))),"",ROUND($G14*(1+Paramètres!$B$10)^(23-$D14),0)) -> 442 | AE14: =IF(OR(24<$D14,24>INDEX(Bâtiments!$E$6:$E$15,MATCH($A14,Bâtiments!$A$6:$A$15,0))),"",ROUND($G14*(1+Paramètres!$B$10)^(24-$D14),0)) -> 495 | AF14: =IF(OR(25<$D14,25>INDEX(Bâtiments!$E$6:$E$15,MATCH($A14,Bâtiments!$A$6:$A$15,0))),"",ROUND($G14*(1+Paramètres!$B$10)^(25-$D14),0)) -> 555 | AG14: =INDEX(Bâtiments!$E$6:$E$15,MATCH($A14,Bâtiments!$A$6:$A$15,0)) -> 25 | AH14: =ROUND($G14*(1+Paramètres!$B$10)^(AG14-$D14),0) -> 555 | AI14: =AH14*Paramètres!$B$11 -> 4440
A15: Champs | B15: étoffe astrale | C15: 5 | D15: 21 | E15: 70 | F15: ressources/etoffe_astrale.png | G15: =INDEX(Paramètres!$B$5:$B$9,$C15) -> 300 | H15: =IF(OR(1<$D15,1>INDEX(Bâtiments!$E$6:$E$15,MATCH($A15,Bâtiments!$A$6:$A$15,0))),"",ROUND($G15*(1+Paramètres!$B$10)^(1-$D15),0)) | I15: =IF(OR(2<$D15,2>INDEX(Bâtiments!$E$6:$E$15,MATCH($A15,Bâtiments!$A$6:$A$15,0))),"",ROUND($G15*(1+Paramètres!$B$10)^(2-$D15),0)) | J15: =IF(OR(3<$D15,3>INDEX(Bâtiments!$E$6:$E$15,MATCH($A15,Bâtiments!$A$6:$A$15,0))),"",ROUND($G15*(1+Paramètres!$B$10)^(3-$D15),0)) | K15: =IF(OR(4<$D15,4>INDEX(Bâtiments!$E$6:$E$15,MATCH($A15,Bâtiments!$A$6:$A$15,0))),"",ROUND($G15*(1+Paramètres!$B$10)^(4-$D15),0)) | L15: =IF(OR(5<$D15,5>INDEX(Bâtiments!$E$6:$E$15,MATCH($A15,Bâtiments!$A$6:$A$15,0))),"",ROUND($G15*(1+Paramètres!$B$10)^(5-$D15),0)) | M15: =IF(OR(6<$D15,6>INDEX(Bâtiments!$E$6:$E$15,MATCH($A15,Bâtiments!$A$6:$A$15,0))),"",ROUND($G15*(1+Paramètres!$B$10)^(6-$D15),0)) | N15: =IF(OR(7<$D15,7>INDEX(Bâtiments!$E$6:$E$15,MATCH($A15,Bâtiments!$A$6:$A$15,0))),"",ROUND($G15*(1+Paramètres!$B$10)^(7-$D15),0)) | O15: =IF(OR(8<$D15,8>INDEX(Bâtiments!$E$6:$E$15,MATCH($A15,Bâtiments!$A$6:$A$15,0))),"",ROUND($G15*(1+Paramètres!$B$10)^(8-$D15),0)) | P15: =IF(OR(9<$D15,9>INDEX(Bâtiments!$E$6:$E$15,MATCH($A15,Bâtiments!$A$6:$A$15,0))),"",ROUND($G15*(1+Paramètres!$B$10)^(9-$D15),0)) | Q15: =IF(OR(10<$D15,10>INDEX(Bâtiments!$E$6:$E$15,MATCH($A15,Bâtiments!$A$6:$A$15,0))),"",ROUND($G15*(1+Paramètres!$B$10)^(10-$D15),0)) | R15: =IF(OR(11<$D15,11>INDEX(Bâtiments!$E$6:$E$15,MATCH($A15,Bâtiments!$A$6:$A$15,0))),"",ROUND($G15*(1+Paramètres!$B$10)^(11-$D15),0)) | S15: =IF(OR(12<$D15,12>INDEX(Bâtiments!$E$6:$E$15,MATCH($A15,Bâtiments!$A$6:$A$15,0))),"",ROUND($G15*(1+Paramètres!$B$10)^(12-$D15),0)) | T15: =IF(OR(13<$D15,13>INDEX(Bâtiments!$E$6:$E$15,MATCH($A15,Bâtiments!$A$6:$A$15,0))),"",ROUND($G15*(1+Paramètres!$B$10)^(13-$D15),0)) | U15: =IF(OR(14<$D15,14>INDEX(Bâtiments!$E$6:$E$15,MATCH($A15,Bâtiments!$A$6:$A$15,0))),"",ROUND($G15*(1+Paramètres!$B$10)^(14-$D15),0)) | V15: =IF(OR(15<$D15,15>INDEX(Bâtiments!$E$6:$E$15,MATCH($A15,Bâtiments!$A$6:$A$15,0))),"",ROUND($G15*(1+Paramètres!$B$10)^(15-$D15),0)) | W15: =IF(OR(16<$D15,16>INDEX(Bâtiments!$E$6:$E$15,MATCH($A15,Bâtiments!$A$6:$A$15,0))),"",ROUND($G15*(1+Paramètres!$B$10)^(16-$D15),0)) | X15: =IF(OR(17<$D15,17>INDEX(Bâtiments!$E$6:$E$15,MATCH($A15,Bâtiments!$A$6:$A$15,0))),"",ROUND($G15*(1+Paramètres!$B$10)^(17-$D15),0)) | Y15: =IF(OR(18<$D15,18>INDEX(Bâtiments!$E$6:$E$15,MATCH($A15,Bâtiments!$A$6:$A$15,0))),"",ROUND($G15*(1+Paramètres!$B$10)^(18-$D15),0)) | Z15: =IF(OR(19<$D15,19>INDEX(Bâtiments!$E$6:$E$15,MATCH($A15,Bâtiments!$A$6:$A$15,0))),"",ROUND($G15*(1+Paramètres!$B$10)^(19-$D15),0)) | AA15: =IF(OR(20<$D15,20>INDEX(Bâtiments!$E$6:$E$15,MATCH($A15,Bâtiments!$A$6:$A$15,0))),"",ROUND($G15*(1+Paramètres!$B$10)^(20-$D15),0)) | AB15: =IF(OR(21<$D15,21>INDEX(Bâtiments!$E$6:$E$15,MATCH($A15,Bâtiments!$A$6:$A$15,0))),"",ROUND($G15*(1+Paramètres!$B$10)^(21-$D15),0)) -> 300 | AC15: =IF(OR(22<$D15,22>INDEX(Bâtiments!$E$6:$E$15,MATCH($A15,Bâtiments!$A$6:$A$15,0))),"",ROUND($G15*(1+Paramètres!$B$10)^(22-$D15),0)) -> 336 | AD15: =IF(OR(23<$D15,23>INDEX(Bâtiments!$E$6:$E$15,MATCH($A15,Bâtiments!$A$6:$A$15,0))),"",ROUND($G15*(1+Paramètres!$B$10)^(23-$D15),0)) -> 376 | AE15: =IF(OR(24<$D15,24>INDEX(Bâtiments!$E$6:$E$15,MATCH($A15,Bâtiments!$A$6:$A$15,0))),"",ROUND($G15*(1+Paramètres!$B$10)^(24-$D15),0)) -> 421 | AF15: =IF(OR(25<$D15,25>INDEX(Bâtiments!$E$6:$E$15,MATCH($A15,Bâtiments!$A$6:$A$15,0))),"",ROUND($G15*(1+Paramètres!$B$10)^(25-$D15),0)) -> 472 | AG15: =INDEX(Bâtiments!$E$6:$E$15,MATCH($A15,Bâtiments!$A$6:$A$15,0)) -> 25 | AH15: =ROUND($G15*(1+Paramètres!$B$10)^(AG15-$D15),0) -> 472 | AI15: =AH15*Paramètres!$B$11 -> 3776
A16: Terrain de chasse | B16: cuir | C16: 1 | D16: 1 | E16: 0 | F16: ressources/cuir.png | G16: =INDEX(Paramètres!$B$5:$B$9,$C16) -> 60 | H16: =IF(OR(1<$D16,1>INDEX(Bâtiments!$E$6:$E$15,MATCH($A16,Bâtiments!$A$6:$A$15,0))),"",ROUND($G16*(1+Paramètres!$B$10)^(1-$D16),0)) -> 60 | I16: =IF(OR(2<$D16,2>INDEX(Bâtiments!$E$6:$E$15,MATCH($A16,Bâtiments!$A$6:$A$15,0))),"",ROUND($G16*(1+Paramètres!$B$10)^(2-$D16),0)) -> 67 | J16: =IF(OR(3<$D16,3>INDEX(Bâtiments!$E$6:$E$15,MATCH($A16,Bâtiments!$A$6:$A$15,0))),"",ROUND($G16*(1+Paramètres!$B$10)^(3-$D16),0)) -> 75 | K16: =IF(OR(4<$D16,4>INDEX(Bâtiments!$E$6:$E$15,MATCH($A16,Bâtiments!$A$6:$A$15,0))),"",ROUND($G16*(1+Paramètres!$B$10)^(4-$D16),0)) -> 84 | L16: =IF(OR(5<$D16,5>INDEX(Bâtiments!$E$6:$E$15,MATCH($A16,Bâtiments!$A$6:$A$15,0))),"",ROUND($G16*(1+Paramètres!$B$10)^(5-$D16),0)) -> 94 | M16: =IF(OR(6<$D16,6>INDEX(Bâtiments!$E$6:$E$15,MATCH($A16,Bâtiments!$A$6:$A$15,0))),"",ROUND($G16*(1+Paramètres!$B$10)^(6-$D16),0)) -> 106 | N16: =IF(OR(7<$D16,7>INDEX(Bâtiments!$E$6:$E$15,MATCH($A16,Bâtiments!$A$6:$A$15,0))),"",ROUND($G16*(1+Paramètres!$B$10)^(7-$D16),0)) -> 118 | O16: =IF(OR(8<$D16,8>INDEX(Bâtiments!$E$6:$E$15,MATCH($A16,Bâtiments!$A$6:$A$15,0))),"",ROUND($G16*(1+Paramètres!$B$10)^(8-$D16),0)) -> 133 | P16: =IF(OR(9<$D16,9>INDEX(Bâtiments!$E$6:$E$15,MATCH($A16,Bâtiments!$A$6:$A$15,0))),"",ROUND($G16*(1+Paramètres!$B$10)^(9-$D16),0)) -> 149 | Q16: =IF(OR(10<$D16,10>INDEX(Bâtiments!$E$6:$E$15,MATCH($A16,Bâtiments!$A$6:$A$15,0))),"",ROUND($G16*(1+Paramètres!$B$10)^(10-$D16),0)) -> 166 | R16: =IF(OR(11<$D16,11>INDEX(Bâtiments!$E$6:$E$15,MATCH($A16,Bâtiments!$A$6:$A$15,0))),"",ROUND($G16*(1+Paramètres!$B$10)^(11-$D16),0)) -> 186 | S16: =IF(OR(12<$D16,12>INDEX(Bâtiments!$E$6:$E$15,MATCH($A16,Bâtiments!$A$6:$A$15,0))),"",ROUND($G16*(1+Paramètres!$B$10)^(12-$D16),0)) -> 209 | T16: =IF(OR(13<$D16,13>INDEX(Bâtiments!$E$6:$E$15,MATCH($A16,Bâtiments!$A$6:$A$15,0))),"",ROUND($G16*(1+Paramètres!$B$10)^(13-$D16),0)) -> 234 | U16: =IF(OR(14<$D16,14>INDEX(Bâtiments!$E$6:$E$15,MATCH($A16,Bâtiments!$A$6:$A$15,0))),"",ROUND($G16*(1+Paramètres!$B$10)^(14-$D16),0)) -> 262 | V16: =IF(OR(15<$D16,15>INDEX(Bâtiments!$E$6:$E$15,MATCH($A16,Bâtiments!$A$6:$A$15,0))),"",ROUND($G16*(1+Paramètres!$B$10)^(15-$D16),0)) -> 293 | W16: =IF(OR(16<$D16,16>INDEX(Bâtiments!$E$6:$E$15,MATCH($A16,Bâtiments!$A$6:$A$15,0))),"",ROUND($G16*(1+Paramètres!$B$10)^(16-$D16),0)) -> 328 | X16: =IF(OR(17<$D16,17>INDEX(Bâtiments!$E$6:$E$15,MATCH($A16,Bâtiments!$A$6:$A$15,0))),"",ROUND($G16*(1+Paramètres!$B$10)^(17-$D16),0)) -> 368 | Y16: =IF(OR(18<$D16,18>INDEX(Bâtiments!$E$6:$E$15,MATCH($A16,Bâtiments!$A$6:$A$15,0))),"",ROUND($G16*(1+Paramètres!$B$10)^(18-$D16),0)) -> 412 | Z16: =IF(OR(19<$D16,19>INDEX(Bâtiments!$E$6:$E$15,MATCH($A16,Bâtiments!$A$6:$A$15,0))),"",ROUND($G16*(1+Paramètres!$B$10)^(19-$D16),0)) -> 461 | AA16: =IF(OR(20<$D16,20>INDEX(Bâtiments!$E$6:$E$15,MATCH($A16,Bâtiments!$A$6:$A$15,0))),"",ROUND($G16*(1+Paramètres!$B$10)^(20-$D16),0)) -> 517 | AB16: =IF(OR(21<$D16,21>INDEX(Bâtiments!$E$6:$E$15,MATCH($A16,Bâtiments!$A$6:$A$15,0))),"",ROUND($G16*(1+Paramètres!$B$10)^(21-$D16),0)) | AC16: =IF(OR(22<$D16,22>INDEX(Bâtiments!$E$6:$E$15,MATCH($A16,Bâtiments!$A$6:$A$15,0))),"",ROUND($G16*(1+Paramètres!$B$10)^(22-$D16),0)) | AD16: =IF(OR(23<$D16,23>INDEX(Bâtiments!$E$6:$E$15,MATCH($A16,Bâtiments!$A$6:$A$15,0))),"",ROUND($G16*(1+Paramètres!$B$10)^(23-$D16),0)) | AE16: =IF(OR(24<$D16,24>INDEX(Bâtiments!$E$6:$E$15,MATCH($A16,Bâtiments!$A$6:$A$15,0))),"",ROUND($G16*(1+Paramètres!$B$10)^(24-$D16),0)) | AF16: =IF(OR(25<$D16,25>INDEX(Bâtiments!$E$6:$E$15,MATCH($A16,Bâtiments!$A$6:$A$15,0))),"",ROUND($G16*(1+Paramètres!$B$10)^(25-$D16),0)) | AG16: =INDEX(Bâtiments!$E$6:$E$15,MATCH($A16,Bâtiments!$A$6:$A$15,0)) -> 20 | AH16: =ROUND($G16*(1+Paramètres!$B$10)^(AG16-$D16),0) -> 517 | AI16: =AH16*Paramètres!$B$11 -> 4136
A17: Terrain de chasse | B17: cuir clouté | C17: 3 | D17: 6 | E17: 30 | F17: ressources/cuir_cloute.png | G17: =INDEX(Paramètres!$B$5:$B$9,$C17) -> 135 | H17: =IF(OR(1<$D17,1>INDEX(Bâtiments!$E$6:$E$15,MATCH($A17,Bâtiments!$A$6:$A$15,0))),"",ROUND($G17*(1+Paramètres!$B$10)^(1-$D17),0)) | I17: =IF(OR(2<$D17,2>INDEX(Bâtiments!$E$6:$E$15,MATCH($A17,Bâtiments!$A$6:$A$15,0))),"",ROUND($G17*(1+Paramètres!$B$10)^(2-$D17),0)) | J17: =IF(OR(3<$D17,3>INDEX(Bâtiments!$E$6:$E$15,MATCH($A17,Bâtiments!$A$6:$A$15,0))),"",ROUND($G17*(1+Paramètres!$B$10)^(3-$D17),0)) | K17: =IF(OR(4<$D17,4>INDEX(Bâtiments!$E$6:$E$15,MATCH($A17,Bâtiments!$A$6:$A$15,0))),"",ROUND($G17*(1+Paramètres!$B$10)^(4-$D17),0)) | L17: =IF(OR(5<$D17,5>INDEX(Bâtiments!$E$6:$E$15,MATCH($A17,Bâtiments!$A$6:$A$15,0))),"",ROUND($G17*(1+Paramètres!$B$10)^(5-$D17),0)) | M17: =IF(OR(6<$D17,6>INDEX(Bâtiments!$E$6:$E$15,MATCH($A17,Bâtiments!$A$6:$A$15,0))),"",ROUND($G17*(1+Paramètres!$B$10)^(6-$D17),0)) -> 135 | N17: =IF(OR(7<$D17,7>INDEX(Bâtiments!$E$6:$E$15,MATCH($A17,Bâtiments!$A$6:$A$15,0))),"",ROUND($G17*(1+Paramètres!$B$10)^(7-$D17),0)) -> 151 | O17: =IF(OR(8<$D17,8>INDEX(Bâtiments!$E$6:$E$15,MATCH($A17,Bâtiments!$A$6:$A$15,0))),"",ROUND($G17*(1+Paramètres!$B$10)^(8-$D17),0)) -> 169 | P17: =IF(OR(9<$D17,9>INDEX(Bâtiments!$E$6:$E$15,MATCH($A17,Bâtiments!$A$6:$A$15,0))),"",ROUND($G17*(1+Paramètres!$B$10)^(9-$D17),0)) -> 190 | Q17: =IF(OR(10<$D17,10>INDEX(Bâtiments!$E$6:$E$15,MATCH($A17,Bâtiments!$A$6:$A$15,0))),"",ROUND($G17*(1+Paramètres!$B$10)^(10-$D17),0)) -> 212 | R17: =IF(OR(11<$D17,11>INDEX(Bâtiments!$E$6:$E$15,MATCH($A17,Bâtiments!$A$6:$A$15,0))),"",ROUND($G17*(1+Paramètres!$B$10)^(11-$D17),0)) -> 238 | S17: =IF(OR(12<$D17,12>INDEX(Bâtiments!$E$6:$E$15,MATCH($A17,Bâtiments!$A$6:$A$15,0))),"",ROUND($G17*(1+Paramètres!$B$10)^(12-$D17),0)) -> 266 | T17: =IF(OR(13<$D17,13>INDEX(Bâtiments!$E$6:$E$15,MATCH($A17,Bâtiments!$A$6:$A$15,0))),"",ROUND($G17*(1+Paramètres!$B$10)^(13-$D17),0)) -> 298 | U17: =IF(OR(14<$D17,14>INDEX(Bâtiments!$E$6:$E$15,MATCH($A17,Bâtiments!$A$6:$A$15,0))),"",ROUND($G17*(1+Paramètres!$B$10)^(14-$D17),0)) -> 334 | V17: =IF(OR(15<$D17,15>INDEX(Bâtiments!$E$6:$E$15,MATCH($A17,Bâtiments!$A$6:$A$15,0))),"",ROUND($G17*(1+Paramètres!$B$10)^(15-$D17),0)) -> 374 | W17: =IF(OR(16<$D17,16>INDEX(Bâtiments!$E$6:$E$15,MATCH($A17,Bâtiments!$A$6:$A$15,0))),"",ROUND($G17*(1+Paramètres!$B$10)^(16-$D17),0)) -> 419 | X17: =IF(OR(17<$D17,17>INDEX(Bâtiments!$E$6:$E$15,MATCH($A17,Bâtiments!$A$6:$A$15,0))),"",ROUND($G17*(1+Paramètres!$B$10)^(17-$D17),0)) -> 470 | Y17: =IF(OR(18<$D17,18>INDEX(Bâtiments!$E$6:$E$15,MATCH($A17,Bâtiments!$A$6:$A$15,0))),"",ROUND($G17*(1+Paramètres!$B$10)^(18-$D17),0)) -> 526 | Z17: =IF(OR(19<$D17,19>INDEX(Bâtiments!$E$6:$E$15,MATCH($A17,Bâtiments!$A$6:$A$15,0))),"",ROUND($G17*(1+Paramètres!$B$10)^(19-$D17),0)) -> 589 | AA17: =IF(OR(20<$D17,20>INDEX(Bâtiments!$E$6:$E$15,MATCH($A17,Bâtiments!$A$6:$A$15,0))),"",ROUND($G17*(1+Paramètres!$B$10)^(20-$D17),0)) -> 660 | AB17: =IF(OR(21<$D17,21>INDEX(Bâtiments!$E$6:$E$15,MATCH($A17,Bâtiments!$A$6:$A$15,0))),"",ROUND($G17*(1+Paramètres!$B$10)^(21-$D17),0)) | AC17: =IF(OR(22<$D17,22>INDEX(Bâtiments!$E$6:$E$15,MATCH($A17,Bâtiments!$A$6:$A$15,0))),"",ROUND($G17*(1+Paramètres!$B$10)^(22-$D17),0)) | AD17: =IF(OR(23<$D17,23>INDEX(Bâtiments!$E$6:$E$15,MATCH($A17,Bâtiments!$A$6:$A$15,0))),"",ROUND($G17*(1+Paramètres!$B$10)^(23-$D17),0)) | AE17: =IF(OR(24<$D17,24>INDEX(Bâtiments!$E$6:$E$15,MATCH($A17,Bâtiments!$A$6:$A$15,0))),"",ROUND($G17*(1+Paramètres!$B$10)^(24-$D17),0)) | AF17: =IF(OR(25<$D17,25>INDEX(Bâtiments!$E$6:$E$15,MATCH($A17,Bâtiments!$A$6:$A$15,0))),"",ROUND($G17*(1+Paramètres!$B$10)^(25-$D17),0)) | AG17: =INDEX(Bâtiments!$E$6:$E$15,MATCH($A17,Bâtiments!$A$6:$A$15,0)) -> 20 | AH17: =ROUND($G17*(1+Paramètres!$B$10)^(AG17-$D17),0) -> 660 | AI17: =AH17*Paramètres!$B$11 -> 5280
... A35: Tour d'alchimie | B35: éther | C35: 5 | D35: 1 | E35: 85 | F35: ressources/ether.png | G35: =INDEX(Paramètres!$B$5:$B$9,$C35) -> 300 | H35: =IF(OR(1<$D35,1>INDEX(Bâtiments!$E$6:$E$15,MATCH($A35,Bâtiments!$A$6:$A$15,0))),"",ROUND($G35*(1+Paramètres!$B$10)^(1-$D35),0)) -> 300 | I35: =IF(OR(2<$D35,2>INDEX(Bâtiments!$E$6:$E$15,MATCH($A35,Bâtiments!$A$6:$A$15,0))),"",ROUND($G35*(1+Paramètres!$B$10)^(2-$D35),0)) -> 336 | J35: =IF(OR(3<$D35,3>INDEX(Bâtiments!$E$6:$E$15,MATCH($A35,Bâtiments!$A$6:$A$15,0))),"",ROUND($G35*(1+Paramètres!$B$10)^(3-$D35),0)) -> 376 | K35: =IF(OR(4<$D35,4>INDEX(Bâtiments!$E$6:$E$15,MATCH($A35,Bâtiments!$A$6:$A$15,0))),"",ROUND($G35*(1+Paramètres!$B$10)^(4-$D35),0)) -> 421 | L35: =IF(OR(5<$D35,5>INDEX(Bâtiments!$E$6:$E$15,MATCH($A35,Bâtiments!$A$6:$A$15,0))),"",ROUND($G35*(1+Paramètres!$B$10)^(5-$D35),0)) -> 472 | M35: =IF(OR(6<$D35,6>INDEX(Bâtiments!$E$6:$E$15,MATCH($A35,Bâtiments!$A$6:$A$15,0))),"",ROUND($G35*(1+Paramètres!$B$10)^(6-$D35),0)) | N35: =IF(OR(7<$D35,7>INDEX(Bâtiments!$E$6:$E$15,MATCH($A35,Bâtiments!$A$6:$A$15,0))),"",ROUND($G35*(1+Paramètres!$B$10)^(7-$D35),0)) | O35: =IF(OR(8<$D35,8>INDEX(Bâtiments!$E$6:$E$15,MATCH($A35,Bâtiments!$A$6:$A$15,0))),"",ROUND($G35*(1+Paramètres!$B$10)^(8-$D35),0)) | P35: =IF(OR(9<$D35,9>INDEX(Bâtiments!$E$6:$E$15,MATCH($A35,Bâtiments!$A$6:$A$15,0))),"",ROUND($G35*(1+Paramètres!$B$10)^(9-$D35),0)) | Q35: =IF(OR(10<$D35,10>INDEX(Bâtiments!$E$6:$E$15,MATCH($A35,Bâtiments!$A$6:$A$15,0))),"",ROUND($G35*(1+Paramètres!$B$10)^(10-$D35),0)) | R35: =IF(OR(11<$D35,11>INDEX(Bâtiments!$E$6:$E$15,MATCH($A35,Bâtiments!$A$6:$A$15,0))),"",ROUND($G35*(1+Paramètres!$B$10)^(11-$D35),0)) | S35: =IF(OR(12<$D35,12>INDEX(Bâtiments!$E$6:$E$15,MATCH($A35,Bâtiments!$A$6:$A$15,0))),"",ROUND($G35*(1+Paramètres!$B$10)^(12-$D35),0)) | T35: =IF(OR(13<$D35,13>INDEX(Bâtiments!$E$6:$E$15,MATCH($A35,Bâtiments!$A$6:$A$15,0))),"",ROUND($G35*(1+Paramètres!$B$10)^(13-$D35),0)) | U35: =IF(OR(14<$D35,14>INDEX(Bâtiments!$E$6:$E$15,MATCH($A35,Bâtiments!$A$6:$A$15,0))),"",ROUND($G35*(1+Paramètres!$B$10)^(14-$D35),0)) | V35: =IF(OR(15<$D35,15>INDEX(Bâtiments!$E$6:$E$15,MATCH($A35,Bâtiments!$A$6:$A$15,0))),"",ROUND($G35*(1+Paramètres!$B$10)^(15-$D35),0)) | W35: =IF(OR(16<$D35,16>INDEX(Bâtiments!$E$6:$E$15,MATCH($A35,Bâtiments!$A$6:$A$15,0))),"",ROUND($G35*(1+Paramètres!$B$10)^(16-$D35),0)) | X35: =IF(OR(17<$D35,17>INDEX(Bâtiments!$E$6:$E$15,MATCH($A35,Bâtiments!$A$6:$A$15,0))),"",ROUND($G35*(1+Paramètres!$B$10)^(17-$D35),0)) | Y35: =IF(OR(18<$D35,18>INDEX(Bâtiments!$E$6:$E$15,MATCH($A35,Bâtiments!$A$6:$A$15,0))),"",ROUND($G35*(1+Paramètres!$B$10)^(18-$D35),0)) | Z35: =IF(OR(19<$D35,19>INDEX(Bâtiments!$E$6:$E$15,MATCH($A35,Bâtiments!$A$6:$A$15,0))),"",ROUND($G35*(1+Paramètres!$B$10)^(19-$D35),0)) | AA35: =IF(OR(20<$D35,20>INDEX(Bâtiments!$E$6:$E$15,MATCH($A35,Bâtiments!$A$6:$A$15,0))),"",ROUND($G35*(1+Paramètres!$B$10)^(20-$D35),0)) | AB35: =IF(OR(21<$D35,21>INDEX(Bâtiments!$E$6:$E$15,MATCH($A35,Bâtiments!$A$6:$A$15,0))),"",ROUND($G35*(1+Paramètres!$B$10)^(21-$D35),0)) | AC35: =IF(OR(22<$D35,22>INDEX(Bâtiments!$E$6:$E$15,MATCH($A35,Bâtiments!$A$6:$A$15,0))),"",ROUND($G35*(1+Paramètres!$B$10)^(22-$D35),0)) | AD35: =IF(OR(23<$D35,23>INDEX(Bâtiments!$E$6:$E$15,MATCH($A35,Bâtiments!$A$6:$A$15,0))),"",ROUND($G35*(1+Paramètres!$B$10)^(23-$D35),0)) | AE35: =IF(OR(24<$D35,24>INDEX(Bâtiments!$E$6:$E$15,MATCH($A35,Bâtiments!$A$6:$A$15,0))),"",ROUND($G35*(1+Paramètres!$B$10)^(24-$D35),0)) | AF35: =IF(OR(25<$D35,25>INDEX(Bâtiments!$E$6:$E$15,MATCH($A35,Bâtiments!$A$6:$A$15,0))),"",ROUND($G35*(1+Paramètres!$B$10)^(25-$D35),0)) | AG35: =INDEX(Bâtiments!$E$6:$E$15,MATCH($A35,Bâtiments!$A$6:$A$15,0)) -> 5 | AH35: =ROUND($G35*(1+Paramètres!$B$10)^(AG35-$D35),0) -> 472 | AI35: =AH35*Paramètres!$B$11 -> 3776
A38: Repère : ressources pour monter UN objet Commun de +0 au maximum de son palier (formule du fichier équipements : 3 × L^1,25 par niveau)
A39: Palier | B39: Amélioration max | C39: Ressource nécessaire (Commun) | D39: Ressource nécessaire (Épique ×1,75) | E39: Bâtiment repère | F39: Niveau repère | G39: Production au niveau repère (/h) | H39: Heures pour un objet Commun | I39: Heures pour un objet Épique
A40: 1 | B40: 19 | C40: =SUMPRODUCT(ROUND(3*ROW(INDIRECT("1:"&B40))^1.25,0)) -> 1064 | D40: =SUMPRODUCT(ROUND(3*ROW(INDIRECT("1:"&B40))^1.25*1.75,0)) -> 1863 | E40: Scierie (bois) | F40: 5 | G40: =INDEX($H$6:$AF$6,1,F40) -> 94 | H40: =ROUND(C40/G40,1) -> 11.3 | I40: =ROUND(D40/G40,1) -> 19.8
A41: 2 | B41: 20 | C41: =SUMPRODUCT(ROUND(3*ROW(INDIRECT("1:"&B41))^1.25,0)) -> 1191 | D41: =SUMPRODUCT(ROUND(3*ROW(INDIRECT("1:"&B41))^1.25*1.75,0)) -> 2085 | E41: Mine (fer) | F41: 5 | G41: =INDEX($H$22:$AF$22,1,F41) -> 142 | H41: =ROUND(C41/G41,1) -> 8.4 | I41: =ROUND(D41/G41,1) -> 14.7
A42: 3 | B42: 25 | C42: =SUMPRODUCT(ROUND(3*ROW(INDIRECT("1:"&B42))^1.25,0)) -> 1947 | D42: =SUMPRODUCT(ROUND(3*ROW(INDIRECT("1:"&B42))^1.25*1.75,0)) -> 3407 | E42: Mine (acier) | F42: 10 | G42: =INDEX($H$25:$AF$25,1,F42) -> 212 | H42: =ROUND(C42/G42,1) -> 9.2 | I42: =ROUND(D42/G42,1) -> 16.1
A43: 4 | B43: 25 | C43: =SUMPRODUCT(ROUND(3*ROW(INDIRECT("1:"&B43))^1.25,0)) -> 1947 | D43: =SUMPRODUCT(ROUND(3*ROW(INDIRECT("1:"&B43))^1.25*1.75,0)) -> 3407 | E43: Mine (mithril) | F43: 15 | G43: =INDEX($H$28:$AF$28,1,F43) -> 315 | H43: =ROUND(C43/G43,1) -> 6.2 | I43: =ROUND(D43/G43,1) -> 10.8
A44: 5 | B44: 30 | C44: =SUMPRODUCT(ROUND(3*ROW(INDIRECT("1:"&B44))^1.25,0)) -> 2914 | D44: =SUMPRODUCT(ROUND(3*ROW(INDIRECT("1:"&B44))^1.25*1.75,0)) -> 5098 | E44: Mine (adamantite) | F44: 20 | G44: =INDEX($H$32:$AF$32,1,F44) -> 472 | H44: =ROUND(C44/G44,1) -> 6.2 | I44: =ROUND(D44/G44,1) -> 10.8
A46: Lecture : avec le bâtiment au niveau repère, une nuit hors ligne (8 h) suffit environ pour un objet Commun complet. Un set de 10 objets se construit donc sur plusieurs jours, complété par le farm et la boutique.

Sheet Améliorations
A1: Coût de chaque amélioration de bâtiment
A2: Une ligne = passer au niveau indiqué. Ce que le joueur voit au survol du bouton « Améliorer » : étage requis, or, matériaux et effet du niveau suivant.
A5: Bâtiment | B5: Niveau visé | C5: Étage requis | D5: Or | E5: Matériau | F5: Quantité | G5: Charbon | H5: Minutes de chasse pour l'or | I5: Effet du niveau visé
A6: Taverne | B6: 2 | C6: =MAX(INDEX(Bâtiments!$D$6:$D$15,MATCH($A6,Bâtiments!$A$6:$A$15,0)),INDEX(Paramètres!$E$22:$E$26,MATCH($B6,Paramètres!$B$22:$B$26,1)),_xlfn.MAXIFS(Production!$E$6:$E$35,Production!$A$6:$A$35,$A6,Production!$D$6:$D$35,"<="&$B6)) -> 0 | D6: =ROUND(INDEX(Bâtiments!$F$6:$F$15,MATCH($A6,Bâtiments!$A$6:$A$15,0))*($B6-1)^Paramètres!$B$14,-1) -> 800 | E6: =INDEX(Paramètres!$D$22:$D$26,MATCH($C6,Paramètres!$E$22:$E$26,1)) -> bois | F6: =ROUND(Paramètres!$B$15*$B6^Paramètres!$B$16*INDEX(Bâtiments!$G$6:$G$15,MATCH($A6,Bâtiments!$A$6:$A$15,0)),0) -> 37 | G6: =IF($C6>=Paramètres!$E$23,ROUND($F6*Paramètres!$B$17,0),0) -> 0 | H6: =ROUND($D6/INDEX(Paramètres!$B$38:$B$57,MATCH(MAX(5,$C6),Paramètres!$A$38:$A$57,1))*60,1) -> 1.9 | I6: ="Objets proposés : "&(Paramètres!$B$32+INT(($B6-1)/2))&" · lots : "&(Paramètres!$B$33+INT(($B6-1)/2))&" · remise : "&ROUND(($B6-1)*Paramètres!$B$34*100,0)&" %" -> Objets proposés : 6 · lots : 4 · remise : 2 %
A7: Taverne | B7: 3 | C7: =MAX(INDEX(Bâtiments!$D$6:$D$15,MATCH($A7,Bâtiments!$A$6:$A$15,0)),INDEX(Paramètres!$E$22:$E$26,MATCH($B7,Paramètres!$B$22:$B$26,1)),_xlfn.MAXIFS(Production!$E$6:$E$35,Production!$A$6:$A$35,$A7,Production!$D$6:$D$35,"<="&$B7)) -> 0 | D7: =ROUND(INDEX(Bâtiments!$F$6:$F$15,MATCH($A7,Bâtiments!$A$6:$A$15,0))*($B7-1)^Paramètres!$B$14,-1) -> 3200 | E7: =INDEX(Paramètres!$D$22:$D$26,MATCH($C7,Paramètres!$E$22:$E$26,1)) -> bois | F7: =ROUND(Paramètres!$B$15*$B7^Paramètres!$B$16*INDEX(Bâtiments!$G$6:$G$15,MATCH($A7,Bâtiments!$A$6:$A$15,0)),0) -> 63 | G7: =IF($C7>=Paramètres!$E$23,ROUND($F7*Paramètres!$B$17,0),0) -> 0 | H7: =ROUND($D7/INDEX(Paramètres!$B$38:$B$57,MATCH(MAX(5,$C7),Paramètres!$A$38:$A$57,1))*60,1) -> 7.6 | I7: ="Objets proposés : "&(Paramètres!$B$32+INT(($B7-1)/2))&" · lots : "&(Paramètres!$B$33+INT(($B7-1)/2))&" · remise : "&ROUND(($B7-1)*Paramètres!$B$34*100,0)&" %" -> Objets proposés : 7 · lots : 5 · remise : 4 %
A8: Taverne | B8: 4 | C8: =MAX(INDEX(Bâtiments!$D$6:$D$15,MATCH($A8,Bâtiments!$A$6:$A$15,0)),INDEX(Paramètres!$E$22:$E$26,MATCH($B8,Paramètres!$B$22:$B$26,1)),_xlfn.MAXIFS(Production!$E$6:$E$35,Production!$A$6:$A$35,$A8,Production!$D$6:$D$35,"<="&$B8)) -> 0 | D8: =ROUND(INDEX(Bâtiments!$F$6:$F$15,MATCH($A8,Bâtiments!$A$6:$A$15,0))*($B8-1)^Paramètres!$B$14,-1) -> 7200 | E8: =INDEX(Paramètres!$D$22:$D$26,MATCH($C8,Paramètres!$E$22:$E$26,1)) -> bois | F8: =ROUND(Paramètres!$B$15*$B8^Paramètres!$B$16*INDEX(Bâtiments!$G$6:$G$15,MATCH($A8,Bâtiments!$A$6:$A$15,0)),0) -> 91 | G8: =IF($C8>=Paramètres!$E$23,ROUND($F8*Paramètres!$B$17,0),0) -> 0 | H8: =ROUND($D8/INDEX(Paramètres!$B$38:$B$57,MATCH(MAX(5,$C8),Paramètres!$A$38:$A$57,1))*60,1) -> 17.1 | I8: ="Objets proposés : "&(Paramètres!$B$32+INT(($B8-1)/2))&" · lots : "&(Paramètres!$B$33+INT(($B8-1)/2))&" · remise : "&ROUND(($B8-1)*Paramètres!$B$34*100,0)&" %" -> Objets proposés : 7 · lots : 5 · remise : 6 %
A9: Taverne | B9: 5 | C9: =MAX(INDEX(Bâtiments!$D$6:$D$15,MATCH($A9,Bâtiments!$A$6:$A$15,0)),INDEX(Paramètres!$E$22:$E$26,MATCH($B9,Paramètres!$B$22:$B$26,1)),_xlfn.MAXIFS(Production!$E$6:$E$35,Production!$A$6:$A$35,$A9,Production!$D$6:$D$35,"<="&$B9)) -> 0 | D9: =ROUND(INDEX(Bâtiments!$F$6:$F$15,MATCH($A9,Bâtiments!$A$6:$A$15,0))*($B9-1)^Paramètres!$B$14,-1) -> 12800 | E9: =INDEX(Paramètres!$D$22:$D$26,MATCH($C9,Paramètres!$E$22:$E$26,1)) -> bois | F9: =ROUND(Paramètres!$B$15*$B9^Paramètres!$B$16*INDEX(Bâtiments!$G$6:$G$15,MATCH($A9,Bâtiments!$A$6:$A$15,0)),0) -> 122 | G9: =IF($C9>=Paramètres!$E$23,ROUND($F9*Paramètres!$B$17,0),0) -> 0 | H9: =ROUND($D9/INDEX(Paramètres!$B$38:$B$57,MATCH(MAX(5,$C9),Paramètres!$A$38:$A$57,1))*60,1) -> 30.4 | I9: ="Objets proposés : "&(Paramètres!$B$32+INT(($B9-1)/2))&" · lots : "&(Paramètres!$B$33+INT(($B9-1)/2))&" · remise : "&ROUND(($B9-1)*Paramètres!$B$34*100,0)&" %" -> Objets proposés : 8 · lots : 6 · remise : 8 %
A10: Taverne | B10: 6 | C10: =MAX(INDEX(Bâtiments!$D$6:$D$15,MATCH($A10,Bâtiments!$A$6:$A$15,0)),INDEX(Paramètres!$E$22:$E$26,MATCH($B10,Paramètres!$B$22:$B$26,1)),_xlfn.MAXIFS(Production!$E$6:$E$35,Production!$A$6:$A$35,$A10,Production!$D$6:$D$35,"<="&$B10)) -> 15 | D10: =ROUND(INDEX(Bâtiments!$F$6:$F$15,MATCH($A10,Bâtiments!$A$6:$A$15,0))*($B10-1)^Paramètres!$B$14,-1) -> 20000 | E10: =INDEX(Paramètres!$D$22:$D$26,MATCH($C10,Paramètres!$E$22:$E$26,1)) -> fer | F10: =ROUND(Paramètres!$B$15*$B10^Paramètres!$B$16*INDEX(Bâtiments!$G$6:$G$15,MATCH($A10,Bâtiments!$A$6:$A$15,0)),0) -> 154 | G10: =IF($C10>=Paramètres!$E$23,ROUND($F10*Paramètres!$B$17,0),0) -> 77 | H10: =ROUND($D10/INDEX(Paramètres!$B$38:$B$57,MATCH(MAX(5,$C10),Paramètres!$A$38:$A$57,1))*60,1) -> 16.5 | I10: ="Objets proposés : "&(Paramètres!$B$32+INT(($B10-1)/2))&" · lots : "&(Paramètres!$B$33+INT(($B10-1)/2))&" · remise : "&ROUND(($B10-1)*Paramètres!$B$34*100,0)&" %" -> Objets proposés : 8 · lots : 6 · remise : 10 %
A11: Taverne | B11: 7 | C11: =MAX(INDEX(Bâtiments!$D$6:$D$15,MATCH($A11,Bâtiments!$A$6:$A$15,0)),INDEX(Paramètres!$E$22:$E$26,MATCH($B11,Paramètres!$B$22:$B$26,1)),_xlfn.MAXIFS(Production!$E$6:$E$35,Production!$A$6:$A$35,$A11,Production!$D$6:$D$35,"<="&$B11)) -> 15 | D11: =ROUND(INDEX(Bâtiments!$F$6:$F$15,MATCH($A11,Bâtiments!$A$6:$A$15,0))*($B11-1)^Paramètres!$B$14,-1) -> 28800 | E11: =INDEX(Paramètres!$D$22:$D$26,MATCH($C11,Paramètres!$E$22:$E$26,1)) -> fer | F11: =ROUND(Paramètres!$B$15*$B11^Paramètres!$B$16*INDEX(Bâtiments!$G$6:$G$15,MATCH($A11,Bâtiments!$A$6:$A$15,0)),0) -> 188 | G11: =IF($C11>=Paramètres!$E$23,ROUND($F11*Paramètres!$B$17,0),0) -> 94 | H11: =ROUND($D11/INDEX(Paramètres!$B$38:$B$57,MATCH(MAX(5,$C11),Paramètres!$A$38:$A$57,1))*60,1) -> 23.8 | I11: ="Objets proposés : "&(Paramètres!$B$32+INT(($B11-1)/2))&" · lots : "&(Paramètres!$B$33+INT(($B11-1)/2))&" · remise : "&ROUND(($B11-1)*Paramètres!$B$34*100,0)&" %" -> Objets proposés : 9 · lots : 7 · remise : 12 %
A12: Taverne | B12: 8 | C12: =MAX(INDEX(Bâtiments!$D$6:$D$15,MATCH($A12,Bâtiments!$A$6:$A$15,0)),INDEX(Paramètres!$E$22:$E$26,MATCH($B12,Paramètres!$B$22:$B$26,1)),_xlfn.MAXIFS(Production!$E$6:$E$35,Production!$A$6:$A$35,$A12,Production!$D$6:$D$35,"<="&$B12)) -> 15 | D12: =ROUND(INDEX(Bâtiments!$F$6:$F$15,MATCH($A12,Bâtiments!$A$6:$A$15,0))*($B12-1)^Paramètres!$B$14,-1) -> 39200 | E12: =INDEX(Paramètres!$D$22:$D$26,MATCH($C12,Paramètres!$E$22:$E$26,1)) -> fer | F12: =ROUND(Paramètres!$B$15*$B12^Paramètres!$B$16*INDEX(Bâtiments!$G$6:$G$15,MATCH($A12,Bâtiments!$A$6:$A$15,0)),0) -> 224 | G12: =IF($C12>=Paramètres!$E$23,ROUND($F12*Paramètres!$B$17,0),0) -> 112 | H12: =ROUND($D12/INDEX(Paramètres!$B$38:$B$57,MATCH(MAX(5,$C12),Paramètres!$A$38:$A$57,1))*60,1) -> 32.4 | I12: ="Objets proposés : "&(Paramètres!$B$32+INT(($B12-1)/2))&" · lots : "&(Paramètres!$B$33+INT(($B12-1)/2))&" · remise : "&ROUND(($B12-1)*Paramètres!$B$34*100,0)&" %" -> Objets proposés : 9 · lots : 7 · remise : 14 %
A13: Taverne | B13: 9 | C13: =MAX(INDEX(Bâtiments!$D$6:$D$15,MATCH($A13,Bâtiments!$A$6:$A$15,0)),INDEX(Paramètres!$E$22:$E$26,MATCH($B13,Paramètres!$B$22:$B$26,1)),_xlfn.MAXIFS(Production!$E$6:$E$35,Production!$A$6:$A$35,$A13,Production!$D$6:$D$35,"<="&$B13)) -> 15 | D13: =ROUND(INDEX(Bâtiments!$F$6:$F$15,MATCH($A13,Bâtiments!$A$6:$A$15,0))*($B13-1)^Paramètres!$B$14,-1) -> 51200 | E13: =INDEX(Paramètres!$D$22:$D$26,MATCH($C13,Paramètres!$E$22:$E$26,1)) -> fer | F13: =ROUND(Paramètres!$B$15*$B13^Paramètres!$B$16*INDEX(Bâtiments!$G$6:$G$15,MATCH($A13,Bâtiments!$A$6:$A$15,0)),0) -> 261 | G13: =IF($C13>=Paramètres!$E$23,ROUND($F13*Paramètres!$B$17,0),0) -> 131 | H13: =ROUND($D13/INDEX(Paramètres!$B$38:$B$57,MATCH(MAX(5,$C13),Paramètres!$A$38:$A$57,1))*60,1) -> 42.3 | I13: ="Objets proposés : "&(Paramètres!$B$32+INT(($B13-1)/2))&" · lots : "&(Paramètres!$B$33+INT(($B13-1)/2))&" · remise : "&ROUND(($B13-1)*Paramètres!$B$34*100,0)&" %" -> Objets proposés : 10 · lots : 8 · remise : 16 %
A14: Taverne | B14: 10 | C14: =MAX(INDEX(Bâtiments!$D$6:$D$15,MATCH($A14,Bâtiments!$A$6:$A$15,0)),INDEX(Paramètres!$E$22:$E$26,MATCH($B14,Paramètres!$B$22:$B$26,1)),_xlfn.MAXIFS(Production!$E$6:$E$35,Production!$A$6:$A$35,$A14,Production!$D$6:$D$35,"<="&$B14)) -> 15 | D14: =ROUND(INDEX(Bâtiments!$F$6:$F$15,MATCH($A14,Bâtiments!$A$6:$A$15,0))*($B14-1)^Paramètres!$B$14,-1) -> 64800 | E14: =INDEX(Paramètres!$D$22:$D$26,MATCH($C14,Paramètres!$E$22:$E$26,1)) -> fer | F14: =ROUND(Paramètres!$B$15*$B14^Paramètres!$B$16*INDEX(Bâtiments!$G$6:$G$15,MATCH($A14,Bâtiments!$A$6:$A$15,0)),0) -> 299 | G14: =IF($C14>=Paramètres!$E$23,ROUND($F14*Paramètres!$B$17,0),0) -> 150 | H14: =ROUND($D14/INDEX(Paramètres!$B$38:$B$57,MATCH(MAX(5,$C14),Paramètres!$A$38:$A$57,1))*60,1) -> 53.5 | I14: ="Objets proposés : "&(Paramètres!$B$32+INT(($B14-1)/2))&" · lots : "&(Paramètres!$B$33+INT(($B14-1)/2))&" · remise : "&ROUND(($B14-1)*Paramètres!$B$34*100,0)&" %" -> Objets proposés : 10 · lots : 8 · remise : 18 %
A15: Entrepôt | B15: 2 | C15: =MAX(INDEX(Bâtiments!$D$6:$D$15,MATCH($A15,Bâtiments!$A$6:$A$15,0)),INDEX(Paramètres!$E$22:$E$26,MATCH($B15,Paramètres!$B$22:$B$26,1)),_xlfn.MAXIFS(Production!$E$6:$E$35,Production!$A$6:$A$35,$A15,Production!$D$6:$D$35,"<="&$B15)) -> 0 | D15: =ROUND(INDEX(Bâtiments!$F$6:$F$15,MATCH($A15,Bâtiments!$A$6:$A$15,0))*($B15-1)^Paramètres!$B$14,-1) -> 400 | E15: =INDEX(Paramètres!$D$22:$D$26,MATCH($C15,Paramètres!$E$22:$E$26,1)) -> bois | F15: =ROUND(Paramètres!$B$15*$B15^Paramètres!$B$16*INDEX(Bâtiments!$G$6:$G$15,MATCH($A15,Bâtiments!$A$6:$A$15,0)),0) -> 37 | G15: =IF($C15>=Paramètres!$E$23,ROUND($F15*Paramètres!$B$17,0),0) -> 0 | H15: =ROUND($D15/INDEX(Paramètres!$B$38:$B$57,MATCH(MAX(5,$C15),Paramètres!$A$38:$A$57,1))*60,1) -> 1 | I15: ="Capacité : "&ROUND(Paramètres!$B$30*$B15^Paramètres!$B$31,-2)&" par ressource" -> Capacité : 2800 par ressource
A16: Entrepôt | B16: 3 | C16: =MAX(INDEX(Bâtiments!$D$6:$D$15,MATCH($A16,Bâtiments!$A$6:$A$15,0)),INDEX(Paramètres!$E$22:$E$26,MATCH($B16,Paramètres!$B$22:$B$26,1)),_xlfn.MAXIFS(Production!$E$6:$E$35,Production!$A$6:$A$35,$A16,Production!$D$6:$D$35,"<="&$B16)) -> 0 | D16: =ROUND(INDEX(Bâtiments!$F$6:$F$15,MATCH($A16,Bâtiments!$A$6:$A$15,0))*($B16-1)^Paramètres!$B$14,-1) -> 1600 | E16: =INDEX(Paramètres!$D$22:$D$26,MATCH($C16,Paramètres!$E$22:$E$26,1)) -> bois | F16: =ROUND(Paramètres!$B$15*$B16^Paramètres!$B$16*INDEX(Bâtiments!$G$6:$G$15,MATCH($A16,Bâtiments!$A$6:$A$15,0)),0) -> 63 | G16: =IF($C16>=Paramètres!$E$23,ROUND($F16*Paramètres!$B$17,0),0) -> 0 | H16: =ROUND($D16/INDEX(Paramètres!$B$38:$B$57,MATCH(MAX(5,$C16),Paramètres!$A$38:$A$57,1))*60,1) -> 3.8 | I16: ="Capacité : "&ROUND(Paramètres!$B$30*$B16^Paramètres!$B$31,-2)&" par ressource" -> Capacité : 5200 par ressource
A17: Entrepôt | B17: 4 | C17: =MAX(INDEX(Bâtiments!$D$6:$D$15,MATCH($A17,Bâtiments!$A$6:$A$15,0)),INDEX(Paramètres!$E$22:$E$26,MATCH($B17,Paramètres!$B$22:$B$26,1)),_xlfn.MAXIFS(Production!$E$6:$E$35,Production!$A$6:$A$35,$A17,Production!$D$6:$D$35,"<="&$B17)) -> 0 | D17: =ROUND(INDEX(Bâtiments!$F$6:$F$15,MATCH($A17,Bâtiments!$A$6:$A$15,0))*($B17-1)^Paramètres!$B$14,-1) -> 3600 | E17: =INDEX(Paramètres!$D$22:$D$26,MATCH($C17,Paramètres!$E$22:$E$26,1)) -> bois | F17: =ROUND(Paramètres!$B$15*$B17^Paramètres!$B$16*INDEX(Bâtiments!$G$6:$G$15,MATCH($A17,Bâtiments!$A$6:$A$15,0)),0) -> 91 | G17: =IF($C17>=Paramètres!$E$23,ROUND($F17*Paramètres!$B$17,0),0) -> 0 | H17: =ROUND($D17/INDEX(Paramètres!$B$38:$B$57,MATCH(MAX(5,$C17),Paramètres!$A$38:$A$57,1))*60,1) -> 8.6 | I17: ="Capacité : "&ROUND(Paramètres!$B$30*$B17^Paramètres!$B$31,-2)&" par ressource" -> Capacité : 8000 par ressource
A18: Entrepôt | B18: 5 | C18: =MAX(INDEX(Bâtiments!$D$6:$D$15,MATCH($A18,Bâtiments!$A$6:$A$15,0)),INDEX(Paramètres!$E$22:$E$26,MATCH($B18,Paramètres!$B$22:$B$26,1)),_xlfn.MAXIFS(Production!$E$6:$E$35,Production!$A$6:$A$35,$A18,Production!$D$6:$D$35,"<="&$B18)) -> 0 | D18: =ROUND(INDEX(Bâtiments!$F$6:$F$15,MATCH($A18,Bâtiments!$A$6:$A$15,0))*($B18-1)^Paramètres!$B$14,-1) -> 6400 | E18: =INDEX(Paramètres!$D$22:$D$26,MATCH($C18,Paramètres!$E$22:$E$26,1)) -> bois | F18: =ROUND(Paramètres!$B$15*$B18^Paramètres!$B$16*INDEX(Bâtiments!$G$6:$G$15,MATCH($A18,Bâtiments!$A$6:$A$15,0)),0) -> 122 | G18: =IF($C18>=Paramètres!$E$23,ROUND($F18*Paramètres!$B$17,0),0) -> 0 | H18: =ROUND($D18/INDEX(Paramètres!$B$38:$B$57,MATCH(MAX(5,$C18),Paramètres!$A$38:$A$57,1))*60,1) -> 15.2 | I18: ="Capacité : "&ROUND(Paramètres!$B$30*$B18^Paramètres!$B$31,-2)&" par ressource" -> Capacité : 11200 par ressource
A19: Entrepôt | B19: 6 | C19: =MAX(INDEX(Bâtiments!$D$6:$D$15,MATCH($A19,Bâtiments!$A$6:$A$15,0)),INDEX(Paramètres!$E$22:$E$26,MATCH($B19,Paramètres!$B$22:$B$26,1)),_xlfn.MAXIFS(Production!$E$6:$E$35,Production!$A$6:$A$35,$A19,Production!$D$6:$D$35,"<="&$B19)) -> 15 | D19: =ROUND(INDEX(Bâtiments!$F$6:$F$15,MATCH($A19,Bâtiments!$A$6:$A$15,0))*($B19-1)^Paramètres!$B$14,-1) -> 10000 | E19: =INDEX(Paramètres!$D$22:$D$26,MATCH($C19,Paramètres!$E$22:$E$26,1)) -> fer | F19: =ROUND(Paramètres!$B$15*$B19^Paramètres!$B$16*INDEX(Bâtiments!$G$6:$G$15,MATCH($A19,Bâtiments!$A$6:$A$15,0)),0) -> 154 | G19: =IF($C19>=Paramètres!$E$23,ROUND($F19*Paramètres!$B$17,0),0) -> 77 | H19: =ROUND($D19/INDEX(Paramètres!$B$38:$B$57,MATCH(MAX(5,$C19),Paramètres!$A$38:$A$57,1))*60,1) -> 8.3 | I19: ="Capacité : "&ROUND(Paramètres!$B$30*$B19^Paramètres!$B$31,-2)&" par ressource" -> Capacité : 14700 par ressource
A20: Entrepôt | B20: 7 | C20: =MAX(INDEX(Bâtiments!$D$6:$D$15,MATCH($A20,Bâtiments!$A$6:$A$15,0)),INDEX(Paramètres!$E$22:$E$26,MATCH($B20,Paramètres!$B$22:$B$26,1)),_xlfn.MAXIFS(Production!$E$6:$E$35,Production!$A$6:$A$35,$A20,Production!$D$6:$D$35,"<="&$B20)) -> 15 | D20: =ROUND(INDEX(Bâtiments!$F$6:$F$15,MATCH($A20,Bâtiments!$A$6:$A$15,0))*($B20-1)^Paramètres!$B$14,-1) -> 14400 | E20: =INDEX(Paramètres!$D$22:$D$26,MATCH($C20,Paramètres!$E$22:$E$26,1)) -> fer | F20: =ROUND(Paramètres!$B$15*$B20^Paramètres!$B$16*INDEX(Bâtiments!$G$6:$G$15,MATCH($A20,Bâtiments!$A$6:$A$15,0)),0) -> 188 | G20: =IF($C20>=Paramètres!$E$23,ROUND($F20*Paramètres!$B$17,0),0) -> 94 | H20: =ROUND($D20/INDEX(Paramètres!$B$38:$B$57,MATCH(MAX(5,$C20),Paramètres!$A$38:$A$57,1))*60,1) -> 11.9 | I20: ="Capacité : "&ROUND(Paramètres!$B$30*$B20^Paramètres!$B$31,-2)&" par ressource" -> Capacité : 18500 par ressource
A21: Entrepôt | B21: 8 | C21: =MAX(INDEX(Bâtiments!$D$6:$D$15,MATCH($A21,Bâtiments!$A$6:$A$15,0)),INDEX(Paramètres!$E$22:$E$26,MATCH($B21,Paramètres!$B$22:$B$26,1)),_xlfn.MAXIFS(Production!$E$6:$E$35,Production!$A$6:$A$35,$A21,Production!$D$6:$D$35,"<="&$B21)) -> 15 | D21: =ROUND(INDEX(Bâtiments!$F$6:$F$15,MATCH($A21,Bâtiments!$A$6:$A$15,0))*($B21-1)^Paramètres!$B$14,-1) -> 19600 | E21: =INDEX(Paramètres!$D$22:$D$26,MATCH($C21,Paramètres!$E$22:$E$26,1)) -> fer | F21: =ROUND(Paramètres!$B$15*$B21^Paramètres!$B$16*INDEX(Bâtiments!$G$6:$G$15,MATCH($A21,Bâtiments!$A$6:$A$15,0)),0) -> 224 | G21: =IF($C21>=Paramètres!$E$23,ROUND($F21*Paramètres!$B$17,0),0) -> 112 | H21: =ROUND($D21/INDEX(Paramètres!$B$38:$B$57,MATCH(MAX(5,$C21),Paramètres!$A$38:$A$57,1))*60,1) -> 16.2 | I21: ="Capacité : "&ROUND(Paramètres!$B$30*$B21^Paramètres!$B$31,-2)&" par ressource" -> Capacité : 22600 par ressource
A22: Entrepôt | B22: 9 | C22: =MAX(INDEX(Bâtiments!$D$6:$D$15,MATCH($A22,Bâtiments!$A$6:$A$15,0)),INDEX(Paramètres!$E$22:$E$26,MATCH($B22,Paramètres!$B$22:$B$26,1)),_xlfn.MAXIFS(Production!$E$6:$E$35,Production!$A$6:$A$35,$A22,Production!$D$6:$D$35,"<="&$B22)) -> 15 | D22: =ROUND(INDEX(Bâtiments!$F$6:$F$15,MATCH($A22,Bâtiments!$A$6:$A$15,0))*($B22-1)^Paramètres!$B$14,-1) -> 25600 | E22: =INDEX(Paramètres!$D$22:$D$26,MATCH($C22,Paramètres!$E$22:$E$26,1)) -> fer | F22: =ROUND(Paramètres!$B$15*$B22^Paramètres!$B$16*INDEX(Bâtiments!$G$6:$G$15,MATCH($A22,Bâtiments!$A$6:$A$15,0)),0) -> 261 | G22: =IF($C22>=Paramètres!$E$23,ROUND($F22*Paramètres!$B$17,0),0) -> 131 | H22: =ROUND($D22/INDEX(Paramètres!$B$38:$B$57,MATCH(MAX(5,$C22),Paramètres!$A$38:$A$57,1))*60,1) -> 21.2 | I22: ="Capacité : "&ROUND(Paramètres!$B$30*$B22^Paramètres!$B$31,-2)&" par ressource" -> Capacité : 27000 par ressource
A23: Entrepôt | B23: 10 | C23: =MAX(INDEX(Bâtiments!$D$6:$D$15,MATCH($A23,Bâtiments!$A$6:$A$15,0)),INDEX(Paramètres!$E$22:$E$26,MATCH($B23,Paramètres!$B$22:$B$26,1)),_xlfn.MAXIFS(Production!$E$6:$E$35,Production!$A$6:$A$35,$A23,Production!$D$6:$D$35,"<="&$B23)) -> 15 | D23: =ROUND(INDEX(Bâtiments!$F$6:$F$15,MATCH($A23,Bâtiments!$A$6:$A$15,0))*($B23-1)^Paramètres!$B$14,-1) -> 32400 | E23: =INDEX(Paramètres!$D$22:$D$26,MATCH($C23,Paramètres!$E$22:$E$26,1)) -> fer | F23: =ROUND(Paramètres!$B$15*$B23^Paramètres!$B$16*INDEX(Bâtiments!$G$6:$G$15,MATCH($A23,Bâtiments!$A$6:$A$15,0)),0) -> 299 | G23: =IF($C23>=Paramètres!$E$23,ROUND($F23*Paramètres!$B$17,0),0) -> 150 | H23: =ROUND($D23/INDEX(Paramètres!$B$38:$B$57,MATCH(MAX(5,$C23),Paramètres!$A$38:$A$57,1))*60,1) -> 26.8 | I23: ="Capacité : "&ROUND(Paramètres!$B$30*$B23^Paramètres!$B$31,-2)&" par ressource" -> Capacité : 31600 par ressource
A24: Entrepôt | B24: 11 | C24: =MAX(INDEX(Bâtiments!$D$6:$D$15,MATCH($A24,Bâtiments!$A$6:$A$15,0)),INDEX(Paramètres!$E$22:$E$26,MATCH($B24,Paramètres!$B$22:$B$26,1)),_xlfn.MAXIFS(Production!$E$6:$E$35,Production!$A$6:$A$35,$A24,Production!$D$6:$D$35,"<="&$B24)) -> 30 | D24: =ROUND(INDEX(Bâtiments!$F$6:$F$15,MATCH($A24,Bâtiments!$A$6:$A$15,0))*($B24-1)^Paramètres!$B$14,-1) -> 40000 | E24: =INDEX(Paramètres!$D$22:$D$26,MATCH($C24,Paramètres!$E$22:$E$26,1)) -> acier | F24: =ROUND(Paramètres!$B$15*$B24^Paramètres!$B$16*INDEX(Bâtiments!$G$6:$G$15,MATCH($A24,Bâtiments!$A$6:$A$15,0)),0) -> 339 | G24: =IF($C24>=Paramètres!$E$23,ROUND($F24*Paramètres!$B$17,0),0) -> 170 | H24: =ROUND($D24/INDEX(Paramètres!$B$38:$B$57,MATCH(MAX(5,$C24),Paramètres!$A$38:$A$57,1))*60,1) -> 15.5 | I24: ="Capacité : "&ROUND(Paramètres!$B$30*$B24^Paramètres!$B$31,-2)&" par ressource" -> Capacité : 36500 par ressource
A25: Entrepôt | B25: 12 | C25: =MAX(INDEX(Bâtiments!$D$6:$D$15,MATCH($A25,Bâtiments!$A$6:$A$15,0)),INDEX(Paramètres!$E$22:$E$26,MATCH($B25,Paramètres!$B$22:$B$26,1)),_xlfn.MAXIFS(Production!$E$6:$E$35,Production!$A$6:$A$35,$A25,Production!$D$6:$D$35,"<="&$B25)) -> 30 | D25: =ROUND(INDEX(Bâtiments!$F$6:$F$15,MATCH($A25,Bâtiments!$A$6:$A$15,0))*($B25-1)^Paramètres!$B$14,-1) -> 48400 | E25: =INDEX(Paramètres!$D$22:$D$26,MATCH($C25,Paramètres!$E$22:$E$26,1)) -> acier | F25: =ROUND(Paramètres!$B$15*$B25^Paramètres!$B$16*INDEX(Bâtiments!$G$6:$G$15,MATCH($A25,Bâtiments!$A$6:$A$15,0)),0) -> 379 | G25: =IF($C25>=Paramètres!$E$23,ROUND($F25*Paramètres!$B$17,0),0) -> 190 | H25: =ROUND($D25/INDEX(Paramètres!$B$38:$B$57,MATCH(MAX(5,$C25),Paramètres!$A$38:$A$57,1))*60,1) -> 18.7 | I25: ="Capacité : "&ROUND(Paramètres!$B$30*$B25^Paramètres!$B$31,-2)&" par ressource" -> Capacité : 41600 par ressource
A26: Entrepôt | B26: 13 | C26: =MAX(INDEX(Bâtiments!$D$6:$D$15,MATCH($A26,Bâtiments!$A$6:$A$15,0)),INDEX(Paramètres!$E$22:$E$26,MATCH($B26,Paramètres!$B$22:$B$26,1)),_xlfn.MAXIFS(Production!$E$6:$E$35,Production!$A$6:$A$35,$A26,Production!$D$6:$D$35,"<="&$B26)) -> 30 | D26: =ROUND(INDEX(Bâtiments!$F$6:$F$15,MATCH($A26,Bâtiments!$A$6:$A$15,0))*($B26-1)^Paramètres!$B$14,-1) -> 57600 | E26: =INDEX(Paramètres!$D$22:$D$26,MATCH($C26,Paramètres!$E$22:$E$26,1)) -> acier | F26: =ROUND(Paramètres!$B$15*$B26^Paramètres!$B$16*INDEX(Bâtiments!$G$6:$G$15,MATCH($A26,Bâtiments!$A$6:$A$15,0)),0) -> 421 | G26: =IF($C26>=Paramètres!$E$23,ROUND($F26*Paramètres!$B$17,0),0) -> 211 | H26: =ROUND($D26/INDEX(Paramètres!$B$38:$B$57,MATCH(MAX(5,$C26),Paramètres!$A$38:$A$57,1))*60,1) -> 22.3 | I26: ="Capacité : "&ROUND(Paramètres!$B$30*$B26^Paramètres!$B$31,-2)&" par ressource" -> Capacité : 46900 par ressource
... A38: Entrepôt | B38: 25 | C38: =MAX(INDEX(Bâtiments!$D$6:$D$15,MATCH($A38,Bâtiments!$A$6:$A$15,0)),INDEX(Paramètres!$E$22:$E$26,MATCH($B38,Paramètres!$B$22:$B$26,1)),_xlfn.MAXIFS(Production!$E$6:$E$35,Production!$A$6:$A$35,$A38,Production!$D$6:$D$35,"<="&$B38)) -> 70 | D38: =ROUND(INDEX(Bâtiments!$F$6:$F$15,MATCH($A38,Bâtiments!$A$6:$A$15,0))*($B38-1)^Paramètres!$B$14,-1) -> 230400 | E38: =INDEX(Paramètres!$D$22:$D$26,MATCH($C38,Paramètres!$E$22:$E$26,1)) -> adamantite | F38: =ROUND(Paramètres!$B$15*$B38^Paramètres!$B$16*INDEX(Bâtiments!$G$6:$G$15,MATCH($A38,Bâtiments!$A$6:$A$15,0)),0) -> 985 | G38: =IF($C38>=Paramètres!$E$23,ROUND($F38*Paramètres!$B$17,0),0) -> 493 | H38: =ROUND($D38/INDEX(Paramètres!$B$38:$B$57,MATCH(MAX(5,$C38),Paramètres!$A$38:$A$57,1))*60,1) -> 29 | I38: ="Capacité : "&ROUND(Paramètres!$B$30*$B38^Paramètres!$B$31,-2)&" par ressource" -> Capacité : 125000 par ressource
A39: Scierie | B39: 2 | C39: =MAX(INDEX(Bâtiments!$D$6:$D$15,MATCH($A39,Bâtiments!$A$6:$A$15,0)),INDEX(Paramètres!$E$22:$E$26,MATCH($B39,Paramètres!$B$22:$B$26,1)),_xlfn.MAXIFS(Production!$E$6:$E$35,Production!$A$6:$A$35,$A39,Production!$D$6:$D$35,"<="&$B39)) -> 0 | D39: =ROUND(INDEX(Bâtiments!$F$6:$F$15,MATCH($A39,Bâtiments!$A$6:$A$15,0))*($B39-1)^Paramètres!$B$14,-1) -> 500 | E39: =INDEX(Paramètres!$D$22:$D$26,MATCH($C39,Paramètres!$E$22:$E$26,1)) -> bois | F39: =ROUND(Paramètres!$B$15*$B39^Paramètres!$B$16*INDEX(Bâtiments!$G$6:$G$15,MATCH($A39,Bâtiments!$A$6:$A$15,0)),0) -> 37 | G39: =IF($C39>=Paramètres!$E$23,ROUND($F39*Paramètres!$B$17,0),0) -> 0 | H39: =ROUND($D39/INDEX(Paramètres!$B$38:$B$57,MATCH(MAX(5,$C39),Paramètres!$A$38:$A$57,1))*60,1) -> 1.2 | I39: Production +12 % sur les ressources débloquées
A40: Scierie | B40: 3 | C40: =MAX(INDEX(Bâtiments!$D$6:$D$15,MATCH($A40,Bâtiments!$A$6:$A$15,0)),INDEX(Paramètres!$E$22:$E$26,MATCH($B40,Paramètres!$B$22:$B$26,1)),_xlfn.MAXIFS(Production!$E$6:$E$35,Production!$A$6:$A$35,$A40,Production!$D$6:$D$35,"<="&$B40)) -> 0 | D40: =ROUND(INDEX(Bâtiments!$F$6:$F$15,MATCH($A40,Bâtiments!$A$6:$A$15,0))*($B40-1)^Paramètres!$B$14,-1) -> 2000 | E40: =INDEX(Paramètres!$D$22:$D$26,MATCH($C40,Paramètres!$E$22:$E$26,1)) -> bois | F40: =ROUND(Paramètres!$B$15*$B40^Paramètres!$B$16*INDEX(Bâtiments!$G$6:$G$15,MATCH($A40,Bâtiments!$A$6:$A$15,0)),0) -> 63 | G40: =IF($C40>=Paramètres!$E$23,ROUND($F40*Paramètres!$B$17,0),0) -> 0 | H40: =ROUND($D40/INDEX(Paramètres!$B$38:$B$57,MATCH(MAX(5,$C40),Paramètres!$A$38:$A$57,1))*60,1) -> 4.8 | I40: Production +12 % sur les ressources débloquées
A41: Scierie | B41: 4 | C41: =MAX(INDEX(Bâtiments!$D$6:$D$15,MATCH($A41,Bâtiments!$A$6:$A$15,0)),INDEX(Paramètres!$E$22:$E$26,MATCH($B41,Paramètres!$B$22:$B$26,1)),_xlfn.MAXIFS(Production!$E$6:$E$35,Production!$A$6:$A$35,$A41,Production!$D$6:$D$35,"<="&$B41)) -> 0 | D41: =ROUND(INDEX(Bâtiments!$F$6:$F$15,MATCH($A41,Bâtiments!$A$6:$A$15,0))*($B41-1)^Paramètres!$B$14,-1) -> 4500 | E41: =INDEX(Paramètres!$D$22:$D$26,MATCH($C41,Paramètres!$E$22:$E$26,1)) -> bois | F41: =ROUND(Paramètres!$B$15*$B41^Paramètres!$B$16*INDEX(Bâtiments!$G$6:$G$15,MATCH($A41,Bâtiments!$A$6:$A$15,0)),0) -> 91 | G41: =IF($C41>=Paramètres!$E$23,ROUND($F41*Paramètres!$B$17,0),0) -> 0 | H41: =ROUND($D41/INDEX(Paramètres!$B$38:$B$57,MATCH(MAX(5,$C41),Paramètres!$A$38:$A$57,1))*60,1) -> 10.7 | I41: Production +12 % sur les ressources débloquées
A42: Scierie | B42: 5 | C42: =MAX(INDEX(Bâtiments!$D$6:$D$15,MATCH($A42,Bâtiments!$A$6:$A$15,0)),INDEX(Paramètres!$E$22:$E$26,MATCH($B42,Paramètres!$B$22:$B$26,1)),_xlfn.MAXIFS(Production!$E$6:$E$35,Production!$A$6:$A$35,$A42,Production!$D$6:$D$35,"<="&$B42)) -> 0 | D42: =ROUND(INDEX(Bâtiments!$F$6:$F$15,MATCH($A42,Bâtiments!$A$6:$A$15,0))*($B42-1)^Paramètres!$B$14,-1) -> 8000 | E42: =INDEX(Paramètres!$D$22:$D$26,MATCH($C42,Paramètres!$E$22:$E$26,1)) -> bois | F42: =ROUND(Paramètres!$B$15*$B42^Paramètres!$B$16*INDEX(Bâtiments!$G$6:$G$15,MATCH($A42,Bâtiments!$A$6:$A$15,0)),0) -> 122 | G42: =IF($C42>=Paramètres!$E$23,ROUND($F42*Paramètres!$B$17,0),0) -> 0 | H42: =ROUND($D42/INDEX(Paramètres!$B$38:$B$57,MATCH(MAX(5,$C42),Paramètres!$A$38:$A$57,1))*60,1) -> 19 | I42: Production +12 % sur les ressources débloquées
A43: Scierie | B43: 6 | C43: =MAX(INDEX(Bâtiments!$D$6:$D$15,MATCH($A43,Bâtiments!$A$6:$A$15,0)),INDEX(Paramètres!$E$22:$E$26,MATCH($B43,Paramètres!$B$22:$B$26,1)),_xlfn.MAXIFS(Production!$E$6:$E$35,Production!$A$6:$A$35,$A43,Production!$D$6:$D$35,"<="&$B43)) -> 15 | D43: =ROUND(INDEX(Bâtiments!$F$6:$F$15,MATCH($A43,Bâtiments!$A$6:$A$15,0))*($B43-1)^Paramètres!$B$14,-1) -> 12500 | E43: =INDEX(Paramètres!$D$22:$D$26,MATCH($C43,Paramètres!$E$22:$E$26,1)) -> fer | F43: =ROUND(Paramètres!$B$15*$B43^Paramètres!$B$16*INDEX(Bâtiments!$G$6:$G$15,MATCH($A43,Bâtiments!$A$6:$A$15,0)),0) -> 154 | G43: =IF($C43>=Paramètres!$E$23,ROUND($F43*Paramètres!$B$17,0),0) -> 77 | H43: =ROUND($D43/INDEX(Paramètres!$B$38:$B$57,MATCH(MAX(5,$C43),Paramètres!$A$38:$A$57,1))*60,1) -> 10.3 | I43: Production +12 % sur les ressources débloquées · débloque : chêne, frêne
A44: Scierie | B44: 7 | C44: =MAX(INDEX(Bâtiments!$D$6:$D$15,MATCH($A44,Bâtiments!$A$6:$A$15,0)),INDEX(Paramètres!$E$22:$E$26,MATCH($B44,Paramètres!$B$22:$B$26,1)),_xlfn.MAXIFS(Production!$E$6:$E$35,Production!$A$6:$A$35,$A44,Production!$D$6:$D$35,"<="&$B44)) -> 15 | D44: =ROUND(INDEX(Bâtiments!$F$6:$F$15,MATCH($A44,Bâtiments!$A$6:$A$15,0))*($B44-1)^Paramètres!$B$14,-1) -> 18000 | E44: =INDEX(Paramètres!$D$22:$D$26,MATCH($C44,Paramètres!$E$22:$E$26,1)) -> fer | F44: =ROUND(Paramètres!$B$15*$B44^Paramètres!$B$16*INDEX(Bâtiments!$G$6:$G$15,MATCH($A44,Bâtiments!$A$6:$A$15,0)),0) -> 188 | G44: =IF($C44>=Paramètres!$E$23,ROUND($F44*Paramètres!$B$17,0),0) -> 94 | H44: =ROUND($D44/INDEX(Paramètres!$B$38:$B$57,MATCH(MAX(5,$C44),Paramètres!$A$38:$A$57,1))*60,1) -> 14.9 | I44: Production +12 % sur les ressources débloquées
A45: Scierie | B45: 8 | C45: =MAX(INDEX(Bâtiments!$D$6:$D$15,MATCH($A45,Bâtiments!$A$6:$A$15,0)),INDEX(Paramètres!$E$22:$E$26,MATCH($B45,Paramètres!$B$22:$B$26,1)),_xlfn.MAXIFS(Production!$E$6:$E$35,Production!$A$6:$A$35,$A45,Production!$D$6:$D$35,"<="&$B45)) -> 15 | D45: =ROUND(INDEX(Bâtiments!$F$6:$F$15,MATCH($A45,Bâtiments!$A$6:$A$15,0))*($B45-1)^Paramètres!$B$14,-1) -> 24500 | E45: =INDEX(Paramètres!$D$22:$D$26,MATCH($C45,Paramètres!$E$22:$E$26,1)) -> fer | F45: =ROUND(Paramètres!$B$15*$B45^Paramètres!$B$16*INDEX(Bâtiments!$G$6:$G$15,MATCH($A45,Bâtiments!$A$6:$A$15,0)),0) -> 224 | G45: =IF($C45>=Paramètres!$E$23,ROUND($F45*Paramètres!$B$17,0),0) -> 112 | H45: =ROUND($D45/INDEX(Paramètres!$B$38:$B$57,MATCH(MAX(5,$C45),Paramètres!$A$38:$A$57,1))*60,1) -> 20.2 | I45: Production +12 % sur les ressources débloquées
A46: Scierie | B46: 9 | C46: =MAX(INDEX(Bâtiments!$D$6:$D$15,MATCH($A46,Bâtiments!$A$6:$A$15,0)),INDEX(Paramètres!$E$22:$E$26,MATCH($B46,Paramètres!$B$22:$B$26,1)),_xlfn.MAXIFS(Production!$E$6:$E$35,Production!$A$6:$A$35,$A46,Production!$D$6:$D$35,"<="&$B46)) -> 15 | D46: =ROUND(INDEX(Bâtiments!$F$6:$F$15,MATCH($A46,Bâtiments!$A$6:$A$15,0))*($B46-1)^Paramètres!$B$14,-1) -> 32000 | E46: =INDEX(Paramètres!$D$22:$D$26,MATCH($C46,Paramètres!$E$22:$E$26,1)) -> fer | F46: =ROUND(Paramètres!$B$15*$B46^Paramètres!$B$16*INDEX(Bâtiments!$G$6:$G$15,MATCH($A46,Bâtiments!$A$6:$A$15,0)),0) -> 261 | G46: =IF($C46>=Paramètres!$E$23,ROUND($F46*Paramètres!$B$17,0),0) -> 131 | H46: =ROUND($D46/INDEX(Paramètres!$B$38:$B$57,MATCH(MAX(5,$C46),Paramètres!$A$38:$A$57,1))*60,1) -> 26.4 | I46: Production +12 % sur les ressources débloquées
A47: Scierie | B47: 10 | C47: =MAX(INDEX(Bâtiments!$D$6:$D$15,MATCH($A47,Bâtiments!$A$6:$A$15,0)),INDEX(Paramètres!$E$22:$E$26,MATCH($B47,Paramètres!$B$22:$B$26,1)),_xlfn.MAXIFS(Production!$E$6:$E$35,Production!$A$6:$A$35,$A47,Production!$D$6:$D$35,"<="&$B47)) -> 15 | D47: =ROUND(INDEX(Bâtiments!$F$6:$F$15,MATCH($A47,Bâtiments!$A$6:$A$15,0))*($B47-1)^Paramètres!$B$14,-1) -> 40500 | E47: =INDEX(Paramètres!$D$22:$D$26,MATCH($C47,Paramètres!$E$22:$E$26,1)) -> fer | F47: =ROUND(Paramètres!$B$15*$B47^Paramètres!$B$16*INDEX(Bâtiments!$G$6:$G$15,MATCH($A47,Bâtiments!$A$6:$A$15,0)),0) -> 299 | G47: =IF($C47>=Paramètres!$E$23,ROUND($F47*Paramètres!$B$17,0),0) -> 150 | H47: =ROUND($D47/INDEX(Paramètres!$B$38:$B$57,MATCH(MAX(5,$C47),Paramètres!$A$38:$A$57,1))*60,1) -> 33.5 | I47: Production +12 % sur les ressources débloquées
A48: Scierie | B48: 11 | C48: =MAX(INDEX(Bâtiments!$D$6:$D$15,MATCH($A48,Bâtiments!$A$6:$A$15,0)),INDEX(Paramètres!$E$22:$E$26,MATCH($B48,Paramètres!$B$22:$B$26,1)),_xlfn.MAXIFS(Production!$E$6:$E$35,Production!$A$6:$A$35,$A48,Production!$D$6:$D$35,"<="&$B48)) -> 30 | D48: =ROUND(INDEX(Bâtiments!$F$6:$F$15,MATCH($A48,Bâtiments!$A$6:$A$15,0))*($B48-1)^Paramètres!$B$14,-1) -> 50000 | E48: =INDEX(Paramètres!$D$22:$D$26,MATCH($C48,Paramètres!$E$22:$E$26,1)) -> acier | F48: =ROUND(Paramètres!$B$15*$B48^Paramètres!$B$16*INDEX(Bâtiments!$G$6:$G$15,MATCH($A48,Bâtiments!$A$6:$A$15,0)),0) -> 339 | G48: =IF($C48>=Paramètres!$E$23,ROUND($F48*Paramètres!$B$17,0),0) -> 170 | H48: =ROUND($D48/INDEX(Paramètres!$B$38:$B$57,MATCH(MAX(5,$C48),Paramètres!$A$38:$A$57,1))*60,1) -> 19.4 | I48: Production +12 % sur les ressources débloquées · débloque : ébène, if
A49: Scierie | B49: 12 | C49: =MAX(INDEX(Bâtiments!$D$6:$D$15,MATCH($A49,Bâtiments!$A$6:$A$15,0)),INDEX(Paramètres!$E$22:$E$26,MATCH($B49,Paramètres!$B$22:$B$26,1)),_xlfn.MAXIFS(Production!$E$6:$E$35,Production!$A$6:$A$35,$A49,Production!$D$6:$D$35,"<="&$B49)) -> 30 | D49: =ROUND(INDEX(Bâtiments!$F$6:$F$15,MATCH($A49,Bâtiments!$A$6:$A$15,0))*($B49-1)^Paramètres!$B$14,-1) -> 60500 | E49: =INDEX(Paramètres!$D$22:$D$26,MATCH($C49,Paramètres!$E$22:$E$26,1)) -> acier | F49: =ROUND(Paramètres!$B$15*$B49^Paramètres!$B$16*INDEX(Bâtiments!$G$6:$G$15,MATCH($A49,Bâtiments!$A$6:$A$15,0)),0) -> 379 | G49: =IF($C49>=Paramètres!$E$23,ROUND($F49*Paramètres!$B$17,0),0) -> 190 | H49: =ROUND($D49/INDEX(Paramètres!$B$38:$B$57,MATCH(MAX(5,$C49),Paramètres!$A$38:$A$57,1))*60,1) -> 23.4 | I49: Production +12 % sur les ressources débloquées
A50: Scierie | B50: 13 | C50: =MAX(INDEX(Bâtiments!$D$6:$D$15,MATCH($A50,Bâtiments!$A$6:$A$15,0)),INDEX(Paramètres!$E$22:$E$26,MATCH($B50,Paramètres!$B$22:$B$26,1)),_xlfn.MAXIFS(Production!$E$6:$E$35,Production!$A$6:$A$35,$A50,Production!$D$6:$D$35,"<="&$B50)) -> 30 | D50: =ROUND(INDEX(Bâtiments!$F$6:$F$15,MATCH($A50,Bâtiments!$A$6:$A$15,0))*($B50-1)^Paramètres!$B$14,-1) -> 72000 | E50: =INDEX(Paramètres!$D$22:$D$26,MATCH($C50,Paramètres!$E$22:$E$26,1)) -> acier | F50: =ROUND(Paramètres!$B$15*$B50^Paramètres!$B$16*INDEX(Bâtiments!$G$6:$G$15,MATCH($A50,Bâtiments!$A$6:$A$15,0)),0) -> 421 | G50: =IF($C50>=Paramètres!$E$23,ROUND($F50*Paramètres!$B$17,0),0) -> 211 | H50: =ROUND($D50/INDEX(Paramètres!$B$38:$B$57,MATCH(MAX(5,$C50),Paramètres!$A$38:$A$57,1))*60,1) -> 27.9 | I50: Production +12 % sur les ressources débloquées
... A114: Mine | B114: 20 | C114: =MAX(INDEX(Bâtiments!$D$6:$D$15,MATCH($A114,Bâtiments!$A$6:$A$15,0)),INDEX(Paramètres!$E$22:$E$26,MATCH($B114,Paramètres!$B$22:$B$26,1)),_xlfn.MAXIFS(Production!$E$6:$E$35,Production!$A$6:$A$35,$A114,Production!$D$6:$D$35,"<="&$B114)) -> 70 | D114: =ROUND(INDEX(Bâtiments!$F$6:$F$15,MATCH($A114,Bâtiments!$A$6:$A$15,0))*($B114-1)^Paramètres!$B$14,-1) -> 216600 | E114: =INDEX(Paramètres!$D$22:$D$26,MATCH($C114,Paramètres!$E$22:$E$26,1)) -> adamantite | F114: =ROUND(Paramètres!$B$15*$B114^Paramètres!$B$16*INDEX(Bâtiments!$G$6:$G$15,MATCH($A114,Bâtiments!$A$6:$A$15,0)),0) -> 737 | G114: =IF($C114>=Paramètres!$E$23,ROUND($F114*Paramètres!$B$17,0),0) -> 369 | H114: =ROUND($D114/INDEX(Paramètres!$B$38:$B$57,MATCH(MAX(5,$C114),Paramètres!$A$38:$A$57,1))*60,1) -> 27.3 | I114: Production +12 % sur les ressources débloquées
A115: Atelier de fabrication | B115: 2 | C115: 30 | D115: =ROUND(INDEX(Bâtiments!$F$6:$F$15,MATCH($A115,Bâtiments!$A$6:$A$15,0))*($B115-1)^Paramètres!$B$14,-1) -> 10000 | E115: =INDEX(Paramètres!$D$22:$D$26,MATCH($C115,Paramètres!$E$22:$E$26,1)) -> acier | F115: =ROUND(Paramètres!$B$15*$B115^Paramètres!$B$16*INDEX(Bâtiments!$G$6:$G$15,MATCH($A115,Bâtiments!$A$6:$A$15,0)),0) -> 148 | G115: =IF($C115>=Paramètres!$E$23,ROUND($F115*Paramètres!$B$17,0),0) -> 74 | H115: =ROUND($D115/INDEX(Paramètres!$B$38:$B$57,MATCH(MAX(5,$C115),Paramètres!$A$38:$A$57,1))*60,1) -> 3.9 | I115: Fabrication et amélioration des objets de palier 3 (acier, soie, cuir clouté…)
A116: Atelier de fabrication | B116: 3 | C116: 50 | D116: =ROUND(INDEX(Bâtiments!$F$6:$F$15,MATCH($A116,Bâtiments!$A$6:$A$15,0))*($B116-1)^Paramètres!$B$14,-1) -> 40000 | E116: =INDEX(Paramètres!$D$22:$D$26,MATCH($C116,Paramètres!$E$22:$E$26,1)) -> mithril | F116: =ROUND(Paramètres!$B$15*$B116^Paramètres!$B$16*INDEX(Bâtiments!$G$6:$G$15,MATCH($A116,Bâtiments!$A$6:$A$15,0)),0) -> 250 | G116: =IF($C116>=Paramètres!$E$23,ROUND($F116*Paramètres!$B$17,0),0) -> 125 | H116: =ROUND($D116/INDEX(Paramètres!$B$38:$B$57,MATCH(MAX(5,$C116),Paramètres!$A$38:$A$57,1))*60,1) -> 10.7 | I116: Palier 4 (mithril, velours enchanté, écailles…)
A117: Atelier de fabrication | B117: 4 | C117: 70 | D117: =ROUND(INDEX(Bâtiments!$F$6:$F$15,MATCH($A117,Bâtiments!$A$6:$A$15,0))*($B117-1)^Paramètres!$B$14,-1) -> 90000 | E117: =INDEX(Paramètres!$D$22:$D$26,MATCH($C117,Paramètres!$E$22:$E$26,1)) -> adamantite | F117: =ROUND(Paramètres!$B$15*$B117^Paramètres!$B$16*INDEX(Bâtiments!$G$6:$G$15,MATCH($A117,Bâtiments!$A$6:$A$15,0)),0) -> 364 | G117: =IF($C117>=Paramètres!$E$23,ROUND($F117*Paramètres!$B$17,0),0) -> 182 | H117: =ROUND($D117/INDEX(Paramètres!$B$38:$B$57,MATCH(MAX(5,$C117),Paramètres!$A$38:$A$57,1))*60,1) -> 11.3 | I117: Palier 5 (adamantite, étoffe astrale, peau de dragon…)
A118: Atelier de fabrication | B118: 5 | C118: 85 | D118: =ROUND(INDEX(Bâtiments!$F$6:$F$15,MATCH($A118,Bâtiments!$A$6:$A$15,0))*($B118-1)^Paramètres!$B$14,-1) -> 160000 | E118: =INDEX(Paramètres!$D$22:$D$26,MATCH($C118,Paramètres!$E$22:$E$26,1)) -> adamantite | F118: =ROUND(Paramètres!$B$15*$B118^Paramètres!$B$16*INDEX(Bâtiments!$G$6:$G$15,MATCH($A118,Bâtiments!$A$6:$A$15,0)),0) -> 486 | G118: =IF($C118>=Paramètres!$E$23,ROUND($F118*Paramètres!$B$17,0),0) -> 243 | H118: =ROUND($D118/INDEX(Paramètres!$B$38:$B$57,MATCH(MAX(5,$C118),Paramètres!$A$38:$A$57,1))*60,1) -> 19.4 | I118: −10 % sur toutes les ressources d'amélioration d'objets
A119: Tour d'alchimie | B119: 2 | C119: 90 | D119: =ROUND(INDEX(Bâtiments!$F$6:$F$15,MATCH($A119,Bâtiments!$A$6:$A$15,0))*($B119-1)^Paramètres!$B$14,-1) -> 50000 | E119: =INDEX(Paramètres!$D$22:$D$26,MATCH($C119,Paramètres!$E$22:$E$26,1)) -> adamantite | F119: =ROUND(Paramètres!$B$15*$B119^Paramètres!$B$16*INDEX(Bâtiments!$G$6:$G$15,MATCH($A119,Bâtiments!$A$6:$A$15,0)),0) -> 222 | G119: =IF($C119>=Paramètres!$E$23,ROUND($F119*Paramètres!$B$17,0),0) -> 111 | H119: =ROUND($D119/INDEX(Paramètres!$B$38:$B$57,MATCH(MAX(5,$C119),Paramètres!$A$38:$A$57,1))*60,1) -> 4.7 | I119: Fusions : 2 fusions de plus par compétence possibles · éther +12 % par niveau
A120: Tour d'alchimie | B120: 3 | C120: 95 | D120: =ROUND(INDEX(Bâtiments!$F$6:$F$15,MATCH($A120,Bâtiments!$A$6:$A$15,0))*($B120-1)^Paramètres!$B$14,-1) -> 200000 | E120: =INDEX(Paramètres!$D$22:$D$26,MATCH($C120,Paramètres!$E$22:$E$26,1)) -> adamantite | F120: =ROUND(Paramètres!$B$15*$B120^Paramètres!$B$16*INDEX(Bâtiments!$G$6:$G$15,MATCH($A120,Bâtiments!$A$6:$A$15,0)),0) -> 375 | G120: =IF($C120>=Paramètres!$E$23,ROUND($F120*Paramètres!$B$17,0),0) -> 188 | H120: =ROUND($D120/INDEX(Paramètres!$B$38:$B$57,MATCH(MAX(5,$C120),Paramètres!$A$38:$A$57,1))*60,1) -> 21.4 | I120: Infusion d'un élément en 1 manche de moins · éther +12 %
A121: Tour d'alchimie | B121: 4 | C121: 100 | D121: =ROUND(INDEX(Bâtiments!$F$6:$F$15,MATCH($A121,Bâtiments!$A$6:$A$15,0))*($B121-1)^Paramètres!$B$14,-1) -> 450000 | E121: =INDEX(Paramètres!$D$22:$D$26,MATCH($C121,Paramètres!$E$22:$E$26,1)) -> adamantite | F121: =ROUND(Paramètres!$B$15*$B121^Paramètres!$B$16*INDEX(Bâtiments!$G$6:$G$15,MATCH($A121,Bâtiments!$A$6:$A$15,0)),0) -> 546 | G121: =IF($C121>=Paramètres!$E$23,ROUND($F121*Paramètres!$B$17,0),0) -> 273 | H121: =ROUND($D121/INDEX(Paramètres!$B$38:$B$57,MATCH(MAX(5,$C121),Paramètres!$A$38:$A$57,1))*60,1) -> 39 | I121: Fusions −20 % de coût · éther +12 %
A122: Tour d'alchimie | B122: 5 | C122: 100 | D122: =ROUND(INDEX(Bâtiments!$F$6:$F$15,MATCH($A122,Bâtiments!$A$6:$A$15,0))*($B122-1)^Paramètres!$B$14,-1) -> 800000 | E122: =INDEX(Paramètres!$D$22:$D$26,MATCH($C122,Paramètres!$E$22:$E$26,1)) -> adamantite | F122: =ROUND(Paramètres!$B$15*$B122^Paramètres!$B$16*INDEX(Bâtiments!$G$6:$G$15,MATCH($A122,Bâtiments!$A$6:$A$15,0)),0) -> 729 | G122: =IF($C122>=Paramètres!$E$23,ROUND($F122*Paramètres!$B$17,0),0) -> 365 | H122: =ROUND($D122/INDEX(Paramètres!$B$38:$B$57,MATCH(MAX(5,$C122),Paramètres!$A$38:$A$57,1))*60,1) -> 69.4 | I122: Fusion triple débloquée (proposition) · éther +12 %
A124: Minutes de chasse = or demandé ÷ or gagné par heure dans la meilleure zone de chasse disponible à l'étage requis (Paramètres §5). Les effets de l'Atelier et de la Tour d'alchimie sont des propositions à valider.

Sheet Tour d'amélioration
A1: Tour d'amélioration (étage 100)
A2: Bonus permanents achetés avec des ressources de fin de jeu. Chaque branche a ses niveaux ; le coût d'un niveau est le même pour toutes les branches.
A5: Branche | B5: Bonus par niveau | C5: Unité | D5: Niveau max | E5: Bonus au niveau max | F5: Ressource de la branche | G5: Effet
A6: Dégâts | B6: 0.01 | C6: % | D6: 20 | E6: =B6*D6 -> 0.2 | F6: adamantite | G6: Dégâts de toutes les compétences.
A7: Points de vie | B7: 0.01 | C7: % | D7: 20 | E7: =B7*D7 -> 0.2 | F7: peau de dragon | G7: PV max de tous les personnages.
A8: Défense | B8: 0.01 | C8: % | D8: 20 | E8: =B8*D8 -> 0.2 | F8: orichalque | G8: Réduit les dégâts reçus (s'ajoute à Armure et Résistance).
A9: Production du village | B9: 0.05 | C9: % | D9: 20 | E9: =B9*D9 -> 1 | F9: diamant | G9: Multiplie la production de tous les bâtiments.
A10: Durée hors ligne | B10: 1 | C10: h | D10: 8 | E10: =B10*D10 -> 8 | F10: étoffe astrale | G10: Heures de production en plus quand le joueur est déconnecté.
A11: Or et XP | B11: 0.02 | C11: % | D11: 20 | E11: =B11*D11 -> 0.4 | F11: os de dragon | G11: Or et XP gagnés en combat (tour et zones de chasse).
A13: Coût par niveau (identique pour chaque branche)
A14: Or : coefficient | B14: 50000
A15: Or : exposant | B15: 1.3
A16: Éther : coefficient | B16: 50
A17: Ressource de branche : coefficient | B17: 80
A18: Exposant des ressources | B18: 1.3
A20: Niveau visé | B20: Or | C20: Éther | D20: Ressource de branche | E20: Minutes de chasse (étage 100) | F20: Or cumulé | G20: Éther cumulé
A21: 1 | B21: =ROUND($B$14*A21^$B$15,-3) -> 50000 | C21: =ROUND($B$16*A21^$B$18,0) -> 50 | D21: =ROUND($B$17*A21^$B$18,0) -> 80 | E21: =ROUND(B21/INDEX(Paramètres!$B$38:$B$57,MATCH(100,Paramètres!$A$38:$A$57,1))*60,1) -> 4.3 | F21: =SUM($B$21:B21) -> 50000 | G21: =SUM($C$21:C21) -> 50
A22: 2 | B22: =ROUND($B$14*A22^$B$15,-3) -> 123000 | C22: =ROUND($B$16*A22^$B$18,0) -> 123 | D22: =ROUND($B$17*A22^$B$18,0) -> 197 | E22: =ROUND(B22/INDEX(Paramètres!$B$38:$B$57,MATCH(100,Paramètres!$A$38:$A$57,1))*60,1) -> 10.7 | F22: =SUM($B$21:B22) -> 173000 | G22: =SUM($C$21:C22) -> 173
A23: 3 | B23: =ROUND($B$14*A23^$B$15,-3) -> 209000 | C23: =ROUND($B$16*A23^$B$18,0) -> 209 | D23: =ROUND($B$17*A23^$B$18,0) -> 334 | E23: =ROUND(B23/INDEX(Paramètres!$B$38:$B$57,MATCH(100,Paramètres!$A$38:$A$57,1))*60,1) -> 18.1 | F23: =SUM($B$21:B23) -> 382000 | G23: =SUM($C$21:C23) -> 382
A24: 4 | B24: =ROUND($B$14*A24^$B$15,-3) -> 303000 | C24: =ROUND($B$16*A24^$B$18,0) -> 303 | D24: =ROUND($B$17*A24^$B$18,0) -> 485 | E24: =ROUND(B24/INDEX(Paramètres!$B$38:$B$57,MATCH(100,Paramètres!$A$38:$A$57,1))*60,1) -> 26.3 | F24: =SUM($B$21:B24) -> 685000 | G24: =SUM($C$21:C24) -> 685
A25: 5 | B25: =ROUND($B$14*A25^$B$15,-3) -> 405000 | C25: =ROUND($B$16*A25^$B$18,0) -> 405 | D25: =ROUND($B$17*A25^$B$18,0) -> 648 | E25: =ROUND(B25/INDEX(Paramètres!$B$38:$B$57,MATCH(100,Paramètres!$A$38:$A$57,1))*60,1) -> 35.1 | F25: =SUM($B$21:B25) -> 1090000 | G25: =SUM($C$21:C25) -> 1090
A26: 6 | B26: =ROUND($B$14*A26^$B$15,-3) -> 514000 | C26: =ROUND($B$16*A26^$B$18,0) -> 514 | D26: =ROUND($B$17*A26^$B$18,0) -> 822 | E26: =ROUND(B26/INDEX(Paramètres!$B$38:$B$57,MATCH(100,Paramètres!$A$38:$A$57,1))*60,1) -> 44.6 | F26: =SUM($B$21:B26) -> 1604000 | G26: =SUM($C$21:C26) -> 1604
A27: 7 | B27: =ROUND($B$14*A27^$B$15,-3) -> 627000 | C27: =ROUND($B$16*A27^$B$18,0) -> 627 | D27: =ROUND($B$17*A27^$B$18,0) -> 1004 | E27: =ROUND(B27/INDEX(Paramètres!$B$38:$B$57,MATCH(100,Paramètres!$A$38:$A$57,1))*60,1) -> 54.4 | F27: =SUM($B$21:B27) -> 2231000 | G27: =SUM($C$21:C27) -> 2231
A28: 8 | B28: =ROUND($B$14*A28^$B$15,-3) -> 746000 | C28: =ROUND($B$16*A28^$B$18,0) -> 746 | D28: =ROUND($B$17*A28^$B$18,0) -> 1194 | E28: =ROUND(B28/INDEX(Paramètres!$B$38:$B$57,MATCH(100,Paramètres!$A$38:$A$57,1))*60,1) -> 64.7 | F28: =SUM($B$21:B28) -> 2977000 | G28: =SUM($C$21:C28) -> 2977
A29: 9 | B29: =ROUND($B$14*A29^$B$15,-3) -> 870000 | C29: =ROUND($B$16*A29^$B$18,0) -> 870 | D29: =ROUND($B$17*A29^$B$18,0) -> 1392 | E29: =ROUND(B29/INDEX(Paramètres!$B$38:$B$57,MATCH(100,Paramètres!$A$38:$A$57,1))*60,1) -> 75.5 | F29: =SUM($B$21:B29) -> 3847000 | G29: =SUM($C$21:C29) -> 3847
A30: 10 | B30: =ROUND($B$14*A30^$B$15,-3) -> 998000 | C30: =ROUND($B$16*A30^$B$18,0) -> 998 | D30: =ROUND($B$17*A30^$B$18,0) -> 1596 | E30: =ROUND(B30/INDEX(Paramètres!$B$38:$B$57,MATCH(100,Paramètres!$A$38:$A$57,1))*60,1) -> 86.6 | F30: =SUM($B$21:B30) -> 4845000 | G30: =SUM($C$21:C30) -> 4845
A31: 11 | B31: =ROUND($B$14*A31^$B$15,-3) -> 1129000 | C31: =ROUND($B$16*A31^$B$18,0) -> 1129 | D31: =ROUND($B$17*A31^$B$18,0) -> 1807 | E31: =ROUND(B31/INDEX(Paramètres!$B$38:$B$57,MATCH(100,Paramètres!$A$38:$A$57,1))*60,1) -> 97.9 | F31: =SUM($B$21:B31) -> 5974000 | G31: =SUM($C$21:C31) -> 5974
A32: 12 | B32: =ROUND($B$14*A32^$B$15,-3) -> 1264000 | C32: =ROUND($B$16*A32^$B$18,0) -> 1264 | D32: =ROUND($B$17*A32^$B$18,0) -> 2023 | E32: =ROUND(B32/INDEX(Paramètres!$B$38:$B$57,MATCH(100,Paramètres!$A$38:$A$57,1))*60,1) -> 109.6 | F32: =SUM($B$21:B32) -> 7238000 | G32: =SUM($C$21:C32) -> 7238
... A40: 20 | B40: =ROUND($B$14*A40^$B$15,-3) -> 2456000 | C40: =ROUND($B$16*A40^$B$18,0) -> 2456 | D40: =ROUND($B$17*A40^$B$18,0) -> 3930 | E40: =ROUND(B40/INDEX(Paramètres!$B$38:$B$57,MATCH(100,Paramètres!$A$38:$A$57,1))*60,1) -> 213.1 | F40: =SUM($B$21:B40) -> 22599000 | G40: =SUM($C$21:C40) -> 22599
A42: Branche « Durée hors ligne » : niveau max 8 (8 h de base + 8 h = 16 h).

Sheet Paramètres
A1: Paramètres d'équilibrage du village
A2: Cellules jaunes / texte bleu = modifiables. Tout le classeur se recalcule à partir d'ici et de l'onglet Bâtiments.
A4: 1. Production (ressources par heure)
A5: Production de base d'une ressource de palier 1 (/h) | B5: 60 | C5: Au niveau où le bâtiment la débloque.
A6: Production de base d'une ressource de palier 2 (/h) | B6: 90 | C6: Les paliers élevés produisent plus : les objets demandent plus de ressources pour monter.
A7: Production de base d'une ressource de palier 3 (/h) | B7: 135
A8: Production de base d'une ressource de palier 4 (/h) | B8: 200
A9: Production de base d'une ressource de palier 5 (/h) | B9: 300
A10: Hausse de production par niveau du bâtiment | B10: 0.12 | C10: Chaque niveau au-dessus du déblocage d'une ressource : ×1,12 (s'applique à toutes les ressources déjà débloquées).
A11: Durée maximale de production hors ligne (h) | B11: 8 | C11: Au-delà, le bâtiment s'arrête jusqu'à la prochaine connexion. Augmentable par la Tour d'amélioration.
A13: 2. Coûts d'amélioration
A14: Exposant du coût en or | B14: 2 | C14: Or pour passer du niveau N au niveau N+1 = coefficient du bâtiment (onglet Bâtiments) × N ^ exposant.
A15: Matériau de construction : quantité de base | B15: 15 | C15: Quantité = base × (niveau visé) ^ exposant × multiplicateur du bâtiment.
A16: Matériau de construction : exposant | B16: 1.3
A17: Charbon demandé (part de la quantité de matériau) | B17: 0.5 | C17: À partir de l'étage 15 (la Mine produit le charbon).
A18: Bâtiment de départ | B18: Niveau 1 gratuit | C18: Chaque bâtiment est construit au niveau 1 dès son étage de déblocage.
A20: 3. Tranches de niveau : étage requis et matériau de construction
A21: Tranche | B21: Niveau min | C21: Niveau max | D21: Matériau de construction | E21: Étage requis
A22: Niveaux 1 à 5 | B22: 1 | C22: 5 | D22: bois | E22: 0
A23: Niveaux 6 à 10 | B23: 6 | C23: 10 | D23: fer | E23: 15
A24: Niveaux 11 à 15 | B24: 11 | C24: 15 | D24: acier | E24: 30
A25: Niveaux 16 à 20 | B25: 16 | C25: 20 | D25: mithril | E25: 50
A26: Niveaux 21 à 25 | B26: 21 | C26: 25 | D26: adamantite | E26: 70
A27: Un niveau demande au minimum l'étage de sa tranche. Pour un bâtiment de production, il demande aussi l'étage de la ressource qu'il débloque (onglet Production). Le matériau dépend de l'étage requis : bois avant 15, fer, acier, mithril puis adamantite.
A29: 4. Entrepôt et taverne
A30: Entrepôt : capacité de base par ressource | B30: 1000 | C30: Capacité au niveau N = base × N ^ exposant (arrondie à la centaine).
A31: Entrepôt : exposant | B31: 1.5
A32: Taverne : objets proposés au niveau 1 | B32: 6 | C32: +1 objet tous les 2 niveaux.
A33: Taverne : lots de ressources au niveau 1 | B33: 4 | C33: +1 lot tous les 2 niveaux.
A34: Taverne : remise par niveau | B34: 0.02 | C34: Sur tous les prix de la boutique (niveau 10 : −18 %).
A36: 5. Repère : or gagné par heure de chasse (copie du bestiaire, onglet Zones, colonne Y)
A37: Étage de la zone | B37: Or / heure | C37: Zone
A38: 5 | B38: 25255 | C38: Forêt de chasse
A39: 10 | B39: 50401 | C39: Village gobelin
A40: 15 | B40: 72612 | C40: Mine abandonnée
A41: 20 | B41: 94477 | C41: Grotte profonde
A42: 25 | B42: 100072 | C42: Océan de lave
A43: 30 | B43: 154944 | C43: Cœur du volcan
A44: 35 | B44: 233978 | C44: Désert d'Arrakis
A45: 40 | B45: 184235 | C45: Pyramide
A46: 45 | B46: 260010 | C46: Ancienne tour
A47: 50 | B47: 224109 | C47: Marais des morts
A48: 55 | B48: 301518 | C48: Océan profond
A49: 60 | B49: 380431 | C49: Palais des Atlantes
... A57: 100 | B57: 691659 | C57: Palais démoniaque
A58: Valeurs recalculées par le bestiaire : à recopier ici si tu changes l'économie (XP, or, rythme de jeu).
